Workbook

Sheet MONSTER (MNST)
B1: MONSTER
B2: COMMON SIZING AND TREND ANALYSIS (in 000's Except Per Share Data)
B3: INCOME STATEMENT DATA
B4: NAME | U4: Page 1 of 3
B5: FIN320 Section B
J6: Common-Size Analysis | Q6: Trend Analysis
J7: (as a percentage of sales) | Q7: (using 2020 as the base year)
B8: Income Statement | C8: 2021 | D8: 2022 | E8: 2023 | F8: 2024 | G8: 2025 | J8: 2021 | K8: 2022 | L8: 2023 | M8: 2024 | N8: 2025 | Q8: 2021 | R8: 2022 | S8: 2023 | T8: 2024 | U8: 2025
B9: Net Operating Revenues | C9: 5541.352 | D9: 6311.05 | E9: 7140.027 | F9: 7492.709 | G9: 8294.343 | J9: =C9/C$9 -> 1 | K9: =D9/D$9 -> 1 | L9: =E9/E$9 -> 1 | M9: =F9/F$9 -> 1 | N9: =G9/G$9 -> 1 | Q9: =C9/$C9 -> 1 | R9: =D9/$C9 -> 1.1389008 | S9: =E9/$C9 -> 1.2884991 | T9: =F9/$C9 -> 1.3521446 | U9: =G9/$C9 -> 1.4968085
B10: Cost of sales | C10: 2432.839 | D10: 3136.483 | E10: 3345.821 | F10: 3443.831 | G10: 3662.148 | J10: =C10/C$9 -> 0.43903347 | K10: =D10/D$9 -> 0.49698275 | L10: =E10/E$9 -> 0.46860061 | M10: =F10/F$9 -> 0.45962428 | N10: =G10/G$9 -> 0.44152358 | Q10: =C10/$C10 -> 1 | R10: =D10/$C10 -> 1.2892275 | S10: =E10/$C10 -> 1.3752743 | T10: =F10/$C10 -> 1.4155606 | U10: =G10/$C10 -> 1.5052981
B11: Gross Profit | C11: =C9-C10 -> 3108.513 | D11: =D9-D10 -> 3174.567 | E11: =E9-E10 -> 3794.206 | F11: =F9-F10 -> 4048.878 | G11: =G9-G10 -> 4632.195 | J11: =C11/C$9 -> 0.56096653 | K11: =D11/D$9 -> 0.50301725 | L11: =E11/E$9 -> 0.53139939 | M11: =F11/F$9 -> 0.54037572 | N11: =G11/G$9 -> 0.55847642 | Q11: =C11/$C11 -> 1 | R11: =D11/$C11 -> 1.0212494 | S11: =E11/$C11 -> 1.2205855 | T11: =F11/$C11 -> 1.3025128 | U11: =G11/$C11 -> 1.4901643
B13: Operating expenses
B14: Selling, general and administrative expenses
B15: Other operating charges | C15: 1311.046 | D15: 1589.846 | E15: 1840.851 | F15: 2118.584 | G15: 2212.841 | J15: =C15/C$9 -> 0.23659316 | K15: =D15/D$9 -> 0.25191466 | L15: =E15/E$9 -> 0.25782129 | M15: =F15/F$9 -> 0.28275274 | N15: =G15/G$9 -> 0.26678918 | Q15: =C15/$C15 -> 1 | R15: =D15/$C15 -> 1.2126546 | S15: =E15/$C15 -> 1.4041086 | T15: =F15/$C15 -> 1.6159494 | U15: =G15/$C15 -> 1.6878439
B16: Total Oper. Exp | C16: =+C14+C15 -> 1311.046 | D16: =+D14+D15 -> 1589.846 | E16: =+E14+E15 -> 1840.851 | F16: =+F14+F15 -> 2118.584 | G16: =+G14+G15 -> 2212.841 | J16: =C16/C$9 -> 0.23659316 | K16: =D16/D$9 -> 0.25191466 | L16: =E16/E$9 -> 0.25782129 | M16: =F16/F$9 -> 0.28275274 | N16: =G16/G$9 -> 0.26678918 | Q16: =C16/$C16 -> 1 | R16: =D16/$C16 -> 1.2126546 | S16: =E16/$C16 -> 1.4041086 | T16: =F16/$C16 -> 1.6159494 | U16: =G16/$C16 -> 1.6878439
B18: Operating Income (EBIT) | C18: =C11-C16 -> 1797.467 | D18: =D11-D16 -> 1584.721 | E18: =E11-E16 -> 1953.355 | F18: =F11-F16 -> 1930.294 | G18: =G11-G16 -> 2419.354 | J18: =C18/C$9 -> 0.32437337 | K18: =D18/D$9 -> 0.25110259 | L18: =E18/E$9 -> 0.2735781 | M18: =F18/F$9 -> 0.25762298 | N18: =G18/G$9 -> 0.29168724 | Q18: =C18/$C18 -> 1 | R18: =D18/$C18 -> 0.88164122 | S18: =E18/$C18 -> 1.0867265 | T18: =F18/$C18 -> 1.0738968 | U18: =G18/$C18 -> 1.3459796
B19: Interest income
B20: Interest income / (expense) | C20: -3.952 | D20: 12.757 | E20: -115.127 | F20: -59.165 | G20: -63.175 | J20: =C20/C$9 -> -0.00071318335 | K20: =D20/D$9 -> 0.0020213752 | L20: =E20/E$9 -> -0.016124169 | M20: =F20/F$9 -> -0.007896343 | N20: =G20/G$9 -> -0.007616637 | Q20: =C20/$C20 -> 1 | R20: =D20/$C20 -> -3.2279858 | S20: =E20/$C20 -> 29.131326 | T20: =F20/$C20 -> 14.970901 | U20: =G20/$C20 -> 15.985577
B21: Equity income (loss) - net
B22: Other income (loss) - net
B24: Pretax Income | C24: =C18+C19-C20+C21+C22 -> 1801.419 | D24: =D18+D19-D20+D21+D22 -> 1571.964 | E24: =E18+E19-E20+E21+E22 -> 2068.482 | F24: =F18+F19-F20+F21+F22 -> 1989.459 | G24: =G18+G19-G20+G21+G22 -> 2482.529 | J24: =C24/C$9 -> 0.32508655 | K24: =D24/D$9 -> 0.24908121 | L24: =E24/E$9 -> 0.28970227 | M24: =F24/F$9 -> 0.26551932 | N24: =G24/G$9 -> 0.29930387 | Q24: =C24/$C24 -> 1 | R24: =D24/$C24 -> 0.87262541 | S24: =E24/$C24 -> 1.1482515 | T24: =F24/$C24 -> 1.1043844 | U24: =G24/$C24 -> 1.3780964
B25: Provision for income taxes | C25: 423.944 | D25: 380.34 | E25: 437.494 | F25: 480.411 | G25: 577.097 | J25: =C25/C$9 -> 0.076505517 | K25: =D25/D$9 -> 0.060265724 | L25: =E25/E$9 -> 0.061273438 | M25: =F25/F$9 -> 0.06411713 | N25: =G25/G$9 -> 0.06957718 | Q25: =C25/$C25 -> 1 | R25: =D25/$C25 -> 0.89714679 | S25: =E25/$C25 -> 1.0319618 | T25: =F25/$C25 -> 1.1331945 | U25: =G25/$C25 -> 1.3612576
B26: Effective Tax rate | C26: =C25/C24 -> 0.23533892 | D26: =D25/D24 -> 0.24195211 | E26: =E25/E24 -> 0.21150486 | F26: =F25/F24 -> 0.24147821 | G26: =G25/G24 -> 0.23246335 | J26: =C26/C$9 -> 4.2469585e-05 | K26: =D26/D$9 -> 3.8337853e-05 | L26: =E26/E$9 -> 2.9622418e-05 | M26: =F26/F$9 -> 3.2228425e-05 | N26: =G26/G$9 -> 2.8026734e-05 | Q26: =C26/$C26 -> 1 | R26: =D26/$C26 -> 1.0281007 | S26: =E26/$C26 -> 0.89872454 | T26: =F26/$C26 -> 1.026087 | U26: =G26/$C26 -> 0.98778115
B28: Net income | C28: =C24-C25 -> 1377.475 | D28: =D24-D25 -> 1191.624 | E28: =E24-E25 -> 1630.988 | F28: =F24-F25 -> 1509.048 | G28: =G24-G25 -> 1905.432 | J28: =C28/C$9 -> 0.24858103 | K28: =D28/D$9 -> 0.18881549 | L28: =E28/E$9 -> 0.22842883 | M28: =F28/F$9 -> 0.20140219 | N28: =G28/G$9 -> 0.22972669 | Q28: =C28/$C28 -> 1 | R28: =D28/$C28 -> 0.8650785 | S28: =E28/$C28 -> 1.1840418 | T28: =F28/$C28 -> 1.0955175 | U28: =G28/$C28 -> 1.3832788
B30: Number of Shares Outstanding | C30: 528.763 | D30: 526.779 | E30: 1044.887 | F30: 1004.566 | G30: 975.887
B31: Stock Price | C31: 42 | D31: 44 | E31: 44 | F31: 55 | G31: 79
B35: Depreciation and amortization | C35: 5.155 | D35: 61.241 | E35: 68.898 | F35: 80.434 | G35: 114.441
B36: Dividends Paid
B37: Net Cash Provided by Operating Activities
B38: Purchases of property, plant and equipment
B41: MONSTER
B42: COMMON SIZING AND TREND ANALYSIS (in 000's Except Per Share Data)
B43: BALANCE SHEET DATA
B44: YOUR NAME | U44: Page 2 of 3
B45: =B5 -> FIN320 Section B
J47: Common-Size Analysis | Q47: Trend Analysis
J48: (as a percentage of total assets) | Q48: (using 2021 as a base year)
B49: Balance Sheet | C49: 2021 | D49: 2022 | E49: 2023 | F49: 2024 | G49: 2025 | J49: 2021 | K49: 2022 | L49: 2023 | M49: 2024 | N49: 2025 | Q49: 2021 | R49: 2022 | S49: 2023 | T49: 2024 | U49: 2025
B50: ASSETS:
B51: Current assets:
B52: Cash/Cash equivalents | C52: 1326.462 | D52: 1307.141 | E52: 2297.675 | F52: 1533.287 | G52: 2088.117 | J52: =C52/C$67 -> 0.16995499 | K52: =D52/D$67 -> 0.1576178 | L52: =E52/E$67 -> 0.2372033 | M52: =F52/F$67 -> 0.19863575 | N52: =G52/G$67 -> 0.2090428 | Q52: =C52/$C52 -> 1 | R52: =D52/$C52 -> 0.98543419 | S52: =E52/$C52 -> 1.7321831 | T52: =F52/$C52 -> 1.1559223 | U52: =G52/$C52 -> 1.5742004
B53: Short-term market sect | C53: 1749.727 | D53: 1362.314 | E53: 955.605 | F53: 0 | G53: 677.084 | J53: =C53/C$67 -> 0.22418647 | K53: =D53/D$67 -> 0.16427068 | L53: =E53/E$67 -> 0.098653056 | M53: =F53/F$67 -> 0 | N53: =G53/G$67 -> 0.067783334 | Q53: =C53/$C53 -> 1 | R53: =D53/$C53 -> 0.7785866 | S53: =E53/$C53 -> 0.5461452 | T53: =F53/$C53 -> 0 | U53: =G53/$C53 -> 0.38696551
B54: Total Cash, Cash Equivalents and Short-Term Investments | C54: =SUM(C52:C53) -> 3076.189 | D54: =SUM(D52:D53) -> 2669.455 | E54: =SUM(E52:E53) -> 3253.28 | F54: =SUM(F52:F53) -> 1533.287 | G54: =SUM(G52:G53) -> 2765.201 | J54: =C54/C$67 -> 0.39414147 | K54: =D54/D$67 -> 0.32188848 | L54: =E54/E$67 -> 0.33585636 | M54: =F54/F$67 -> 0.19863575 | N54: =G54/G$67 -> 0.27682613 | Q54: =C54/$C54 -> 1 | R54: =D54/$C54 -> 0.86777991 | S54: =E54/$C54 -> 1.0575683 | T54: =F54/$C54 -> 0.49843719 | U54: =G54/$C54 -> 0.89890478
B55: Marketable securities
B56: Accounts receivable | C56: 896.658 | D56: 1016.203 | E56: 1193.964 | F56: 1221.646 | G56: 1618.072 | J56: =C56/C$67 -> 0.11488569 | K56: =D56/D$67 -> 0.12253589 | L56: =E56/E$67 -> 0.12326034 | M56: =F56/F$67 -> 0.15826298 | N56: =G56/G$67 -> 0.16198628 | Q56: =C56/$C56 -> 1 | R56: =D56/$C56 -> 1.1333228 | S56: =E56/$C56 -> 1.3315712 | T56: =F56/$C56 -> 1.3624437 | U56: =G56/$C56 -> 1.8045587
B57: Inventories | C57: 593.357 | D57: 935.631 | E57: 971.406 | F57: 737.107 | G57: 799.623 | J57: =C57/C$67 -> 0.076024782 | K57: =D57/D$67 -> 0.11282035 | L57: =E57/E$67 -> 0.10028429 | M57: =F57/F$67 -> 0.09549145 | N57: =G57/G$67 -> 0.080050796 | Q57: =C57/$C57 -> 1 | R57: =D57/$C57 -> 1.5768433 | S57: =E57/$C57 -> 1.6371358 | T57: =F57/$C57 -> 1.2422656 | U57: =G57/$C57 -> 1.3476255
B58: Prepaid expenses and other current assets | C58: 115.906 | D58: 143.608 | E58: 170.346 | F58: 149.464 | G58: 178.188 | J58: =C58/C$67 -> 0.014850635 | K58: =D58/D$67 -> 0.017316554 | L58: =E58/E$67 -> 0.017585879 | M58: =F58/F$67 -> 0.019362907 | N58: =G58/G$67 -> 0.01783852 | Q58: =C58/$C58 -> 1 | R58: =D58/$C58 -> 1.239004 | S58: =E58/$C58 -> 1.469691 | T58: =F58/$C58 -> 1.2895277 | U58: =G58/$C58 -> 1.5373492
B59: Total Current Assets | C59: =SUM(C54:C58) -> 4682.11 | D59: =SUM(D54:D58) -> 4764.897 | E59: =SUM(E54:E58) -> 5588.996 | F59: =SUM(F54:F58) -> 3641.504 | G59: =SUM(G54:G58) -> 5361.084 | J59: =C59/C$67 -> 0.59990257 | K59: =D59/D$67 -> 0.57456128 | L59: =E59/E$67 -> 0.57698687 | M59: =F59/F$67 -> 0.47175308 | N59: =G59/G$67 -> 0.53670172 | Q59: =C59/$C59 -> 1 | R59: =D59/$C59 -> 1.0176816 | S59: =E59/$C59 -> 1.1936917 | T59: =F59/$C59 -> 0.77774849 | U59: =G59/$C59 -> 1.1450145
B60: Equity method investments | C60: 99.419 | D60: 61.443 | E60: 76.431 | F60: 0 | G60: 487.329 | J60: =C60/C$67 -> 0.012738213 | K60: =D60/D$67 -> 0.0074089258 | L60: =E60/E$67 -> 0.0078904482 | M60: =F60/F$67 -> 0 | N60: =G60/G$67 -> 0.048786834 | Q60: =C60/$C60 -> 1 | R60: =D60/$C60 -> 0.6180207 | S60: =E60/$C60 -> 0.76877659 | T60: =F60/$C60 -> 0 | U60: =G60/$C60 -> 4.9017693
B61: Deferred income tax assets | C61: 225.221 | D61: 177.039 | E61: 175.003 | F61: 184.26 | G61: 188.646 | J61: =C61/C$67 -> 0.028856788 | K61: =D61/D$67 -> 0.021347734 | L61: =E61/E$67 -> 0.01806665 | M61: =F61/F$67 -> 0.023870693 | N61: =G61/G$67 -> 0.018885478 | Q61: =C61/$C61 -> 1 | R61: =D61/$C61 -> 0.78606791 | S61: =E61/$C61 -> 0.7770279 | T61: =F61/$C61 -> 0.81812975 | U61: =G61/$C61 -> 0.83760395
B62: PP&E, net | C62: 313.753 | D62: 516.897 | E62: 890.796 | F62: 1047.024 | G62: 1081.544 | J62: =C62/C$67 -> 0.040200088 | K62: =D62/D$67 -> 0.062328525 | L62: =E62/E$67 -> 0.09196242 | M62: =F62/F$67 -> 0.13564088 | N62: =G62/G$67 -> 0.1082741 | Q62: =C62/$C62 -> 1 | R62: =D62/$C62 -> 1.6474647 | S62: =E62/$C62 -> 2.8391633 | T62: =F62/$C62 -> 3.3370964 | U62: =G62/$C62 -> 3.4471192
B63: Trademarks with indefinite lives | C63: 1072.386 | D63: 1220.41 | E63: 1427.139 | F63: 1414.252 | G63: 1379.268 | J63: =C63/C$67 -> 0.13740111 | K63: =D63/D$67 -> 0.1471596 | L63: =E63/E$67 -> 0.14733245 | M63: =F63/F$67 -> 0.18321488 | N63: =G63/G$67 -> 0.13807945 | Q63: =C63/$C63 -> 1 | R63: =D63/$C63 -> 1.1380324 | S63: =E63/$C63 -> 1.3308072 | T63: =F63/$C63 -> 1.3187901 | U63: =G63/$C63 -> 1.2861675
B64: Goodwill | C64: 1331.643 | D64: 1417.941 | E64: 1417.941 | F64: 1331.643 | G64: 1331.643 | J64: =C64/C$67 -> 0.17061882 | K64: =D64/D$67 -> 0.1709783 | L64: =E64/E$67 -> 0.14638288 | M64: =F64/F$67 -> 0.17251297 | N64: =G64/G$67 -> 0.13331168 | Q64: =C64/$C64 -> 1 | R64: =D64/$C64 -> 1.0648057 | S64: =E64/$C64 -> 1.0648057 | T64: =F64/$C64 -> 1 | U64: =G64/$C64 -> 1
B65: Other noncurrent assets | C65: 80.252 | D65: 134.478 | E65: 110.216 | F65: 100.406 | G65: 159.431 | J65: =C65/C$67 -> 0.010282411 | K65: =D65/D$67 -> 0.016215639 | L65: =E65/E$67 -> 0.011378284 | M65: =F65/F$67 -> 0.013007494 | N65: =G65/G$67 -> 0.015960745 | Q65: =C65/$C65 -> 1 | R65: =D65/$C65 -> 1.6756966 | S65: =E65/$C65 -> 1.3733739 | T65: =F65/$C65 -> 1.2511339 | U65: =G65/$C65 -> 1.9866296
B67: Total Assets | C67: =SUM(C59:C65) -> 7804.784 | D67: =SUM(D59:D65) -> 8293.105 | E67: =SUM(E59:E65) -> 9686.522 | F67: =SUM(F59:F65) -> 7719.089 | G67: =SUM(G59:G65) -> 9988.945 | J67: =C67/C$67 -> 1 | K67: =D67/D$67 -> 1 | L67: =E67/E$67 -> 1 | M67: =F67/F$67 -> 1 | N67: =G67/G$67 -> 1 | Q67: =C67/$C67 -> 1 | R67: =D67/$C67 -> 1.0625669 | S67: =E67/$C67 -> 1.2411006 | T67: =F67/$C67 -> 0.9890202 | U67: =G67/$C67 -> 1.279849
B69: LIABILITIES AND SHAREHOLDERS' EQUITY:
B70: Current Liabilities
B71: Accounts payable and accrued expenses | C71: 892.147 | D71: 945.35 | E71: 1104.82 | F71: 1047.704 | G71: 1370.152 | J71: =C71/C$67 -> 0.11430771 | K71: =D71/D$67 -> 0.11399229 | L71: =E71/E$67 -> 0.11405745 | M71: =F71/F$67 -> 0.13572897 | N71: =G71/G$67 -> 0.13716684 | Q71: =C71/$C71 -> 1 | R71: =D71/$C71 -> 1.0596348 | S71: =E71/$C71 -> 1.2383834 | T71: =F71/$C71 -> 1.1743625 | U71: =G71/$C71 -> 1.5357917
B72: Deferred revenue | C72: 42.53 | D72: 43.311 | E72: 41.914 | F72: 45.809 | G72: 45.323
B73: Loans and notes payable
B74: Current maturities of long-term debt
B75: Accrued income taxes | C75: 30.399 | D75: 13.317 | E75: 14.955 | F75: 4.006 | G75: 32.305 | J75: =C75/C$67 -> 0.0038949188 | K75: =D75/D$67 -> 0.0016057918 | L75: =E75/E$67 -> 0.0015438978 | M75: =F75/F$67 -> 0.00051897316 | N75: =G75/G$67 -> 0.0032340753 | Q75: =C75/$C75 -> 1 | R75: =D75/$C75 -> 0.43807362 | S75: =E75/$C75 -> 0.49195697 | T75: =F75/$C75 -> 0.13178065 | U75: =G75/$C75 -> 1.0626994
B76: Total Current Liabilities | C76: =SUM(C71:C75) -> 965.076 | D76: =SUM(D71:D75) -> 1001.978 | E76: =SUM(E71:E75) -> 1161.689 | F76: =SUM(F71:F75) -> 1097.519 | G76: =SUM(G71:G75) -> 1447.78 | J76: =C76/C$67 -> 0.12365185 | K76: =D76/D$67 -> 0.12082061 | L76: =E76/E$67 -> 0.11992839 | M76: =F76/F$67 -> 0.14218245 | N76: =G76/G$67 -> 0.14493823 | Q76: =C76/$C76 -> 1 | R76: =D76/$C76 -> 1.0382374 | S76: =E76/$C76 -> 1.203728 | T76: =F76/$C76 -> 1.1372358 | U76: =G76/$C76 -> 1.500172
B77: Long-term debt | F77: 373.951 | J77: =C77/C$67 -> 0 | K77: =D77/D$67 -> 0 | L77: =E77/E$67 -> 0 | M77: =F77/F$67 -> 0.048444965 | N77: =G77/G$67 -> 0
B78: Deferred revenue | C78: 243.249 | D78: 223.8 | E78: 204.251 | F78: 179.008 | G78: 159.991
B79: Other noncurrent liabilities | C79: 29.508 | D79: 42.286 | E79: 91.838 | F79: 110.893 | G79: 127.066 | J79: =C79/C$67 -> 0.0037807581 | K79: =D79/D$67 -> 0.0050989346 | L79: =E79/E$67 -> 0.0094810088 | M79: =F79/F$67 -> 0.014366074 | N79: =G79/G$67 -> 0.012720663 | Q79: =C79/$C79 -> 1 | R79: =D79/$C79 -> 1.4330351 | S79: =E79/$C79 -> 3.1123085 | T79: =F79/$C79 -> 3.7580656 | U79: =G79/$C79 -> 4.3061543
B80: Deferred income tax liabilities
B81: Total Liabilities | C81: =SUM(C76:C80) -> 1237.833 | D81: =SUM(D76:D80) -> 1268.064 | E81: =SUM(E76:E80) -> 1457.778 | F81: =SUM(F76:F80) -> 1761.371 | G81: =SUM(G76:G80) -> 1734.837 | J81: =C81/C$67 -> 0.15859926 | K81: =D81/D$67 -> 0.15290582 | L81: =E81/E$67 -> 0.1504955 | M81: =F81/F$67 -> 0.22818379 | N81: =G81/G$67 -> 0.1736757 | Q81: =C81/$C81 -> 1 | R81: =D81/$C81 -> 1.0244225 | S81: =E81/$C81 -> 1.1776855 | T81: =F81/$C81 -> 1.4229472 | U81: =G81/$C81 -> 1.4015114
B82: Stockholders equity:
B83: Common stock | C83: 3.2 | D83: 3.209 | E83: 5.613 | F83: 5.632 | G83: 5.665 | J83: =C83/C$67 -> 0.00041000494 | K83: =D83/D$67 -> 0.00038694795 | L83: =E83/E$67 -> 0.00057946495 | M83: =F83/F$67 -> 0.00072961978 | N83: =G83/G$67 -> 0.00056712696 | Q83: =C83/$C83 -> 1 | R83: =D83/$C83 -> 1.0028125 | S83: =E83/$C83 -> 1.7540625 | T83: =F83/$C83 -> 1.76 | U83: =G83/$C83 -> 1.7703125
B84: Capital surplus | C84: 4652.62 | D84: 4780.013 | E84: 4975.115 | F84: 5144.922 | G84: 5430.847 | J84: =C84/C$67 -> 0.59612412 | K84: =D84/D$67 -> 0.576384 | L84: =E84/E$67 -> 0.51361211 | M84: =F84/F$67 -> 0.66651933 | N84: =G84/G$67 -> 0.54368574 | Q84: =C84/$C84 -> 1 | R84: =D84/$C84 -> 1.0273809 | S84: =E84/$C84 -> 1.0693147 | T84: =F84/$C84 -> 1.1058118 | U84: =G84/$C84 -> 1.1672664
B85: Reinvested earnings | C85: 7809.549 | D85: 9001.173 | E85: 5939.736 | F85: 7448.784 | G85: 9354.216 | J85: =C85/C$67 -> 1.0006105 | K85: =D85/D$67 -> 1.0853803 | L85: =E85/E$67 -> 0.61319594 | M85: =F85/F$67 -> 0.96498227 | N85: =G85/G$67 -> 0.93645685 | Q85: =C85/$C85 -> 1 | R85: =D85/$C85 -> 1.1525855 | S85: =E85/$C85 -> 0.7605735 | T85: =F85/$C85 -> 0.95380463 | U85: =G85/$C85 -> 1.1977921
B86: Accumulated other comprehensive income (loss) | C86: -69.165 | D86: -159.073 | E86: -125.337 | F86: -269.487 | G86: -60.841 | J86: =C86/C$67 -> -0.0088618724 | K86: =D86/D$67 -> -0.019181356 | L86: =E86/E$67 -> -0.012939319 | M86: =F86/F$67 -> -0.034911762 | N86: =G86/G$67 -> -0.0060908334 | Q86: =C86/$C86 -> 1 | R86: =D86/$C86 -> 2.299906 | S86: =E86/$C86 -> 1.8121449 | T86: =F86/$C86 -> 3.8962915 | U86: =G86/$C86 -> 0.87965011
B87: Treasury stock | C87: -5829.253 | D87: -6600.281 | E87: -2566.383 | F87: -6372.133 | G87: -6475.779 | J87: =C87/C$67 -> -0.74688204 | K87: =D87/D$67 -> -0.79587573 | L87: =E87/E$67 -> -0.2649437 | M87: =F87/F$67 -> -0.82550324 | N87: =G87/G$67 -> -0.64829459 | Q87: =C87/$C87 -> 1 | R87: =D87/$C87 -> 1.1322687 | S87: =E87/$C87 -> 0.44025933 | T87: =F87/$C87 -> 1.0931303 | U87: =G87/$C87 -> 1.1109106
B88: Total Shareholders' Equity (S/E) | C88: =SUM(C83:C87) -> 6566.951 | D88: =SUM(D83:D87) -> 7025.041 | E88: =SUM(E83:E87) -> 8228.744 | F88: =SUM(F83:F87) -> 5957.718 | G88: =SUM(G83:G87) -> 8254.108 | J88: =C88/C$67 -> 0.84140074 | K88: =D88/D$67 -> 0.84709418 | L88: =E88/E$67 -> 0.8495045 | M88: =F88/F$67 -> 0.77181621 | N88: =G88/G$67 -> 0.8263243 | Q88: =C88/$C88 -> 1 | R88: =D88/$C88 -> 1.0697569 | S88: =E88/$C88 -> 1.253054 | T88: =F88/$C88 -> 0.90722742 | U88: =G88/$C88 -> 1.2569163
B89: Equity Attributable to Noncontrolling Interests
B90: Total Equity | C90: =SUM(C88:C89) -> 6566.951 | D90: =SUM(D88:D89) -> 7025.041 | E90: =SUM(E88:E89) -> 8228.744 | F90: =SUM(F88:F89) -> 5957.718 | G90: =SUM(G88:G89) -> 8254.108 | J90: =C90/C$67 -> 0.84140074 | K90: =D90/D$67 -> 0.84709418 | L90: =E90/E$67 -> 0.8495045 | M90: =F90/F$67 -> 0.77181621 | N90: =G90/G$67 -> 0.8263243 | Q90: =C90/$C90 -> 1 | R90: =D90/$C90 -> 1.0697569 | S90: =E90/$C90 -> 1.253054 | T90: =F90/$C90 -> 0.90722742 | U90: =G90/$C90 -> 1.2569163
B91: Total Liabilities and S/E | C91: =C90+C81 -> 7804.784 | D91: =D90+D81 -> 8293.105 | E91: =E90+E81 -> 9686.522 | F91: =F90+F81 -> 7719.089 | G91: =G90+G81 -> 9988.945 | J91: =C91/C$67 -> 1 | K91: =D91/D$67 -> 1 | L91: =E91/E$67 -> 1 | M91: =F91/F$67 -> 1 | N91: =G91/G$67 -> 1 | Q91: =C91/$C91 -> 1 | R91: =D91/$C91 -> 1.0625669 | S91: =E91/$C91 -> 1.2411006 | T91: =F91/$C91 -> 0.9890202 | U91: =G91/$C91 -> 1.279849
B94: Liquidity ratios | C94: 2021 | D94: 2022 | E94: 2023 | F94: 2024 | G94: 2025
B95: ='FINANCIAL RATIOS'!B15 -> Current Ratio = Current Assets / Current Liabilities | C95: ='FINANCIAL RATIOS'!C16 -> 4.8515454 | D95: ='FINANCIAL RATIOS'!D16 -> 4.7554906 | E95: ='FINANCIAL RATIOS'!E16 -> 4.8110949 | F95: ='FINANCIAL RATIOS'!F16 -> 3.3179416 | G95: ='FINANCIAL RATIOS'!G16 -> 3.7029687
B96: ='FINANCIAL RATIOS'!B23 -> Quick Ratio = (Current Assets - Inventories) / Current Liabilities | C96: ='FINANCIAL RATIOS'!C24 -> 4.2367161 | D96: ='FINANCIAL RATIOS'!D24 -> 3.8217067 | E96: ='FINANCIAL RATIOS'!E24 -> 3.9748935 | F96: ='FINANCIAL RATIOS'!F24 -> 2.6463296 | G96: ='FINANCIAL RATIOS'!G24 -> 3.1506589
B97: ='FINANCIAL RATIOS'!B31 -> Cash Ratio = Cash / Current Liabilities | C97: ='FINANCIAL RATIOS'!C32 -> 1.3744638 | D97: ='FINANCIAL RATIOS'!D32 -> 1.3045606 | E97: ='FINANCIAL RATIOS'!E32 -> 1.9778745 | F97: ='FINANCIAL RATIOS'!F32 -> 1.3970483 | G97: ='FINANCIAL RATIOS'!G32 -> 1.4422889
B98: ='FINANCIAL RATIOS'!B39 -> NWC Ratio = (Current Assets - Current Liabilities) / Total Assets | C98: ='FINANCIAL RATIOS'!C40 -> 0.47625072 | D98: ='FINANCIAL RATIOS'!D40 -> 0.45374067 | E98: ='FINANCIAL RATIOS'!E40 -> 0.45705848 | F98: ='FINANCIAL RATIOS'!F40 -> 0.32957063 | G98: ='FINANCIAL RATIOS'!G40 -> 0.39176349
B99: ='FINANCIAL RATIOS'!B47 -> Interval Measure = Current Assets / Average Daily Costs (COGS + Oper. Exp.) | C99: ='FINANCIAL RATIOS'!C48 -> 456.46972 | D99: ='FINANCIAL RATIOS'!D48 -> 367.97849 | E99: ='FINANCIAL RATIOS'!E48 -> 393.31262 | F99: ='FINANCIAL RATIOS'!F48 -> 238.95178 | G99: ='FINANCIAL RATIOS'!G48 -> 333.07223
B101: Solvency ratios | C101: 2021 | D101: 2022 | E101: 2023 | F101: 2024 | G101: 2025
B102: ='FINANCIAL RATIOS'!B58 -> Total Debt Ratio = Financial Debt / Total Assets | C102: ='FINANCIAL RATIOS'!C59 -> 0 | D102: ='FINANCIAL RATIOS'!D59 -> 0 | E102: ='FINANCIAL RATIOS'!E59 -> 0 | F102: ='FINANCIAL RATIOS'!F59 -> 0.048444965 | G102: ='FINANCIAL RATIOS'!G59 -> 0
B103: ='FINANCIAL RATIOS'!B66 -> Debt-to-Equity Ratio = (Short-term Debt + Long-term Debt) / Total Equity | C103: ='FINANCIAL RATIOS'!C67 -> 0 | D103: ='FINANCIAL RATIOS'!D67 -> 0 | E103: ='FINANCIAL RATIOS'!E67 -> 0 | F103: ='FINANCIAL RATIOS'!F67 -> 0.062767489 | G103: ='FINANCIAL RATIOS'!G67 -> 0
B104: ='FINANCIAL RATIOS'!B74 -> Times Interest Earned = EBIT / Interest Expenses | C104: ='FINANCIAL RATIOS'!C75 -> -454.82465 | D104: ='FINANCIAL RATIOS'!D75 -> 124.22364 | E104: ='FINANCIAL RATIOS'!E75 -> -16.966958 | F104: ='FINANCIAL RATIOS'!F75 -> -32.625606 | G104: ='FINANCIAL RATIOS'!G75 -> -38.296066
B105: ='FINANCIAL RATIOS'!B82 -> Cash Coverage Ratio = (EBIT+Depreciation) / Interest Expenses | C105: ='FINANCIAL RATIOS'!C83 -> -456.12905 | D105: ='FINANCIAL RATIOS'!D83 -> 129.02422 | E105: ='FINANCIAL RATIOS'!E83 -> -17.56541 | F105: ='FINANCIAL RATIOS'!F83 -> -33.985093 | G105: ='FINANCIAL RATIOS'!G83 -> -40.107558
B107: Asset Management / Turnover Ratios | C107: 2021 | D107: 2022 | E107: 2023 | F107: 2024 | G107: 2025
B108: ='FINANCIAL RATIOS'!B93 -> Assets Turnover Ratio = Sales / Total Assets | C108: ='FINANCIAL RATIOS'!C94 -> 0.70999428 | D108: ='FINANCIAL RATIOS'!D94 -> 0.76099965 | E108: ='FINANCIAL RATIOS'!E94 -> 0.73710946 | F108: ='FINANCIAL RATIOS'!F94 -> 0.97067271 | G108: ='FINANCIAL RATIOS'!G94 -> 0.83035225
B109: ='FINANCIAL RATIOS'!B100 -> Inventory Turnover = COGS / Inventories | C109: ='FINANCIAL RATIOS'!C101 -> 4.1001269 | D109: ='FINANCIAL RATIOS'!D101 -> 3.3522649 | E109: ='FINANCIAL RATIOS'!E101 -> 3.4443075 | F109: ='FINANCIAL RATIOS'!F101 -> 4.672091 | G109: ='FINANCIAL RATIOS'!G101 -> 4.5798433
B110: ='FINANCIAL RATIOS'!B107 -> Days Sales in Inventory = 365 / Inventory Turnover | C110: ='FINANCIAL RATIOS'!C108 -> 89.021635 | D110: ='FINANCIAL RATIOS'!D108 -> 108.88161 | E110: ='FINANCIAL RATIOS'!E108 -> 105.97195 | F110: ='FINANCIAL RATIOS'!F108 -> 78.123478 | G110: ='FINANCIAL RATIOS'!G108 -> 79.697051
B111: ='FINANCIAL RATIOS'!B114 -> Receivables Turnover = Sales / Accounts Receivables | C111: ='FINANCIAL RATIOS'!C115 -> 6.1800062 | D111: ='FINANCIAL RATIOS'!D115 -> 6.2104225 | E111: ='FINANCIAL RATIOS'!E115 -> 5.9801024 | F111: ='FINANCIAL RATIOS'!F115 -> 6.1332898 | G111: ='FINANCIAL RATIOS'!G115 -> 5.1260655
B112: ='FINANCIAL RATIOS'!B121 -> Days Sales in Receivables = 365 / Receivables Turnover | C112: ='FINANCIAL RATIOS'!C122 -> 59.061429 | D112: ='FINANCIAL RATIOS'!D122 -> 58.772169 | E112: ='FINANCIAL RATIOS'!E122 -> 61.035744 | F112: ='FINANCIAL RATIOS'!F122 -> 59.511292 | G112: ='FINANCIAL RATIOS'!G122 -> 71.204709
B113: ='FINANCIAL RATIOS'!B128 -> Operating Cycle = Days Sales in Inventory + Days Sales in Receivables | C113: ='FINANCIAL RATIOS'!C129 -> 148.08306 | D113: ='FINANCIAL RATIOS'!D129 -> 167.65378 | E113: ='FINANCIAL RATIOS'!E129 -> 167.0077 | F113: ='FINANCIAL RATIOS'!F129 -> 137.63477 | G113: ='FINANCIAL RATIOS'!G129 -> 150.90176
B115: Profitability Ratios | C115: 2021 | D115: 2022 | E115: 2023 | F115: 2024 | G115: 2025
B116: ='FINANCIAL RATIOS'!B139 -> Gross Profit Margin = Gross Profits / Sales | C116: ='FINANCIAL RATIOS'!C140 -> 0.56096653 | D116: ='FINANCIAL RATIOS'!D140 -> 0.50301725 | E116: ='FINANCIAL RATIOS'!E140 -> 0.53139939 | F116: ='FINANCIAL RATIOS'!F140 -> 0.54037572 | G116: ='FINANCIAL RATIOS'!G140 -> 0.55847642
B117: ='FINANCIAL RATIOS'!B147 -> Operating Profit Margin = Operating Profits / Sales | C117: ='FINANCIAL RATIOS'!C148 -> 0.32437337 | D117: ='FINANCIAL RATIOS'!D148 -> 0.25110259 | E117: ='FINANCIAL RATIOS'!E148 -> 0.2735781 | F117: ='FINANCIAL RATIOS'!F148 -> 0.25762298 | G117: ='FINANCIAL RATIOS'!G148 -> 0.29168724
B118: ='FINANCIAL RATIOS'!B155 -> Net Profit Margin = Net Income / Sales | C118: ='FINANCIAL RATIOS'!C156 -> 0.24858103 | D118: ='FINANCIAL RATIOS'!D156 -> 0.18881549 | E118: ='FINANCIAL RATIOS'!E156 -> 0.22842883 | F118: ='FINANCIAL RATIOS'!F156 -> 0.20140219 | G118: ='FINANCIAL RATIOS'!G156 -> 0.22972669
...

Sheet Monster data sheet
I2: CONSOLIDATED BALANCE SHEETS - USD ($) | J2: Dec. 31, 2025 | K2: Dec. 31, 2024 | L2: Dec. 31, 2023 | M2: Dec. 31, 2022 | N2: Dec. 31, 2021 | O2: Dec. 31, 2020
I3: $ in Thousands
I4: CURRENT ASSETS:
I5: Cash and cash equivalents | J5: 2088117 | K5: 1533287 | L5: 2297675 | M5: 1307141 | N5: 1326462 | O5: 1180413
B6: CONSOLIDATED STATEMENTS OF INCOME - USD ($) | C6: 12 Months Ended | I6: Short-term investments | J6: 677084 | K6: 0 | L6: 955605 | M6: 1362314 | N6: 1749727 | O6: 881354
B7: shares in Thousands, $ in Thousands | I7: Accounts receivable, net | J7: 1618072 | K7: 1221646 | L7: 1193964 | M7: 1016203 | N7: 896658 | O7: 666012
B8: Dec. 31, 2025 | C8: Dec. 31, 2025 | D8: Dec. 31, 2024 | E8: Dec. 31, 2023 | F8: Dec. 31, 2022 | G8: Dec. 31, 2021 | I8: Inventories | J8: 799623 | K8: 737107 | L8: 971406 | M8: 935631 | N8: 593357 | O8: 333085
B9: CONSOLIDATED STATEMENTS OF INCOME | I9: Prepaid expenses and other current assets | J9: 103551 | K9: 107262 | L9: 116195 | M9: 109823 | N9: 82668 | O9: 55358
B10: NET SALES | C10: 8294343 | D10: 7492709 | E10: 7140027 | F10: 6311050 | G10: 5541352 | I10: Prepaid income taxes | J10: 74637 | K10: 42202 | L10: 54151 | M10: 33785 | N10: 33238 | O10: 24733
B11: COST OF SALES | C11: 3662148 | D11: 3443831 | E11: 3345821 | F11: 3136483 | G11: 2432839 | I11: Total current assets | J11: 5361084 | K11: 3641504 | L11: 5588996 | M11: 4764897 | N11: 4682110 | O11: 3140955
B12: GROSS PROFIT | C12: 4632195 | D12: 4048878 | E12: 3794206 | F12: 3174567 | G12: 3108513 | I12: INVESTMENTS | J12: 487329 | K12: 0 | L12: 76431 | M12: 61443 | N12: 99419 | O12: 44291
B13: OPERATING EXPENSES | C13: 2212841 | D13: 2118584 | E13: 1840851 | F13: 1589846 | G13: 1311046 | I13: PROPERTY AND EQUIPMENT, net | J13: 1081544 | K13: 1047024 | L13: 890796 | M13: 516897 | N13: 313753 | O13: 314656
B14: OPERATING INCOME | C14: 2419354 | D14: 1930294 | E14: 1953355 | F14: 1584721 | G14: 1797467 | I14: DEFERRED INCOME TAXES, net | J14: 188646 | K14: 184260 | L14: 175003 | M14: 177039 | N14: 225221 | O14: 241650
B15: INTEREST AND OTHER INCOME, NET | C15: 63175 | D15: 59165 | E15: 115127 | F15: -12757 | G15: 3952 | I15: GOODWILL | J15: 1331643 | K15: 1331643 | L15: 1417941 | M15: 1417941 | N15: 1331643 | O15: 1331643
B16: INCOME BEFORE PROVISION FOR INCOME TAXES | C16: 2482529 | D16: 1989459 | E16: 2068482 | F16: 1571964 | G16: 1801419 | I16: OTHER INTANGIBLE ASSETS, net | J16: 1379268 | K16: 1414252 | L16: 1427139 | M16: 1220410 | N16: 1072386 | O16: 1059046
B17: PROVISION FOR INCOME TAXES | C17: 577097 | D17: 480411 | E17: 437494 | F17: 380340 | G17: 423944 | I17: OTHER ASSETS | J17: 159431 | K17: 100406 | L17: 110216 | M17: 134478 | N17: 80252 | O17: 70475
B18: NET INCOME | C18: 1905432 | D18: 1509048 | E18: 1630988 | F18: 1191624 | G18: 1377475 | I18: Total Assets | J18: 9988945 | K18: 7719089 | L18: 9686522 | M18: 8293105 | N18: 7804784 | O18: 6202716
B19: NET INCOME PER COMMON SHARE: | I19: CURRENT LIABILITIES:
B20: Basic (in dollar per share) | C20: 1.95 | D20: 1.5 | E20: 1.56 | F20: 2.26 | G20: 2.61 | I20: Accounts payable | J20: 565974 | K20: 466775 | L20: 564379 | M20: 444265 | N20: 404263 | O20: 296800
B21: Diluted (in dollar per share) | C21: 1.94 | D21: 1.49 | E21: 1.54 | F21: 2.23 | G21: 2.57 | I21: Accrued liabilities | J21: 306085 | K21: 220764 | L21: 183988 | M21: 172991 | N21: 210964 | O21: 142653
B22: Basic (in shares) | C22: 975887 | D22: 1004566 | E22: 1044887 | F22: 526779 | G22: 528763 | I22: Accrued promotional allowances | J22: 384070 | K22: 267711 | L22: 269061 | M22: 255631 | N22: 211461 | O22: 186658
B23: Diluted (in shares) | C23: 984451 | D23: 1013107 | E23: 1057981 | F23: 533221 | G23: 535639 | I23: Deferred revenue | J23: 45323 | K23: 45809 | L23: 41914 | M23: 43311 | N23: 42530 | O23: 45429
I24: Accrued compensation | J24: 114023 | K24: 92454 | L24: 87392 | M24: 72463 | N24: 65459 | O24: 55015
I25: Income taxes payable | J25: 32305 | K25: 4006 | L25: 14955 | M25: 13317 | N25: 30399 | O25: 23433
I26: Total current liabilities | J26: 1447780 | K26: 1097519 | L26: 1161689 | M26: 1001978 | N26: 965076 | O26: 749988
I27: DEFERRED REVENUE | J27: 159991 | K27: 179008 | L27: 204251 | M27: 223800 | N27: 243249 | O27: 264436
I28: OTHER LIABILITIES | J28: 127066 | K28: 110893 | L28: 91838 | M28: 42286 | N28: 29508 | O28: 27432
I29: LONG-TERM DEBT | K29: 373951
I30: COMMITMENTS AND CONTINGENCIES (Note 10)
I31: STOCKHOLDERS' EQUITY:
I32: Common stock - $0.005 par value; 5,000,000 shares authorized; 1,132,906 shares issued and 978,113 shares outstanding as of December 31, 2025; 1,126,329 shares issued and 973,079 shares outstanding as of December 31, 2024 | J32: 5665 | K32: 5632 | L32: 5613 | M32: 3209 | N32: 3200 | O32: 3193
I33: Additional paid-in capital | J33: 5430847 | K33: 5144922 | L33: 4975115 | M33: 4780013 | N33: 4652620 | O33: 4537982
I34: Retained earnings | J34: 9354216 | K34: 7448784 | L34: 5939736 | M34: 9001173 | N34: 7809549 | O34: 6432074
I35: Accumulated other comprehensive loss | J35: -60841 | K35: -269487 | L35: -125337 | M35: -159073 | N35: -69165 | O35: 3034
I36: Common stock in treasury, at cost; 154,793 shares and 153,250 shares as of December 31, 2025 and December 31, 2024, respectively | J36: -6475779 | K36: -6372133 | L36: -2566383 | M36: -6600281 | N36: -5829253 | O36: -5815423
I37: Total stockholders' equity | J37: 8254108 | K37: 5957718 | L37: 8228744 | M37: 7025041 | N37: 6566951 | O37: 5160860
I38: Total Liabilities and Stockholders' Equity | J38: 9988945 | K38: 7719089 | L38: 9686522 | M38: 8293105 | N38: 7804784 | O38: 6202716

Sheet PepsiCo (PEP)
A1: PEPSI CO
A2: COMMON SIZING AND TREND ANALYSIS (in 000's Except Per Share Data)
A3: INCOME STATEMENT DATA
I4: Common-Size Analysis | P4: Trend Analysis
I5: (as a percentage of sales) | P5: (using 2020 as the base year)
A6: Income Statement | B6: 2021 | C6: 2022 | D6: 2023 | E6: 2024 | F6: 2025 | I6: 2021 | J6: 2022 | K6: 2023 | L6: 2024 | M6: 2025 | P6: 2021 | Q6: 2022 | R6: 2023 | S6: 2024 | T6: 2025
A7: Revenue | B7: 79474 | C7: 86392 | D7: 91471 | E7: 91854 | F7: 93925 | I7: =B7/$B$7 -> 1 | J7: =C7/$C$7 -> 1 | K7: =D7/$D$7 -> 1 | L7: =E7/$E$7 -> 1 | M7: =F7/$F$7 -> 1 | P7: =B7/$B$7 -> 1 | Q7: =C7/$B$7 -> 1.0870473 | R7: =D7/$B$7 -> 1.150955 | S7: =E7/$B$7 -> 1.1557742 | T7: =F7/$B$7 -> 1.1818331
A8: Cost of sales | B8: 37075 | C8: 40576 | D8: 41881 | E8: 41744 | F8: 43066 | I8: =B8/$B$7 -> 0.46650477 | J8: =C8/$C$7 -> 0.46967312 | K8: =D8/$D$7 -> 0.45786096 | L8: =E8/$E$7 -> 0.45446034 | M8: =F8/$F$7 -> 0.45851477 | P8: =B8/$B$8 -> 1 | Q8: =C8/$B$8 -> 1.0944302 | R8: =D8/$B$8 -> 1.1296291 | S8: =E8/$B$8 -> 1.1259339 | T8: =F8/$B$8 -> 1.1615914
A9: Gross Profit | B9: 42399 | C9: 45816 | D9: 49590 | E9: 50110 | F9: 50859 | I9: =B9/$B$7 -> 0.53349523 | J9: =C9/$C$7 -> 0.53032688 | K9: =D9/$D$7 -> 0.54213904 | L9: =E9/$E$7 -> 0.54553966 | M9: =F9/$F$7 -> 0.54148523 | P9: =B9/$B$9 -> 1 | Q9: =C9/$B$9 -> 1.0805915 | R9: =D9/$B$9 -> 1.1696031 | S9: =E9/$B$9 -> 1.1818675 | T9: =F9/$B$9 -> 1.199533
A11: Operating expenses
A12: SGA | B12: 31237 | C12: 34459 | D12: 36677 | E12: 37190 | F12: 37368 | I12: =B12/$B$7 -> 0.39304678 | J12: =C12/$C$7 -> 0.39886795 | K12: =D12/$D$7 -> 0.40096861 | L12: =E12/$E$7 -> 0.40488166 | M12: =F12/$F$7 -> 0.39784935 | P12: =B12/$B$12 -> 1 | Q12: =C12/$B$12 -> 1.1031469 | R12: =D12/$B$12 -> 1.1741524 | S12: =E12/$B$12 -> 1.1905753 | T12: =F12/$B$12 -> 1.1962736
A13: Impairment of Intangible Assets (Excluding Goodwill) | B13: 0 | C13: 3166 | D13: 927 | E13: 33 | F13: 1993 | I13: =B13/$B$7 -> 0 | J13: =C13/$C$7 -> 0.036646912 | K13: =D13/$D$7 -> 0.01013436 | L13: =E13/$E$7 -> 0.00035926579 | M13: =F13/$F$7 -> 0.021219058 | P13: =B13/$B$12 -> 0 | Q13: =C13/$B$12 -> 0.10135416 | R13: =D13/$B$12 -> 0.029676345 | S13: =E13/$B$12 -> 0.0010564395 | T13: =F13/$B$12 -> 0.063802542
A14: Gain associated with the Juice Transaction | B14: 0 | C14: -3321 | D14: 0 | E14: 0 | F14: 0 | I14: =B14/$B$7 -> 0 | J14: =C14/$C$7 -> -0.038441059 | K14: =D14/$D$7 -> 0 | L14: =E14/$E$7 -> 0 | M14: =F14/$F$7 -> 0 | P14: =B14/$B$12 -> 0 | Q14: =C14/$B$12 -> -0.10631623 | R14: =D14/$B$12 -> 0 | S14: =E14/$B$12 -> 0 | T14: =F14/$B$12 -> 0
A15: Total Oper. Exp | B15: =SUM(B12:B14) -> 31237 | C15: =SUM(C12:C14) -> 34304 | D15: =SUM(D12:D14) -> 37604 | E15: =SUM(E12:E14) -> 37223 | F15: =SUM(F12:F14) -> 39361
P16: =B16/$B$12 -> 0 | Q16: =C16/$B$12 -> 0 | R16: =D16/$B$12 -> 0 | S16: =E16/$B$12 -> 0 | T16: =F16/$B$12 -> 0
A17: Operating Income (EBIT) | B17: 11162 | C17: 11512 | D17: 11986 | E17: 12887 | F17: 11498 | I17: =B17/$B$7 -> 0.14044845 | J17: =C17/$C$7 -> 0.13325308 | K17: =D17/$D$7 -> 0.13103607 | L17: =E17/$E$7 -> 0.14029873 | M17: =F17/$F$7 -> 0.12241682 | P17: =B17/$B$17 -> 1 | Q17: =C17/$B$17 -> 1.0313564 | R17: =D17/$B$17 -> 1.0738219 | S17: =E17/$B$17 -> 1.1545422 | T17: =F17/$B$17 -> 1.0301021
A18: Interest Expense | B18: 1863 | C18: 939 | D18: 819 | E18: 919 | F18: 1121 | I18: =B18/$B$7 -> 0.023441629 | J18: =C18/$C$7 -> 0.010869062 | K18: =D18/$D$7 -> 0.0089536574 | L18: =E18/$E$7 -> 0.010005008 | M18: =F18/$F$7 -> 0.011935055 | P18: =B18/$B$18 -> 1 | Q18: =C18/$B$18 -> 0.50402576 | R18: =D18/$B$18 -> 0.43961353 | S18: =E18/$B$18 -> 0.49329039 | T18: =F18/$B$18 -> 0.60171766
A19: Other expenses (net) | B19: 522 | C19: 132 | D19: 250 | E19: -22 | F19: -133 | I19: =B19/$B$7 -> 0.0065681858 | J19: =C19/$C$7 -> 0.0015279193 | K19: =D19/$D$7 -> 0.0027331067 | L19: =E19/$E$7 -> -0.00023951053 | M19: =F19/$F$7 -> -0.0014160234 | P19: =B19/$B$19 -> 1 | Q19: =C19/$B$19 -> 0.25287356 | R19: =D19/$B$19 -> 0.4789272 | S19: =E19/$B$19 -> -0.042145594 | T19: =F19/$B$19 -> -0.25478927
A21: Pretax Income | B21: 9821 | C21: 10705 | D21: 11417 | E21: 11946 | F21: 10244 | I21: =B21/$B$7 -> 0.12357501 | J21: =C21/$C$7 -> 0.12391194 | K21: =D21/$D$7 -> 0.12481552 | L21: =E21/$E$7 -> 0.13005422 | M21: =F21/$F$7 -> 0.10906574 | P21: =B21/$B$21 -> 1 | Q21: =C21/$B$21 -> 1.0900112 | R21: =D21/$B$21 -> 1.1625089 | S21: =E21/$B$21 -> 1.2163731 | T21: =F21/$B$21 -> 1.043071
A22: Provision for income taxes | B22: 2142 | C22: 1727 | D22: 2262 | E22: 2320 | F22: 1949 | I22: =B22/$B$7 -> 0.026952211 | J22: =C22/$C$7 -> 0.019990277 | K22: =D22/$D$7 -> 0.024729149 | L22: =E22/$E$7 -> 0.025257474 | M22: =F22/$F$7 -> 0.020750599 | P22: =B22/$B$22 -> 1 | Q22: =C22/$B$22 -> 0.80625584 | R22: =D22/$B$22 -> 1.0560224 | S22: =E22/$B$22 -> 1.0830999 | T22: =F22/$B$22 -> 0.90989729
A23: Effective Tax rate | B23: =B22/B21 -> 0.21810406 | C23: =C22/C21 -> 0.16132648 | D23: =D22/D21 -> 0.1981256 | E23: =E22/E21 -> 0.19420727 | F23: =F22/F21 -> 0.19025771
A25: Net income | B25: 7679 | C25: 8978 | D25: 9155 | E25: 9626 | F25: 8295 | I25: =B25/$B$7 -> 0.096622795 | J25: =C25/$C$7 -> 0.10392166 | K25: =D25/$D$7 -> 0.10008637 | L25: =E25/$E$7 -> 0.10479674 | M25: =F25/$F$7 -> 0.088315145 | P25: =B25/$B$25 -> 1 | Q25: =C25/$B$25 -> 1.1691627 | R25: =D25/$B$25 -> 1.1922125 | S25: =E25/$B$25 -> 1.2535486 | T25: =F25/$B$25 -> 1.0802188
A27: Number of Shares Outstanding | B27: 1382 | C27: 1380 | D27: 1376 | E27: 1373 | F27: 1369
A28: Stock Price | B28: 151.88 | C28: 162.18 | D28: 156.85 | E28: 144.92 | F28: 142.25
A30: Depreciation and amortization | B30: 2710 | C30: 2763 | D30: 2948 | E30: 3160 | F30: 3451
A31: Dividends Paid | B31: 5815 | C31: 6172 | D31: 6682 | E31: 7229 | F31: 7638
A32: Net Cash Provided by Operating Activities | B32: 11616 | C32: 10811 | D32: 13442 | E32: 12507 | F32: 12087
A33: Purchases of property, plant and equipment | B33: 4459 | C33: 4956 | D33: 5320 | E33: 4976 | F33: 3887
A34: Free cash flow | B34: =B32-B33 -> 7157 | C34: =C32-C33 -> 5855 | D34: =D32-D33 -> 8122 | E34: =E32-E33 -> 7531 | F34: =F32-F33 -> 8200
A45: PEPSI CO
A46: COMMON SIZING AND TREND ANALYSIS (in 000's Except Per Share Data)
A47: BALANCE SHEET DATA
I49: Common-Size Analysis | P49: Trend Analysis
I50: (as a percentage of total assets) | P50: (using 2020 as a base year)
A51: Balance Sheet | B51: 2021 | C51: 2022 | D51: 2023 | E51: 2024 | F51: 2025 | I51: 2021 | J51: 2022 | K51: 2023 | L51: 2024 | M51: 2025 | P51: 2021 | Q51: 2022 | R51: 2023 | S51: 2024 | T51: 2025
A52: ASSETS:
A53: Current assets:
A54: Cash/Cash equivalents | B54: ='Pepsi data sheet'!B32 -> 5596 | C54: ='Pepsi data sheet'!C32 -> 4964 | D54: ='Pepsi data sheet'!D32 -> 9711 | E54: ='Pepsi data sheet'!E32 -> 8505 | F54: ='Pepsi data sheet'!F32 -> 9159 | I54: =B54/$B$68 -> 0.060577849 | J54: =C54/$C$68 -> 0.053841231 | K54: =D54/$D$68 -> 0.096631673 | L54: =E54/$E$68 -> 0.085505746 | M54: =F54/$F$68 -> 0.085280124 | P54: =B54/$B$54 -> 1 | Q54: =C54/$B$54 -> 0.88706219 | R54: =D54/$B$54 -> 1.7353467 | S54: =E54/$B$54 -> 1.5198356 | T54: =F54/$B$54 -> 1.6367048
A55: Short-term market sect | B55: ='Pepsi data sheet'!B33 -> 392 | C55: ='Pepsi data sheet'!C33 -> 394 | D55: ='Pepsi data sheet'!D33 -> 292 | E55: ='Pepsi data sheet'!E33 -> 761 | F55: ='Pepsi data sheet'!F33 -> 371 | I55: =B55/$B$68 -> 0.0042434805 | J55: =C55/$C$68 -> 0.0042734579 | K55: =D55/$D$68 -> 0.0029056172 | L55: =E55/$E$68 -> 0.0076507787 | M55: =F55/$F$68 -> 0.0034544083 | P55: =B55/$B$55 -> 1 | Q55: =C55/$B$55 -> 1.005102 | R55: =D55/$B$55 -> 0.74489796 | S55: =E55/$B$55 -> 1.9413265 | T55: =F55/$B$55 -> 0.94642857
A56: Accounts receivable | B56: ='Pepsi data sheet'!B34 -> 8680 | C56: ='Pepsi data sheet'!C34 -> 10163 | D56: ='Pepsi data sheet'!D34 -> 10815 | E56: ='Pepsi data sheet'!E34 -> 10333 | F56: ='Pepsi data sheet'!F34 -> 11506 | I56: =B56/$B$68 -> 0.093962783 | J56: =C56/$C$68 -> 0.11023135 | K56: =D56/$D$68 -> 0.10761729 | L56: =E56/$E$68 -> 0.1038837 | M56: =F56/$F$68 -> 0.10713321 | P56: =B56/$B$56 -> 1 | Q56: =C56/$B$56 -> 1.1708525 | R56: =D56/$B$56 -> 1.2459677 | S56: =E56/$B$56 -> 1.1904378 | T56: =F56/$B$56 -> 1.325576
A57: Inventories | B57: ='Pepsi data sheet'!B35 -> 4347 | C57: ='Pepsi data sheet'!C35 -> 5222 | D57: ='Pepsi data sheet'!D35 -> 5334 | E57: ='Pepsi data sheet'!E35 -> 5306 | F57: ='Pepsi data sheet'!F35 -> 5845 | I57: =B57/$B$68 -> 0.047057168 | J57: =C57/$C$68 -> 0.056639587 | K57: =D57/$D$68 -> 0.053077268 | L57: =E57/$E$68 -> 0.053344325 | M57: =F57/$F$68 -> 0.054423226 | P57: =B57/$B$57 -> 1 | Q57: =C57/$B$57 -> 1.2012882 | R57: =D57/$B$57 -> 1.2270531 | S57: =E57/$B$57 -> 1.2206119 | T57: =F57/$B$57 -> 1.3446055
A58: Prepaid expenses and other current assets | B58: ='Pepsi data sheet'!B36 -> 980 | C58: ='Pepsi data sheet'!C36 -> 806 | D58: ='Pepsi data sheet'!D36 -> 798 | E58: ='Pepsi data sheet'!E36 -> 921 | F58: ='Pepsi data sheet'!F36 -> 1068 | I58: =B58/$B$68 -> 0.010608701 | J58: =C58/$C$68 -> 0.00874215 | K58: =D58/$D$68 -> 0.0079406936 | L58: =E58/$E$68 -> 0.0092593523 | M58: =F58/$F$68 -> 0.0099442267 | P58: =B58/$B$58 -> 1 | Q58: =C58/$B$58 -> 0.82244898 | R58: =D58/$B$58 -> 0.81428571 | S58: =E58/$B$58 -> 0.93979592 | T58: =F58/$B$58 -> 1.0897959
A59: Disposal Group, Including Discontinued Operation, Assets | B59: ='Pepsi data sheet'!B37 -> 1788 | C59: ='Pepsi data sheet'!C37 -> 0 | D59: ='Pepsi data sheet'!D37 -> 0 | E59: ='Pepsi data sheet'!E37 -> 0 | F59: ='Pepsi data sheet'!F37 -> 0 | I59: =B59/$B$68 -> 0.019355467 | J59: =C59/$C$68 -> 0 | K59: =D59/$D$68 -> 0 | L59: =E59/$E$68 -> 0 | M59: =F59/$F$68 -> 0 | P59: =B59/$B$59 -> 1 | Q59: =C59/$B$59 -> 0 | R59: =D59/$B$59 -> 0 | S59: =E59/$B$59 -> 0 | T59: =F59/$B$59 -> 0
A60: Total Current Assets | B60: 21783 | C60: 21549 | D60: 26950 | E60: 25826 | F60: 27949 | I60: =B60/$B$68 -> 0.23580545 | J60: =C60/$C$68 -> 0.23372778 | K60: =D60/$D$68 -> 0.26817255 | L60: =E60/$E$68 -> 0.2596439 | M60: =F60/$F$68 -> 0.2602352 | P60: =B60/$B$60 -> 1 | Q60: =C60/$B$60 -> 0.98925768 | R60: =D60/$B$60 -> 1.2372033 | S60: =E60/$B$60 -> 1.1856035 | T60: =F60/$B$60 -> 1.2830648
A61: PP&E, net | B61: ='Pepsi data sheet'!B39 -> 22407 | C61: ='Pepsi data sheet'!C39 -> 24291 | D61: ='Pepsi data sheet'!D39 -> 27039 | E61: ='Pepsi data sheet'!E39 -> 28008 | F61: ='Pepsi data sheet'!F39 -> 29905 | I61: =B61/$B$68 -> 0.24256038 | J61: =C61/$C$68 -> 0.26346844 | K61: =D61/$D$68 -> 0.26905816 | L61: =E61/$E$68 -> 0.28158083 | M61: =F61/$F$68 -> 0.27844766 | P61: =B61/$B$61 -> 1 | Q61: =C61/$B$61 -> 1.0840809 | R61: =D61/$B$61 -> 1.2067211 | S61: =E61/$B$61 -> 1.2499665 | T61: =F61/$B$61 -> 1.3346276
A62: Amortizable Intangible Assets, net | B62: ='Pepsi data sheet'!B40 -> 1538 | C62: ='Pepsi data sheet'!C40 -> 1277 | D62: ='Pepsi data sheet'!D40 -> 1199 | E62: ='Pepsi data sheet'!E40 -> 1102 | F62: ='Pepsi data sheet'!F40 -> 1219 | I62: =B62/$B$68 -> 0.016649166 | J62: =C62/$C$68 -> 0.013850776 | K62: =D62/$D$68 -> 0.011930942 | L62: =E62/$E$68 -> 0.011079051 | M62: =F62/$F$68 -> 0.011350199 | P62: =B62/$B$62 -> 1 | Q62: =C62/$B$62 -> 0.83029909 | R62: =D62/$B$62 -> 0.77958388 | S62: =E62/$B$62 -> 0.71651495 | T62: =F62/$B$62 -> 0.79258778
A63: Goodwill | B63: ='Pepsi data sheet'!B41 -> 18381 | C63: ='Pepsi data sheet'!C41 -> 18202 | D63: ='Pepsi data sheet'!D41 -> 17728 | E63: ='Pepsi data sheet'!E41 -> 17534 | F63: ='Pepsi data sheet'!F41 -> 18916 | I63: =B63/$B$68 -> 0.1989781 | J63: =C63/$C$68 -> 0.19742508 | K63: =D63/$D$68 -> 0.17640679 | L63: =E63/$E$68 -> 0.17627957 | M63: =F63/$F$68 -> 0.17612827 | P63: =B63/$B$63 -> 1 | Q63: =C63/$B$63 -> 0.99026168 | R63: =D63/$B$63 -> 0.96447419 | S63: =E63/$B$63 -> 0.95391981 | T63: =F63/$B$63 -> 1.0291061
A64: Indefinite-lived Intangible Assets (Excluding Goodwill) | B64: ='Pepsi data sheet'!B42 -> 17127 | C64: ='Pepsi data sheet'!C42 -> 14309 | D64: ='Pepsi data sheet'!D42 -> 13730 | E64: ='Pepsi data sheet'!E42 -> 13699 | F64: ='Pepsi data sheet'!F42 -> 13847 | I64: =B64/$B$68 -> 0.18540329 | J64: =C64/$C$68 -> 0.15520028 | K64: =D64/$D$68 -> 0.13662371 | L64: =E64/$E$68 -> 0.13772407 | M64: =F64/$F$68 -> 0.12893044 | P64: =B64/$B$64 -> 1 | Q64: =C64/$B$64 -> 0.83546447 | R64: =D64/$B$64 -> 0.8016582 | S64: =E64/$B$64 -> 0.79984819 | T64: =F64/$B$64 -> 0.80848952
A65: Equity Method Investments | B65: ='Pepsi data sheet'!B43 -> 2350 | C65: ='Pepsi data sheet'!C43 -> 3073 | D65: ='Pepsi data sheet'!D43 -> 2714 | E65: ='Pepsi data sheet'!E43 -> 1985 | F65: ='Pepsi data sheet'!F43 -> 2038 | I65: =B65/$B$68 -> 0.025439233 | J65: =C65/$C$68 -> 0.033330803 | K65: =D65/$D$68 -> 0.027006319 | L65: =E65/$E$68 -> 0.019956367 | M65: =F65/$F$68 -> 0.018975968 | P65: =B65/$B$65 -> 1 | Q65: =C65/$B$65 -> 1.3076596 | R65: =D65/$B$65 -> 1.1548936 | S65: =E65/$B$65 -> 0.84468085 | T65: =F65/$B$65 -> 0.86723404
A66: Deferred Income Tax Assets, Net | B66: ='Pepsi data sheet'!B44 -> 4310 | C66: ='Pepsi data sheet'!C44 -> 4204 | D66: ='Pepsi data sheet'!D44 -> 4474 | E66: ='Pepsi data sheet'!E44 -> 4362 | F66: ='Pepsi data sheet'!F44 -> 4541 | I66: =B66/$B$68 -> 0.046656635 | J66: =C66/$C$68 -> 0.045598013 | K66: =D66/$D$68 -> 0.044519628 | L66: =E66/$E$68 -> 0.04385374 | M66: =F66/$F$68 -> 0.042281585 | P66: =B66/$B$66 -> 1 | Q66: =C66/$B$66 -> 0.97540603 | R66: =D66/$B$66 -> 1.038051 | S66: =E66/$B$66 -> 1.012065 | T66: =F66/$B$66 -> 1.0535963
A67: Other assets | B67: ='Pepsi data sheet'!B45 -> 4481 | C67: ='Pepsi data sheet'!C45 -> 5292 | D67: ='Pepsi data sheet'!D45 -> 6661 | E67: ='Pepsi data sheet'!E45 -> 6951 | F67: ='Pepsi data sheet'!F45 -> 8984 | I67: =B67/$B$68 -> 0.048507745 | J67: =C67/$C$68 -> 0.057398831 | K67: =D67/$D$68 -> 0.066281905 | L67: =E67/$E$68 -> 0.069882474 | M67: =F67/$F$68 -> 0.083650686 | P67: =B67/$B$67 -> 1 | Q67: =C67/$B$67 -> 1.1809864 | R67: =D67/$B$67 -> 1.4864985 | S67: =E67/$B$67 -> 1.5512162 | T67: =F67/$B$67 -> 2.0049096
A68: Total Assets | B68: 92377 | C68: 92197 | D68: 100495 | E68: 99467 | F68: 107399 | I68: =B68/$B$68 -> 1 | J68: =C68/$C$68 -> 1 | K68: =D68/$D$68 -> 1 | L68: =E68/$E$68 -> 1 | M68: =F68/$F$68 -> 1 | P68: =B68/$B$68 -> 1 | Q68: =C68/$B$68 -> 0.99805146 | R68: =D68/$B$68 -> 1.087879 | S68: =E68/$B$68 -> 1.0767507 | T68: =F68/$B$68 -> 1.1626162
A70: LIABILITIES AND SHAREHOLDERS' EQUITY:
A71: Current Liabilities
A72: Short-term debt obligations | B72: ='Pepsi data sheet'!B48 -> 4308 | C72: ='Pepsi data sheet'!C48 -> 3414 | D72: ='Pepsi data sheet'!D48 -> 6510 | E72: ='Pepsi data sheet'!E48 -> 7082 | F72: ='Pepsi data sheet'!F48 -> 6861 | I72: =B72/$B$68 -> 0.046634985 | J72: =C72/$C$68 -> 0.037029404 | K72: =D72/$D$68 -> 0.064779342 | L72: =E72/$E$68 -> 0.071199493 | M72: =F72/$F$68 -> 0.063883276 | P72: =B72/$B$72 -> 1 | Q72: =C72/$B$72 -> 0.79247911 | R72: =D72/$B$72 -> 1.5111421 | S72: =E72/$B$72 -> 1.6439183 | T72: =F72/$B$72 -> 1.5926184
A73: Accounts payable | B73: ='Pepsi data sheet'!B49 -> 21159 | C73: ='Pepsi data sheet'!C49 -> 23371 | D73: ='Pepsi data sheet'!D49 -> 25137 | E73: ='Pepsi data sheet'!E49 -> 24454 | F73: ='Pepsi data sheet'!F49 -> 25903 | I73: =B73/$B$68 -> 0.22905052 | J73: =C73/$C$68 -> 0.25348981 | K73: =D73/$D$68 -> 0.25013185 | L73: =E73/$E$68 -> 0.24585038 | M73: =F73/$F$68 -> 0.24118474 | P73: =B73/$B$73 -> 1 | Q73: =C73/$B$73 -> 1.1045418 | R73: =D73/$B$73 -> 1.1880051 | S73: =E73/$B$73 -> 1.1557257 | T73: =F73/$B$73 -> 1.2242072
A74: Disposal Group, Including Discontinued Operation, Liabilities | B74: ='Pepsi data sheet'!B50 -> 753 | C74: ='Pepsi data sheet'!C50 -> 0 | D74: ='Pepsi data sheet'!D50 -> 0 | E74: ='Pepsi data sheet'!E50 -> 0 | F74: ='Pepsi data sheet'!F50 -> 0 | I74: =B74/$B$68 -> 0.0081513797 | J74: =C74/$C$68 -> 0 | K74: =D74/$D$68 -> 0 | L74: =E74/$E$68 -> 0 | M74: =F74/$F$68 -> 0 | P74: =B74/$B$74 -> 1 | Q74: =C74/$B$74 -> 0 | R74: =D74/$B$74 -> 0 | S74: =E74/$B$74 -> 0 | T74: =F74/$B$74 -> 0
A75: Short-term debt | I75: =B75/$B$68 -> 0 | J75: =C75/$C$68 -> 0 | K75: =D75/$D$68 -> 0 | L75: =E75/$E$68 -> 0 | M75: =F75/$F$68 -> 0 | P75: =B75/$B$68 -> 0 | Q75: =C75/$B$68 -> 0 | R75: =D75/$B$68 -> 0 | S75: =E75/$B$68 -> 0 | T75: =F75/$B$68 -> 0
A76: Other current liabilities | I76: =B76/$B$68 -> 0 | J76: =C76/$C$68 -> 0 | K76: =D76/$D$68 -> 0 | L76: =E76/$E$68 -> 0 | M76: =F76/$F$68 -> 0 | P76: =B76/$B$68 -> 0 | Q76: =C76/$B$68 -> 0 | R76: =D76/$B$68 -> 0 | S76: =E76/$B$68 -> 0 | T76: =F76/$B$68 -> 0
A77: Total Current Liabilities | B77: =SUM(B72:B74) -> 26220 | C77: =SUM(C72:C74) -> 26785 | D77: =SUM(D72:D74) -> 31647 | E77: =SUM(E72:E74) -> 31536 | F77: =SUM(F72:F74) -> 32764 | I77: =B77/$B$68 -> 0.28383689 | J77: =C77/$C$68 -> 0.29051921 | K77: =D77/$D$68 -> 0.31491119 | L77: =E77/$E$68 -> 0.31704988 | M77: =F77/$F$68 -> 0.30506802 | P77: =B77/$B$77 -> 1 | Q77: =C77/$B$77 -> 1.0215484 | R77: =D77/$B$77 -> 1.2069794 | S77: =E77/$B$77 -> 1.202746 | T77: =F77/$B$77 -> 1.2495805
A78: Long-term debt | B78: ='Pepsi data sheet'!B52 -> 36026 | C78: ='Pepsi data sheet'!C52 -> 35657 | D78: ='Pepsi data sheet'!D52 -> 37595 | E78: ='Pepsi data sheet'!E52 -> 37224 | F78: ='Pepsi data sheet'!F52 -> 42321 | I78: =B78/$B$68 -> 0.38998885 | J78: =C78/$C$68 -> 0.38674794 | K78: =D78/$D$68 -> 0.37409821 | L78: =E78/$E$68 -> 0.37423467 | M78: =F78/$F$68 -> 0.39405395 | P78: =B78/$B$78 -> 1 | Q78: =C78/$B$78 -> 0.9897574 | R78: =D78/$B$78 -> 1.0435519 | S78: =E78/$B$78 -> 1.0332538 | T78: =F78/$B$78 -> 1.1747349
A79: Deferred Income Tax Liabilities, Net | B79: ='Pepsi data sheet'!B53 -> 4826 | C79: ='Pepsi data sheet'!C53 -> 4133 | D79: ='Pepsi data sheet'!D53 -> 3895 | E79: ='Pepsi data sheet'!E53 -> 3484 | F79: ='Pepsi data sheet'!F53 -> 3802 | I79: =B79/$B$68 -> 0.052242441 | J79: =C79/$C$68 -> 0.044827923 | K79: =D79/$D$68 -> 0.038758147 | L79: =E79/$E$68 -> 0.035026692 | M79: =F79/$F$68 -> 0.035400702 | P79: =B79/$B$79 -> 1 | Q79: =C79/$B$79 -> 0.85640282 | R79: =D79/$B$79 -> 0.80708661 | S79: =E79/$B$79 -> 0.72192292 | T79: =F79/$B$79 -> 0.787816
A80: Other non-current liabilities | B80: ='Pepsi data sheet'!B54 -> 9154 | C80: ='Pepsi data sheet'!C54 -> 8339 | D80: ='Pepsi data sheet'!D54 -> 8721 | E80: ='Pepsi data sheet'!E54 -> 9052 | F80: ='Pepsi data sheet'!F54 -> 7965 | I80: =B80/$B$68 -> 0.09909393 | J80: =C80/$C$68 -> 0.090447628 | K80: =D80/$D$68 -> 0.086780437 | L80: =E80/$E$68 -> 0.091005057 | M80: =F80/$F$68 -> 0.074162702 | P80: =B80/$B$80 -> 1 | Q80: =C80/$B$80 -> 0.91096788 | R80: =D80/$B$80 -> 0.95269827 | S80: =E80/$B$80 -> 0.98885733 | T80: =F80/$B$80 -> 0.87011143
A81: Total Liabilities | B81: =SUM(B78:B80) -> 50006 | C81: =SUM(C78:C80) -> 48129 | D81: =SUM(D78:D80) -> 50211 | E81: =SUM(E78:E80) -> 49760 | F81: =SUM(F78:F80) -> 54088 | I81: =B81/$B$68 -> 0.54132522 | J81: =C81/$C$68 -> 0.52202349 | K81: =D81/$D$68 -> 0.4996368 | L81: =E81/$E$68 -> 0.50026642 | M81: =F81/$F$68 -> 0.50361735 | P81: =B81/$B$81 -> 1 | Q81: =C81/$B$81 -> 0.9624645 | R81: =D81/$B$81 -> 1.0040995 | S81: =E81/$B$81 -> 0.99508059 | T81: =F81/$B$81 -> 1.0816302
A82: Stockholders equity: | I82: =B82/$B$68 -> 0 | J82: =C82/$C$68 -> 0 | K82: =D82/$D$68 -> 0 | L82: =E82/$E$68 -> 0 | M82: =F82/$F$68 -> 0
A83: Common stock, authorized | B83: ='Pepsi data sheet'!B57 -> 3600 | C83: ='Pepsi data sheet'!C57 -> 3600 | D83: ='Pepsi data sheet'!D57 -> 3600 | E83: ='Pepsi data sheet'!E57 -> 3600 | F83: ='Pepsi data sheet'!F57 -> 3600 | I83: =B83/$B$68 -> 0.038970739 | J83: =C83/$C$68 -> 0.039046824 | K83: =D83/$D$68 -> 0.035822678 | L83: =E83/$E$68 -> 0.036192908 | M83: =F83/$F$68 -> 0.033519865 | P83: =B83/$B$83 -> 1 | Q83: =C83/$B$83 -> 1 | R83: =D83/$B$83 -> 1 | S83: =E83/$B$83 -> 1 | T83: =F83/$B$83 -> 1
A84: Common stock, issued | B84: ='Pepsi data sheet'!B58 -> 1383 | C84: ='Pepsi data sheet'!C58 -> 1377 | D84: ='Pepsi data sheet'!D58 -> 1374 | E84: ='Pepsi data sheet'!E58 -> 1372 | F84: ='Pepsi data sheet'!F58 -> 1367 | I84: =B84/$B$68 -> 0.014971259 | J84: =C84/$C$68 -> 0.01493541 | K84: =D84/$D$68 -> 0.013672322 | L84: =E84/$E$68 -> 0.013793519 | M84: =F84/$F$68 -> 0.012728238 | P84: =B84/$B$84 -> 1 | Q84: =C84/$B$84 -> 0.99566161 | R84: =D84/$B$84 -> 0.99349241 | S84: =E84/$B$84 -> 0.99204628 | T84: =F84/$B$84 -> 0.98843095
I85: =B85/$B$68 -> 0 | J85: =C85/$C$68 -> 0 | K85: =D85/$D$68 -> 0 | L85: =E85/$E$68 -> 0 | M85: =F85/$F$68 -> 0
A86: Common stock | B86: ='Pepsi data sheet'!B60 -> 23 | C86: ='Pepsi data sheet'!C60 -> 23 | D86: ='Pepsi data sheet'!D60 -> 23 | E86: ='Pepsi data sheet'!E60 -> 23 | F86: ='Pepsi data sheet'!F60 -> 23 | I86: =B86/$B$68 -> 0.00024897972 | J86: =C86/$C$68 -> 0.00024946582 | K86: =D86/$D$68 -> 0.00022886711 | L86: =E86/$E$68 -> 0.00023123247 | M86: =F86/$F$68 -> 0.00021415469 | P86: =B86/$B$86 -> 1 | Q86: =C86/$B$86 -> 1 | R86: =D86/$B$86 -> 1 | S86: =E86/$B$86 -> 1 | T86: =F86/$B$86 -> 1
A87: Additional Paid in Capital, Common Stock | B87: ='Pepsi data sheet'!B61 -> 4001 | C87: ='Pepsi data sheet'!C61 -> 4134 | D87: ='Pepsi data sheet'!D61 -> 4261 | E87: ='Pepsi data sheet'!E61 -> 4385 | F87: ='Pepsi data sheet'!F61 -> 4451 | I87: =B87/$B$68 -> 0.043311647 | J87: =C87/$C$68 -> 0.044838769 | K87: =D87/$D$68 -> 0.042400119 | L87: =E87/$E$68 -> 0.044084973 | M87: =F87/$F$68 -> 0.041443589 | P87: =B87/$B$87 -> 1 | Q87: =C87/$B$87 -> 1.0332417 | R87: =D87/$B$87 -> 1.0649838 | S87: =E87/$B$87 -> 1.095976 | T87: =F87/$B$87 -> 1.1124719
A88: Retained Earnings (Accumulated Deficit) | B88: ='Pepsi data sheet'!B62 -> 65165 | C88: ='Pepsi data sheet'!C62 -> 67800 | D88: ='Pepsi data sheet'!D62 -> 70035 | E88: ='Pepsi data sheet'!E62 -> 72266 | F88: ='Pepsi data sheet'!F62 -> 72788 | I88: =B88/$B$68 -> 0.70542451 | J88: =C88/$C$68 -> 0.73538185 | K88: =D88/$D$68 -> 0.69690034 | L88: =E88/$E$68 -> 0.72653242 | M88: =F88/$F$68 -> 0.67773443 | P88: =B88/$B$88 -> 1 | Q88: =C88/$B$88 -> 1.0404358 | R88: =D88/$B$88 -> 1.0747334 | S88: =E88/$B$88 -> 1.1089695 | T88: =F88/$B$88 -> 1.11698
A89: Accumulated Other Comprehensive Income (Loss), Net of Tax | B89: ='Pepsi data sheet'!B63 -> -14898 | C89: ='Pepsi data sheet'!C63 -> -15302 | D89: ='Pepsi data sheet'!D63 -> -15534 | E89: ='Pepsi data sheet'!E63 -> -17612 | F89: ='Pepsi data sheet'!F63 -> -15024 | I89: =B89/$B$68 -> -0.16127391 | J89: =C89/$C$68 -> -0.16597069 | K89: =D89/$D$68 -> -0.15457485 | L89: =E89/$E$68 -> -0.17706375 | M89: =F89/$F$68 -> -0.13988957 | P89: =B89/$B$89 -> 1 | Q89: =C89/$B$89 -> 1.0271177 | R89: =D89/$B$89 -> 1.0426903 | S89: =E89/$B$89 -> 1.1821721 | T89: =F89/$B$89 -> 1.0084575
A90: Treasury Stock, Common, Shares | B90: ='Pepsi data sheet'!B64 -> 484 | C90: ='Pepsi data sheet'!C64 -> 490 | D90: ='Pepsi data sheet'!D64 -> 493 | E90: ='Pepsi data sheet'!E64 -> 495 | F90: ='Pepsi data sheet'!F64 -> 500 | I90: =B90/$B$68 -> 0.0052393994 | J90: =C90/$C$68 -> 0.0053147066 | K90: =D90/$D$68 -> 0.0049057167 | L90: =E90/$E$68 -> 0.0049765249 | M90: =F90/$F$68 -> 0.0046555368 | P90: =B90/$B$90 -> 1 | Q90: =C90/$B$90 -> 1.0123967 | R90: =D90/$B$90 -> 1.018595 | S90: =E90/$B$90 -> 1.0227273 | T90: =F90/$B$90 -> 1.0330579
A91: Treasury Stock, Value | B91: ='Pepsi data sheet'!B65 -> -38248 | C91: ='Pepsi data sheet'!C65 -> -39506 | D91: ='Pepsi data sheet'!D65 -> -40282 | E91: ='Pepsi data sheet'!E65 -> -41021 | F91: ='Pepsi data sheet'!F65 -> -41832 | I91: =B91/$B$68 -> -0.41404246 | J91: =C91/$C$68 -> -0.4284955 | K91: =D91/$D$68 -> -0.40083586 | L91: =E91/$E$68 -> -0.41240814 | M91: =F91/$F$68 -> -0.38950083 | P91: =B91/$B$91 -> 1 | Q91: =C91/$B$91 -> 1.0328906 | R91: =D91/$B$91 -> 1.0531793 | S91: =E91/$B$91 -> 1.0725005 | T91: =F91/$B$91 -> 1.0937042
A92: Stockholders' Equity Attributable to Parent | B92: ='Pepsi data sheet'!B66 -> 16043 | C92: ='Pepsi data sheet'!C66 -> 17149 | D92: ='Pepsi data sheet'!D66 -> 18503 | E92: ='Pepsi data sheet'!E66 -> 18041 | F92: ='Pepsi data sheet'!F66 -> 20406 | I92: =B92/$B$68 -> 0.17366877 | J92: =C92/$C$68 -> 0.18600388 | K92: =D92/$D$68 -> 0.18411861 | L92: =E92/$E$68 -> 0.18137674 | M92: =F92/$F$68 -> 0.19000177 | P92: =B92/$B$92 -> 1 | Q92: =C92/$B$92 -> 1.0689397 | R92: =D92/$B$92 -> 1.1533379 | S92: =E92/$B$92 -> 1.1245403 | T92: =F92/$B$92 -> 1.2719566
A93: Stockholders' Equity Attributable to Noncontrolling Interest | B93: ='Pepsi data sheet'!B67 -> 108 | C93: ='Pepsi data sheet'!C67 -> 124 | D93: ='Pepsi data sheet'!D67 -> 134 | E93: ='Pepsi data sheet'!E67 -> 130 | F93: ='Pepsi data sheet'!F67 -> 141 | I93: =B93/$B$68 -> 0.0011691222 | J93: =C93/$C$68 -> 0.0013449461 | K93: =D93/$D$68 -> 0.0013333997 | L93: =E93/$E$68 -> 0.0013069661 | M93: =F93/$F$68 -> 0.0013128614 | P93: =B93/$B$93 -> 1 | Q93: =C93/$B$93 -> 1.1481481 | R93: =D93/$B$93 -> 1.2407407 | S93: =E93/$B$93 -> 1.2037037 | T93: =F93/$B$93 -> 1.3055556
A94: Total Shareholders' Equity (S/E) | B94: =SUM(B92:B93) -> 16151 | C94: =SUM(C92:C93) -> 17273 | D94: =SUM(D92:D93) -> 18637 | E94: =SUM(E92:E93) -> 18171 | F94: =SUM(F92:F93) -> 20547 | I94: =B94/$B$68 -> 0.17483789 | J94: =C94/$C$68 -> 0.18734883 | K94: =D94/$D$68 -> 0.18545201 | L94: =E94/$E$68 -> 0.1826837 | M94: =F94/$F$68 -> 0.19131463 | P94: =B94/$B$94 -> 1 | Q94: =C94/$B$94 -> 1.0694694 | R94: =D94/$B$94 -> 1.1539224 | S94: =E94/$B$94 -> 1.1250697 | T94: =F94/$B$94 -> 1.2721813
A95: Total Liabilities and S/E | B95: =B81+B77+B94 -> 92377 | C95: =C81+C77+C94 -> 92187 | D95: =D81+D77+D94 -> 100495 | E95: =E81+E77+E94 -> 99467 | F95: =F81+F77+F94 -> 107399 | I95: =B95/$B$68 -> 1 | J95: =C95/$C$68 -> 0.99989154 | K95: =D95/$D$68 -> 1 | L95: =E95/$E$68 -> 1 | M95: =F95/$F$68 -> 1 | P95: =B95/$B$95 -> 1 | Q95: =C95/$B$95 -> 0.99794321 | R95: =D95/$B$95 -> 1.087879 | S95: =E95/$B$95 -> 1.0767507 | T95: =F95/$B$95 -> 1.1626162
A103: Liquidity ratios | B103: 2021 | C103: 2022 | D103: 2023 | E103: 2024 | F103: 2025
A104: ='FINANCIAL RATIOS'!B15 -> Current Ratio = Current Assets / Current Liabilities | B104: ='FINANCIAL RATIOS'!C17 -> 0.83077803 | C104: ='FINANCIAL RATIOS'!D17 -> 0.80451745 | D104: ='FINANCIAL RATIOS'!E17 -> 0.85158151 | E104: ='FINANCIAL RATIOS'!F17 -> 0.81893709 | F104: ='FINANCIAL RATIOS'!G17 -> 0.85303992
A105: ='FINANCIAL RATIOS'!B23 -> Quick Ratio = (Current Assets - Inventories) / Current Liabilities | B105: ='FINANCIAL RATIOS'!C25 -> 0.66498856 | C105: ='FINANCIAL RATIOS'!D25 -> 0.60955759 | D105: ='FINANCIAL RATIOS'!E25 -> 0.68303473 | E105: ='FINANCIAL RATIOS'!F25 -> 0.65068493 | F105: ='FINANCIAL RATIOS'!G25 -> 0.6746429
A106: ='FINANCIAL RATIOS'!B31 -> Cash Ratio = Cash / Current Liabilities | B106: ='FINANCIAL RATIOS'!C33 -> 0.21342487 | C106: ='FINANCIAL RATIOS'!D33 -> 0.18532761 | D106: ='FINANCIAL RATIOS'!E33 -> 0.30685373 | E106: ='FINANCIAL RATIOS'!F33 -> 0.26969178 | F106: ='FINANCIAL RATIOS'!G33 -> 0.27954462
A107: ='FINANCIAL RATIOS'!B39 -> NWC Ratio = (Current Assets - Current Liabilities) / Total Assets | B107: ='FINANCIAL RATIOS'!C41 -> -0.048031436 | C107: ='FINANCIAL RATIOS'!D41 -> -0.056791436 | D107: ='FINANCIAL RATIOS'!E41 -> -0.046738644 | E107: ='FINANCIAL RATIOS'!F41 -> -0.057405974 | F107: ='FINANCIAL RATIOS'!G41 -> -0.04483282
A108: ='FINANCIAL RATIOS'!B47 -> Interval Measure = Current Assets / Average Daily Costs (COGS + Oper. Exp.) | B108: ='FINANCIAL RATIOS'!C49 -> 116.38943 | C108: ='FINANCIAL RATIOS'!D49 -> 105.03986 | D108: ='FINANCIAL RATIOS'!E49 -> 123.75605 | E108: ='FINANCIAL RATIOS'!F49 -> 119.37252 | F108: ='FINANCIAL RATIOS'!G49 -> 123.76266
A110: Solvency ratios | B110: 2021 | C110: 2022 | D110: 2023 | E110: 2024 | F110: 2025
A111: ='FINANCIAL RATIOS'!B58 -> Total Debt Ratio = Financial Debt / Total Assets | B111: ='FINANCIAL RATIOS'!C60 -> 0.43662383 | C111: ='FINANCIAL RATIOS'!D60 -> 0.42377735 | D111: ='FINANCIAL RATIOS'!E60 -> 0.43887756 | E111: ='FINANCIAL RATIOS'!F60 -> 0.44543416 | F111: ='FINANCIAL RATIOS'!G60 -> 0.45793722
A112: ='FINANCIAL RATIOS'!B66 -> Debt-to-Equity Ratio = (Short-term Debt + Long-term Debt) / Total Equity | B112: ='FINANCIAL RATIOS'!C68 -> 2.4973067 | C112: ='FINANCIAL RATIOS'!D68 -> 2.2619695 | D112: ='FINANCIAL RATIOS'!E68 -> 2.3665289 | E112: ='FINANCIAL RATIOS'!F68 -> 2.4382808 | F112: ='FINANCIAL RATIOS'!G68 -> 2.3936341
A113: ='FINANCIAL RATIOS'!B74 -> Times Interest Earned = EBIT / Interest Expenses | B113: ='FINANCIAL RATIOS'!C76 -> 5.9914117 | C113: ='FINANCIAL RATIOS'!D76 -> 12.259851 | D113: ='FINANCIAL RATIOS'!E76 -> 14.634921 | E113: ='FINANCIAL RATIOS'!F76 -> 14.022851 | F113: ='FINANCIAL RATIOS'!G76 -> 10.256913
A114: ='FINANCIAL RATIOS'!B82 -> Cash Coverage Ratio = (EBIT+Depreciation) / Interest Expenses | B114: ='FINANCIAL RATIOS'!C84 -> 7.4460548 | C114: ='FINANCIAL RATIOS'!D84 -> 15.202343 | D114: ='FINANCIAL RATIOS'!E84 -> 18.234432 | E114: ='FINANCIAL RATIOS'!F84 -> 17.461371 | F114: ='FINANCIAL RATIOS'!G84 -> 13.335415
A116: Asset Management / Turnover Ratios | B116: 2021 | C116: 2022 | D116: 2023 | E116: 2024 | F116: 2025
A117: ='FINANCIAL RATIOS'!B93 -> Assets Turnover Ratio = Sales / Total Assets | B117: ='FINANCIAL RATIOS'!C95 -> 0.86032237 | C117: ='FINANCIAL RATIOS'!D95 -> 0.937037 | D117: ='FINANCIAL RATIOS'!E95 -> 0.91020449 | E117: ='FINANCIAL RATIOS'!F95 -> 0.92346205 | F117: ='FINANCIAL RATIOS'!G95 -> 0.87454259
A118: ='FINANCIAL RATIOS'!B100 -> Inventory Turnover = COGS / Inventories | B118: ='FINANCIAL RATIOS'!C102 -> 8.5288705 | C118: ='FINANCIAL RATIOS'!D102 -> 7.770203 | D118: ='FINANCIAL RATIOS'!E102 -> 7.851706 | E118: ='FINANCIAL RATIOS'!F102 -> 7.86732 | F118: ='FINANCIAL RATIOS'!G102 -> 7.3680068
A119: ='FINANCIAL RATIOS'!B107 -> Days Sales in Inventory = 365 / Inventory Turnover | B119: ='FINANCIAL RATIOS'!C109 -> 42.795819 | C119: ='FINANCIAL RATIOS'!D109 -> 46.97432 | D119: ='FINANCIAL RATIOS'!E109 -> 46.486712 | E119: ='FINANCIAL RATIOS'!F109 -> 46.394452 | F119: ='FINANCIAL RATIOS'!G109 -> 49.538499
A120: ='FINANCIAL RATIOS'!B114 -> Receivables Turnover = Sales / Accounts Receivables | B120: ='FINANCIAL RATIOS'!C116 -> 9.1559908 | C120: ='FINANCIAL RATIOS'!D116 -> 8.5006396 | D120: ='FINANCIAL RATIOS'!E116 -> 8.4577901 | E120: ='FINANCIAL RATIOS'!F116 -> 8.8893835 | F120: ='FINANCIAL RATIOS'!G116 -> 8.1631323
A121: ='FINANCIAL RATIOS'!B121 -> Days Sales in Receivables = 365 / Receivables Turnover | B121: ='FINANCIAL RATIOS'!C123 -> 39.86461 | C121: ='FINANCIAL RATIOS'!D123 -> 42.937946 | D121: ='FINANCIAL RATIOS'!E123 -> 43.155481 | E121: ='FINANCIAL RATIOS'!F123 -> 41.060215 | F121: ='FINANCIAL RATIOS'!G123 -> 44.713229
A122: ='FINANCIAL RATIOS'!B128 -> Operating Cycle = Days Sales in Inventory + Days Sales in Receivables | B122: ='FINANCIAL RATIOS'!C130 -> 82.660429 | C122: ='FINANCIAL RATIOS'!D130 -> 89.912265 | D122: ='FINANCIAL RATIOS'!E130 -> 89.642193 | E122: ='FINANCIAL RATIOS'!F130 -> 87.454667 | F122: ='FINANCIAL RATIOS'!G130 -> 94.251728
A124: Profitability Ratios | B124: 2021 | C124: 2022 | D124: 2023 | E124: 2024 | F124: 2025
A125: ='FINANCIAL RATIOS'!B139 -> Gross Profit Margin = Gross Profits / Sales | B125: ='FINANCIAL RATIOS'!C141 -> 0.53349523 | C125: ='FINANCIAL RATIOS'!D141 -> 0.53032688 | D125: ='FINANCIAL RATIOS'!E141 -> 0.54213904 | E125: ='FINANCIAL RATIOS'!F141 -> 0.54553966 | F125: ='FINANCIAL RATIOS'!G141 -> 0.54148523
A126: ='FINANCIAL RATIOS'!B147 -> Operating Profit Margin = Operating Profits / Sales | B126: ='FINANCIAL RATIOS'!C149 -> 0.14044845 | C126: ='FINANCIAL RATIOS'!D149 -> 0.13325308 | D126: ='FINANCIAL RATIOS'!E149 -> 0.13103607 | E126: ='FINANCIAL RATIOS'!F149 -> 0.14029873 | F126: ='FINANCIAL RATIOS'!G149 -> 0.12241682
A127: ='FINANCIAL RATIOS'!B155 -> Net Profit Margin = Net Income / Sales | B127: ='FINANCIAL RATIOS'!C157 -> 0.096622795 | C127: ='FINANCIAL RATIOS'!D157 -> 0.10392166 | D127: ='FINANCIAL RATIOS'!E157 -> 0.10008637 | E127: ='FINANCIAL RATIOS'!F157 -> 0.10479674 | F127: ='FINANCIAL RATIOS'!G157 -> 0.088315145
...

Sheet Pepsi data sheet
A1: Consolidated Statement of Income - USD ($) | B1: 12 Months Ended
A2: shares in Millions, $ in Millions
B3: Dec. 25, 2021 | C3: Dec. 31, 2022 | D3: Dec. 30, 2023 | E3: Dec. 28, 2024 | F3: Dec. 27, 2025
A4: Income Statement [Abstract]
A5: Net Revenue | B5: 79474 | C5: 86392 | D5: 91471 | E5: 91854 | F5: 93925 | H5: =C5-C6 -> 45816
A6: Cost of sales | B6: 37075 | C6: 40576 | D6: 41881 | E6: 41744 | F6: 43066 | H6: =SUM(C8:C10) -> 34304
A7: Gross profit | B7: 42399 | C7: 45816 | D7: 49590 | E7: 50110 | F7: 50859 | H7: =H5-H6 -> 11512
A8: Selling, general and administrative expenses | B8: 31237 | C8: 34459 | D8: 36677 | E8: 37190 | F8: 37368
A9: Gain associated with the Juice Transaction | B9: 0 | C9: -3321 | D9: 0 | E9: 0 | F9: 0
A10: Impairment of Intangible Assets (Excluding Goodwill) | B10: 0 | C10: 3166 | D10: 927 | E10: 33 | F10: 1993
A11: Operating Profit | B11: 11162 | C11: 11512 | D11: 11986 | E11: 12887 | F11: 11498
A12: Other pension and retiree medical benefits (expense)/income | B12: 522 | C12: 132 | D12: 250 | E12: -22 | F12: -133
A13: Net interest expense and other | B13: -1863 | C13: -939 | D13: -819 | E13: -919 | F13: -1121
A14: Income before income taxes | B14: 9821 | C14: 10705 | D14: 11417 | E14: 11946 | F14: 10244
A15: Provision for income taxes | B15: 2142 | C15: 1727 | D15: 2262 | E15: 2320 | F15: 1949
A16: Net income | B16: 7679 | C16: 8978 | D16: 9155 | E16: 9626 | F16: 8295
A17: Less: Net income attributable to noncontrolling interests | B17: 61 | C17: 68 | D17: 81 | E17: 48 | F17: 55
A18: Net Income Attributable to PepsiCo | B18: $7,618 | C18: $8,910 | D18: $9,074 | E18: $9,578 | F18: $8,240
A20: Net Income Attributable to PepsiCo per Common Share
A21: Basic | B21: $5.51 | C21: $6.45 | D21: $6.59 | E21: $6.97 | F21: $6.02
A22: Diluted | B22: $5.49 | C22: $6.42 | D22: $6.56 | E22: $6.95 | F22: $6.00
A23: Weighted-average common shares outstanding
A24: Basic | B24: 1382 | C24: 1380 | D24: 1376 | E24: 1373 | F24: 1369
A25: Diluted | B25: 1389 | C25: 1387 | D25: 1383 | E25: 1378 | F25: 1373
A29: Consolidated Balance Sheet - USD ($) | B29: 12 Months Ended
A30: shares in Millions, $ in Millions | B30: Dec. 25, 2021 | C30: Dec. 31, 2022 | D30: Dec. 30, 2023 | E30: Dec. 28, 2024 | F30: Dec. 27, 2025
A31: ASSETS
A32: Cash and cash equivalents | B32: 5596 | C32: 4964 | D32: 9711 | E32: 8505 | F32: 9159
A33: Short-term Investments | B33: 392 | C33: 394 | D33: 292 | E33: 761 | F33: 371
A34: Accounts and notes receivable, net | B34: 8680 | C34: 10163 | D34: 10815 | E34: 10333 | F34: 11506
A35: Inventories | B35: 4347 | C35: 5222 | D35: 5334 | E35: 5306 | F35: 5845
A36: Prepaid expenses and other current assets | B36: 980 | C36: 806 | D36: 798 | E36: 921 | F36: 1068
A37: Disposal Group, Including Discontinued Operation, Assets | B37: 1788
A38: Assets, Current | B38: 21783 | C38: 21539 | D38: 26950 | E38: 25826 | F38: 27949
A39: Property, Plant and Equipment, net | B39: 22407 | C39: 24291 | D39: 27039 | E39: 28008 | F39: 29905
A40: Amortizable Intangible Assets, net | B40: 1538 | C40: 1277 | D40: 1199 | E40: 1102 | F40: 1219
A41: Goodwill | B41: 18381 | C41: 18202 | D41: 17728 | E41: 17534 | F41: 18916
A42: Indefinite-lived Intangible Assets (Excluding Goodwill) | B42: 17127 | C42: 14309 | D42: 13730 | E42: 13699 | F42: 13847
A43: Equity Method Investments | B43: 2350 | C43: 3073 | D43: 2714 | E43: 1985 | F43: 2038
A44: Deferred Income Tax Assets, Net | B44: 4310 | C44: 4204 | D44: 4474 | E44: 4362 | F44: 4541
A45: Other Assets | B45: 4481 | C45: 5292 | D45: 6661 | E45: 6951 | F45: 8984
A46: Total Assets | B46: 92377 | C46: 92187 | D46: 100495 | E46: 99467 | F46: 107399
A47: LIABILITIES AND EQUITY
A48: Short-term debt obligations | B48: 4308 | C48: 3414 | D48: 6510 | E48: 7082 | F48: 6861
A49: Accounts payable and other current liabilities | B49: 21159 | C49: 23371 | D49: 25137 | E49: 24454 | F49: 25903
A50: Disposal Group, Including Discontinued Operation, Liabilities | B50: 753 | C50: 0 | D50: 0 | E50: 0 | F50: 0
A51: Liabilities, Current | B51: 26220 | C51: 26785 | D51: 31647 | E51: 31536 | F51: 32764
A52: Long-Term Debt Obligations | B52: 36026 | C52: 35657 | D52: 37595 | E52: 37224 | F52: 42321
A53: Deferred Income Tax Liabilities, Net | B53: 4826 | C53: 4133 | D53: 3895 | E53: 3484 | F53: 3802
A54: Other Liabilities, Noncurrent | B54: 9154 | C54: 8339 | D54: 8721 | E54: 9052 | F54: 7965
A55: Liabilities | B55: 76226 | C55: 74914 | D55: 81858 | E55: 81296 | F55: 86852
A56: Commitments and contingencies
A57: Common stock, authorized | B57: 3600 | C57: 3600 | D57: 3600 | E57: 3600 | F57: 3600
A58: Common stock, issued | B58: 1383 | C58: 1377 | D58: 1374 | E58: 1372 | F58: 1367
A59: PepsiCo Common Shareholders’ Equity
A60: Common stock, par value 12/3¢ per share (authorized 3,600 shares, issued, net of repurchased common stock at par value: 1,380 and 1,391 shares, respectively) | B60: 23 | C60: 23 | D60: 23 | E60: 23 | F60: 23
A61: Additional Paid in Capital, Common Stock | B61: 4001 | C61: 4134 | D61: 4261 | E61: 4385 | F61: 4451
A62: Retained Earnings (Accumulated Deficit) | B62: 65165 | C62: 67800 | D62: 70035 | E62: 72266 | F62: 72788
A63: Accumulated Other Comprehensive Income (Loss), Net of Tax | B63: -14898 | C63: -15302 | D63: -15534 | E63: -17612 | F63: -15024
A64: Treasury Stock, Common, Shares | B64: 484 | C64: 490 | D64: 493 | E64: 495 | F64: 500
A65: Treasury Stock, Value | B65: -38248 | C65: -39506 | D65: -40282 | E65: -41021 | F65: -41832
A66: Stockholders' Equity Attributable to Parent | B66: 16043 | C66: 17149 | D66: 18503 | E66: 18041 | F66: 20406
A67: Stockholders' Equity Attributable to Noncontrolling Interest | B67: 108 | C67: 124 | D67: 134 | E67: 130 | F67: 141
A68: Total Equity | B68: 16151 | C68: 17273 | D68: 18637 | E68: 18171 | F68: 20547
A69: Liabilities and Equity | B69: 92377 | C69: 92187 | D69: 100495 | E69: 99467 | F69: 107399
A70: Other Investments | B70: $277 | C70: $813 | D70: $1,616 | E70: $1,346 | F70: $2,526
A71: Operating Lease, Right-of-Use Asset, Statement of Financial Position [Extensible Enumeration] | B71: Other Assets | C71: Other Assets | D71: Other Assets | E71: Other Assets | F71: Other Assets
A72: Accounts Receivable, Allowance for Credit Loss, Current | D72: $175 | E72: $356 | F72: $230

Sheet Coca Cola (KO)
B1: COCA COLA
B2: COMMON SIZING AND TREND ANALYSIS (in 000's Except Per Share Data)
B3: INCOME STATEMENT DATA
B4: NAME | U4: Page 1 of 3
B5: FIN320 Section B
J6: Common-Size Analysis | Q6: Trend Analysis
J7: (as a percentage of sales) | Q7: (using 2020 as the base year)
B8: Income Statement | C8: 2021 | D8: 2022 | E8: 2023 | F8: 2024 | G8: 2025 | J8: 2021 | K8: 2022 | L8: 2023 | M8: 2024 | N8: 2025 | Q8: 2021 | R8: 2022 | S8: 2023 | T8: 2024 | U8: 2025
B9: Net Operating Revenues | C9: 38655 | D9: 43004 | E9: 45754 | F9: 47061 | G9: 47941 | J9: =C9/C$9 -> 1 | K9: =D9/D$9 -> 1 | L9: =E9/E$9 -> 1 | M9: =F9/F$9 -> 1 | N9: =G9/G$9 -> 1 | Q9: =C9/$C9 -> 1 | R9: =D9/$C9 -> 1.1125081 | S9: =E9/$C9 -> 1.1836502 | T9: =F9/$C9 -> 1.2174622 | U9: =G9/$C9 -> 1.2402277
B10: Cost of sales | C10: 15357 | D10: 18000 | E10: 18520 | F10: 18324 | G10: 18397 | J10: =C10/C$9 -> 0.39728366 | K10: =D10/D$9 -> 0.41856571 | L10: =E10/E$9 -> 0.40477335 | M10: =F10/F$9 -> 0.38936699 | N10: =G10/G$9 -> 0.38374252 | Q10: =C10/$C10 -> 1 | R10: =D10/$C10 -> 1.1721039 | S10: =E10/$C10 -> 1.2059647 | T10: =F10/$C10 -> 1.1932018 | U10: =G10/$C10 -> 1.1979553
B11: Gross Profit | C11: =C9-C10 -> 23298 | D11: =D9-D10 -> 25004 | E11: =E9-E10 -> 27234 | F11: =F9-F10 -> 28737 | G11: =G9-G10 -> 29544 | J11: =C11/C$9 -> 0.60271634 | K11: =D11/D$9 -> 0.58143429 | L11: =E11/E$9 -> 0.59522665 | M11: =F11/F$9 -> 0.61063301 | N11: =G11/G$9 -> 0.61625748 | Q11: =C11/$C11 -> 1 | R11: =D11/$C11 -> 1.0732252 | S11: =E11/$C11 -> 1.1689415 | T11: =F11/$C11 -> 1.2334535 | U11: =G11/$C11 -> 1.2680917
B13: Operating expenses
B14: Selling, general and administrative expenses | C14: 12144 | D14: 12880 | E14: 13972 | F14: 14582 | G14: 14521 | J14: =C14/C$9 -> 0.31416376 | K14: =D14/D$9 -> 0.29950702 | L14: =E14/E$9 -> 0.30537221 | M14: =F14/F$9 -> 0.30985317 | N14: =G14/G$9 -> 0.30289314 | Q14: =C14/$C14 -> 1 | R14: =D14/$C14 -> 1.0606061 | S14: =E14/$C14 -> 1.150527 | T14: =F14/$C14 -> 1.2007576 | U14: =G14/$C14 -> 1.1957345
B15: Other operating charges | C15: 846 | D15: 1215 | E15: 1951 | F15: 4163 | G15: 1261 | J15: =C15/C$9 -> 0.021885914 | K15: =D15/D$9 -> 0.028253186 | L15: =E15/E$9 -> 0.042641081 | M15: =F15/F$9 -> 0.088459659 | N15: =G15/G$9 -> 0.026303164 | Q15: =C15/$C15 -> 1 | R15: =D15/$C15 -> 1.4361702 | S15: =E15/$C15 -> 2.3061466 | T15: =F15/$C15 -> 4.9208038 | U15: =G15/$C15 -> 1.4905437
B16: Total Oper. Exp | C16: =+C14+C15 -> 12990 | D16: =+D14+D15 -> 14095 | E16: =+E14+E15 -> 15923 | F16: =+F14+F15 -> 18745 | G16: =+G14+G15 -> 15782 | J16: =C16/C$9 -> 0.33604967 | K16: =D16/D$9 -> 0.32776021 | L16: =E16/E$9 -> 0.34801329 | M16: =F16/F$9 -> 0.39831283 | N16: =G16/G$9 -> 0.3291963 | Q16: =C16/$C16 -> 1 | R16: =D16/$C16 -> 1.0850654 | S16: =E16/$C16 -> 1.2257891 | T16: =F16/$C16 -> 1.4430331 | U16: =G16/$C16 -> 1.2149346
B18: Operating Income (EBIT) | C18: =C11-C16 -> 10308 | D18: =D11-D16 -> 10909 | E18: =E11-E16 -> 11311 | F18: =F11-F16 -> 9992 | G18: =G11-G16 -> 13762 | J18: =C18/C$9 -> 0.26666667 | K18: =D18/D$9 -> 0.25367408 | L18: =E18/E$9 -> 0.24721336 | M18: =F18/F$9 -> 0.21232018 | N18: =G18/G$9 -> 0.28706118 | Q18: =C18/$C18 -> 1 | R18: =D18/$C18 -> 1.0583042 | S18: =E18/$C18 -> 1.0973031 | T18: =F18/$C18 -> 0.9693442 | U18: =G18/$C18 -> 1.3350795
B19: Interest income | C19: 276 | D19: 449 | E19: 907 | F19: 988 | G19: 786 | J19: =C19/C$9 -> 0.0071400854 | K19: =D19/D$9 -> 0.010440889 | L19: =E19/E$9 -> 0.019823403 | M19: =F19/F$9 -> 0.020994029 | N19: =G19/G$9 -> 0.016395152 | Q19: =C19/$C19 -> 1 | R19: =D19/$C19 -> 1.6268116 | S19: =E19/$C19 -> 3.2862319 | T19: =F19/$C19 -> 3.5797101 | U19: =G19/$C19 -> 2.8478261
B20: Interest expense | C20: 1597 | D20: 882 | E20: 1527 | F20: 1656 | G20: 1654 | J20: =C20/C$9 -> 0.04131419 | K20: =D20/D$9 -> 0.02050972 | L20: =E20/E$9 -> 0.033374131 | M20: =F20/F$9 -> 0.035188373 | N20: =G20/G$9 -> 0.03450074 | Q20: =C20/$C20 -> 1 | R20: =D20/$C20 -> 0.55228554 | S20: =E20/$C20 -> 0.95616781 | T20: =F20/$C20 -> 1.0369443 | U20: =G20/$C20 -> 1.0356919
B21: Equity income (loss) - net | C21: 1438 | D21: 1472 | E21: 1691 | F21: 1770 | G21: 2031 | J21: =C21/C$9 -> 0.03720088 | K21: =D21/D$9 -> 0.034229374 | L21: =E21/E$9 -> 0.036958517 | M21: =F21/F$9 -> 0.037610761 | N21: =G21/G$9 -> 0.042364573 | Q21: =C21/$C21 -> 1 | R21: =D21/$C21 -> 1.0236439 | S21: =E21/$C21 -> 1.1759388 | T21: =F21/$C21 -> 1.2308762 | U21: =G21/$C21 -> 1.4123783
B22: Other income (loss) - net | C22: 2000 | D22: -262 | E22: 570 | F22: 1992 | G22: 1073 | J22: =C22/C$9 -> 0.051739749 | K22: =D22/D$9 -> -0.0060924565 | L22: =E22/E$9 -> 0.012457927 | M22: =F22/F$9 -> 0.042328042 | N22: =G22/G$9 -> 0.022381677 | Q22: =C22/$C22 -> 1 | R22: =D22/$C22 -> -0.131 | S22: =E22/$C22 -> 0.285 | T22: =F22/$C22 -> 0.996 | U22: =G22/$C22 -> 0.5365
B24: Pretax Income | C24: =C18+C19-C20+C21+C22 -> 12425 | D24: =D18+D19-D20+D21+D22 -> 11686 | E24: =E18+E19-E20+E21+E22 -> 12952 | F24: =F18+F19-F20+F21+F22 -> 13086 | G24: =G18+G19-G20+G21+G22 -> 15998 | J24: =C24/C$9 -> 0.32143319 | K24: =D24/D$9 -> 0.27174216 | L24: =E24/E$9 -> 0.28307908 | M24: =F24/F$9 -> 0.27806464 | N24: =G24/G$9 -> 0.33370184 | Q24: =C24/$C24 -> 1 | R24: =D24/$C24 -> 0.94052314 | S24: =E24/$C24 -> 1.0424145 | T24: =F24/$C24 -> 1.0531992 | U24: =G24/$C24 -> 1.2875654
B25: Provision for income taxes | C25: 2621 | D25: 2115 | E25: 2249 | F25: 2437 | G25: 2861 | J25: =C25/C$9 -> 0.067804941 | K25: =D25/D$9 -> 0.049181471 | L25: =E25/E$9 -> 0.049154172 | M25: =F25/F$9 -> 0.051783855 | N25: =G25/G$9 -> 0.05967752 | Q25: =C25/$C25 -> 1 | R25: =D25/$C25 -> 0.80694391 | S25: =E25/$C25 -> 0.85806944 | T25: =F25/$C25 -> 0.92979779 | U25: =G25/$C25 -> 1.0915681
B26: Effective Tax rate | C26: =C25/C24 -> 0.21094567 | D26: =D25/D24 -> 0.18098579 | E26: =E25/E24 -> 0.17364114 | F26: =F25/F24 -> 0.18622956 | G26: =G25/G24 -> 0.17883485 | J26: =C26/C$9 -> 5.4571381e-06 | K26: =D26/D$9 -> 4.2085805e-06 | L26: =E26/E$9 -> 3.7951029e-06 | M26: =F26/F$9 -> 3.9571951e-06 | N26: =G26/G$9 -> 3.7303113e-06 | Q26: =C26/$C26 -> 1 | R26: =D26/$C26 -> 0.85797348 | S26: =E26/$C26 -> 0.82315571 | T26: =F26/$C26 -> 0.88283184 | U26: =G26/$C26 -> 0.84777683
B28: Net income | C28: =C24-C25 -> 9804 | D28: =D24-D25 -> 9571 | E28: =E24-E25 -> 10703 | F28: =F24-F25 -> 10649 | G28: =G24-G25 -> 13137 | J28: =C28/C$9 -> 0.25362825 | K28: =D28/D$9 -> 0.22256069 | L28: =E28/E$9 -> 0.2339249 | M28: =F28/F$9 -> 0.22628078 | N28: =G28/G$9 -> 0.27402432 | Q28: =C28/$C28 -> 1 | R28: =D28/$C28 -> 0.97623419 | S28: =E28/$C28 -> 1.0916973 | T28: =F28/$C28 -> 1.0861893 | U28: =G28/$C28 -> 1.3399633
B30: Number of Shares Outstanding | C30: 4315 | D30: 4328 | E30: 4323 | F30: 4309 | G30: 4303
B31: Stock Price | C31: 59.21 | D31: 63.61 | E31: 58.93 | F31: 62.26 | G31: 69.91
B35: Depreciation and amortization | C35: 1050 | D35: 1075 | E35: 1128 | F35: 1260 | G35: 1452
B36: Dividends Paid | C36: 8779 | D36: 8359 | E36: 7952 | F36: 7616 | G36: 7252
B37: Net Cash Provided by Operating Activities | C37: 7408 | D37: 6805 | E37: 11599 | F37: 11018 | G37: 12625
B38: Purchases of property, plant and equipment | C38: 2112 | D38: 2064 | E38: 1852 | F38: 1484 | G38: 1367
B41: COCA COLA
B42: COMMON SIZING AND TREND ANALYSIS (in 000's Except Per Share Data)
B43: BALANCE SHEET DATA
B44: YOUR NAME | U44: Page 2 of 3
B45: =B5 -> FIN320 Section B
J47: Common-Size Analysis | Q47: Trend Analysis
J48: (as a percentage of total assets) | Q48: (using 2021 as a base year)
B49: Balance Sheet | C49: 2021 | D49: 2022 | E49: 2023 | F49: 2024 | G49: 2025 | J49: 2021 | K49: 2022 | L49: 2023 | M49: 2024 | N49: 2025 | Q49: 2021 | R49: 2022 | S49: 2023 | T49: 2024 | U49: 2025
B50: ASSETS:
B51: Current assets:
B52: Cash/Cash equivalents | C52: 9684 | D52: 9519 | E52: 9366 | F52: 10828 | G52: 10270 | J52: =C52/C$67 -> 0.10263476 | K52: =D52/D$67 -> 0.10261634 | L52: =E52/E$67 -> 0.095861949 | M52: =F52/F$67 -> 0.10768879 | N52: =G52/G$67 -> 0.097981224 | Q52: =C52/$C52 -> 1 | R52: =D52/$C52 -> 0.98296159 | S52: =E52/$C52 -> 0.96716233 | T52: =F52/$C52 -> 1.118133 | U52: =G52/$C52 -> 1.0605122
B53: Short-term market sect | C53: 1242 | D53: 1043 | E53: 2997 | F53: 2020 | G53: 3602 | J53: =C53/C$67 -> 0.013163194 | K53: =D53/D$67 -> 0.011243707 | L53: =E53/E$67 -> 0.030674595 | M53: =F53/F$67 -> 0.020089708 | N53: =G53/G$67 -> 0.034364982 | Q53: =C53/$C53 -> 1 | R53: =D53/$C53 -> 0.83977456 | S53: =E53/$C53 -> 2.4130435 | T53: =F53/$C53 -> 1.626409 | U53: =G53/$C53 -> 2.900161
B54: Total Cash, Cash Equivalents and Short-Term Investments | C54: =SUM(C52:C53) -> 10926 | D54: =SUM(D52:D53) -> 10562 | E54: =SUM(E52:E53) -> 12363 | F54: =SUM(F52:F53) -> 12848 | G54: =SUM(G52:G53) -> 13872 | J54: =C54/C$67 -> 0.11579795 | K54: =D54/D$67 -> 0.11386005 | L54: =E54/E$67 -> 0.12653654 | M54: =F54/F$67 -> 0.1277785 | N54: =G54/G$67 -> 0.13234621 | Q54: =C54/$C54 -> 1 | R54: =D54/$C54 -> 0.96668497 | S54: =E54/$C54 -> 1.1315211 | T54: =F54/$C54 -> 1.1759107 | U54: =G54/$C54 -> 1.2696321
B55: Marketable securities | C55: 1699 | D55: 1069 | E55: 1300 | F55: 1723 | G55: 1934 | J55: =C55/C$67 -> 0.018006656 | K55: =D55/D$67 -> 0.011523991 | L55: =E55/E$67 -> 0.01330563 | M55: =F55/F$67 -> 0.017135924 | N55: =G55/G$67 -> 0.018451381 | Q55: =C55/$C55 -> 1 | R55: =D55/$C55 -> 0.62919364 | S55: =E55/$C55 -> 0.76515597 | T55: =F55/$C55 -> 1.014126 | U55: =G55/$C55 -> 1.1383167
B56: Accounts receivable | C56: 3512 | D56: 3487 | E56: 3410 | F56: 3569 | G56: 3038 | J56: =C56/C$67 -> 0.037221527 | K56: =D56/D$67 -> 0.037590419 | L56: =E56/E$67 -> 0.034901692 | M56: =F56/F$67 -> 0.035495132 | N56: =G56/G$67 -> 0.028984125 | Q56: =C56/$C56 -> 1 | R56: =D56/$C56 -> 0.99288155 | S56: =E56/$C56 -> 0.97095672 | T56: =F56/$C56 -> 1.0162301 | U56: =G56/$C56 -> 0.86503417
B57: Inventories | C57: 3414 | D57: 4233 | E57: 4424 | F57: 4728 | G57: 4425 | J57: =C57/C$67 -> 0.036182886 | K57: =D57/D$67 -> 0.045632418 | L57: =E57/E$67 -> 0.045280084 | M57: =F57/F$67 -> 0.04702185 | N57: =G57/G$67 -> 0.042216837 | Q57: =C57/$C57 -> 1 | R57: =D57/$C57 -> 1.2398946 | S57: =E57/$C57 -> 1.2958407 | T57: =F57/$C57 -> 1.3848858 | U57: =G57/$C57 -> 1.2961336
B58: Prepaid expenses and other current assets | C58: 2994 | D58: 3240 | E58: 5235 | F58: 3129 | G58: 7775 | J58: =C58/C$67 -> 0.031731564 | K58: =D58/D$67 -> 0.034927719 | L58: =E58/E$67 -> 0.05358075 | M58: =F58/F$67 -> 0.031119156 | N58: =G58/G$67 -> 0.074177606 | Q58: =C58/$C58 -> 1 | R58: =D58/$C58 -> 1.0821643 | S58: =E58/$C58 -> 1.748497 | T58: =F58/$C58 -> 1.0450902 | U58: =G58/$C58 -> 2.5968604
B59: Total Current Assets | C59: =SUM(C54:C58) -> 22545 | D59: =SUM(D54:D58) -> 22591 | E59: =SUM(E54:E58) -> 26732 | F59: =SUM(F54:F58) -> 25997 | G59: =SUM(G54:G58) -> 31044 | J59: =C59/C$67 -> 0.23894059 | K59: =D59/D$67 -> 0.2435346 | L59: =E59/E$67 -> 0.2736047 | M59: =F59/F$67 -> 0.25855056 | N59: =G59/G$67 -> 0.29617616 | Q59: =C59/$C59 -> 1 | R59: =D59/$C59 -> 1.0020404 | S59: =E59/$C59 -> 1.1857175 | T59: =F59/$C59 -> 1.153116 | U59: =G59/$C59 -> 1.3769794
B60: Equity method investments | C60: 17598 | D60: 18264 | E60: 19671 | F60: 18087 | G60: 20235 | J60: =C60/C$67 -> 0.18651038 | K60: =D60/D$67 -> 0.19688885 | L60: =E60/E$67 -> 0.20133466 | M60: =F60/F$67 -> 0.17988245 | N60: =G60/G$67 -> 0.19305259 | Q60: =C60/$C60 -> 1 | R60: =D60/$C60 -> 1.0378452 | S60: =E60/$C60 -> 1.1177975 | T60: =F60/$C60 -> 1.0277872 | U60: =G60/$C60 -> 1.1498466
B61: Deferred income tax assets | C61: 2129 | D61: 1746 | E61: 1561 | F61: 1319 | G61: 1206 | J61: =C61/C$67 -> 0.022563961 | K61: =D61/D$67 -> 0.01882216 | L61: =E61/E$67 -> 0.015976991 | M61: =F61/F$67 -> 0.013117982 | N61: =G61/G$67 -> 0.011505877 | Q61: =C61/$C61 -> 1 | R61: =D61/$C61 -> 0.82010333 | S61: =E61/$C61 -> 0.73320808 | T61: =F61/$C61 -> 0.61953969 | U61: =G61/$C61 -> 0.56646313
B62: PP&E, net | C62: 9920 | D62: 9841 | E62: 9236 | F62: 10303 | G62: 9613 | J62: =C62/C$67 -> 0.10513598 | K62: =D62/D$67 -> 0.10608756 | L62: =E62/E$67 -> 0.094531386 | M62: =F62/F$67 -> 0.10246745 | N62: =G62/G$67 -> 0.091713097 | Q62: =C62/$C62 -> 1 | R62: =D62/$C62 -> 0.99203629 | S62: =E62/$C62 -> 0.93104839 | T62: =F62/$C62 -> 1.0386089 | U62: =G62/$C62 -> 0.96905242
B63: Trademarks with indefinite lives | C63: 14465 | D63: 14214 | E63: 14349 | F63: 13301 | G63: 12531 | J63: =C63/C$67 -> 0.15330564 | K63: =D63/D$67 -> 0.1532292 | L63: =E63/E$67 -> 0.14686345 | M63: =F63/F$67 -> 0.13228376 | N63: =G63/G$67 -> 0.11955236 | Q63: =C63/$C63 -> 1 | R63: =D63/$C63 -> 0.98264777 | S63: =E63/$C63 -> 0.99198064 | T63: =F63/$C63 -> 0.9195299 | U63: =G63/$C63 -> 0.86629796
B64: Goodwill | C64: 19363 | D64: 18782 | E64: 18358 | F64: 18139 | G64: 15491 | J64: =C64/C$67 -> 0.20521653 | K64: =D64/D$67 -> 0.20247297 | L64: =E64/E$67 -> 0.18789597 | M64: =F64/F$67 -> 0.18039961 | N64: =G64/G$67 -> 0.14779232 | Q64: =C64/$C64 -> 1 | R64: =D64/$C64 -> 0.96999432 | S64: =E64/$C64 -> 0.94809689 | T64: =F64/$C64 -> 0.93678665 | U64: =G64/$C64 -> 0.80003099
B65: Other noncurrent assets | C65: 8334 | D65: 7325 | E65: 7796 | F65: 13403 | G65: 14696 | J65: =C65/C$67 -> 0.088326939 | K65: =D65/D$67 -> 0.078964673 | L65: =E65/E$67 -> 0.079792842 | M65: =F65/F$67 -> 0.13329819 | N65: =G65/G$67 -> 0.1402076 | Q65: =C65/$C65 -> 1 | R65: =D65/$C65 -> 0.87892969 | S65: =E65/$C65 -> 0.93544516 | T65: =F65/$C65 -> 1.6082313 | U65: =G65/$C65 -> 1.7633789
B67: Total Assets | C67: =SUM(C59:C65) -> 94354 | D67: =SUM(D59:D65) -> 92763 | E67: =SUM(E59:E65) -> 97703 | F67: =SUM(F59:F65) -> 100549 | G67: =SUM(G59:G65) -> 104816 | J67: =C67/C$67 -> 1 | K67: =D67/D$67 -> 1 | L67: =E67/E$67 -> 1 | M67: =F67/F$67 -> 1 | N67: =G67/G$67 -> 1 | Q67: =C67/$C67 -> 1 | R67: =D67/$C67 -> 0.98313797 | S67: =E67/$C67 -> 1.035494 | T67: =F67/$C67 -> 1.065657 | U67: =G67/$C67 -> 1.1108803
B69: LIABILITIES AND SHAREHOLDERS' EQUITY:
B70: Current Liabilities
B71: Accounts payable and accrued expenses | C71: 14619 | D71: 15749 | E71: 15485 | F71: 21712 | G71: 14813 | J71: =C71/C$67 -> 0.15493779 | K71: =D71/D$67 -> 0.16977674 | L71: =E71/E$67 -> 0.15849053 | M71: =F71/F$67 -> 0.21593452 | N71: =G71/G$67 -> 0.14132384 | Q71: =C71/$C71 -> 1 | R71: =D71/$C71 -> 1.0772967 | S71: =E71/$C71 -> 1.059238 | T71: =F71/$C71 -> 1.4851905 | U71: =G71/$C71 -> 1.0132704
B72: Loans and notes payable | C72: 3307 | D72: 2373 | E72: 4557 | F72: 1499 | G72: 1551 | J72: =C72/C$67 -> 0.035048859 | K72: =D72/D$67 -> 0.02558132 | L72: =E72/E$67 -> 0.046641352 | M72: =F72/F$67 -> 0.014908154 | N72: =G72/G$67 -> 0.014797359 | Q72: =C72/$C72 -> 1 | R72: =D72/$C72 -> 0.71756879 | S72: =E72/$C72 -> 1.3779861 | T72: =F72/$C72 -> 0.45328092 | U72: =G72/$C72 -> 0.46900514
B73: Current maturities of long-term debt | C73: 1338 | D73: 399 | E73: 1960 | F73: 648 | G73: 1822 | J73: =C73/C$67 -> 0.014180639 | K73: =D73/D$67 -> 0.0043012839 | L73: =E73/E$67 -> 0.020060796 | M73: =F73/F$67 -> 0.006444619 | N73: =G73/G$67 -> 0.017382842 | Q73: =C73/$C73 -> 1 | R73: =D73/$C73 -> 0.29820628 | S73: =E73/$C73 -> 1.4648729 | T73: =F73/$C73 -> 0.48430493 | U73: =G73/$C73 -> 1.3617339
B74: Accrued income taxes | C74: 686 | D74: 1203 | E74: 1569 | F74: 1390 | G74: 3095 | J74: =C74/C$67 -> 0.007270492 | K74: =D74/D$67 -> 0.012968533 | L74: =E74/E$67 -> 0.016058872 | M74: =F74/F$67 -> 0.013824106 | N74: =G74/G$67 -> 0.029527935 | Q74: =C74/$C74 -> 1 | R74: =D74/$C74 -> 1.7536443 | S74: =E74/$C74 -> 2.287172 | T74: =F74/$C74 -> 2.0262391 | U74: =G74/$C74 -> 4.5116618
B75: Total Current Liabilities | C75: =SUM(C71:C74) -> 19950 | D75: =SUM(D71:D74) -> 19724 | E75: =SUM(E71:E74) -> 23571 | F75: =SUM(F71:F74) -> 25249 | G75: =SUM(G71:G74) -> 21281 | J75: =C75/C$67 -> 0.21143778 | K75: =D75/D$67 -> 0.21262788 | L75: =E75/E$67 -> 0.24125155 | M75: =F75/F$67 -> 0.2511114 | N75: =G75/G$67 -> 0.20303198 | Q75: =C75/$C75 -> 1 | R75: =D75/$C75 -> 0.98867168 | S75: =E75/$C75 -> 1.1815038 | T75: =F75/$C75 -> 1.265614 | U75: =G75/$C75 -> 1.0667168
B76: Long-term debt | C76: 38116 | D76: 36377 | E76: 35547 | F76: 42375 | G76: 42119 | J76: =C76/C$67 -> 0.40396804 | K76: =D76/D$67 -> 0.39214989 | L76: =E76/E$67 -> 0.36382711 | M76: =F76/F$67 -> 0.42143631 | N76: =G76/G$67 -> 0.40183751 | Q76: =C76/$C76 -> 1 | R76: =D76/$C76 -> 0.95437612 | S76: =E76/$C76 -> 0.93260048 | T76: =F76/$C76 -> 1.1117379 | U76: =G76/$C76 -> 1.1050215
B77: Other noncurrent liabilities | C77: 8607 | D77: 7922 | E77: 8466 | F77: 4084 | G77: 4735 | J77: =C77/C$67 -> 0.091220298 | K77: =D77/D$67 -> 0.085400429 | L77: =E77/E$67 -> 0.086650359 | M77: =F77/F$67 -> 0.040617013 | N77: =G77/G$67 -> 0.045174401 | Q77: =C77/$C77 -> 1 | R77: =D77/$C77 -> 0.92041362 | S77: =E77/$C77 -> 0.98361799 | T77: =F77/$C77 -> 0.4744975 | U77: =G77/$C77 -> 0.55013361
B78: Deferred income tax liabilities | C78: 2821 | D78: 2914 | E78: 2639 | F78: 2469 | G78: 2406 | J78: =C78/C$67 -> 0.029898044 | K78: =D78/D$67 -> 0.031413387 | L78: =E78/E$67 -> 0.02701043 | M78: =F78/F$67 -> 0.024555192 | N78: =G78/G$67 -> 0.022954511 | Q78: =C78/$C78 -> 1 | R78: =D78/$C78 -> 1.032967 | S78: =E78/$C78 -> 0.93548387 | T78: =F78/$C78 -> 0.87522155 | U78: =G78/$C78 -> 0.85288905
B79: Total Liabilities | C79: =SUM(C75:C78) -> 69494 | D79: =SUM(D75:D78) -> 66937 | E79: =SUM(E75:E78) -> 70223 | F79: =SUM(F75:F78) -> 74177 | G79: =SUM(G75:G78) -> 70541 | J79: =C79/C$67 -> 0.73652415 | K79: =D79/D$67 -> 0.72159158 | L79: =E79/E$67 -> 0.71873945 | M79: =F79/F$67 -> 0.73771992 | N79: =G79/G$67 -> 0.6729984 | Q79: =C79/$C79 -> 1 | R79: =D79/$C79 -> 0.96320546 | S79: =E79/$C79 -> 1.0104901 | T79: =F79/$C79 -> 1.0673871 | U79: =G79/$C79 -> 1.015066
B80: Stockholders equity:
B81: Common stock | C81: 1760 | D81: 1760 | E81: 1760 | F81: 1760 | G81: 1760 | J81: =C81/C$67 -> 0.018653157 | K81: =D81/D$67 -> 0.018973082 | L81: =E81/E$67 -> 0.018013776 | M81: =F81/F$67 -> 0.017503904 | N81: =G81/G$67 -> 0.01679133 | Q81: =C81/$C81 -> 1 | R81: =D81/$C81 -> 1 | S81: =E81/$C81 -> 1 | T81: =F81/$C81 -> 1 | U81: =G81/$C81 -> 1
B82: Capital surplus | C82: 18116 | D82: 18822 | E82: 19209 | F82: 19801 | G82: 20581 | J82: =C82/C$67 -> 0.19200034 | K82: =D82/D$67 -> 0.20290418 | L82: =E82/E$67 -> 0.19660604 | M82: =F82/F$67 -> 0.19692886 | N82: =G82/G$67 -> 0.19635361 | Q82: =C82/$C82 -> 1 | R82: =D82/$C82 -> 1.0389711 | S82: =E82/$C82 -> 1.0603334 | T82: =F82/$C82 -> 1.0930117 | U82: =G82/$C82 -> 1.1360676
B83: Reinvested earnings | C83: 69094 | D83: 71019 | E83: 73782 | F83: 76054 | G83: 80382 | J83: =C83/C$67 -> 0.7322848 | K83: =D83/D$67 -> 0.7655962 | L83: =E83/E$67 -> 0.75516617 | M83: =F83/F$67 -> 0.75638743 | N83: =G83/G$67 -> 0.76688673 | Q83: =C83/$C83 -> 1 | R83: =D83/$C83 -> 1.0278606 | S83: =E83/$C83 -> 1.0678496 | T83: =F83/$C83 -> 1.1007323 | U83: =G83/$C83 -> 1.1633716
B84: Accumulated other comprehensive income (loss) | C84: -14330 | D84: -14895 | E84: -14275 | F84: -16843 | G84: -14131 | J84: =C84/C$67 -> -0.15187485 | K84: =D84/D$67 -> -0.16057049 | L84: =E84/E$67 -> -0.14610606 | M84: =F84/F$67 -> -0.16751037 | N84: =G84/G$67 -> -0.1348172 | Q84: =C84/$C84 -> 1 | R84: =D84/$C84 -> 1.0394278 | S84: =E84/$C84 -> 0.9961619 | T84: =F84/$C84 -> 1.1753664 | U84: =G84/$C84 -> 0.98611305
B85: Treasury stock | C85: -51641 | D85: -52601 | E85: -54535 | F85: -55916 | G85: -56423 | J85: =C85/C$67 -> -0.54731119 | K85: =D85/D$67 -> -0.56704721 | L85: =E85/E$67 -> -0.55817119 | M85: =F85/F$67 -> -0.55610697 | N85: =G85/G$67 -> -0.53830522 | Q85: =C85/$C85 -> 1 | R85: =D85/$C85 -> 1.0185899 | S85: =E85/$C85 -> 1.0560407 | T85: =F85/$C85 -> 1.0827831 | U85: =G85/$C85 -> 1.0926008
B86: Total Shareholders' Equity (S/E) | C86: =SUM(C81:C85) -> 22999 | D86: =SUM(D81:D85) -> 24105 | E86: =SUM(E81:E85) -> 25941 | F86: =SUM(F81:F85) -> 24856 | G86: =SUM(G81:G85) -> 32169 | J86: =C86/C$67 -> 0.24375225 | K86: =D86/D$67 -> 0.25985576 | L86: =E86/E$67 -> 0.26550874 | M86: =F86/F$67 -> 0.24720286 | N86: =G86/G$67 -> 0.30690925 | Q86: =C86/$C86 -> 1 | R86: =D86/$C86 -> 1.048089 | S86: =E86/$C86 -> 1.1279186 | T86: =F86/$C86 -> 1.0807426 | U86: =G86/$C86 -> 1.398713
B87: Equity Attributable to Noncontrolling Interests | C87: 1861 | D87: 1721 | E87: 1539 | F87: 1516 | G87: 2106 | J87: =C87/C$67 -> 0.019723594 | K87: =D87/D$67 -> 0.018552656 | L87: =E87/E$67 -> 0.015751819 | M87: =F87/F$67 -> 0.015077226 | N87: =G87/G$67 -> 0.020092352 | Q87: =C87/$C87 -> 1 | R87: =D87/$C87 -> 0.92477163 | S87: =E87/$C87 -> 0.82697474 | T87: =F87/$C87 -> 0.8146158 | U87: =G87/$C87 -> 1.1316497
B88: Total Equity | C88: =SUM(C86:C87) -> 24860 | D88: =SUM(D86:D87) -> 25826 | E88: =SUM(E86:E87) -> 27480 | F88: =SUM(F86:F87) -> 26372 | G88: =SUM(G86:G87) -> 34275 | J88: =C88/C$67 -> 0.26347585 | K88: =D88/D$67 -> 0.27840842 | L88: =E88/E$67 -> 0.28126055 | M88: =F88/F$67 -> 0.26228008 | N88: =G88/G$67 -> 0.3270016 | Q88: =C88/$C88 -> 1 | R88: =D88/$C88 -> 1.0388576 | S88: =E88/$C88 -> 1.1053902 | T88: =F88/$C88 -> 1.0608206 | U88: =G88/$C88 -> 1.3787208
B89: Total Liabilities and S/E | C89: =C88+C79 -> 94354 | D89: =D88+D79 -> 92763 | E89: =E88+E79 -> 97703 | F89: =F88+F79 -> 100549 | G89: =G88+G79 -> 104816 | J89: =C89/C$67 -> 1 | K89: =D89/D$67 -> 1 | L89: =E89/E$67 -> 1 | M89: =F89/F$67 -> 1 | N89: =G89/G$67 -> 1 | Q89: =C89/$C89 -> 1 | R89: =D89/$C89 -> 0.98313797 | S89: =E89/$C89 -> 1.035494 | T89: =F89/$C89 -> 1.065657 | U89: =G89/$C89 -> 1.1108803
B92: Liquidity ratios | C92: 2021 | D92: 2022 | E92: 2023 | F92: 2024 | G92: 2025
B93: ='FINANCIAL RATIOS'!B15 -> Current Ratio = Current Assets / Current Liabilities | C93: ='FINANCIAL RATIOS'!C18 -> 1.1300752 | D93: ='FINANCIAL RATIOS'!D18 -> 1.1453559 | E93: ='FINANCIAL RATIOS'!E18 -> 1.1341055 | F93: ='FINANCIAL RATIOS'!F18 -> 1.0296249 | G93: ='FINANCIAL RATIOS'!G18 -> 1.458766
B94: ='FINANCIAL RATIOS'!B23 -> Quick Ratio = (Current Assets - Inventories) / Current Liabilities | C94: ='FINANCIAL RATIOS'!C26 -> 0.95894737 | D94: ='FINANCIAL RATIOS'!D26 -> 0.93074427 | E94: ='FINANCIAL RATIOS'!E26 -> 0.94641721 | F94: ='FINANCIAL RATIOS'!F26 -> 0.84236999 | G94: ='FINANCIAL RATIOS'!G26 -> 1.2508341
B95: ='FINANCIAL RATIOS'!B31 -> Cash Ratio = Cash / Current Liabilities | C95: ='FINANCIAL RATIOS'!C34 -> 0.48541353 | D95: ='FINANCIAL RATIOS'!D34 -> 0.48261002 | E95: ='FINANCIAL RATIOS'!E34 -> 0.39735268 | F95: ='FINANCIAL RATIOS'!F34 -> 0.42884867 | G95: ='FINANCIAL RATIOS'!G34 -> 0.4825901
B96: ='FINANCIAL RATIOS'!B39 -> NWC Ratio = (Current Assets - Current Liabilities) / Total Assets | C96: ='FINANCIAL RATIOS'!C42 -> 0.027502809 | D96: ='FINANCIAL RATIOS'!D42 -> 0.030906719 | E96: ='FINANCIAL RATIOS'!E42 -> 0.032353152 | F96: ='FINANCIAL RATIOS'!F42 -> 0.007439159 | G96: ='FINANCIAL RATIOS'!G42 -> 0.093144176
B97: ='FINANCIAL RATIOS'!B47 -> Interval Measure = Current Assets / Average Daily Costs (COGS + Oper. Exp.) | C97: ='FINANCIAL RATIOS'!C50 -> 290.29262 | D97: ='FINANCIAL RATIOS'!D50 -> 256.91587 | E97: ='FINANCIAL RATIOS'!E50 -> 283.28485 | F97: ='FINANCIAL RATIOS'!F50 -> 255.97952 | G97: ='FINANCIAL RATIOS'!G50 -> 331.52111
B99: Solvency ratios | C99: 2021 | D99: 2022 | E99: 2023 | F99: 2024 | G99: 2025
B100: ='FINANCIAL RATIOS'!B58 -> Total Debt Ratio = Financial Debt / Total Assets | C100: ='FINANCIAL RATIOS'!C61 -> 0.45319753 | D100: ='FINANCIAL RATIOS'!D61 -> 0.42203249 | E100: ='FINANCIAL RATIOS'!E61 -> 0.43052926 | F100: ='FINANCIAL RATIOS'!F61 -> 0.44278909 | G100: ='FINANCIAL RATIOS'!G61 -> 0.43401771
B101: ='FINANCIAL RATIOS'!B66 -> Debt-to-Equity Ratio = (Short-term Debt + Long-term Debt) / Total Equity | C101: ='FINANCIAL RATIOS'!C69 -> 1.7200724 | D101: ='FINANCIAL RATIOS'!D69 -> 1.5158755 | E101: ='FINANCIAL RATIOS'!E69 -> 1.5307132 | F101: ='FINANCIAL RATIOS'!F69 -> 1.6882299 | G101: ='FINANCIAL RATIOS'!G69 -> 1.3272648
B102: ='FINANCIAL RATIOS'!B74 -> Times Interest Earned = EBIT / Interest Expenses | C102: ='FINANCIAL RATIOS'!C77 -> 6.4546024 | D102: ='FINANCIAL RATIOS'!D77 -> 12.368481 | E102: ='FINANCIAL RATIOS'!E77 -> 7.4073346 | F102: ='FINANCIAL RATIOS'!F77 -> 6.0338164 | G102: ='FINANCIAL RATIOS'!G77 -> 8.3204353
B103: ='FINANCIAL RATIOS'!B82 -> Cash Coverage Ratio = (EBIT+Depreciation) / Interest Expenses | C103: ='FINANCIAL RATIOS'!C85 -> 7.1120852 | D103: ='FINANCIAL RATIOS'!D85 -> 13.587302 | E103: ='FINANCIAL RATIOS'!E85 -> 8.146038 | F103: ='FINANCIAL RATIOS'!F85 -> 6.794686 | G103: ='FINANCIAL RATIOS'!G85 -> 9.1983071
B105: Asset Management / Turnover Ratios | C105: 2021 | D105: 2022 | E105: 2023 | F105: 2024 | G105: 2025
B106: Assets Turnover Ratio = Sales / Total Assets | C106: ='FINANCIAL RATIOS'!C96 -> 0.40968056 | D106: ='FINANCIAL RATIOS'!D96 -> 0.46359001 | E106: ='FINANCIAL RATIOS'!E96 -> 0.46829678 | F106: ='FINANCIAL RATIOS'!F96 -> 0.46804046 | G106: ='FINANCIAL RATIOS'!G96 -> 0.45738246
B107: ='FINANCIAL RATIOS'!B100 -> Inventory Turnover = COGS / Inventories | C107: ='FINANCIAL RATIOS'!C103 -> 4.4982425 | D107: ='FINANCIAL RATIOS'!D103 -> 4.2523033 | E107: ='FINANCIAL RATIOS'!E103 -> 4.1862568 | F107: ='FINANCIAL RATIOS'!F103 -> 3.8756345 | G107: ='FINANCIAL RATIOS'!G103 -> 4.1575141
B108: ='FINANCIAL RATIOS'!B107 -> Days Sales in Inventory = 365 / Inventory Turnover | C108: ='FINANCIAL RATIOS'!C110 -> 81.142801 | D108: ='FINANCIAL RATIOS'!D110 -> 85.835833 | E108: ='FINANCIAL RATIOS'!E110 -> 87.190065 | F108: ='FINANCIAL RATIOS'!F110 -> 94.178127 | G108: ='FINANCIAL RATIOS'!G110 -> 87.792847
B109: ='FINANCIAL RATIOS'!B114 -> Receivables Turnover = Sales / Accounts Receivables | C109: ='FINANCIAL RATIOS'!C117 -> 11.006549 | D109: ='FINANCIAL RATIOS'!D117 -> 12.332664 | E109: ='FINANCIAL RATIOS'!E117 -> 13.417595 | F109: ='FINANCIAL RATIOS'!F117 -> 13.186047 | G109: ='FINANCIAL RATIOS'!G117 -> 15.780448
B110: ='FINANCIAL RATIOS'!B121 -> Days Sales in Receivables = 365 / Receivables Turnover | C110: ='FINANCIAL RATIOS'!C124 -> 33.162075 | D110: ='FINANCIAL RATIOS'!D124 -> 29.5962 | E110: ='FINANCIAL RATIOS'!E124 -> 27.203086 | F110: ='FINANCIAL RATIOS'!F124 -> 27.680776 | G110: ='FINANCIAL RATIOS'!G124 -> 23.129889
B111: ='FINANCIAL RATIOS'!B128 -> Operating Cycle = Days Sales in Inventory + Days Sales in Receivables | C111: ='FINANCIAL RATIOS'!C131 -> 114.30488 | D111: ='FINANCIAL RATIOS'!D131 -> 115.43203 | E111: ='FINANCIAL RATIOS'!E131 -> 114.39315 | F111: ='FINANCIAL RATIOS'!F131 -> 121.8589 | G111: ='FINANCIAL RATIOS'!G131 -> 110.92274
B113: ='FINANCIAL RATIOS'!B137 -> Profitability Ratios | C113: 2021 | D113: 2022 | E113: 2023 | F113: 2024 | G113: 2025
B114: ='FINANCIAL RATIOS'!B139 -> Gross Profit Margin = Gross Profits / Sales | C114: ='FINANCIAL RATIOS'!C142 -> 0.60271634 | D114: ='FINANCIAL RATIOS'!D142 -> 0.58143429 | E114: ='FINANCIAL RATIOS'!E142 -> 0.59522665 | F114: ='FINANCIAL RATIOS'!F142 -> 0.61063301 | G114: ='FINANCIAL RATIOS'!G142 -> 0.61625748
B115: ='FINANCIAL RATIOS'!B147 -> Operating Profit Margin = Operating Profits / Sales | C115: ='FINANCIAL RATIOS'!C150 -> 0.26666667 | D115: ='FINANCIAL RATIOS'!D150 -> 0.25367408 | E115: ='FINANCIAL RATIOS'!E150 -> 0.24721336 | F115: ='FINANCIAL RATIOS'!F150 -> 0.21232018 | G115: ='FINANCIAL RATIOS'!G150 -> 0.28706118
B116: ='FINANCIAL RATIOS'!B155 -> Net Profit Margin = Net Income / Sales | C116: ='FINANCIAL RATIOS'!C158 -> 0.25362825 | D116: ='FINANCIAL RATIOS'!D158 -> 0.22256069 | E116: ='FINANCIAL RATIOS'!E158 -> 0.2339249 | F116: ='FINANCIAL RATIOS'!F158 -> 0.22628078 | G116: ='FINANCIAL RATIOS'!G158 -> 0.27402432
B117: ='FINANCIAL RATIOS'!B163 -> Return on Assets (ROA) = Net Income / Total Assets | C117: ='FINANCIAL RATIOS'!C166 -> 0.10390656 | D117: ='FINANCIAL RATIOS'!D166 -> 0.10317691 | E117: ='FINANCIAL RATIOS'!E166 -> 0.10954628 | F117: ='FINANCIAL RATIOS'!F166 -> 0.10590856 | G117: ='FINANCIAL RATIOS'!G166 -> 0.12533392
B118: ='FINANCIAL RATIOS'!B170 -> Return on Equity (ROE) -based on BV of equity = Net Income / Total Equity | C118: ='FINANCIAL RATIOS'!C173 -> 0.39436846 | D118: ='FINANCIAL RATIOS'!D173 -> 0.37059552 | E118: ='FINANCIAL RATIOS'!E173 -> 0.38948326 | F118: ='FINANCIAL RATIOS'!F173 -> 0.40379948 | G118: ='FINANCIAL RATIOS'!G173 -> 0.38328228
...

Sheet CELSIUS (CELH)
B2: COMMON SIZING AND TREND ANALYSIS (in 000's Except Per Share Data)
B3: INCOME STATEMENT DATA
B4: NAME | U4: Page 1 of 3
B5: FIN320 Section B
J6: Common-Size Analysis | Q6: Trend Analysis
J7: (as a percentage of sales) | Q7: (using 2020 as the base year)
B8: Income Statement | C8: 2021 | D8: 2022 | E8: 2023 | F8: 2024 | G8: 2025 | J8: 2021 | K8: 2022 | L8: 2023 | M8: 2024 | N8: 2025 | Q8: 2021 | R8: 2022 | S8: 2023 | T8: 2024 | U8: 2025
B9: Net Operating Revenues | C9: 314272 | D9: 653604 | E9: 1318014 | F9: 1355630 | G9: 2515269 | J9: =C9/C$9 -> 1 | K9: =D9/D$9 -> 1 | L9: =E9/E$9 -> 1 | M9: =F9/F$9 -> 1 | N9: =G9/G$9 -> 1 | Q9: =C9/$C9 -> 1 | R9: =D9/$C9 -> 2.0797398 | S9: =E9/$C9 -> 4.1938639 | T9: =F9/$C9 -> 4.3135564 | U9: =G9/$C9 -> 8.0034779
B10: Cost of sales | C10: 186103 | D10: 382735 | E10: 684875 | F10: 675423 | G10: 1247936 | J10: =C10/C$9 -> 0.59217175 | K10: =D10/D$9 -> 0.58557628 | L10: =E10/E$9 -> 0.5196265 | M10: =F10/F$9 -> 0.49823551 | N10: =G10/G$9 -> 0.49614415 | Q10: =C10/$C10 -> 1 | R10: =D10/$C10 -> 2.0565762 | S10: =E10/$C10 -> 3.6800858 | T10: =F10/$C10 -> 3.6292967 | U10: =G10/$C10 -> 6.70562
B11: Gross Profit | C11: =C9-C10 -> 128169 | D11: =D9-D10 -> 270869 | E11: =E9-E10 -> 633139 | F11: =F9-F10 -> 680207 | G11: =G9-G10 -> 1267333 | J11: =C11/C$9 -> 0.40782825 | K11: =D11/D$9 -> 0.41442372 | L11: =E11/E$9 -> 0.4803735 | M11: =F11/F$9 -> 0.50176449 | N11: =G11/G$9 -> 0.50385585 | Q11: =C11/$C11 -> 1 | R11: =D11/$C11 -> 2.1133737 | S11: =E11/$C11 -> 4.9398763 | T11: =F11/$C11 -> 5.3071101 | U11: =G11/$C11 -> 9.8879838
B13: Operating expenses
B14: Selling, general and administrative expenses | C14: 132259 | D14: 428670 | E14: 366773 | F14: 524479 | G14: 798810 | J14: =C14/C$9 -> 0.42084245 | K14: =D14/D$9 -> 0.65585584 | L14: =E14/E$9 -> 0.27827701 | M14: =F14/F$9 -> 0.38688949 | N14: =G14/G$9 -> 0.31758432 | Q14: =C14/$C14 -> 1 | R14: =D14/$C14 -> 3.2411405 | S14: =E14/$C14 -> 2.7731421 | T14: =F14/$C14 -> 3.9655449 | U14: =G14/$C14 -> 6.0397402
B15: Other operating charges | G15: 327461 | J15: =C15/C$9 -> 0 | K15: =D15/D$9 -> 0 | L15: =E15/E$9 -> 0 | M15: =F15/F$9 -> 0 | N15: =G15/G$9 -> 0.13018926
B16: Total Oper. Exp | C16: =+C14+C15 -> 132259 | D16: =+D14+D15 -> 428670 | E16: =+E14+E15 -> 366773 | F16: =+F14+F15 -> 524479 | G16: =+G14+G15 -> 1126271 | J16: =C16/C$9 -> 0.42084245 | K16: =D16/D$9 -> 0.65585584 | L16: =E16/E$9 -> 0.27827701 | M16: =F16/F$9 -> 0.38688949 | N16: =G16/G$9 -> 0.44777358 | Q16: =C16/$C16 -> 1 | R16: =D16/$C16 -> 3.2411405 | S16: =E16/$C16 -> 2.7731421 | T16: =F16/$C16 -> 3.9655449 | U16: =G16/$C16 -> 8.5156473
B18: Operating Income (EBIT) | C18: =C11-C16 -> -4090 | D18: =D11-D16 -> -157801 | E18: =E11-E16 -> 266366 | F18: =F11-F16 -> 155728 | G18: =G11-G16 -> 141062 | J18: =C18/C$9 -> -0.013014204 | K18: =D18/D$9 -> -0.24143212 | L18: =E18/E$9 -> 0.20209649 | M18: =F18/F$9 -> 0.114875 | N18: =G18/G$9 -> 0.056082272 | Q18: =C18/$C18 -> 1 | R18: =D18/$C18 -> 38.582152 | S18: =E18/$C18 -> -65.126161 | T18: =F18/$C18 -> -38.075306 | U18: =G18/$C18 -> -34.489487
B19: Interest income | C19: 315 | D19: 237 | E19: 26629 | F19: 39263 | G19: 21085 | J19: =C19/C$9 -> 0.0010023165 | K19: =D19/D$9 -> 0.00036260488 | L19: =E19/E$9 -> 0.020203883 | M19: =F19/F$9 -> 0.028962918 | N19: =G19/G$9 -> 0.0083828012 | Q19: =C19/$C19 -> 1 | R19: =D19/$C19 -> 0.75238095 | S19: =E19/$C19 -> 84.536508 | T19: =F19/$C19 -> 124.64444 | U19: =G19/$C19 -> 66.936508
B20: Interest expense | C20: 8 | D20: -5292 | G20: 48977 | J20: =C20/C$9 -> 2.5455656e-05 | K20: =D20/D$9 -> -0.0080966457 | L20: =E20/E$9 -> 0 | M20: =F20/F$9 -> 0 | N20: =G20/G$9 -> 0.019471874 | Q20: =C20/$C20 -> 1 | R20: =D20/$C20 -> -661.5 | S20: =E20/$C20 -> 0 | T20: =F20/$C20 -> 0 | U20: =G20/$C20 -> 6122.125
B21: Equity income (loss) - net | J21: =C21/C$9 -> 0 | K21: =D21/D$9 -> 0 | L21: =E21/E$9 -> 0 | M21: =F21/F$9 -> 0 | N21: =G21/G$9 -> 0
B22: Other income (loss) - net | D22: -392 | E22: -1246 | F22: 59 | G22: 11863 | J22: =C22/C$9 -> 0 | K22: =D22/D$9 -> -0.00059975153 | L22: =E22/E$9 -> -0.00094536173 | M22: =F22/F$9 -> 4.35222e-05 | N22: =G22/G$9 -> 0.0047163942
B24: Pretax Income | C24: =C18+C19-C20+C21+C22 -> -3783 | D24: =D18+D19-D20+D21+D22 -> -152664 | E24: =E18+E19-E20+E21+E22 -> 291749 | F24: =F18+F19-F20+F21+F22 -> 195050 | G24: =G18+G19-G20+G21+G22 -> 125033 | J24: =C24/C$9 -> -0.012037343 | K24: =D24/D$9 -> -0.23357262 | L24: =E24/E$9 -> 0.22135501 | M24: =F24/F$9 -> 0.14388144 | N24: =G24/G$9 -> 0.049709594 | Q24: =C24/$C24 -> 1 | R24: =D24/$C24 -> 40.355274 | S24: =E24/$C24 -> -77.121068 | T24: =F24/$C24 -> -51.559609 | U24: =G24/$C24 -> -33.051282
B25: Provision for income taxes | C25: -7996 | D25: 34618 | E25: 64948 | F25: 49976 | G25: 17034 | J25: =C25/C$9 -> -0.025442928 | K25: =D25/D$9 -> 0.052964792 | L25: =E25/E$9 -> 0.04927717 | M25: =F25/F$9 -> 0.036865516 | N25: =G25/G$9 -> 0.0067722379 | Q25: =C25/$C25 -> 1 | R25: =D25/$C25 -> -4.3294147 | S25: =E25/$C25 -> -8.1225613 | T25: =F25/$C25 -> -6.2501251 | U25: =G25/$C25 -> -2.1303152
B26: Effective Tax rate | C26: =C25/C24 -> 2.1136664 | D26: =D25/D24 -> -0.22675942 | E26: =E25/E24 -> 0.22261602 | F26: =F25/F24 -> 0.25622148 | G26: =G25/G24 -> 0.13623603 | J26: =C26/C$9 -> 6.7255957e-06 | K26: =D26/D$9 -> -3.4693701e-07 | L26: =E26/E$9 -> 1.6890262e-07 | M26: =F26/F$9 -> 1.8900547e-07 | N26: =G26/G$9 -> 5.4163604e-08 | Q26: =C26/$C26 -> 1 | R26: =D26/$C26 -> -0.1072825 | S26: =E26/$C26 -> 0.10532221 | T26: =F26/$C26 -> 0.12122134 | U26: =G26/$C26 -> 0.064454842
B28: Net income | C28: =C24-C25 -> 4213 | D28: =D24-D25 -> -187282 | E28: =E24-E25 -> 226801 | F28: =F24-F25 -> 145074 | G28: =G24-G25 -> 107999 | J28: =C28/C$9 -> 0.013405585 | K28: =D28/D$9 -> -0.28653741 | L28: =E28/E$9 -> 0.17207784 | M28: =F28/F$9 -> 0.10701593 | N28: =G28/G$9 -> 0.042937356 | Q28: =C28/$C28 -> 1 | R28: =D28/$C28 -> -44.453359 | S28: =E28/$C28 -> 53.83361 | T28: =F28/$C28 -> 34.434845 | U28: =G28/$C28 -> 25.634702
B30: Number of Shares Outstanding | C30: =74909000/1000 -> 74909 | D30: =76382000/1000 -> 76382 | E30: =231787482/1000 -> 231787.48 | F30: =235014000/1000 -> 235014 | G30: =256906000/1000 -> 256906
B31: Stock Price | C31: 24.86 | D31: 34.68 | E31: 54.52 | F31: 26.34 | G31: 45.74
B35: Depreciation and amortization | C35: ='Celsius Holdings, Inc.'!B104 -> 1264 | D35: ='Celsius Holdings, Inc.'!C104 -> 1917 | E35: ='Celsius Holdings, Inc.'!D104 -> 3226 | F35: ='Celsius Holdings, Inc.'!E104 -> 7274 | G35: ='Celsius Holdings, Inc.'!F104 -> 29451
B36: Dividends Paid
B37: Net Cash Provided by Operating Activities
B38: Purchases of property, plant and equipment
B41: CELSIUS
B42: COMMON SIZING AND TREND ANALYSIS (in 000's Except Per Share Data)
B43: BALANCE SHEET DATA
B44: YOUR NAME | U44: Page 2 of 3
B45: =B5 -> FIN320 Section B
J47: Common-Size Analysis | Q47: Trend Analysis
J48: (as a percentage of total assets) | Q48: (using 2021 as a base year)
B49: Balance Sheet | C49: 2021 | D49: 2022 | E49: 2023 | F49: 2024 | G49: 2025 | J49: 2021 | K49: 2022 | L49: 2023 | M49: 2024 | N49: 2025 | Q49: 2021 | R49: 2022 | S49: 2023 | T49: 2024 | U49: 2025
B50: ASSETS:
B51: Current assets:
B52: Cash/Cash equivalents | C52: 16255 | D52: 614159 | E52: 755981 | F52: 890190 | G52: 398866 | J52: =C52/C$67 -> 0.051764549 | K52: =D52/D$67 -> 0.50255673 | L52: =E52/E$67 -> 0.49204827 | M52: =F52/F$67 -> 0.50382001 | N52: =G52/G$67 -> 0.077909283 | Q52: =C52/$C52 -> 1 | R52: =D52/$C52 -> 37.782775 | S52: =E52/$C52 -> 46.507598 | T52: =F52/$C52 -> 54.764073 | U52: =G52/$C52 -> 24.53805
B53: Short-term market sect | J53: =C53/C$67 -> 0 | K53: =D53/D$67 -> 0 | L53: =E53/E$67 -> 0 | M53: =F53/F$67 -> 0 | N53: =G53/G$67 -> 0
B54: Total Cash, Cash Equivalents and Short-Term Investments | C54: =SUM(C52:C53) -> 16255 | D54: =SUM(D52:D53) -> 614159 | E54: =SUM(E52:E53) -> 755981 | F54: =SUM(F52:F53) -> 890190 | G54: =SUM(G52:G53) -> 398866 | J54: =C54/C$67 -> 0.051764549 | K54: =D54/D$67 -> 0.50255673 | L54: =E54/E$67 -> 0.49204827 | M54: =F54/F$67 -> 0.50382001 | N54: =G54/G$67 -> 0.077909283 | Q54: =C54/$C54 -> 1 | R54: =D54/$C54 -> 37.782775 | S54: =E54/$C54 -> 46.507598 | T54: =F54/$C54 -> 54.764073 | U54: =G54/$C54 -> 24.53805
B55: Marketable securities | J55: =C55/C$67 -> 0 | K55: =D55/D$67 -> 0 | L55: =E55/E$67 -> 0 | M55: =F55/F$67 -> 0 | N55: =G55/G$67 -> 0
B56: Accounts receivable | C56: 38741 | D56: 63311 | E56: 183703 | F56: 270342 | G56: 755499 | J56: =C56/C$67 -> 0.12337191 | K56: =D56/D$67 -> 0.051806404 | L56: =E56/E$67 -> 0.11956748 | M56: =F56/F$67 -> 0.15300521 | N56: =G56/G$67 -> 0.14756932 | Q56: =C56/$C56 -> 1 | R56: =D56/$C56 -> 1.6342118 | S56: =E56/$C56 -> 4.7418239 | T56: =F56/$C56 -> 6.9781885 | U56: =G56/$C56 -> 19.501278
B57: Inventories | C57: 191222 | D57: 173289 | E57: 229275 | F57: 131165 | G57: 337698 | J57: =C57/C$67 -> 0.60895235 | K57: =D57/D$67 -> 0.14179969 | L57: =E57/E$67 -> 0.1492291 | M57: =F57/F$67 -> 0.074235333 | N57: =G57/G$67 -> 0.065961523 | Q57: =C57/$C57 -> 1 | R57: =D57/$C57 -> 0.90621895 | S57: =E57/$C57 -> 1.1989991 | T57: =F57/$C57 -> 0.68593049 | U57: =G57/$C57 -> 1.7659997
B58: Prepaid expenses and other current assets | C58: 16143 | D58: 67212 | E58: 35945 | F58: 32883 | G58: 319091 | J58: =C58/C$67 -> 0.051407881 | K58: =D58/D$67 -> 0.054998531 | L58: =E58/E$67 -> 0.023395661 | M58: =F58/F$67 -> 0.018610761 | N58: =G58/G$67 -> 0.062327075 | Q58: =C58/$C58 -> 1 | R58: =D58/$C58 -> 4.1635384 | S58: =E58/$C58 -> 2.2266617 | T58: =F58/$C58 -> 2.036982 | U58: =G58/$C58 -> 19.766524
B59: Total Current Assets | C59: =SUM(C54:C58) -> 262361 | D59: =SUM(D54:D58) -> 917971 | E59: =SUM(E54:E58) -> 1204904 | F59: =SUM(F54:F58) -> 1324580 | G59: =SUM(G54:G58) -> 1811154 | J59: =C59/C$67 -> 0.83549669 | K59: =D59/D$67 -> 0.75116135 | L59: =E59/E$67 -> 0.78424052 | M59: =F59/F$67 -> 0.74967131 | N59: =G59/G$67 -> 0.3537672 | Q59: =C59/$C59 -> 1 | R59: =D59/$C59 -> 3.4988851 | S59: =E59/$C59 -> 4.5925423 | T59: =F59/$C59 -> 5.0486925 | U59: =G59/$C59 -> 6.9032897
B60: Equity method investments | J60: =C60/C$67 -> 0 | K60: =D60/D$67 -> 0 | L60: =E60/E$67 -> 0 | M60: =F60/F$67 -> 0 | N60: =G60/G$67 -> 0
B61: Deferred income tax assets | C61: 9019 | D61: 501 | E61: 29518 | F61: 38699 | G61: 96013 | J61: =C61/C$67 -> 0.028721283 | K61: =D61/D$67 -> 0.00040996049 | L61: =E61/E$67 -> 0.019212495 | M61: =F61/F$67 -> 0.021902437 | N61: =G61/G$67 -> 0.018753927 | Q61: =C61/$C61 -> 1 | R61: =D61/$C61 -> 0.055549396 | S61: =E61/$C61 -> 3.2728684 | T61: =F61/$C61 -> 4.2908305 | U61: =G61/$C61 -> 10.645637
B62: PP&E, net | C62: 3180 | D62: 10185 | E62: 24868 | F62: 55602 | G62: 87910 | J62: =C62/C$67 -> 0.010126808 | K62: =D62/D$67 -> 0.0083342266 | L62: =E62/E$67 -> 0.016185931 | M62: =F62/F$67 -> 0.031469012 | N62: =G62/G$67 -> 0.017171193 | Q62: =C62/$C62 -> 1 | R62: =D62/$C62 -> 3.2028302 | S62: =E62/$C62 -> 7.8201258 | T62: =F62/$C62 -> 17.484906 | U62: =G62/$C62 -> 27.644654
B63: Trademarks with indefinite lives | C63: 16301 | D63: 12254 | E63: 12139 | F63: 12213 | G63: =111604+1280311 -> 1391915 | J63: =C63/C$67 -> 0.051911037 | K63: =D63/D$67 -> 0.010027257 | L63: =E63/E$67 -> 0.0079009578 | M63: =F63/F$67 -> 0.0069121803 | N63: =G63/G$67 -> 0.27187852 | Q63: =C63/$C63 -> 1 | R63: =D63/$C63 -> 0.75173302 | S63: =E63/$C63 -> 0.74467824 | T63: =F63/$C63 -> 0.74921784 | U63: =G63/$C63 -> 85.38832
B64: Goodwill | C64: 14527 | D64: 13679 | E64: 14173 | F64: 71582 | G64: 917560 | J64: =C64/C$67 -> 0.046261679 | K64: =D64/D$67 -> 0.011193312 | L64: =E64/E$67 -> 0.0092248353 | M64: =F64/F$67 -> 0.040513198 | N64: =G64/G$67 -> 0.1792242 | Q64: =C64/$C64 -> 1 | R64: =D64/$C64 -> 0.94162594 | S64: =E64/$C64 -> 0.97563158 | T64: =F64/$C64 -> 4.9275143 | U64: =G64/$C64 -> 63.162387
B65: Other noncurrent assets | C65: 8630 | D65: 267479 | E65: 250794 | F65: 264205 | G65: 815069 | J65: =C65/C$67 -> 0.027482501 | K65: =D65/D$67 -> 0.21887389 | L65: =E65/E$67 -> 0.16323526 | M65: =F65/F$67 -> 0.14953186 | N65: =G65/G$67 -> 0.15920495 | Q65: =C65/$C65 -> 1 | R65: =D65/$C65 -> 30.99409 | S65: =E65/$C65 -> 29.060718 | T65: =F65/$C65 -> 30.614716 | U65: =G65/$C65 -> 94.446002
B67: Total Assets | C67: =SUM(C59:C65) -> 314018 | D67: =SUM(D59:D65) -> 1222069 | E67: =SUM(E59:E65) -> 1536396 | F67: =SUM(F59:F65) -> 1766881 | G67: =SUM(G59:G65) -> 5119621 | J67: =C67/C$67 -> 1 | K67: =D67/D$67 -> 1 | L67: =E67/E$67 -> 1 | M67: =F67/F$67 -> 1 | N67: =G67/G$67 -> 1 | Q67: =C67/$C67 -> 1 | R67: =D67/$C67 -> 3.8917164 | S67: =E67/$C67 -> 4.8927004 | T67: =F67/$C67 -> 5.626687 | U67: =G67/$C67 -> 16.303591
B69: LIABILITIES AND SHAREHOLDERS' EQUITY:
B70: Current Liabilities
B71: Accounts payable and accrued expenses | C71: 72442 | D71: 107340 | E71: 104960 | F71: 190067 | G71: 368651 | J71: =C71/C$67 -> 0.23069378 | K71: =D71/D$67 -> 0.087834648 | L71: =E71/E$67 -> 0.068315721 | M71: =F71/F$67 -> 0.10757204 | N71: =G71/G$67 -> 0.072007479 | Q71: =C71/$C71 -> 1 | R71: =D71/$C71 -> 1.4817371 | S71: =E71/$C71 -> 1.4488832 | T71: =F71/$C71 -> 2.6237128 | U71: =G71/$C71 -> 5.0889125
B72: Loans and notes payable | J72: =C72/C$67 -> 0 | K72: =D72/D$67 -> 0 | L72: =E72/E$67 -> 0 | M72: =F72/F$67 -> 0 | N72: =G72/G$67 -> 0
B73: Accrued income taxes | C73: 0 | D73: 0 | E73: 50424 | F73: 10834 | G73: 49612 | J73: =C73/C$67 -> 0 | K73: =D73/D$67 -> 0 | L73: =E73/E$67 -> 0.032819664 | M73: =F73/F$67 -> 0.0061317089 | N73: =G73/G$67 -> 0.0096905611
B74: Other current liabilities | C74: 20682 | D74: 53955 | E74: 121229 | F74: 164634 | G74: 660463 | J74: =C74/C$67 -> 0.065862466 | K74: =D74/D$67 -> 0.044150535 | L74: =E74/E$67 -> 0.078904788 | M74: =F74/F$67 -> 0.093177752 | N74: =G74/G$67 -> 0.12900623 | Q74: =C74/$C74 -> 1 | R74: =D74/$C74 -> 2.6087903 | S74: =E74/$C74 -> 5.8615704 | T74: =F74/$C74 -> 7.9602553 | U74: =G74/$C74 -> 31.934194
B75: Total Current Liabilities | C75: =SUM(C71:C74) -> 93124 | D75: =SUM(D71:D74) -> 161295 | E75: =SUM(E71:E74) -> 276613 | F75: =SUM(F71:F74) -> 365535 | G75: =SUM(G71:G74) -> 1078726 | J75: =C75/C$67 -> 0.29655625 | K75: =D75/D$67 -> 0.13198518 | L75: =E75/E$67 -> 0.18004017 | M75: =F75/F$67 -> 0.2068815 | N75: =G75/G$67 -> 0.21070427 | Q75: =C75/$C75 -> 1 | R75: =D75/$C75 -> 1.7320454 | S75: =E75/$C75 -> 2.9703728 | T75: =F75/$C75 -> 3.9252502 | U75: =G75/$C75 -> 11.583759
B76: Long-term debt | C76: 0 | D76: 0 | E76: 0 | F76: 0 | G76: 669926 | N76: =G76/G$67 -> 0.13085461
B77: Other noncurrent liabilities | C77: 3849 | D77: 16407 | E77: 4028 | F77: 19215 | G77: 28372 | J77: =C77/C$67 -> 0.012257259 | K77: =D77/D$67 -> 0.013425592 | L77: =E77/E$67 -> 0.0026217199 | M77: =F77/F$67 -> 0.010875096 | N77: =G77/G$67 -> 0.0055418165 | Q77: =C77/$C77 -> 1 | R77: =D77/$C77 -> 4.2626656 | S77: =E77/$C77 -> 1.0465056 | T77: =F77/$C77 -> 4.9922058 | U77: =G77/$C77 -> 7.3712653
B78: Deferred revenue | C78: 0 | D78: 179788 | E78: 167227 | F78: 157714 | G78: 401155 | J78: =C78/C$67 -> 0 | K78: =D78/D$67 -> 0.14711772 | L78: =E78/E$67 -> 0.10884368 | M78: =F78/F$67 -> 0.089261246 | N78: =G78/G$67 -> 0.078356386
B79: Total Liabilities | C79: =SUM(C75:C78) -> 96973 | D79: =SUM(D75:D78) -> 357490 | E79: =SUM(E75:E78) -> 447868 | F79: =SUM(F75:F78) -> 542464 | G79: =SUM(G75:G78) -> 2178179 | J79: =C79/C$67 -> 0.30881351 | K79: =D79/D$67 -> 0.29252849 | L79: =E79/E$67 -> 0.29150558 | M79: =F79/F$67 -> 0.30701785 | N79: =G79/G$67 -> 0.42545708 | Q79: =C79/$C79 -> 1 | R79: =D79/$C79 -> 3.6864901 | S79: =E79/$C79 -> 4.6184814 | T79: =F79/$C79 -> 5.5939695 | U79: =G79/$C79 -> 22.461706
B80: Stockholders equity:
B81: Common stock | C81: 75 | D81: 76 | E81: 77 | F81: 79 | G81: 101 | J81: =C81/C$67 -> 0.00023883981 | K81: =D81/D$67 -> 6.2189614e-05 | L81: =E81/E$67 -> 5.0117287e-05 | M81: =F81/F$67 -> 4.4711557e-05 | N81: =G81/G$67 -> 1.9728023e-05 | Q81: =C81/$C81 -> 1 | R81: =D81/$C81 -> 1.0133333 | S81: =E81/$C81 -> 1.0266667 | T81: =F81/$C81 -> 1.0533333 | U81: =G81/$C81 -> 1.3466667
B82: Capital surplus | C82: 267846 | D82: 280668 | E82: 276717 | F82: 297579 | G82: 1050518 | J82: =C82/C$67 -> 0.85296384 | K82: =D82/D$67 -> 0.22966625 | L82: =E82/E$67 -> 0.18010786 | M82: =F82/F$67 -> 0.16842051 | N82: =G82/G$67 -> 0.20519449 | Q82: =C82/$C82 -> 1 | R82: =D82/$C82 -> 1.0478708 | S82: =E82/$C82 -> 1.0331198 | T82: =F82/$C82 -> 1.1110078 | U82: =G82/$C82 -> 3.922097
B83: Reinvested earnings | C83: -51490 | D83: -238772 | E83: -12053 | F83: 105521 | G83: 175912 | J83: =C83/C$67 -> -0.16397149 | K83: =D83/D$67 -> -0.1953834 | L83: =E83/E$67 -> -0.0078449827 | M83: =F83/F$67 -> 0.059721622 | N83: =G83/G$67 -> 0.034360356 | Q83: =C83/$C83 -> 1 | R83: =D83/$C83 -> 4.63725 | S83: =E83/$C83 -> 0.23408429 | T83: =F83/$C83 -> -2.0493494 | U83: =G83/$C83 -> -3.4164304
B84: Accumulated other comprehensive income (loss) | C84: 614 | D84: -1881 | E84: -701 | F84: -3250 | G84: 3162 | J84: =C84/C$67 -> 0.0019553019 | K84: =D84/D$67 -> -0.001539193 | L84: =E84/E$67 -> -0.00045626258 | M84: =F84/F$67 -> -0.0018393995 | N84: =G84/G$67 -> 0.00061762384 | Q84: =C84/$C84 -> 1 | R84: =D84/$C84 -> -3.0635179 | S84: =E84/$C84 -> -1.1416938 | T84: =F84/$C84 -> -5.2931596 | U84: =G84/$C84 -> 5.1498371
B85: Converitble preferred stock | C85: 0 | D85: 824488 | E85: 824488 | F85: 824488 | G85: 1759975
B86: Treasury stock | G86: -48226
B87: Total Shareholders' Equity (S/E) | C87: =SUM(C81:C86) -> 217045 | D87: =SUM(D81:D86) -> 864579 | E87: =SUM(E81:E86) -> 1088528 | F87: =SUM(F81:F86) -> 1224417 | G87: =SUM(G81:G86) -> 2941442 | J87: =C87/C$67 -> 0.69118649 | K87: =D87/D$67 -> 0.70747151 | L87: =E87/E$67 -> 0.70849442 | M87: =F87/F$67 -> 0.69298215 | N87: =G87/G$67 -> 0.57454292 | Q87: =C87/$C87 -> 1 | R87: =D87/$C87 -> 3.983409 | S87: =E87/$C87 -> 5.015218 | T87: =F87/$C87 -> 5.6413048 | U87: =G87/$C87 -> 13.552222
B88: Equity Attributable to Noncontrolling Interests | J88: =C88/C$67 -> 0 | K88: =D88/D$67 -> 0 | L88: =E88/E$67 -> 0 | M88: =F88/F$67 -> 0 | N88: =G88/G$67 -> 0 | Q88: =C88/$C88 -> #DIV/0! | R88: =D88/$C88 -> #DIV/0! | S88: =E88/$C88 -> #DIV/0! | T88: =F88/$C88 -> #DIV/0! | U88: =G88/$C88 -> #DIV/0!
B89: Total Equity | C89: =SUM(C87:C88) -> 217045 | D89: =SUM(D87:D88) -> 864579 | E89: =SUM(E87:E88) -> 1088528 | F89: =SUM(F87:F88) -> 1224417 | G89: =SUM(G87:G88) -> 2941442 | J89: =C89/C$67 -> 0.69118649 | K89: =D89/D$67 -> 0.70747151 | L89: =E89/E$67 -> 0.70849442 | M89: =F89/F$67 -> 0.69298215 | N89: =G89/G$67 -> 0.57454292 | Q89: =C89/$C89 -> 1 | R89: =D89/$C89 -> 3.983409 | S89: =E89/$C89 -> 5.015218 | T89: =F89/$C89 -> 5.6413048 | U89: =G89/$C89 -> 13.552222
B90: Total Liabilities and S/E | C90: =C89+C79 -> 314018 | D90: =D89+D79 -> 1222069 | E90: =E89+E79 -> 1536396 | F90: =F89+F79 -> 1766881 | G90: =G89+G79 -> 5119621 | J90: =C90/C$67 -> 1 | K90: =D90/D$67 -> 1 | L90: =E90/E$67 -> 1 | M90: =F90/F$67 -> 1 | N90: =G90/G$67 -> 1 | Q90: =C90/$C90 -> 1 | R90: =D90/$C90 -> 3.8917164 | S90: =E90/$C90 -> 4.8927004 | T90: =F90/$C90 -> 5.626687 | U90: =G90/$C90 -> 16.303591
B93: Liquidity ratios | C93: 2021 | D93: 2022 | E93: 2023 | F93: 2024 | G93: 2025
B94: ='FINANCIAL RATIOS'!B15 -> Current Ratio = Current Assets / Current Liabilities | C94: ='FINANCIAL RATIOS'!C19 -> 2.8173296 | D94: ='FINANCIAL RATIOS'!D19 -> 5.6912552 | E94: ='FINANCIAL RATIOS'!E19 -> 4.3559196 | F94: ='FINANCIAL RATIOS'!F19 -> 3.6236749 | G94: ='FINANCIAL RATIOS'!G19 -> 1.678975
B95: ='FINANCIAL RATIOS'!B23 -> Quick Ratio = (Current Assets - Inventories) / Current Liabilities | C95: ='FINANCIAL RATIOS'!C27 -> 0.76391693 | D95: ='FINANCIAL RATIOS'!D27 -> 4.6168945 | E95: ='FINANCIAL RATIOS'!E27 -> 3.527054 | F95: ='FINANCIAL RATIOS'!F27 -> 3.2648447 | G95: ='FINANCIAL RATIOS'!G27 -> 1.3659224
B96: ='FINANCIAL RATIOS'!B31 -> Cash Ratio = Cash / Current Liabilities | C96: ='FINANCIAL RATIOS'!C35 -> 0.17455221 | D96: ='FINANCIAL RATIOS'!D35 -> 3.8076754 | E96: ='FINANCIAL RATIOS'!E35 -> 2.7329916 | F96: ='FINANCIAL RATIOS'!F35 -> 2.4353072 | G96: ='FINANCIAL RATIOS'!G35 -> 0.36975655
B97: ='FINANCIAL RATIOS'!B39 -> NWC Ratio = (Current Assets - Current Liabilities) / Total Assets | C97: ='FINANCIAL RATIOS'!C43 -> 0.53894044 | D97: ='FINANCIAL RATIOS'!D43 -> 0.61917617 | E97: ='FINANCIAL RATIOS'!E43 -> 0.60420035 | F97: ='FINANCIAL RATIOS'!F43 -> 0.54278981 | G97: ='FINANCIAL RATIOS'!G43 -> 0.14306293
B98: ='FINANCIAL RATIOS'!B47 -> Interval Measure = Current Assets / Average Daily Costs (COGS + Oper. Exp.) | C98: ='FINANCIAL RATIOS'!C51 -> 300.79521 | D98: ='FINANCIAL RATIOS'!D51 -> 412.93733 | E98: ='FINANCIAL RATIOS'!E51 -> 418.19122 | F98: ='FINANCIAL RATIOS'!F51 -> 402.92599 | G98: ='FINANCIAL RATIOS'!G51 -> 278.43874
B100: Solvency ratios | C100: 2021 | D100: 2022 | E100: 2023 | F100: 2024 | G100: 2025
B101: ='FINANCIAL RATIOS'!B58 -> Total Debt Ratio = Financial Debt / Total Assets | C101: ='FINANCIAL RATIOS'!C62 -> 0 | D101: ='FINANCIAL RATIOS'!D62 -> 0 | E101: ='FINANCIAL RATIOS'!E62 -> 0 | F101: ='FINANCIAL RATIOS'!F62 -> 0 | G101: ='FINANCIAL RATIOS'!G62 -> 0.13085461
B102: ='FINANCIAL RATIOS'!B66 -> Debt-to-Equity Ratio = (Short-term Debt + Long-term Debt) / Total Equity | C102: ='FINANCIAL RATIOS'!C70 -> 0 | D102: ='FINANCIAL RATIOS'!D70 -> 0 | E102: ='FINANCIAL RATIOS'!E70 -> 0 | F102: ='FINANCIAL RATIOS'!F70 -> 0 | G102: ='FINANCIAL RATIOS'!G70 -> 0.22775428
B103: ='FINANCIAL RATIOS'!B74 -> Times Interest Earned = EBIT / Interest Expenses | C103: ='FINANCIAL RATIOS'!C78 -> -511.25 | D103: ='FINANCIAL RATIOS'!D78 -> 29.818783 | E103: ='FINANCIAL RATIOS'!E78 -> N/A | F103: ='FINANCIAL RATIOS'!F78 -> N/A | G103: ='FINANCIAL RATIOS'!G78 -> 2.8801682
B104: ='FINANCIAL RATIOS'!B82 -> Cash Coverage Ratio = (EBIT+Depreciation) / Interest Expenses | C104: ='FINANCIAL RATIOS'!C86 -> -353.25 | D104: ='FINANCIAL RATIOS'!D86 -> 29.456538 | E104: ='FINANCIAL RATIOS'!E86 -> N/A | F104: ='FINANCIAL RATIOS'!F86 -> N/A | G104: ='FINANCIAL RATIOS'!G86 -> 3.4814913
B106: Asset Management / Turnover Ratios | C106: 2021 | D106: 2022 | E106: 2023 | F106: 2024 | G106: 2025
B107: ='FINANCIAL RATIOS'!B93 -> Assets Turnover Ratio = Sales / Total Assets | C107: ='FINANCIAL RATIOS'!C97 -> 1.0008089 | D107: ='FINANCIAL RATIOS'!D97 -> 0.53483396 | E107: ='FINANCIAL RATIOS'!E97 -> 0.85786086 | F107: ='FINANCIAL RATIOS'!F97 -> 0.76724465 | G107: ='FINANCIAL RATIOS'!G97 -> 0.49129984
B108: ='FINANCIAL RATIOS'!B100 -> Inventory Turnover = COGS / Inventories | C108: ='FINANCIAL RATIOS'!C104 -> 0.97323007 | D108: ='FINANCIAL RATIOS'!D104 -> 2.2086514 | E108: ='FINANCIAL RATIOS'!E104 -> 2.9871334 | F108: ='FINANCIAL RATIOS'!F104 -> 5.1494149 | G108: ='FINANCIAL RATIOS'!G104 -> 3.6954202
B109: ='FINANCIAL RATIOS'!B107 -> Days Sales in Inventory = 365 / Inventory Turnover | C109: ='FINANCIAL RATIOS'!C111 -> 375.03979 | D109: ='FINANCIAL RATIOS'!D111 -> 165.25921 | E109: ='FINANCIAL RATIOS'!E111 -> 122.19073 | F109: ='FINANCIAL RATIOS'!F111 -> 70.88184 | G109: ='FINANCIAL RATIOS'!G111 -> 98.770907
B110: ='FINANCIAL RATIOS'!B114 -> Receivables Turnover = Sales / Accounts Receivables | C110: ='FINANCIAL RATIOS'!C118 -> 8.1121293 | D110: ='FINANCIAL RATIOS'!D118 -> 10.323704 | E110: ='FINANCIAL RATIOS'!E118 -> 7.1747005 | F110: ='FINANCIAL RATIOS'!F118 -> 5.0145002 | G110: ='FINANCIAL RATIOS'!G118 -> 3.3292817
B111: ='FINANCIAL RATIOS'!B121 -> Days Sales in Receivables = 365 / Receivables Turnover | C111: ='FINANCIAL RATIOS'!C125 -> 44.994352 | D111: ='FINANCIAL RATIOS'!D125 -> 35.355529 | E111: ='FINANCIAL RATIOS'!E125 -> 50.873204 | F111: ='FINANCIAL RATIOS'!F125 -> 72.78891 | G111: ='FINANCIAL RATIOS'!G125 -> 109.63326
B112: ='FINANCIAL RATIOS'!B128 -> Operating Cycle = Days Sales in Inventory + Days Sales in Receivables | C112: ='FINANCIAL RATIOS'!C132 -> 420.03414 | D112: ='FINANCIAL RATIOS'!D132 -> 200.61474 | E112: ='FINANCIAL RATIOS'!E132 -> 173.06393 | F112: ='FINANCIAL RATIOS'!F132 -> 143.67075 | G112: ='FINANCIAL RATIOS'!G132 -> 208.40416
B114: Profitability Ratios | C114: 2021 | D114: 2022 | E114: 2023 | F114: 2024 | G114: 2025
B115: ='FINANCIAL RATIOS'!B139 -> Gross Profit Margin = Gross Profits / Sales | C115: ='FINANCIAL RATIOS'!C143 -> 0.40782825 | D115: ='FINANCIAL RATIOS'!D143 -> 0.41442372 | E115: ='FINANCIAL RATIOS'!E143 -> 0.4803735 | F115: ='FINANCIAL RATIOS'!F143 -> 0.50176449 | G115: ='FINANCIAL RATIOS'!G143 -> 0.50385585
B116: ='FINANCIAL RATIOS'!B147 -> Operating Profit Margin = Operating Profits / Sales | C116: ='FINANCIAL RATIOS'!C151 -> -0.013014204 | D116: ='FINANCIAL RATIOS'!D151 -> -0.24143212 | E116: ='FINANCIAL RATIOS'!E151 -> 0.20209649 | F116: ='FINANCIAL RATIOS'!F151 -> 0.114875 | G116: ='FINANCIAL RATIOS'!G151 -> 0.056082272
B117: ='FINANCIAL RATIOS'!B155 -> Net Profit Margin = Net Income / Sales | C117: ='FINANCIAL RATIOS'!C159 -> 0.013405585 | D117: ='FINANCIAL RATIOS'!D159 -> -0.28653741 | E117: ='FINANCIAL RATIOS'!E159 -> 0.17207784 | F117: ='FINANCIAL RATIOS'!F159 -> 0.10701593 | G117: ='FINANCIAL RATIOS'!G159 -> 0.042937356
B118: ='FINANCIAL RATIOS'!B163 -> Return on Assets (ROA) = Net Income / Total Assets | C118: ='FINANCIAL RATIOS'!C167 -> 0.013416428 | D118: ='FINANCIAL RATIOS'!D167 -> -0.15324994 | E118: ='FINANCIAL RATIOS'!E167 -> 0.14761884 | F118: ='FINANCIAL RATIOS'!F167 -> 0.082107397 | G118: ='FINANCIAL RATIOS'!G167 -> 0.021095116
B119: ='FINANCIAL RATIOS'!B170 -> Return on Equity (ROE) -based on BV of equity = Net Income / Total Equity | C119: ='FINANCIAL RATIOS'!C174 -> 0.019410721 | D119: ='FINANCIAL RATIOS'!D174 -> -0.21661641 | E119: ='FINANCIAL RATIOS'!E174 -> 0.20835569 | F119: ='FINANCIAL RATIOS'!F174 -> 0.11848414 | G119: ='FINANCIAL RATIOS'!G174 -> 0.036716345
...

Sheet K.Dr Paper (KDP)
B1: DR. PEPPER
B2: COMMON SIZING AND TREND ANALYSIS (in 000's Except Per Share Data)
B3: INCOME STATEMENT DATA
B4: NAME | U4: Page 1 of 3
B5: FIN320 Section B
J6: Common-Size Analysis | Q6: Trend Analysis
J7: (as a percentage of sales) | Q7: (using 2020 as the base year)
B8: Income Statement | C8: 2021 | D8: 2022 | E8: 2023 | F8: 2024 | G8: 2025 | J8: 2021 | K8: 2022 | L8: 2023 | M8: 2024 | N8: 2025 | Q8: 2021 | R8: 2022 | S8: 2023 | T8: 2024 | U8: 2025
B9: Net Operating Revenues | C9: 12683 | D9: 14057 | E9: 14814 | F9: 15351 | G9: 16603 | J9: =C9/C$9 -> 1 | K9: =D9/D$9 -> 1 | L9: =E9/E$9 -> 1 | M9: =F9/F$9 -> 1 | N9: =G9/G$9 -> 1 | Q9: =C9/$C9 -> 1 | R9: =D9/$C9 -> 1.108334 | S9: =E9/$C9 -> 1.1680202 | T9: =F9/$C9 -> 1.2103603 | U9: =G9/$C9 -> 1.3090751
B10: Cost of sales | C10: 5706 | D10: 6734 | E10: 6734 | F10: 6822 | G10: 7604 | J10: =C10/C$9 -> 0.44989356 | K10: =D10/D$9 -> 0.47904958 | L10: =E10/E$9 -> 0.45457 | M10: =F10/F$9 -> 0.44440102 | N10: =G10/G$9 -> 0.45798952 | Q10: =C10/$C10 -> 1 | R10: =D10/$C10 -> 1.1801612 | S10: =E10/$C10 -> 1.1801612 | T10: =F10/$C10 -> 1.1955836 | U10: =G10/$C10 -> 1.3326323
B11: Gross Profit | C11: =C9-C10 -> 6977 | D11: =D9-D10 -> 7323 | E11: =E9-E10 -> 8080 | F11: =F9-F10 -> 8529 | G11: =G9-G10 -> 8999 | J11: =C11/C$9 -> 0.55010644 | K11: =D11/D$9 -> 0.52095042 | L11: =E11/E$9 -> 0.54543 | M11: =F11/F$9 -> 0.55559898 | N11: =G11/G$9 -> 0.54201048 | Q11: =C11/$C11 -> 1 | R11: =D11/$C11 -> 1.0495915 | S11: =E11/$C11 -> 1.1580909 | T11: =F11/$C11 -> 1.2224452 | U11: =G11/$C11 -> 1.2898094
B13: Operating expenses
B14: Selling, general and administrative expenses | C14: 3765 | D14: 4283 | E14: 4488 | F14: 4525 | G14: 4874 | J14: =C14/C$9 -> 0.29685406 | K14: =D14/D$9 -> 0.30468806 | L14: =E14/E$9 -> 0.30295666 | M14: =F14/F$9 -> 0.29476907 | N14: =G14/G$9 -> 0.2935614 | Q14: =C14/$C14 -> 1 | R14: =D14/$C14 -> 1.137583 | S14: =E14/$C14 -> 1.1920319 | T14: =F14/$C14 -> 1.2018592 | U14: =G14/$C14 -> 1.2945551
B15: Other operating charges | C15: 183 | D15: 166 | E15: 365 | F15: 608 | G15: 413 | J15: =C15/C$9 -> 0.014428763 | K15: =D15/D$9 -> 0.011809063 | L15: =E15/E$9 -> 0.024638855 | M15: =F15/F$9 -> 0.03960654 | N15: =G15/G$9 -> 0.024875023 | Q15: =C15/$C15 -> 1 | R15: =D15/$C15 -> 0.90710383 | S15: =E15/$C15 -> 1.9945355 | T15: =F15/$C15 -> 3.3224044 | U15: =G15/$C15 -> 2.2568306
B16: Total Oper. Exp | C16: =+C14+C15 -> 3948 | D16: =+D14+D15 -> 4449 | E16: =+E14+E15 -> 4853 | F16: =+F14+F15 -> 5133 | G16: =+G14+G15 -> 5287 | J16: =C16/C$9 -> 0.31128282 | K16: =D16/D$9 -> 0.31649712 | L16: =E16/E$9 -> 0.32759552 | M16: =F16/F$9 -> 0.33437561 | N16: =G16/G$9 -> 0.31843643 | Q16: =C16/$C16 -> 1 | R16: =D16/$C16 -> 1.1268997 | S16: =E16/$C16 -> 1.22923 | T16: =F16/$C16 -> 1.300152 | U16: =G16/$C16 -> 1.3391591
B18: Operating Income (EBIT) | C18: =C11-C16 -> 3029 | D18: =D11-D16 -> 2874 | E18: =E11-E16 -> 3227 | F18: =F11-F16 -> 3396 | G18: =G11-G16 -> 3712 | J18: =C18/C$9 -> 0.23882362 | K18: =D18/D$9 -> 0.2044533 | L18: =E18/E$9 -> 0.21783448 | M18: =F18/F$9 -> 0.22122337 | N18: =G18/G$9 -> 0.22357405 | Q18: =C18/$C18 -> 1 | R18: =D18/$C18 -> 0.948828 | S18: =E18/$C18 -> 1.0653681 | T18: =F18/$C18 -> 1.1211621 | U18: =G18/$C18 -> 1.225487
B19: Interest income | J19: =C19/C$9 -> 0 | K19: =D19/D$9 -> 0 | L19: =E19/E$9 -> 0 | M19: =F19/F$9 -> 0 | N19: =G19/G$9 -> 0
B20: Interest expense | C20: 500 | D20: 693 | E20: 496 | F20: 735 | G20: 754 | J20: =C20/C$9 -> 0.039422849 | K20: =D20/D$9 -> 0.049299281 | L20: =E20/E$9 -> 0.033481842 | M20: =F20/F$9 -> 0.047879617 | N20: =G20/G$9 -> 0.045413479 | Q20: =C20/$C20 -> 1 | R20: =D20/$C20 -> 1.386 | S20: =E20/$C20 -> 0.992 | T20: =F20/$C20 -> 1.47 | U20: =G20/$C20 -> 1.508
B21: Equity income (loss) - net | C21: -5 | D21: -5 | E21: 33 | F21: 42 | G21: 81 | J21: =C21/C$9 -> -0.00039422849 | K21: =D21/D$9 -> -0.00035569467 | L21: =E21/E$9 -> 0.0022276225 | M21: =F21/F$9 -> 0.0027359781 | N21: =G21/G$9 -> 0.0048786364 | Q21: =C21/$C21 -> 1 | R21: =D21/$C21 -> 1 | S21: =E21/$C21 -> -6.6 | T21: =F21/$C21 -> -8.4 | U21: =G21/$C21 -> -16.2
B22: Other income (loss) - net | C22: 274 | D22: -457 | E22: -7 | F22: -789 | G22: -352 | J22: =C22/C$9 -> 0.021603722 | K22: =D22/D$9 -> -0.032510493 | L22: =E22/E$9 -> -0.00047252599 | M22: =F22/F$9 -> -0.051397303 | N22: =G22/G$9 -> -0.021200988 | Q22: =C22/$C22 -> 1 | R22: =D22/$C22 -> -1.6678832 | S22: =E22/$C22 -> -0.025547445 | T22: =F22/$C22 -> -2.879562 | U22: =G22/$C22 -> -1.2846715
B24: Pretax Income | C24: =C18+C19-C20+C21+C22 -> 2798 | D24: =D18+D19-D20+D21+D22 -> 1719 | E24: =E18+E19-E20+E21+E22 -> 2757 | F24: =F18+F19-F20+F21+F22 -> 1914 | G24: =G18+G19-G20+G21+G22 -> 2687 | J24: =C24/C$9 -> 0.22061027 | K24: =D24/D$9 -> 0.12228783 | L24: =E24/E$9 -> 0.18610774 | M24: =F24/F$9 -> 0.12468243 | N24: =G24/G$9 -> 0.16183822 | Q24: =C24/$C24 -> 1 | R24: =D24/$C24 -> 0.61436741 | S24: =E24/$C24 -> 0.98534668 | T24: =F24/$C24 -> 0.68406004 | U24: =G24/$C24 -> 0.96032881
B25: Provision for income taxes | C25: 653 | D25: 284 | E25: 576 | F25: 473 | G25: 608 | J25: =C25/C$9 -> 0.051486241 | K25: =D25/D$9 -> 0.020203457 | L25: =E25/E$9 -> 0.038882139 | M25: =F25/F$9 -> 0.030812325 | N25: =G25/G$9 -> 0.036619888 | Q25: =C25/$C25 -> 1 | R25: =D25/$C25 -> 0.43491577 | S25: =E25/$C25 -> 0.8820827 | T25: =F25/$C25 -> 0.72434916 | U25: =G25/$C25 -> 0.93108729
B26: Effective Tax rate | C26: =C25/C24 -> 0.23338099 | D26: =D25/D24 -> 0.16521233 | E26: =E25/E24 -> 0.20892274 | F26: =F25/F24 -> 0.24712644 | G26: =G25/G24 -> 0.22627466 | J26: =C26/C$9 -> 1.8401087e-05 | K26: =D26/D$9 -> 1.1753029e-05 | L26: =E26/E$9 -> 1.4103061e-05 | M26: =F26/F$9 -> 1.6098393e-05 | N26: =G26/G$9 -> 1.362854e-05 | Q26: =C26/$C26 -> 1 | R26: =D26/$C26 -> 0.70790828 | S26: =E26/$C26 -> 0.89520036 | T26: =F26/$C26 -> 1.058897 | U26: =G26/$C26 -> 0.96955052
B28: Net income | C28: =C24-C25 -> 2145 | D28: =D24-D25 -> 1435 | E28: =E24-E25 -> 2181 | F28: =F24-F25 -> 1441 | G28: =G24-G25 -> 2079 | J28: =C28/C$9 -> 0.16912402 | K28: =D28/D$9 -> 0.10208437 | L28: =E28/E$9 -> 0.1472256 | M28: =F28/F$9 -> 0.093870106 | N28: =G28/G$9 -> 0.12521833 | Q28: =C28/$C28 -> 1 | R28: =D28/$C28 -> 0.66899767 | S28: =E28/$C28 -> 1.0167832 | T28: =F28/$C28 -> 0.67179487 | U28: =G28/$C28 -> 0.96923077
B30: Number of Shares Outstanding | C30: =KDP!B45 -> 1415.7 | D30: =KDP!C45 -> 1416.8 | E30: =KDP!D45 -> 1399.3 | F30: =KDP!E45 -> 1362.2 | G30: =KDP!F45 -> 1358.1
B31: Stock Price | C31: =KDP!B101 -> 29 | D31: =KDP!C101 -> 36 | E31: =KDP!D101 -> 32 | F31: =KDP!E101 -> 32 | G31: =KDP!F101 -> 28
B35: Depreciation and amortization | C35: =KDP!B18 -> 177 | D35: =KDP!C18 -> 170 | E35: =KDP!D18 -> 171 | F35: =KDP!E18 -> 188 | G35: =KDP!F18 -> 209
B36: Dividends Paid
B37: Net Cash Provided by Operating Activities
B38: Purchases of property, plant and equipment
B41: DR. PEPPER
B42: COMMON SIZING AND TREND ANALYSIS (in 000's Except Per Share Data)
B43: BALANCE SHEET DATA
B44: YOUR NAME | U44: Page 2 of 3
B45: =B5 -> FIN320 Section B
J47: Common-Size Analysis | Q47: Trend Analysis
J48: (as a percentage of total assets) | Q48: (using 2021 as a base year)
B49: Balance Sheet | C49: 2021 | D49: 2022 | E49: 2023 | F49: 2024 | G49: 2025 | J49: 2021 | K49: 2022 | L49: 2023 | M49: 2024 | N49: 2025 | Q49: 2021 | R49: 2022 | S49: 2023 | T49: 2024 | U49: 2025
B50: ASSETS:
B51: Current assets:
B52: Cash/Cash equivalents | C52: 567 | D52: 535 | E52: 267 | F52: 510 | G52: 1026 | J52: =C52/C$67 -> 0.011205977 | K52: =D52/D$67 -> 0.010320813 | L52: =E52/E$67 -> 0.0051218109 | M52: =F52/F$67 -> 0.0095451993 | N52: =G52/G$67 -> 0.018500153 | Q52: =C52/$C52 -> 1 | R52: =D52/$C52 -> 0.94356261 | S52: =E52/$C52 -> 0.47089947 | T52: =F52/$C52 -> 0.8994709 | U52: =G52/$C52 -> 1.8095238
B53: Short-term market sect | C53: 2 | J53: =C53/C$67 -> 3.9527254e-05 | K53: =D53/D$67 -> 0 | L53: =E53/E$67 -> 0 | M53: =F53/F$67 -> 0 | N53: =G53/G$67 -> 0 | Q53: =C53/$C53 -> 1 | R53: =D53/$C53 -> 0 | S53: =E53/$C53 -> 0 | T53: =F53/$C53 -> 0 | U53: =G53/$C53 -> 0
B54: Total Cash, Cash Equivalents and Short-Term Investments | C54: =SUM(C52:C53) -> 569 | D54: =SUM(D52:D53) -> 535 | E54: =SUM(E52:E53) -> 267 | F54: =SUM(F52:F53) -> 510 | G54: =SUM(G52:G53) -> 1026 | J54: =C54/C$67 -> 0.011245504 | K54: =D54/D$67 -> 0.010320813 | L54: =E54/E$67 -> 0.0051218109 | M54: =F54/F$67 -> 0.0095451993 | N54: =G54/G$67 -> 0.018500153 | Q54: =C54/$C54 -> 1 | R54: =D54/$C54 -> 0.94024605 | S54: =E54/$C54 -> 0.46924429 | T54: =F54/$C54 -> 0.89630931 | U54: =G54/$C54 -> 1.8031634
B55: Marketable securities | J55: =C55/C$67 -> 0 | K55: =D55/D$67 -> 0 | L55: =E55/E$67 -> 0 | M55: =F55/F$67 -> 0 | N55: =G55/G$67 -> 0
B56: Accounts receivable | C56: 1148 | D56: 1484 | E56: 1368 | F56: 1502 | G56: 1671 | J56: =C56/C$67 -> 0.022688644 | K56: =D56/D$67 -> 0.0286282 | L56: =E56/E$67 -> 0.026242087 | M56: =F56/F$67 -> 0.028111548 | N56: =G56/G$67 -> 0.030130367 | Q56: =C56/$C56 -> 1 | R56: =D56/$C56 -> 1.2926829 | S56: =E56/$C56 -> 1.1916376 | T56: =F56/$C56 -> 1.3083624 | U56: =G56/$C56 -> 1.4555749
B57: Inventories | C57: 966 | D57: 1403 | E57: 1253 | F57: 1299 | G57: 1733 | J57: =C57/C$67 -> 0.019091664 | K57: =D57/D$67 -> 0.02706561 | L57: =E57/E$67 -> 0.024036064 | M57: =F57/F$67 -> 0.024312184 | N57: =G57/G$67 -> 0.03124831 | Q57: =C57/$C57 -> 1 | R57: =D57/$C57 -> 1.452381 | S57: =E57/$C57 -> 1.2971014 | T57: =F57/$C57 -> 1.3447205 | U57: =G57/$C57 -> 1.7939959
B58: Prepaid expenses and other current assets | C58: 374 | D58: 382 | E58: 487 | F58: 686 | G58: 836 | J58: =C58/C$67 -> 0.0073915965 | K58: =D58/D$67 -> 0.0073692536 | L58: =E58/E$67 -> 0.0093420295 | M58: =F58/F$67 -> 0.012839229 | N58: =G58/G$67 -> 0.015074199 | Q58: =C58/$C58 -> 1 | R58: =D58/$C58 -> 1.0213904 | S58: =E58/$C58 -> 1.302139 | T58: =F58/$C58 -> 1.8342246 | U58: =G58/$C58 -> 2.2352941
B59: Total Current Assets | C59: =SUM(C54:C58) -> 3057 | D59: =SUM(D54:D58) -> 3804 | E59: =SUM(E54:E58) -> 3375 | F59: =SUM(F54:F58) -> 3997 | G59: =SUM(G54:G58) -> 5266 | J59: =C59/C$67 -> 0.060417408 | K59: =D59/D$67 -> 0.073383876 | L59: =E59/E$67 -> 0.064741991 | M59: =F59/F$67 -> 0.07480816 | N59: =G59/G$67 -> 0.094953028 | Q59: =C59/$C59 -> 1 | R59: =D59/$C59 -> 1.2443572 | S59: =E59/$C59 -> 1.1040236 | T59: =F59/$C59 -> 1.307491 | U59: =G59/$C59 -> 1.7226039
B60: Equity method investments | C60: 31 | D60: 1186 | E60: 1456 | F60: 1543 | G60: 1697 | J60: =C60/C$67 -> 0.00061267244 | K60: =D60/D$67 -> 0.02287941 | L60: =E60/E$67 -> 0.027930175 | M60: =F60/F$67 -> 0.028878907 | N60: =G60/G$67 -> 0.030599181 | Q60: =C60/$C60 -> 1 | R60: =D60/$C60 -> 38.258065 | S60: =E60/$C60 -> 46.967742 | T60: =F60/$C60 -> 49.774194 | U60: =G60/$C60 -> 54.741935
B61: Deferred income tax assets | C61: 42 | D61: 35 | E61: 31 | F61: 39 | G61: 36 | J61: =C61/C$67 -> 0.00083007233 | K61: =D61/D$67 -> 0.00067519339 | L61: =E61/E$67 -> 0.00059466718 | M61: =F61/F$67 -> 0.00072992701 | N61: =G61/G$67 -> 0.00064912818 | Q61: =C61/$C61 -> 1 | R61: =D61/$C61 -> 0.83333333 | S61: =E61/$C61 -> 0.73809524 | T61: =F61/$C61 -> 0.92857143 | U61: =G61/$C61 -> 0.85714286
B62: PP&E, net | C62: 3167 | D62: 3372 | E62: 3575 | F62: 3844 | G62: 4075 | J62: =C62/C$67 -> 0.062591407 | K62: =D62/D$67 -> 0.065050061 | L62: =E62/E$67 -> 0.068578554 | M62: =F62/F$67 -> 0.0719446 | N62: =G62/G$67 -> 0.073477704 | Q62: =C62/$C62 -> 1 | R62: =D62/$C62 -> 1.06473 | S62: =E62/$C62 -> 1.1288285 | T62: =F62/$C62 -> 1.213767 | U62: =G62/$C62 -> 1.2867067
B63: Trademarks with indefinite lives | C63: 23856 | D63: 23183 | E63: 23287 | F63: 23634 | G63: 23725 | J63: =C63/C$67 -> 0.47148109 | K63: =D63/D$67 -> 0.44722881 | L63: =E63/E$67 -> 0.44671015 | M63: =F63/F$67 -> 0.44233577 | N63: =G63/G$67 -> 0.42779351 | Q63: =C63/$C63 -> 1 | R63: =D63/$C63 -> 0.97178907 | S63: =E63/$C63 -> 0.97614856 | T63: =F63/$C63 -> 0.99069416 | U63: =G63/$C63 -> 0.99450872
B64: Goodwill | C64: 20182 | D64: 20072 | E64: 20202 | F64: 20053 | G64: 20247 | J64: =C64/C$67 -> 0.39886952 | K64: =D64/D$67 -> 0.38721377 | L64: =E64/E$67 -> 0.38753117 | M64: =F64/F$67 -> 0.37531349 | N64: =G64/G$67 -> 0.36508051 | Q64: =C64/$C64 -> 1 | R64: =D64/$C64 -> 0.9945496 | S64: =E64/$C64 -> 1.000991 | T64: =F64/$C64 -> 0.99360817 | U64: =G64/$C64 -> 1.0032207
B65: Other noncurrent assets | C65: 263 | D65: 185 | E65: 204 | F65: 320 | G65: 413 | J65: =C65/C$67 -> 0.0051978339 | K65: =D65/D$67 -> 0.0035688794 | L65: =E65/E$67 -> 0.0039132937 | M65: =F65/F$67 -> 0.0059891447 | N65: =G65/G$67 -> 0.0074469428 | Q65: =C65/$C65 -> 1 | R65: =D65/$C65 -> 0.70342205 | S65: =E65/$C65 -> 0.7756654 | T65: =F65/$C65 -> 1.21673 | U65: =G65/$C65 -> 1.5703422
B67: Total Assets | C67: =SUM(C59:C65) -> 50598 | D67: =SUM(D59:D65) -> 51837 | E67: =SUM(E59:E65) -> 52130 | F67: =SUM(F59:F65) -> 53430 | G67: =SUM(G59:G65) -> 55459 | J67: =C67/C$67 -> 1 | K67: =D67/D$67 -> 1 | L67: =E67/E$67 -> 1 | M67: =F67/F$67 -> 1 | N67: =G67/G$67 -> 1 | Q67: =C67/$C67 -> 1 | R67: =D67/$C67 -> 1.0244871 | S67: =E67/$C67 -> 1.0302779 | T67: =F67/$C67 -> 1.0559706 | U67: =G67/$C67 -> 1.096071
B69: LIABILITIES AND SHAREHOLDERS' EQUITY:
B70: Current Liabilities
B71: Accounts payable and accrued expenses | C71: 6029 | D71: 7036 | E71: 5561 | F71: 5423 | G71: 5167 | J71: =C71/C$67 -> 0.11915491 | K71: =D71/D$67 -> 0.13573316 | L71: =E71/E$67 -> 0.10667562 | M71: =F71/F$67 -> 0.10149729 | N71: =G71/G$67 -> 0.093167926 | Q71: =C71/$C71 -> 1 | R71: =D71/$C71 -> 1.167026 | S71: =E71/$C71 -> 0.92237519 | T71: =F71/$C71 -> 0.89948582 | U71: =G71/$C71 -> 0.85702438
B72: Loans and notes payable | C72: 149 | D72: 399 | E72: 2096 | F72: 1616 | G72: 2210 | J72: =C72/C$67 -> 0.0029447804 | K72: =D72/D$67 -> 0.0076972047 | L72: =E72/E$67 -> 0.040207174 | M72: =F72/F$67 -> 0.030245181 | N72: =G72/G$67 -> 0.039849258 | Q72: =C72/$C72 -> 1 | R72: =D72/$C72 -> 2.6778523 | S72: =E72/$C72 -> 14.067114 | T72: =F72/$C72 -> 10.845638 | U72: =G72/$C72 -> 14.832215
B73: Current maturities of long-term debt | C73: 163 | D73: 554 | E73: 1230 | F73: 1048 | G73: 913 | J73: =C73/C$67 -> 0.0032214712 | K73: =D73/D$67 -> 0.010687347 | L73: =E73/E$67 -> 0.023594859 | M73: =F73/F$67 -> 0.019614449 | N73: =G73/G$67 -> 0.016462612 | Q73: =C73/$C73 -> 1 | R73: =D73/$C73 -> 3.398773 | S73: =E73/$C73 -> 7.5460123 | T73: =F73/$C73 -> 6.4294479 | U73: =G73/$C73 -> 5.601227
B74: Accrued income taxes | C74: 144 | D74: 87 | E74: 29 | J74: =C74/C$67 -> 0.0028459623 | K74: =D74/D$67 -> 0.0016783379 | L74: =E74/E$67 -> 0.00055630155 | M74: =F74/F$67 -> 0 | N74: =G74/G$67 -> 0 | Q74: =C74/$C74 -> 1 | R74: =D74/$C74 -> 0.60416667 | S74: =E74/$C74 -> 0.20138889 | T74: =F74/$C74 -> 0 | U74: =G74/$C74 -> 0
B75: Total Current Liabilities | C75: =SUM(C71:C74) -> 6485 | D75: =SUM(D71:D74) -> 8076 | E75: =SUM(E71:E74) -> 8916 | F75: =SUM(F71:F74) -> 8087 | G75: =SUM(G71:G74) -> 8290 | J75: =C75/C$67 -> 0.12816712 | K75: =D75/D$67 -> 0.15579605 | L75: =E75/E$67 -> 0.17103395 | M75: =F75/F$67 -> 0.15135692 | N75: =G75/G$67 -> 0.1494798 | Q75: =C75/$C75 -> 1 | R75: =D75/$C75 -> 1.2453354 | S75: =E75/$C75 -> 1.3748651 | T75: =F75/$C75 -> 1.2470316 | U75: =G75/$C75 -> 1.2783346
B76: Long-term debt | C76: 11711 | D76: 11266 | E76: 10131 | F76: 13946 | G76: 14297 | J76: =C76/C$67 -> 0.23145184 | K76: =D76/D$67 -> 0.21733511 | L76: =E76/E$67 -> 0.19434107 | M76: =F76/F$67 -> 0.26101441 | N76: =G76/G$67 -> 0.25779405 | Q76: =C76/$C76 -> 1 | R76: =D76/$C76 -> 0.96200154 | S76: =E76/$C76 -> 0.86508411 | T76: =F76/$C76 -> 1.1908462 | U76: =G76/$C76 -> 1.220818
B77: Other noncurrent liabilities | C77: 7430 | D77: 7369 | E77: 7407 | F77: 7154 | G77: 7356 | J77: =C77/C$67 -> 0.14684375 | K77: =D77/D$67 -> 0.14215715 | L77: =E77/E$67 -> 0.14208709 | M77: =F77/F$67 -> 0.13389482 | N77: =G77/G$67 -> 0.13263853 | Q77: =C77/$C77 -> 1 | R77: =D77/$C77 -> 0.99179004 | S77: =E77/$C77 -> 0.99690444 | T77: =F77/$C77 -> 0.9628533 | U77: =G77/$C77 -> 0.99004038
B78: Deferred income tax liabilities | J78: =C78/C$67 -> 0 | K78: =D78/D$67 -> 0 | L78: =E78/E$67 -> 0 | M78: =F78/F$67 -> 0 | N78: =G78/G$67 -> 0
B79: Total Liabilities | C79: =SUM(C75:C78) -> 25626 | D79: =SUM(D75:D78) -> 26711 | E79: =SUM(E75:E78) -> 26454 | F79: =SUM(F75:F78) -> 29187 | G79: =SUM(G75:G78) -> 29943 | J79: =C79/C$67 -> 0.50646271 | K79: =D79/D$67 -> 0.51528831 | L79: =E79/E$67 -> 0.50746211 | M79: =F79/F$67 -> 0.54626614 | N79: =G79/G$67 -> 0.53991237 | Q79: =C79/$C79 -> 1 | R79: =D79/$C79 -> 1.0423398 | S79: =E79/$C79 -> 1.0323109 | T79: =F79/$C79 -> 1.1389604 | U79: =G79/$C79 -> 1.1684617
B80: Stockholders equity:
B81: Common stock | C81: 14 | D81: 14 | E81: 14 | F81: 14 | G81: 14 | J81: =C81/C$67 -> 0.00027669078 | K81: =D81/D$67 -> 0.00027007736 | L81: =E81/E$67 -> 0.00026855937 | M81: =F81/F$67 -> 0.00026202508 | N81: =G81/G$67 -> 0.00025243874 | Q81: =C81/$C81 -> 1 | R81: =D81/$C81 -> 1 | S81: =E81/$C81 -> 1 | T81: =F81/$C81 -> 1 | U81: =G81/$C81 -> 1
B82: Capital surplus | C82: 21785 | D82: 21444 | E82: 20788 | F82: 19712 | G82: 19778 | J82: =C82/C$67 -> 0.43055061 | K82: =D82/D$67 -> 0.41368135 | L82: =E82/E$67 -> 0.3987723 | M82: =F82/F$67 -> 0.36893131 | N82: =G82/G$67 -> 0.35662381 | Q82: =C82/$C82 -> 1 | R82: =D82/$C82 -> 0.98434703 | S82: =E82/$C82 -> 0.95423457 | T82: =F82/$C82 -> 0.90484278 | U82: =G82/$C82 -> 0.90787239
B83: Reinvested earnings | C83: 3199 | D83: 3539 | E83: 4559 | F83: 4793 | G83: 5622 | J83: =C83/C$67 -> 0.063223843 | K83: =D83/D$67 -> 0.068271698 | L83: =E83/E$67 -> 0.087454441 | M83: =F83/F$67 -> 0.089706158 | N83: =G83/G$67 -> 0.10137218 | Q83: =C83/$C83 -> 1 | R83: =D83/$C83 -> 1.1062832 | S83: =E83/$C83 -> 1.4251329 | T83: =F83/$C83 -> 1.4982807 | U83: =G83/$C83 -> 1.7574242
B84: Accumulated other comprehensive income (loss) | C84: -26 | D84: 129 | E84: 315 | F84: -276 | G84: 102 | J84: =C84/C$67 -> -0.0005138543 | K84: =D84/D$67 -> 0.0024885699 | L84: =E84/E$67 -> 0.0060425858 | M84: =F84/F$67 -> -0.0051656373 | N84: =G84/G$67 -> 0.0018391965 | Q84: =C84/$C84 -> 1 | R84: =D84/$C84 -> -4.9615385 | S84: =E84/$C84 -> -12.115385 | T84: =F84/$C84 -> 10.615385 | U84: =G84/$C84 -> -3.9230769
B85: Treasury stock | J85: =C85/C$67 -> 0 | K85: =D85/D$67 -> 0 | L85: =E85/E$67 -> 0 | M85: =F85/F$67 -> 0 | N85: =G85/G$67 -> 0
B86: Total Shareholders' Equity (S/E) | C86: =SUM(C81:C85) -> 24972 | D86: =SUM(D81:D85) -> 25126 | E86: =SUM(E81:E85) -> 25676 | F86: =SUM(F81:F85) -> 24243 | G86: =SUM(G81:G85) -> 25516 | J86: =C86/C$67 -> 0.49353729 | K86: =D86/D$67 -> 0.48471169 | L86: =E86/E$67 -> 0.49253789 | M86: =F86/F$67 -> 0.45373386 | N86: =G86/G$67 -> 0.46008763 | Q86: =C86/$C86 -> 1 | R86: =D86/$C86 -> 1.0061669 | S86: =E86/$C86 -> 1.0281916 | T86: =F86/$C86 -> 0.9708073 | U86: =G86/$C86 -> 1.0217844
B87: Equity Attributable to Noncontrolling Interests | J87: =C87/C$67 -> 0 | K87: =D87/D$67 -> 0 | L87: =E87/E$67 -> 0 | M87: =F87/F$67 -> 0 | N87: =G87/G$67 -> 0
B88: Total Equity | C88: =SUM(C86:C87) -> 24972 | D88: =SUM(D86:D87) -> 25126 | E88: =SUM(E86:E87) -> 25676 | F88: =SUM(F86:F87) -> 24243 | G88: =SUM(G86:G87) -> 25516 | J88: =C88/C$67 -> 0.49353729 | K88: =D88/D$67 -> 0.48471169 | L88: =E88/E$67 -> 0.49253789 | M88: =F88/F$67 -> 0.45373386 | N88: =G88/G$67 -> 0.46008763 | Q88: =C88/$C88 -> 1 | R88: =D88/$C88 -> 1.0061669 | S88: =E88/$C88 -> 1.0281916 | T88: =F88/$C88 -> 0.9708073 | U88: =G88/$C88 -> 1.0217844
B89: Total Liabilities and S/E | C89: =C88+C79 -> 50598 | D89: =D88+D79 -> 51837 | E89: =E88+E79 -> 52130 | F89: =F88+F79 -> 53430 | G89: =G88+G79 -> 55459 | J89: =C89/C$67 -> 1 | K89: =D89/D$67 -> 1 | L89: =E89/E$67 -> 1 | M89: =F89/F$67 -> 1 | N89: =G89/G$67 -> 1 | Q89: =C89/$C89 -> 1 | R89: =D89/$C89 -> 1.0244871 | S89: =E89/$C89 -> 1.0302779 | T89: =F89/$C89 -> 1.0559706 | U89: =G89/$C89 -> 1.096071
B92: Liquidity ratios | C92: 2021 | D92: 2022 | E92: 2023 | F92: 2024 | G92: 2025
B93: ='FINANCIAL RATIOS'!B15 -> Current Ratio = Current Assets / Current Liabilities | C93: ='FINANCIAL RATIOS'!C20 -> 0.47139553 | D93: ='FINANCIAL RATIOS'!D20 -> 0.47102526 | E93: ='FINANCIAL RATIOS'!E20 -> 0.37853297 | F93: ='FINANCIAL RATIOS'!F20 -> 0.49425003 | G93: ='FINANCIAL RATIOS'!G20 -> 0.63522316
B94: ='FINANCIAL RATIOS'!B23 -> Quick Ratio = (Current Assets - Inventories) / Current Liabilities | C94: ='FINANCIAL RATIOS'!C28 -> 0.32243639 | D94: ='FINANCIAL RATIOS'!D28 -> 0.29730064 | E94: ='FINANCIAL RATIOS'!E28 -> 0.2379991 | F94: ='FINANCIAL RATIOS'!F28 -> 0.33362186 | G94: ='FINANCIAL RATIOS'!G28 -> 0.42617612
B95: ='FINANCIAL RATIOS'!B31 -> Cash Ratio = Cash / Current Liabilities | C95: ='FINANCIAL RATIOS'!C36 -> 0.087432537 | D95: ='FINANCIAL RATIOS'!D36 -> 0.066245666 | E95: ='FINANCIAL RATIOS'!E36 -> 0.029946164 | F95: ='FINANCIAL RATIOS'!F36 -> 0.063064177 | G95: ='FINANCIAL RATIOS'!G36 -> 0.12376357
B96: ='FINANCIAL RATIOS'!B39 -> NWC Ratio = (Current Assets - Current Liabilities) / Total Assets | C96: ='FINANCIAL RATIOS'!C44 -> -0.067749713 | D96: ='FINANCIAL RATIOS'!D44 -> -0.082412177 | E96: ='FINANCIAL RATIOS'!E44 -> -0.10629196 | F96: ='FINANCIAL RATIOS'!F44 -> -0.076548755 | G96: ='FINANCIAL RATIOS'!G44 -> -0.054526768
B97: ='FINANCIAL RATIOS'!B47 -> Interval Measure = Current Assets / Average Daily Costs (COGS + Oper. Exp.) | C97: ='FINANCIAL RATIOS'!C52 -> 115.57955 | D97: ='FINANCIAL RATIOS'!D52 -> 124.1581 | E97: ='FINANCIAL RATIOS'!E52 -> 106.31527 | F97: ='FINANCIAL RATIOS'!F52 -> 122.03304 | G97: ='FINANCIAL RATIOS'!G52 -> 149.10325
B99: Solvency ratios | C99: 2021 | D99: 2022 | E99: 2023 | F99: 2024 | G99: 2025
B100: ='FINANCIAL RATIOS'!B58 -> Total Debt Ratio = Financial Debt / Total Assets | C100: ='FINANCIAL RATIOS'!C63 -> 0.23761809 | D100: ='FINANCIAL RATIOS'!D63 -> 0.23571966 | E100: ='FINANCIAL RATIOS'!E63 -> 0.2581431 | F100: ='FINANCIAL RATIOS'!F63 -> 0.31087404 | G100: ='FINANCIAL RATIOS'!G63 -> 0.31410592
B101: ='FINANCIAL RATIOS'!B66 -> Debt-to-Equity Ratio = (Short-term Debt + Long-term Debt) / Total Equity | C101: ='FINANCIAL RATIOS'!C71 -> 0.48145923 | D101: ='FINANCIAL RATIOS'!D71 -> 0.486309 | E101: ='FINANCIAL RATIOS'!E71 -> 0.52410812 | F101: ='FINANCIAL RATIOS'!F71 -> 0.68514623 | G101: ='FINANCIAL RATIOS'!G71 -> 0.68270889
B102: ='FINANCIAL RATIOS'!B74 -> Times Interest Earned = EBIT / Interest Expenses | C102: ='FINANCIAL RATIOS'!C79 -> 6.058 | D102: ='FINANCIAL RATIOS'!D79 -> 4.1471861 | E102: ='FINANCIAL RATIOS'!E79 -> 6.5060484 | F102: ='FINANCIAL RATIOS'!F79 -> 4.6204082 | G102: ='FINANCIAL RATIOS'!G79 -> 4.9230769
B103: ='FINANCIAL RATIOS'!B82 -> Cash Coverage Ratio = (EBIT+Depreciation) / Interest Expenses | C103: ='FINANCIAL RATIOS'!C87 -> 6.412 | D103: ='FINANCIAL RATIOS'!D87 -> 4.3924964 | E103: ='FINANCIAL RATIOS'!E87 -> 6.8508065 | F103: ='FINANCIAL RATIOS'!F87 -> 4.8761905 | G103: ='FINANCIAL RATIOS'!G87 -> 5.2002653
B105: Asset Management / Turnover Ratios | C105: 2021 | D105: 2022 | E105: 2023 | F105: 2024 | G105: 2025
B106: ='FINANCIAL RATIOS'!B93 -> Assets Turnover Ratio = Sales / Total Assets | C106: ='FINANCIAL RATIOS'!C98 -> 0.25066208 | D106: ='FINANCIAL RATIOS'!D98 -> 0.27117696 | E106: ='FINANCIAL RATIOS'!E98 -> 0.28417418 | F106: ='FINANCIAL RATIOS'!F98 -> 0.2873105 | G106: ='FINANCIAL RATIOS'!G98 -> 0.29937431
B107: ='FINANCIAL RATIOS'!B100 -> Inventory Turnover = COGS / Inventories | C107: ='FINANCIAL RATIOS'!C105 -> 5.9068323 | D107: ='FINANCIAL RATIOS'!D105 -> 4.7997149 | E107: ='FINANCIAL RATIOS'!E105 -> 5.3743017 | F107: ='FINANCIAL RATIOS'!F105 -> 5.2517321 | G107: ='FINANCIAL RATIOS'!G105 -> 4.3877669
B108: ='FINANCIAL RATIOS'!B107 -> Days Sales in Inventory = 365 / Inventory Turnover | C108: ='FINANCIAL RATIOS'!C112 -> 61.79285 | D108: ='FINANCIAL RATIOS'!D112 -> 76.046184 | E108: ='FINANCIAL RATIOS'!E112 -> 67.9158 | F108: ='FINANCIAL RATIOS'!F112 -> 69.50088 | G108: ='FINANCIAL RATIOS'!G112 -> 83.185823
B109: ='FINANCIAL RATIOS'!B114 -> Receivables Turnover = Sales / Accounts Receivables | C109: ='FINANCIAL RATIOS'!C119 -> 11.047909 | D109: ='FINANCIAL RATIOS'!D119 -> 9.472372 | E109: ='FINANCIAL RATIOS'!E119 -> 10.828947 | F109: ='FINANCIAL RATIOS'!F119 -> 10.220373 | G109: ='FINANCIAL RATIOS'!G119 -> 9.9359665
B110: ='FINANCIAL RATIOS'!B121 -> Days Sales in Receivables = 365 / Receivables Turnover | C110: ='FINANCIAL RATIOS'!C126 -> 33.037925 | D110: ='FINANCIAL RATIOS'!D126 -> 38.533115 | E110: ='FINANCIAL RATIOS'!E126 -> 33.705954 | F110: ='FINANCIAL RATIOS'!F126 -> 35.712983 | G110: ='FINANCIAL RATIOS'!G126 -> 36.735229
B111: ='FINANCIAL RATIOS'!B128 -> Operating Cycle = Days Sales in Inventory + Days Sales in Receivables | C111: ='FINANCIAL RATIOS'!C133 -> 94.830774 | D111: ='FINANCIAL RATIOS'!D133 -> 114.5793 | E111: ='FINANCIAL RATIOS'!E133 -> 101.62175 | F111: ='FINANCIAL RATIOS'!F133 -> 105.21386 | G111: ='FINANCIAL RATIOS'!G133 -> 119.92105
B113: Profitability Ratios | C113: 2021 | D113: 2022 | E113: 2023 | F113: 2024 | G113: 2025
B114: ='FINANCIAL RATIOS'!B139 -> Gross Profit Margin = Gross Profits / Sales | C114: ='FINANCIAL RATIOS'!C144 -> 0.55010644 | D114: ='FINANCIAL RATIOS'!D144 -> 0.52095042 | E114: ='FINANCIAL RATIOS'!E144 -> 0.54543 | F114: ='FINANCIAL RATIOS'!F144 -> 0.55559898 | G114: ='FINANCIAL RATIOS'!G144 -> 0.54201048
B115: ='FINANCIAL RATIOS'!B147 -> Operating Profit Margin = Operating Profits / Sales | C115: ='FINANCIAL RATIOS'!C152 -> 0.23882362 | D115: ='FINANCIAL RATIOS'!D152 -> 0.2044533 | E115: ='FINANCIAL RATIOS'!E152 -> 0.21783448 | F115: ='FINANCIAL RATIOS'!F152 -> 0.22122337 | G115: ='FINANCIAL RATIOS'!G152 -> 0.22357405
B116: ='FINANCIAL RATIOS'!B155 -> Net Profit Margin = Net Income / Sales | C116: ='FINANCIAL RATIOS'!C160 -> 0.16912402 | D116: ='FINANCIAL RATIOS'!D160 -> 0.10208437 | E116: ='FINANCIAL RATIOS'!E160 -> 0.1472256 | F116: ='FINANCIAL RATIOS'!F160 -> 0.093870106 | G116: ='FINANCIAL RATIOS'!G160 -> 0.12521833
B117: ='FINANCIAL RATIOS'!B163 -> Return on Assets (ROA) = Net Income / Total Assets | C117: ='FINANCIAL RATIOS'!C168 -> 0.04239298 | D117: ='FINANCIAL RATIOS'!D168 -> 0.027682929 | E117: ='FINANCIAL RATIOS'!E168 -> 0.041837713 | F117: ='FINANCIAL RATIOS'!F168 -> 0.026969867 | G117: ='FINANCIAL RATIOS'!G168 -> 0.037487153
B118: ='FINANCIAL RATIOS'!B170 -> Return on Equity (ROE) -based on BV of equity = Net Income / Total Equity | C118: ='FINANCIAL RATIOS'!C175 -> 0.085896204 | D118: ='FINANCIAL RATIOS'!D175 -> 0.057112155 | E118: ='FINANCIAL RATIOS'!E175 -> 0.084943138 | F118: ='FINANCIAL RATIOS'!F175 -> 0.059439838 | G118: ='FINANCIAL RATIOS'!G175 -> 0.081478288
...

Sheet KDP
A1: Keurig's Dr Pepper
A2: COMMON SIZING AND TREND ANALYSIS (in millions Except Per Share Data)
A3: INCOME STATEMENT DATA
A4: NAME: Neeha Pyneni | B4: Template: | C4: Standard | E4: Restatement: | F4: Latest Filings | T4: Page 1 of 3
A5: FIN320 Section B | B5: Period Type: | C5: Annual | E5: Order: | F5: Latest on Right
B6: Currency: | C6: Reported Currency | E6: Conversion: | F6: Historical
B7: Units: | C7: S&P Capital IQ (Default) | E7: Decimals: | F7: Capital IQ (Default)
B8: Source: | C8: Capital IQ & Proprietary Data | I8: Common-Size Analysis | P8: Trend Analysis
I9: (as a percentage of sales) | P9: (using 2020 as the base year)
A10: Income Statement | B10: 2021 | C10: 2022 | D10: 2023 | E10: 2024 | F10: 2025 | I10: 2021 | J10: 2022 | K10: 2023 | L10: 2024 | M10: 2025 | P10: 2021 | Q10: 2022 | R10: 2023 | S10: 2024 | T10: 2025
A12: Revenue | B12: 12683 | C12: 14057 | D12: 14814 | E12: 15351 | F12: 16603 | I12: =B12/$B$12 -> 1 | J12: =C12/$C$12 -> 1 | K12: =D12/$D$12 -> 1 | L12: =E12/$E$12 -> 1 | M12: =F12/$F$12 -> 1 | P12: =B12/$B12 -> 1 | Q12: =C12/$B12 -> 1.108334 | R12: =D12/$B12 -> 1.1680202 | S12: =E12/$B12 -> 1.2103603 | T12: =F12/$B12 -> 1.3090751
A13: Total Revenue | B13: 12683 | C13: 14057 | D13: 14814 | E13: 15351 | F13: 16603 | I13: =B13/$B$12 -> 1 | J13: =C13/$C$12 -> 1 | K13: =D13/$D$12 -> 1 | L13: =E13/$E$12 -> 1 | M13: =F13/$F$12 -> 1 | P13: =B13/$B13 -> 1 | Q13: =C13/$B13 -> 1.108334 | R13: =D13/$B13 -> 1.1680202 | S13: =E13/$B13 -> 1.2103603 | T13: =F13/$B13 -> 1.3090751
A14: Cost Of Goods Sold | B14: 5706 | C14: 6734 | D14: 6734 | E14: 6822 | F14: 7604 | I14: =B14/$B$12 -> 0.44989356 | J14: =C14/$C$12 -> 0.47904958 | K14: =D14/$D$12 -> 0.45457 | L14: =E14/$E$12 -> 0.44440102 | M14: =F14/$F$12 -> 0.45798952 | P14: =B14/$B14 -> 1 | Q14: =C14/$B14 -> 1.1801612 | R14: =D14/$B14 -> 1.1801612 | S14: =E14/$B14 -> 1.1955836 | T14: =F14/$B14 -> 1.3326323
A15: Gross Profit | B15: 6977 | C15: 7323 | D15: 8080 | E15: 8529 | F15: 8999 | I15: =B15/$B$12 -> 0.55010644 | J15: =C15/$C$12 -> 0.52095042 | K15: =D15/$D$12 -> 0.54543 | L15: =E15/$E$12 -> 0.55559898 | M15: =F15/$F$12 -> 0.54201048 | P15: =B15/$B15 -> 1 | Q15: =C15/$B15 -> 1.0495915 | R15: =D15/$B15 -> 1.1580909 | S15: =E15/$B15 -> 1.2224452 | T15: =F15/$B15 -> 1.2898094
A16: Selling General & Admin Exp. | B16: 3765 | C16: 4283 | D16: 4488 | E16: 4525 | F16: 4874 | I16: =B16/$B$12 -> 0.29685406 | J16: =C16/$C$12 -> 0.30468806 | K16: =D16/$D$12 -> 0.30295666 | L16: =E16/$E$12 -> 0.29476907 | M16: =F16/$F$12 -> 0.2935614 | P16: =B16/$B16 -> 1 | Q16: =C16/$B16 -> 1.137583 | R16: =D16/$B16 -> 1.1920319 | S16: =E16/$B16 -> 1.2018592 | T16: =F16/$B16 -> 1.2945551
A17: R & D Exp. | B17: 66 | C17: 65 | D17: 66 | E17: 70 | F17: 70 | I17: =B17/$B$12 -> 0.0052038161 | J17: =C17/$C$12 -> 0.0046240307 | K17: =D17/$D$12 -> 0.004455245 | L17: =E17/$E$12 -> 0.0045599635 | M17: =F17/$F$12 -> 0.0042161055 | P17: =B17/$B17 -> 1 | Q17: =C17/$B17 -> 0.98484848 | R17: =D17/$B17 -> 1 | S17: =E17/$B17 -> 1.0606061 | T17: =F17/$B17 -> 1.0606061
A18: Depreciation & Amort. | B18: 177 | C18: 170 | D18: 171 | E18: 188 | F18: 209 | I18: =B18/$B$12 -> 0.013955689 | J18: =C18/$C$12 -> 0.012093619 | K18: =D18/$D$12 -> 0.011543135 | L18: =E18/$E$12 -> 0.012246759 | M18: =F18/$F$12 -> 0.012588086 | P18: =B18/$B18 -> 1 | Q18: =C18/$B18 -> 0.96045198 | R18: =D18/$B18 -> 0.96610169 | S18: =E18/$B18 -> 1.0621469 | T18: =F18/$B18 -> 1.180791
A19: Amort. of Goodwill and Intangibles | B19: - | C19: - | D19: 137 | E19: 133 | F19: 138 | K19: =D19/$D$12 -> 0.0092480086 | L19: =E19/$E$12 -> 0.0086639307 | M19: =F19/$F$12 -> 0.0083117509
A20: Other Operating Expense/(Income) | B20: -60 | C20: -69 | D20: -9 | E20: 217 | F20: -4 | I20: =B20/$B$12 -> -0.0047307419 | J20: =C20/$C$12 -> -0.0049085865 | K20: =D20/$D$12 -> -0.00060753341 | L20: =E20/$E$12 -> 0.014135887 | M20: =F20/$F$12 -> -0.00024092032 | P20: =B20/$B20 -> 1 | Q20: =C20/$B20 -> 1.15 | R20: =D20/$B20 -> 0.15 | S20: =E20/$B20 -> -3.6166667 | T20: =F20/$B20 -> 0.066666667
A21: Other Operating Exp., Total | B21: 3948 | C21: 4449 | D21: 4853 | E21: 5133 | F21: 5287 | I21: =B21/$B$12 -> 0.31128282 | J21: =C21/$C$12 -> 0.31649712 | K21: =D21/$D$12 -> 0.32759552 | L21: =E21/$E$12 -> 0.33437561 | M21: =F21/$F$12 -> 0.31843643 | P21: =B21/$B21 -> 1 | Q21: =C21/$B21 -> 1.1268997 | R21: =D21/$B21 -> 1.22923 | S21: =E21/$B21 -> 1.300152 | T21: =F21/$B21 -> 1.3391591
A22: Operating Income | B22: 3029 | C22: 2874 | D22: 3227 | E22: 3396 | F22: 3712 | I22: =B22/$B$12 -> 0.23882362 | J22: =C22/$C$12 -> 0.2044533 | K22: =D22/$D$12 -> 0.21783448 | L22: =E22/$E$12 -> 0.22122337 | M22: =F22/$F$12 -> 0.22357405 | P22: =B22/$B22 -> 1 | Q22: =C22/$B22 -> 0.948828 | R22: =D22/$B22 -> 1.0653681 | S22: =E22/$B22 -> 1.1211621 | T22: =F22/$B22 -> 1.225487
A23: Interest Expense | B23: -500 | C23: -693 | D23: -496 | E23: -735 | F23: -754 | I23: =B23/$B$12 -> -0.039422849 | J23: =C23/$C$12 -> -0.049299281 | K23: =D23/$D$12 -> -0.033481842 | L23: =E23/$E$12 -> -0.047879617 | M23: =F23/$F$12 -> -0.045413479 | P23: =B23/$B23 -> 1 | Q23: =C23/$B23 -> 1.386 | R23: =D23/$B23 -> 0.992 | S23: =E23/$B23 -> 1.47 | T23: =F23/$B23 -> 1.508
A24: Income/(Loss) from Affiliates | B24: -5 | C24: -5 | D24: 33 | E24: 42 | F24: 81 | I24: =B24/$B$12 -> -0.00039422849 | J24: =C24/$C$12 -> -0.00035569467 | K24: =D24/$D$12 -> 0.0022276225 | L24: =E24/$E$12 -> 0.0027359781 | M24: =F24/$F$12 -> 0.0048786364 | P24: =B24/$B24 -> 1 | Q24: =C24/$B24 -> 1 | R24: =D24/$B24 -> -6.6 | S24: =E24/$B24 -> -8.4 | T24: =F24/$B24 -> -16.2
A25: Currency Exchange Gains (Loss) | B25: - | C25: 9 | D25: -5 | E25: 10 | F25: -36 | J25: =C25/$C$12 -> 0.00064025041 | K25: =D25/$D$12 -> -0.00033751856 | L25: =E25/$E$12 -> 0.00065142336 | M25: =F25/$F$12 -> -0.0021682828
A26: Other Non-Operating Inc. (Exp.) | B26: 4 | C26: -19 | D26: 35 | E26: 10 | F26: -175 | I26: =B26/$B$12 -> 0.0003153828 | J26: =C26/$C$12 -> -0.0013516398 | K26: =D26/$D$12 -> 0.0023626299 | L26: =E26/$E$12 -> 0.00065142336 | M26: =F26/$F$12 -> -0.010540264 | P26: =B26/$B26 -> 1 | Q26: =C26/$B26 -> -4.75 | R26: =D26/$B26 -> 8.75 | S26: =E26/$B26 -> 2.5 | T26: =F26/$B26 -> -43.75
A27: EBT Excl. Unusual Items | B27: 2528 | C27: 2166 | D27: 2794 | E27: 2723 | F27: 2828 | I27: =B27/$B$12 -> 0.19932193 | J27: =C27/$C$12 -> 0.15408693 | K27: =D27/$D$12 -> 0.18860537 | L27: =E27/$E$12 -> 0.17738258 | M27: =F27/$F$12 -> 0.17033066 | P27: =B27/$B27 -> 1 | Q27: =C27/$B27 -> 0.8568038 | R27: =D27/$B27 -> 1.1052215 | S27: =E27/$B27 -> 1.0771361 | T27: =F27/$B27 -> 1.1186709
A28: Merger & Related Restruct. Charges | B28: -202 | C28: -172 | D28: -35 | E28: -91 | F28: -63 | I28: =B28/$B$12 -> -0.015926831 | J28: =C28/$C$12 -> -0.012235897 | K28: =D28/$D$12 -> -0.0023626299 | L28: =E28/$E$12 -> -0.0059279526 | M28: =F28/$F$12 -> -0.003794495 | P28: =B28/$B28 -> 1 | Q28: =C28/$B28 -> 0.85148515 | R28: =D28/$B28 -> 0.17326733 | S28: =E28/$B28 -> 0.45049505 | T28: =F28/$B28 -> 0.31188119
A29: Impairment of Goodwill | B29: - | C29: - | D29: - | E29: -306 | F29: - | L29: =E29/$E$12 -> -0.019933555
A30: Gain (Loss) On Sale Of Invest. | B30: 507 | C30: 38 | D30: - | E30: - | F30: - | I30: =B30/$B$12 -> 0.039974769 | J30: =C30/$C$12 -> 0.0027032795 | P30: =B30/$B30 -> 1 | Q30: =C30/$B30 -> 0.07495069
A31: Gain (Loss) On Sale Of Assets | B31: 70 | C31: 82 | D31: - | E31: - | F31: - | I31: =B31/$B$12 -> 0.0055191989 | J31: =C31/$C$12 -> 0.0058333926 | P31: =B31/$B31 -> 1 | Q31: =C31/$B31 -> 1.1714286
A32: Asset Writedown | B32: - | C32: -477 | D32: -2 | E32: -412 | F32: -78 | J32: =C32/$C$12 -> -0.033933272 | K32: =D32/$D$12 -> -0.00013500743 | L32: =E32/$E$12 -> -0.026838642 | M32: =F32/$F$12 -> -0.0046979462
A33: Legal Settlements | B33: - | C33: 299 | D33: - | E33: - | F33: - | J33: =C33/$C$12 -> 0.021270541
A34: Other Unusual Items | B34: -105 | C34: -217 | D34: - | E34: - | F34: - | I34: =B34/$B$12 -> -0.0082787984 | J34: =C34/$C$12 -> -0.015437149 | P34: =B34/$B34 -> 1 | Q34: =C34/$B34 -> 2.0666667
A35: EBT Incl. Unusual Items | B35: 2798 | C35: 1719 | D35: 2757 | E35: 1914 | F35: 2687 | I35: =B35/$B$12 -> 0.22061027 | J35: =C35/$C$12 -> 0.12228783 | K35: =D35/$D$12 -> 0.18610774 | L35: =E35/$E$12 -> 0.12468243 | M35: =F35/$F$12 -> 0.16183822 | P35: =B35/$B35 -> 1 | Q35: =C35/$B35 -> 0.61436741 | R35: =D35/$B35 -> 0.98534668 | S35: =E35/$B35 -> 0.68406004 | T35: =F35/$B35 -> 0.96032881
A36: Income Tax Expense | B36: 653 | C36: 284 | D36: 576 | E36: 473 | F36: 608 | I36: =B36/$B$12 -> 0.051486241 | J36: =C36/$C$12 -> 0.020203457 | K36: =D36/$D$12 -> 0.038882139 | L36: =E36/$E$12 -> 0.030812325 | M36: =F36/$F$12 -> 0.036619888 | P36: =B36/$B36 -> 1 | Q36: =C36/$B36 -> 0.43491577 | R36: =D36/$B36 -> 0.8820827 | S36: =E36/$B36 -> 0.72434916 | T36: =F36/$B36 -> 0.93108729
A37: Earnings from Cont. Ops. | B37: 2145 | C37: 1435 | D37: 2181 | E37: 1441 | F37: 2079 | I37: =B37/$B$12 -> 0.16912402 | J37: =C37/$C$12 -> 0.10208437 | K37: =D37/$D$12 -> 0.1472256 | L37: =E37/$E$12 -> 0.093870106 | M37: =F37/$F$12 -> 0.12521833 | P37: =B37/$B37 -> 1 | Q37: =C37/$B37 -> 0.66899767 | R37: =D37/$B37 -> 1.0167832 | S37: =E37/$B37 -> 0.67179487 | T37: =F37/$B37 -> 0.96923077
A38: Net Income to Company | B38: 2145 | C38: 1435 | D38: 2181 | E38: 1441 | F38: 2079 | I38: =B38/$B$12 -> 0.16912402 | J38: =C38/$C$12 -> 0.10208437 | K38: =D38/$D$12 -> 0.1472256 | L38: =E38/$E$12 -> 0.093870106 | M38: =F38/$F$12 -> 0.12521833 | P38: =B38/$B38 -> 1 | Q38: =C38/$B38 -> 0.66899767 | R38: =D38/$B38 -> 1.0167832 | S38: =E38/$B38 -> 0.67179487 | T38: =F38/$B38 -> 0.96923077
A39: Minority Int. in Earnings | B39: 1 | C39: 1 | D39: - | E39: - | F39: - | I39: =B39/$B$12 -> 7.8845699e-05 | J39: =C39/$C$12 -> 7.1138934e-05 | P39: =B39/$B39 -> 1 | Q39: =C39/$B39 -> 1
A40: Net Income | B40: 2146 | C40: 1436 | D40: 2181 | E40: 1441 | F40: 2079 | I40: =B40/$B$12 -> 0.16920287 | J40: =C40/$C$12 -> 0.10215551 | K40: =D40/$D$12 -> 0.1472256 | L40: =E40/$E$12 -> 0.093870106 | M40: =F40/$F$12 -> 0.12521833 | P40: =B40/$B40 -> 1 | Q40: =C40/$B40 -> 0.66915191 | R40: =D40/$B40 -> 1.0163094 | S40: =E40/$B40 -> 0.67148183 | T40: =F40/$B40 -> 0.96877912
A41: NI to Common Incl Extra Items | B41: 2146 | C41: 1436 | D41: 2181 | E41: 1441 | F41: 2079 | I41: =B41/$B$12 -> 0.16920287 | J41: =C41/$C$12 -> 0.10215551 | K41: =D41/$D$12 -> 0.1472256 | L41: =E41/$E$12 -> 0.093870106 | M41: =F41/$F$12 -> 0.12521833 | P41: =B41/$B41 -> 1 | Q41: =C41/$B41 -> 0.66915191 | R41: =D41/$B41 -> 1.0163094 | S41: =E41/$B41 -> 0.67148183 | T41: =F41/$B41 -> 0.96877912
A42: NI to Common Excl. Extra Items | B42: 2146 | C42: 1436 | D42: 2181 | E42: 1441 | F42: 2079 | I42: =B42/$B$12 -> 0.16920287 | J42: =C42/$C$12 -> 0.10215551 | K42: =D42/$D$12 -> 0.1472256 | L42: =E42/$E$12 -> 0.093870106 | M42: =F42/$F$12 -> 0.12521833 | P42: =B42/$B42 -> 1 | Q42: =C42/$B42 -> 0.66915191 | R42: =D42/$B42 -> 1.0163094 | S42: =E42/$B42 -> 0.67148183 | T42: =F42/$B42 -> 0.96877912
A43: Per Share Items
A44: Basic EPS | B44: 1.52 | C44: 1.01 | D44: 1.56 | E44: 1.06 | F44: 1.53 | P44: =B44/$B44 -> 1 | Q44: =C44/$B44 -> 0.66447368 | R44: =D44/$B44 -> 1.0263158 | S44: =E44/$B44 -> 0.69736842 | T44: =F44/$B44 -> 1.0065789
A45: Weighted Avg. Basic Shares Out. | B45: 1415.7 | C45: 1416.8 | D45: 1399.3 | E45: 1362.2 | F45: 1358.1 | I45: =B45/$B$12 -> 0.11162186 | J45: =C45/$C$12 -> 0.10078964 | K45: =D45/$D$12 -> 0.094457945 | L45: =E45/$E$12 -> 0.08873689 | M45: =F45/$F$12 -> 0.08179847 | P45: =B45/$B45 -> 1 | Q45: =C45/$B45 -> 1.000777 | R45: =D45/$B45 -> 0.98841562 | S45: =E45/$B45 -> 0.96220951 | T45: =F45/$B45 -> 0.95931341
A46: Diluted EPS | B46: 1.5 | C46: 1.01 | D46: 1.55 | E46: 1.05 | F46: 1.53 | P46: =B46/$B46 -> 1 | Q46: =C46/$B46 -> 0.67333333 | R46: =D46/$B46 -> 1.0333333 | S46: =E46/$B46 -> 0.7 | T46: =F46/$B46 -> 1.02
A49: COMPANY NAME
A50: COMMON SIZING AND TREND ANALYSIS (in millions Except Per Share Data)
A51: BALANCE SHEET DATA
A52: YOUR NAME | T52: Page 2 of 3
A53: =A5 -> FIN320 Section B
I55: Common-Size Analysis | P55: Trend Analysis
I56: (as a percentage of total assets) | P56: (using 2020 as a base year)
A57: Balance Sheet | B57: 2021 | C57: 2022 | D57: 2023 | E57: 2024 | F57: 2025 | I57: 2021 | J57: 2022 | K57: 2023 | L57: 2024 | M57: 2025 | P57: 2021 | Q57: 2022 | R57: 2023 | S57: 2024 | T57: 2025
A58: Current assets:
A59: ASSETS
A60: Cash And Equivalents | B60: 567 | C60: 535 | D60: 267 | E60: 510 | F60: 1026 | I60: =B60/$B$60 -> 1 | J60: =C60/$C$60 -> 1 | K60: =D60/$D$60 -> 1 | L60: =E60/$E$60 -> 1 | M60: =F60/$F$60 -> 1 | P60: =B60/$B60 -> 1 | Q60: =C60/$B60 -> 0.94356261 | R60: =D60/$B60 -> 0.47089947 | S60: =E60/$B60 -> 0.8994709 | T60: =F60/$B60 -> 1.8095238
A61: Trading Asset Securities | B61: 2 | C61: - | D61: - | E61: - | F61: - | I61: =B61/$B$60 -> 0.0035273369 | P61: =B61/$B61 -> 1
A62: Total Cash & ST Investments | B62: 569 | C62: 535 | D62: 267 | E62: 510 | F62: 1026 | I62: =B62/$B$60 -> 1.0035273 | J62: =C62/$C$60 -> 1 | K62: =D62/$D$60 -> 1 | L62: =E62/$E$60 -> 1 | M62: =F62/$F$60 -> 1 | P62: =B62/$B62 -> 1 | Q62: =C62/$B62 -> 0.94024605 | R62: =D62/$B62 -> 0.46924429 | S62: =E62/$B62 -> 0.89630931 | T62: =F62/$B62 -> 1.8031634
A63: Accounts Receivable | B63: 1148 | C63: 1484 | D63: 1368 | E63: 1502 | F63: 1671 | I63: =B63/$B$60 -> 2.0246914 | J63: =C63/$C$60 -> 2.7738318 | K63: =D63/$D$60 -> 5.1235955 | L63: =E63/$E$60 -> 2.945098 | M63: =F63/$F$60 -> 1.628655 | P63: =B63/$B63 -> 1 | Q63: =C63/$B63 -> 1.2926829 | R63: =D63/$B63 -> 1.1916376 | S63: =E63/$B63 -> 1.3083624 | T63: =F63/$B63 -> 1.4555749
A64: Other Receivables | B64: 126 | C64: 184 | D64: 151 | E64: - | F64: - | I64: =B64/$B$60 -> 0.22222222 | J64: =C64/$C$60 -> 0.34392523 | K64: =D64/$D$60 -> 0.56554307 | P64: =B64/$B64 -> 1 | Q64: =C64/$B64 -> 1.4603175 | R64: =D64/$B64 -> 1.1984127
A65: Total Receivables | B65: 1274 | C65: 1668 | D65: 1519 | E65: 1502 | F65: 1671 | I65: =B65/$B$60 -> 2.2469136 | J65: =C65/$C$60 -> 3.117757 | K65: =D65/$D$60 -> 5.6891386 | L65: =E65/$E$60 -> 2.945098 | M65: =F65/$F$60 -> 1.628655 | P65: =B65/$B65 -> 1 | Q65: =C65/$B65 -> 1.3092622 | R65: =D65/$B65 -> 1.1923077 | S65: =E65/$B65 -> 1.1789639 | T65: =F65/$B65 -> 1.311617
A66: Inventory | B66: 966 | C66: 1403 | D66: 1253 | E66: 1299 | F66: 1733 | I66: =B66/$B$60 -> 1.7037037 | J66: =C66/$C$60 -> 2.6224299 | K66: =D66/$D$60 -> 4.6928839 | L66: =E66/$E$60 -> 2.5470588 | M66: =F66/$F$60 -> 1.6890838 | P66: =B66/$B66 -> 1 | Q66: =C66/$B66 -> 1.452381 | R66: =D66/$B66 -> 1.2971014 | S66: =E66/$B66 -> 1.3447205 | T66: =F66/$B66 -> 1.7939959
A67: Prepaid Exp. | B67: 12 | C67: 19 | D67: 20 | E67: 526 | F67: 764 | I67: =B67/$B$60 -> 0.021164021 | J67: =C67/$C$60 -> 0.035514019 | K67: =D67/$D$60 -> 0.074906367 | L67: =E67/$E$60 -> 1.0313725 | M67: =F67/$F$60 -> 0.74463938 | P67: =B67/$B67 -> 1 | Q67: =C67/$B67 -> 1.5833333 | R67: =D67/$B67 -> 1.6666667 | S67: =E67/$B67 -> 43.833333 | T67: =F67/$B67 -> 63.666667
A68: Restricted Cash | B68: 1 | C68: - | D68: - | E68: 80 | F68: 18 | I68: =B68/$B$60 -> 0.0017636684 | L68: =E68/$E$60 -> 0.15686275 | M68: =F68/$F$60 -> 0.01754386 | P68: =B68/$B68 -> 1 | S68: =E68/$B68 -> 80 | T68: =F68/$B68 -> 18
A69: Other Current Assets | B69: 235 | C69: 179 | D69: 316 | E69: 80 | F69: 54 | I69: =B69/$B$60 -> 0.41446208 | J69: =C69/$C$60 -> 0.33457944 | K69: =D69/$D$60 -> 1.1835206 | L69: =E69/$E$60 -> 0.15686275 | M69: =F69/$F$60 -> 0.052631579 | P69: =B69/$B69 -> 1 | Q69: =C69/$B69 -> 0.76170213 | R69: =D69/$B69 -> 1.3446809 | S69: =E69/$B69 -> 0.34042553 | T69: =F69/$B69 -> 0.22978723
A70: Total Current Assets | B70: 3057 | C70: 3804 | D70: 3375 | E70: 3997 | F70: 5266 | I70: =B70/$B$60 -> 5.3915344 | J70: =C70/$C$60 -> 7.1102804 | K70: =D70/$D$60 -> 12.640449 | L70: =E70/$E$60 -> 7.8372549 | M70: =F70/$F$60 -> 5.1325536 | P70: =B70/$B70 -> 1 | Q70: =C70/$B70 -> 1.2443572 | R70: =D70/$B70 -> 1.1040236 | S70: =E70/$B70 -> 1.307491 | T70: =F70/$B70 -> 1.7226039
A71: Gross Property, Plant & Equipment | B71: 4516 | C71: 5023 | D71: 5539 | E71: 6096 | F71: 6678 | I71: =B71/$B$60 -> 7.9647266 | J71: =C71/$C$60 -> 9.388785 | K71: =D71/$D$60 -> 20.745318 | L71: =E71/$E$60 -> 11.952941 | M71: =F71/$F$60 -> 6.5087719 | P71: =B71/$B71 -> 1 | Q71: =C71/$B71 -> 1.1122675 | R71: =D71/$B71 -> 1.2265279 | S71: =E71/$B71 -> 1.3498671 | T71: =F71/$B71 -> 1.4787422
A72: Accumulated Depreciation | B72: -1349 | C72: -1651 | D72: -1964 | E72: -2252 | F72: -2603 | I72: =B72/$B$60 -> -2.3791887 | J72: =C72/$C$60 -> -3.0859813 | K72: =D72/$D$60 -> -7.3558052 | L72: =E72/$E$60 -> -4.4156863 | M72: =F72/$F$60 -> -2.537037 | P72: =B72/$B72 -> 1 | Q72: =C72/$B72 -> 1.2238695 | R72: =D72/$B72 -> 1.4558933 | S72: =E72/$B72 -> 1.6693847 | T72: =F72/$B72 -> 1.9295775
A73: Net Property, Plant & Equipment | B73: 3167 | C73: 3372 | D73: 3575 | E73: 3844 | F73: 4075 | I73: =B73/$B$60 -> 5.5855379 | J73: =C73/$C$60 -> 6.3028037 | K73: =D73/$D$60 -> 13.389513 | L73: =E73/$E$60 -> 7.5372549 | M73: =F73/$F$60 -> 3.9717349 | P73: =B73/$B73 -> 1 | Q73: =C73/$B73 -> 1.06473 | R73: =D73/$B73 -> 1.1288285 | S73: =E73/$B73 -> 1.213767 | T73: =F73/$B73 -> 1.2867067
A74: Long-term Investments | B74: 31 | C74: 1186 | D74: 1456 | E74: 1543 | F74: 1697 | I74: =B74/$B$60 -> 0.054673721 | J74: =C74/$C$60 -> 2.2168224 | K74: =D74/$D$60 -> 5.4531835 | L74: =E74/$E$60 -> 3.0254902 | M74: =F74/$F$60 -> 1.6539961 | P74: =B74/$B74 -> 1 | Q74: =C74/$B74 -> 38.258065 | R74: =D74/$B74 -> 46.967742 | S74: =E74/$B74 -> 49.774194 | T74: =F74/$B74 -> 54.741935
A75: Goodwill | B75: 20182 | C75: 20072 | D75: 20202 | E75: 20053 | F75: 20247 | I75: =B75/$B$60 -> 35.594356 | J75: =C75/$C$60 -> 37.517757 | K75: =D75/$D$60 -> 75.662921 | L75: =E75/$E$60 -> 39.319608 | M75: =F75/$F$60 -> 19.733918 | P75: =B75/$B75 -> 1 | Q75: =C75/$B75 -> 0.9945496 | R75: =D75/$B75 -> 1.000991 | S75: =E75/$B75 -> 0.99360817 | T75: =F75/$B75 -> 1.0032207
A76: Other Intangibles | B76: 23856 | C76: 23183 | D76: 23287 | E76: 23634 | F76: 23725 | I76: =B76/$B$60 -> 42.074074 | J76: =C76/$C$60 -> 43.33271 | K76: =D76/$D$60 -> 87.217228 | L76: =E76/$E$60 -> 46.341176 | M76: =F76/$F$60 -> 23.123782 | P76: =B76/$B76 -> 1 | Q76: =C76/$B76 -> 0.97178907 | R76: =D76/$B76 -> 0.97614856 | S76: =E76/$B76 -> 0.99069416 | T76: =F76/$B76 -> 0.99450872
A77: Deferred Tax Assets, LT | B77: 42 | C77: 35 | D77: 31 | E77: 39 | F77: 36 | I77: =B77/$B$60 -> 0.074074074 | J77: =C77/$C$60 -> 0.065420561 | K77: =D77/$D$60 -> 0.11610487 | L77: =E77/$E$60 -> 0.076470588 | M77: =F77/$F$60 -> 0.035087719 | P77: =B77/$B77 -> 1 | Q77: =C77/$B77 -> 0.83333333 | R77: =D77/$B77 -> 0.73809524 | S77: =E77/$B77 -> 0.92857143 | T77: =F77/$B77 -> 0.85714286
A78: Other Long-Term Assets | B78: 263 | C78: 185 | D78: 204 | E78: 320 | F78: 413 | I78: =B78/$B$60 -> 0.4638448 | J78: =C78/$C$60 -> 0.34579439 | K78: =D78/$D$60 -> 0.76404494 | L78: =E78/$E$60 -> 0.62745098 | M78: =F78/$F$60 -> 0.40253411 | P78: =B78/$B78 -> 1 | Q78: =C78/$B78 -> 0.70342205 | R78: =D78/$B78 -> 0.7756654 | S78: =E78/$B78 -> 1.21673 | T78: =F78/$B78 -> 1.5703422
A79: Total Assets | B79: 50598 | C79: 51837 | D79: 52130 | E79: 53430 | F79: 55459 | I79: =B79/$B$60 -> 89.238095 | J79: =C79/$C$60 -> 96.891589 | K79: =D79/$D$60 -> 195.24345 | L79: =E79/$E$60 -> 104.76471 | M79: =F79/$F$60 -> 54.053606 | P79: =B79/$B79 -> 1 | Q79: =C79/$B79 -> 1.0244871 | R79: =D79/$B79 -> 1.0302779 | S79: =E79/$B79 -> 1.0559706 | T79: =F79/$B79 -> 1.096071
A80: LIABILITIES
A81: Accounts Payable | B81: 4316 | C81: 5206 | D81: 3597 | E81: 2985 | F81: 2996 | I81: =B81/$B$60 -> 7.6119929 | J81: =C81/$C$60 -> 9.7308411 | K81: =D81/$D$60 -> 13.47191 | L81: =E81/$E$60 -> 5.8529412 | M81: =F81/$F$60 -> 2.920078 | P81: =B81/$B81 -> 1 | Q81: =C81/$B81 -> 1.2062095 | R81: =D81/$B81 -> 0.83341057 | S81: =E81/$B81 -> 0.6916126 | T81: =F81/$B81 -> 0.69416126
A82: Accrued Exp. | B82: 1110 | C82: 1153 | D82: 1242 | E82: 1584 | F82: 1379 | I82: =B82/$B$60 -> 1.957672 | J82: =C82/$C$60 -> 2.1551402 | K82: =D82/$D$60 -> 4.6516854 | L82: =E82/$E$60 -> 3.1058824 | M82: =F82/$F$60 -> 1.3440546 | P82: =B82/$B82 -> 1 | Q82: =C82/$B82 -> 1.0387387 | R82: =D82/$B82 -> 1.1189189 | S82: =E82/$B82 -> 1.427027 | T82: =F82/$B82 -> 1.2423423
A83: Short-term Borrowings | B83: 149 | C83: 399 | D83: 2096 | E83: 1616 | F83: 2210 | I83: =B83/$B$60 -> 0.2627866 | J83: =C83/$C$60 -> 0.74579439 | K83: =D83/$D$60 -> 7.8501873 | L83: =E83/$E$60 -> 3.1686275 | M83: =F83/$F$60 -> 2.1539961 | P83: =B83/$B83 -> 1 | Q83: =C83/$B83 -> 2.6778523 | R83: =D83/$B83 -> 14.067114 | S83: =E83/$B83 -> 10.845638 | T83: =F83/$B83 -> 14.832215
A84: Curr. Port. of LT Debt | B84: 163 | C84: 554 | D84: 1230 | E84: 1048 | F84: 913 | I84: =B84/$B$60 -> 0.28747795 | J84: =C84/$C$60 -> 1.035514 | K84: =D84/$D$60 -> 4.6067416 | L84: =E84/$E$60 -> 2.054902 | M84: =F84/$F$60 -> 0.88986355 | P84: =B84/$B84 -> 1 | Q84: =C84/$B84 -> 3.398773 | R84: =D84/$B84 -> 7.5460123 | S84: =E84/$B84 -> 6.4294479 | T84: =F84/$B84 -> 5.601227
A85: Curr. Port. of Leases | B85: 155 | C85: 195 | D85: 220 | E85: 253 | F85: 306 | I85: =B85/$B$60 -> 0.27336861 | J85: =C85/$C$60 -> 0.36448598 | K85: =D85/$D$60 -> 0.82397004 | L85: =E85/$E$60 -> 0.49607843 | M85: =F85/$F$60 -> 0.29824561 | P85: =B85/$B85 -> 1 | Q85: =C85/$B85 -> 1.2580645 | R85: =D85/$B85 -> 1.4193548 | S85: =E85/$B85 -> 1.6322581 | T85: =F85/$B85 -> 1.9741935
A86: Curr. Income Taxes Payable | B86: 144 | C86: 87 | D86: 29 | E86: - | F86: - | I86: =B86/$B$60 -> 0.25396825 | J86: =C86/$C$60 -> 0.16261682 | K86: =D86/$D$60 -> 0.10861423 | P86: =B86/$B86 -> 1 | Q86: =C86/$B86 -> 0.60416667 | R86: =D86/$B86 -> 0.20138889
A87: Other Current Liabilities | B87: 448 | C87: 482 | D87: 502 | E87: 601 | F87: 486 | I87: =B87/$B$60 -> 0.79012346 | J87: =C87/$C$60 -> 0.90093458 | K87: =D87/$D$60 -> 1.8801498 | L87: =E87/$E$60 -> 1.1784314 | M87: =F87/$F$60 -> 0.47368421 | P87: =B87/$B87 -> 1 | Q87: =C87/$B87 -> 1.0758929 | R87: =D87/$B87 -> 1.1205357 | S87: =E87/$B87 -> 1.3415179 | T87: =F87/$B87 -> 1.0848214
A88: Total Current Liabilities | B88: 6485 | C88: 8076 | D88: 8916 | E88: 8087 | F88: 8290 | I88: =B88/$B$60 -> 11.43739 | J88: =C88/$C$60 -> 15.095327 | K88: =D88/$D$60 -> 33.393258 | L88: =E88/$E$60 -> 15.856863 | M88: =F88/$F$60 -> 8.079922 | P88: =B88/$B88 -> 1 | Q88: =C88/$B88 -> 1.2453354 | R88: =D88/$B88 -> 1.3748651 | S88: =E88/$B88 -> 1.2470316 | T88: =F88/$B88 -> 1.2783346
A89: Long-Term Debt | B89: 11711 | C89: 11266 | D89: 10131 | E89: 13946 | F89: 14297 | I89: =B89/$B$60 -> 20.654321 | J89: =C89/$C$60 -> 21.057944 | K89: =D89/$D$60 -> 37.94382 | L89: =E89/$E$60 -> 27.345098 | M89: =F89/$F$60 -> 13.934698 | P89: =B89/$B89 -> 1 | Q89: =C89/$B89 -> 0.96200154 | R89: =D89/$B89 -> 0.86508411 | S89: =E89/$B89 -> 1.1908462 | T89: =F89/$B89 -> 1.220818
A90: Long-Term Leases | B90: 1229 | C90: 1421 | D90: 1413 | E90: 1467 | F90: 1509 | I90: =B90/$B$60 -> 2.1675485 | J90: =C90/$C$60 -> 2.6560748 | K90: =D90/$D$60 -> 5.2921348 | L90: =E90/$E$60 -> 2.8764706 | M90: =F90/$F$60 -> 1.4707602 | P90: =B90/$B90 -> 1 | Q90: =C90/$B90 -> 1.1562246 | R90: =D90/$B90 -> 1.1497152 | S90: =E90/$B90 -> 1.1936534 | T90: =F90/$B90 -> 1.2278275
A91: Total Liabilities | B91: 25626 | C91: 26712 | D91: 26454 | E91: 29187 | F91: 29943 | I91: =B91/$B$60 -> 45.195767 | J91: =C91/$C$60 -> 49.928972 | K91: =D91/$D$60 -> 99.078652 | L91: =E91/$E$60 -> 57.229412 | M91: =F91/$F$60 -> 29.184211 | P91: =B91/$B91 -> 1 | Q91: =C91/$B91 -> 1.0423788 | R91: =D91/$B91 -> 1.0323109 | S91: =E91/$B91 -> 1.1389604 | T91: =F91/$B91 -> 1.1684617
A92: Common Stock | B92: 14 | C92: 14 | D92: 14 | E92: 14 | F92: 14 | I92: =B92/$B$60 -> 0.024691358 | J92: =C92/$C$60 -> 0.026168224 | K92: =D92/$D$60 -> 0.052434457 | L92: =E92/$E$60 -> 0.02745098 | M92: =F92/$F$60 -> 0.013645224 | P92: =B92/$B92 -> 1 | Q92: =C92/$B92 -> 1 | R92: =D92/$B92 -> 1 | S92: =E92/$B92 -> 1 | T92: =F92/$B92 -> 1
A93: Additional Paid In Capital | B93: 21785 | C93: 21444 | D93: 20788 | E93: 19712 | F93: 19778 | I93: =B93/$B$60 -> 38.421517 | J93: =C93/$C$60 -> 40.082243 | K93: =D93/$D$60 -> 77.857678 | L93: =E93/$E$60 -> 38.65098 | M93: =F93/$F$60 -> 19.276803 | P93: =B93/$B93 -> 1 | Q93: =C93/$B93 -> 0.98434703 | R93: =D93/$B93 -> 0.95423457 | S93: =E93/$B93 -> 0.90484278 | T93: =F93/$B93 -> 0.90787239
A94: Retained Earnings | B94: 3199 | C94: 3539 | D94: 4559 | E94: 4793 | F94: 5622 | I94: =B94/$B$60 -> 5.6419753 | J94: =C94/$C$60 -> 6.6149533 | K94: =D94/$D$60 -> 17.074906 | L94: =E94/$E$60 -> 9.3980392 | M94: =F94/$F$60 -> 5.4795322 | P94: =B94/$B94 -> 1 | Q94: =C94/$B94 -> 1.1062832 | R94: =D94/$B94 -> 1.4251329 | S94: =E94/$B94 -> 1.4982807 | T94: =F94/$B94 -> 1.7574242
A95: Comprehensive Inc. and Other | B95: -26 | C95: 129 | D95: 315 | E95: -276 | F95: 102 | I95: =B95/$B$60 -> -0.045855379 | J95: =C95/$C$60 -> 0.2411215 | K95: =D95/$D$60 -> 1.1797753 | L95: =E95/$E$60 -> -0.54117647 | M95: =F95/$F$60 -> 0.099415205 | P95: =B95/$B95 -> 1 | Q95: =C95/$B95 -> -4.9615385 | R95: =D95/$B95 -> -12.115385 | S95: =E95/$B95 -> 10.615385 | T95: =F95/$B95 -> -3.9230769
A96: Total Common Equity | B96: 24972 | C96: 25126 | D96: 25676 | E96: 24243 | F96: 25516 | I96: =B96/$B$60 -> 44.042328 | J96: =C96/$C$60 -> 46.964486 | K96: =D96/$D$60 -> 96.164794 | L96: =E96/$E$60 -> 47.535294 | M96: =F96/$F$60 -> 24.869396 | P96: =B96/$B96 -> 1 | Q96: =C96/$B96 -> 1.0061669 | R96: =D96/$B96 -> 1.0281916 | S96: =E96/$B96 -> 0.9708073 | T96: =F96/$B96 -> 1.0217844
A97: Minority Interest | B97: - | C97: -1 | D97: - | E97: - | F97: -
A98: Total Equity | B98: 24972 | C98: 25125 | D98: 25676 | E98: 24243 | F98: 25516 | I98: =B98/$B$60 -> 44.042328 | J98: =C98/$C$60 -> 46.962617 | K98: =D98/$D$60 -> 96.164794 | L98: =E98/$E$60 -> 47.535294 | M98: =F98/$F$60 -> 24.869396 | P98: =B98/$B98 -> 1 | Q98: =C98/$B98 -> 1.0061269 | R98: =D98/$B98 -> 1.0281916 | S98: =E98/$B98 -> 0.9708073 | T98: =F98/$B98 -> 1.0217844
A99: Total Liabilities And Equity | B99: 50598 | C99: 51837 | D99: 52130 | E99: 53430 | F99: 55459 | I99: =B99/$B$60 -> 89.238095 | J99: =C99/$C$60 -> 96.891589 | K99: =D99/$D$60 -> 195.24345 | L99: =E99/$E$60 -> 104.76471 | M99: =F99/$F$60 -> 54.053606 | P99: =B99/$B99 -> 1 | Q99: =C99/$B99 -> 1.0244871 | R99: =D99/$B99 -> 1.0302779 | S99: =E99/$B99 -> 1.0559706 | T99: =F99/$B99 -> 1.096071
A101: price per share | B101: 29 | C101: 36 | D101: 32 | E101: 32 | F101: 28 | I101: =B101/$B$60 -> 0.051146384 | J101: =C101/$C$60 -> 0.06728972 | K101: =D101/$D$60 -> 0.11985019 | L101: =E101/$E$60 -> 0.062745098 | M101: =F101/$F$60 -> 0.027290448 | P101: =B101/$B101 -> 1 | Q101: =C101/$B101 -> 1.2413793 | R101: =D101/$B101 -> 1.1034483 | S101: =E101/$B101 -> 1.1034483 | T101: =F101/$B101 -> 0.96551724

Sheet Celsius Holdings, Inc.
A1: Celsius Holdings, INC.
A2: COMMON SIZING AND TREND ANALYSIS (in 000's Except Per Share Data)
A3: BALANCE SHEET STATEMENT DATA
A5: CELH Balance Sheet ($ in thousands) | H5: Common size Balance sheet | N5: Trend Analysis
A6: Line Item | B6: 2021 | C6: 2022 | D6: 2023 | E6: 2024 | F6: 2025 | H6: 2021 | I6: 2022 | J6: 2023 | K6: 2024 | L6: 2025 | N6: 2021 | O6: 2022 | P6: 2023 | Q6: 2024 | R6: 2025
A7: ASSETS
A8: Current assets
A9: Cash and cash equivalents | B9: 16255 | C9: 614159 | D9: 755981 | E9: 890190 | F9: 398866 | H9: =B9/$B$31 -> 0.051764549 | I9: =C9/$C$31 -> 0.50255673 | J9: =D9/$D$31 -> 0.49204827 | K9: =E9/$E$31 -> 0.50382001 | L9: =F9/$F$31 -> 0.077909283 | N9: =B9/$B9 -> 1 | O9: =C9/$B9 -> 37.782775 | P9: =D9/$B9 -> 46.507598 | Q9: =E9/$B9 -> 54.764073 | R9: =F9/$B9 -> 24.53805
A10: Accounts receivable-net | B10: 38741 | C10: 63311 | D10: 183703 | E10: 270342 | F10: 755499 | H10: =B10/$B$31 -> 0.12337191 | I10: =C10/$C$31 -> 0.051806404 | J10: =D10/$D$31 -> 0.11956748 | K10: =E10/$E$31 -> 0.15300521 | L10: =F10/$F$31 -> 0.14756932 | N10: =B10/$B10 -> 1 | O10: =C10/$B10 -> 1.6342118 | P10: =D10/$B10 -> 4.7418239 | Q10: =E10/$B10 -> 6.9781885 | R10: =F10/$B10 -> 19.501278
A11: Inventories-net | B11: 191222 | C11: 173289 | D11: 229275 | E11: 131165 | F11: 337698 | H11: =B11/$B$31 -> 0.60895235 | I11: =C11/$C$31 -> 0.14179969 | J11: =D11/$D$31 -> 0.1492291 | K11: =E11/$E$31 -> 0.074235333 | L11: =F11/$F$31 -> 0.065961523 | N11: =B11/$B11 -> 1 | O11: =C11/$B11 -> 0.90621895 | P11: =D11/$B11 -> 1.1989991 | Q11: =E11/$B11 -> 0.68593049 | R11: =F11/$B11 -> 1.7659997
A13: Other current assets | B13: 16143 | C13: 67212 | D13: 35945 | E13: 32883 | F13: 319091 | H13: =B13/$B$31 -> 0.051407881 | I13: =C13/$C$31 -> 0.054998531 | J13: =D13/$D$31 -> 0.023395661 | K13: =E13/$E$31 -> 0.018610761 | L13: =F13/$F$31 -> 0.062327075 | N13: =B13/$B13 -> 1 | O13: =C13/$B13 -> 4.1635384 | P13: =D13/$B13 -> 2.2266617 | Q13: =E13/$B13 -> 2.036982 | R13: =F13/$B13 -> 19.766524
A14: Restricted cash | B14: 0 | C14: 38768 | D14: 0 | E14: 0 | F14: 141121 | H14: 0 | I14: =C14/$C$31 -> 0.03172325 | J14: 0 | K14: 0 | L14: =F14/$F$31 -> 0.027564736 | N14: N/A | O14: =C14/C14 -> 1 | P14: N/A | Q14: N/A | R14: =F14/C14 -> 3.6401414
A15: Note receivable-current | B15: 2588 | C15: 2979 | D15: 2318 | E15: 0 | F15: 0 | H15: =B15/$B$31 -> 0.0082415658 | I15: =C15/$C$31 -> 0.0024376692 | J15: =D15/$D$31 -> 0.0015087256 | K15: 0 | L15: 0 | N15: =B15/$B15 -> 1 | O15: =C15/$B15 -> 1.1510819 | P15: =D15/$B15 -> 0.89567233 | Q15: N/A | R15: N/A
A16: Prepaid expenses and other current assets | B16: 13555 | C16: 11341 | D16: 19503 | E16: 18759 | F16: 128806 | H16: =B16/$B$31 -> 0.043166315 | I16: =C16/$C$31 -> 0.0092801634 | J16: =D16/$D$31 -> 0.012693993 | K16: =E16/$E$31 -> 0.010617014 | L16: =F16/$F$31 -> 0.025159284 | N16: =B16/$B16 -> 1 | O16: =C16/$B16 -> 0.83666544 | P16: =D16/$B16 -> 1.4388049 | Q16: =E16/$B16 -> 1.3839174 | R16: =F16/$B16 -> 9.5024714
A17: Deferred other costs-current | B17: 0 | C17: 14124 | D17: 14124 | E17: 14124 | F17: 49164 | H17: 0 | I17: =C17/$C$31 -> 0.011557449 | J17: =D17/$D$31 -> 0.0091929424 | K17: =E17/$E$31 -> 0.0079937472 | L17: =F17/$F$31 -> 0.0096030546 | N17: N/A | O17: =C17/$C17 -> 1 | P17: =D17/$C17 -> 1 | Q17: =E17/$C17 -> 1 | R17: =F17/$C17 -> 3.4808836
A18: Total current assets | B18: 262361 | C18: 917971 | D18: 1204904 | E18: 1324580 | F18: 1811154 | H18: =B18/$B$31 -> 0.83549669 | I18: =C18/$C$31 -> 0.75116135 | J18: =D18/$D$31 -> 0.78424052 | K18: =E18/$E$31 -> 0.74967131 | L18: =F18/$F$31 -> 0.3537672 | N18: =B18/$B18 -> 1 | O18: =C18/$B18 -> 3.4988851 | P18: =D18/$B18 -> 4.5925423 | Q18: =E18/$B18 -> 5.0486925 | R18: =F18/$B18 -> 6.9032897
A20: Non-current assets
A21: Property, plant and equipment-net | B21: 3180 | C21: 10185 | D21: 24868 | E21: 55602 | F21: 87910 | H21: =B21/$B$31 -> 0.010126808 | I21: =C21/$C$31 -> 0.0083342266 | J21: =D21/$D$31 -> 0.016185931 | K21: =E21/$E$31 -> 0.031469012 | L21: =F21/$F$31 -> 0.017171193 | N21: =B21/$B21 -> 1 | O21: =C21/$B21 -> 3.2028302 | P21: =D21/$B21 -> 7.8201258 | Q21: =E21/$B21 -> 17.484906 | R21: =F21/$B21 -> 27.644654
A22: Goodwill | B22: 14527 | C22: 13679 | D22: 14173 | E22: 71582 | F22: 917560 | H22: =B22/$B$31 -> 0.046261679 | I22: =C22/$C$31 -> 0.011193312 | J22: =D22/$D$31 -> 0.0092248353 | K22: =E22/$E$31 -> 0.040513198 | L22: =F22/$F$31 -> 0.1792242 | N22: =B22/$B22 -> 1 | O22: =C22/$B22 -> 0.94162594 | P22: =D22/$B22 -> 0.97563158 | Q22: =E22/$B22 -> 4.9275143 | R22: =F22/$B22 -> 63.162387
A23: Deferred tax assets | B23: 9019 | C23: 501 | D23: 29518 | E23: 38699 | F23: 96013 | H23: =B23/$B$31 -> 0.028721283 | I23: =C23/$C$31 -> 0.00040996049 | J23: =D23/$D$31 -> 0.019212495 | K23: =E23/$E$31 -> 0.021902437 | L23: =F23/$F$31 -> 0.018753927 | N23: =B23/$B23 -> 1 | O23: =C23/$B23 -> 0.055549396 | P23: =D23/$B23 -> 3.2728684 | Q23: =E23/$B23 -> 4.2908305 | R23: =F23/$B23 -> 10.645637
A25: Other non-current assets | B25: 24931 | C25: 279733 | D25: 262933 | E25: 276418 | F25: 815069 | H25: =B25/$B$31 -> 0.079393538 | I25: =C25/$C$31 -> 0.22890115 | J25: =D25/$D$31 -> 0.17113622 | K25: =E25/$E$31 -> 0.15644404 | L25: =F25/$F$31 -> 0.15920495 | N25: =B25/$B25 -> 1 | O25: =C25/$B25 -> 11.220288 | P25: =D25/$B25 -> 10.546428 | Q25: =E25/$B25 -> 11.087321 | R25: =F25/$B25 -> 32.692993
A26: Note receivable (non-current) | B26: 7117 | C26: 3574 | D26: 0 | E26: 0 | F26: 0 | H26: =B26/$B$31 -> 0.022664306 | I26: =C26/$C$31 -> 0.0029245485 | J26: 0 | K26: 0 | L26: 0 | N26: =B26/$B26 -> 1 | O26: =C26/$B26 -> 0.50217788 | P26: N/A | Q26: N/A | R26: N/A
A27: Deferred other costs-non-current | B27: 0 | C27: 262462 | D27: 248338 | E27: 234215 | F27: 771635 | H27: 0 | I27: =C27/$C$31 -> 0.21476856 | J27: =D27/$D$31 -> 0.16163671 | K27: =E27/$E$31 -> 0.13255845 | L27: =F27/$F$31 -> 0.15072112 | N27: N/A | O27: =C27/$C27 -> 1 | P27: =D27/$C27 -> 0.9461865 | Q27: =E27/$C27 -> 0.8923768 | R27: =F27/$C27 -> 2.9399875
A28: Intangibles-net | B28: 16301 | C28: 12254 | D28: 12139 | E28: 12213 | F28: 0 | H28: =B28/$B$31 -> 0.051911037 | I28: =C28/$C$31 -> 0.010027257 | J28: =D28/$D$31 -> 0.0079009578 | K28: =E28/$E$31 -> 0.0069121803 | L28: 0 | N28: =B28/$B28 -> 1 | O28: =C28/$B28 -> 0.75173302 | P28: =D28/$B28 -> 0.74467824 | Q28: =E28/$B28 -> 0.74921784 | R28: =F28/$B28 -> 0
A29: Other long-term assets | B29: 1513 | C29: 1443 | D29: 2456 | E29: 29990 | F29: 43434 | H29: =B29/$B$31 -> 0.0048181951 | I29: =C29/$C$31 -> 0.0011807844 | J29: =D29/$D$31 -> 0.0015985462 | K29: =E29/$E$31 -> 0.016973412 | L29: =F29/$F$31 -> 0.0084838311 | N29: =B29/$B29 -> 1 | O29: =C29/$B29 -> 0.9537343 | P29: =D29/$B29 -> 1.623265 | Q29: =E29/$B29 -> 19.821547 | R29: =F29/$B29 -> 28.707204
A31: Total Assets | B31: 314018 | C31: 1222069 | D31: 1536396 | E31: 1766881 | F31: 5119621 | H31: =B31/$B$31 -> 1 | I31: =C31/$C$31 -> 1 | J31: =D31/$D$31 -> 1 | K31: =E31/$E$31 -> 1 | L31: =F31/$F$31 -> 1 | N31: =B31/$B31 -> 1 | O31: =C31/$B31 -> 3.8917164 | P31: =D31/$B31 -> 4.8927004 | Q31: =E31/$B31 -> 5.626687 | R31: =F31/$B31 -> 16.303591
A33: LIABILITIES, MEZZANINE EQUITY, AND STOCKHOLDERS’ EQUITY
A35: Current liabilities
A36: Accounts payable and accrued expenses | B36: 72442 | C36: 107340 | D36: 104960 | E36: 190067 | F36: 368651 | H36: =B36/$B$31 -> 0.23069378 | I36: =C36/$C$31 -> 0.087834648 | J36: =D36/$D$31 -> 0.068315721 | K36: =E36/$E$31 -> 0.10757204 | L36: =F36/$F$31 -> 0.072007479 | N36: =B36/$B36 -> 1 | O36: =C36/$B36 -> 1.4817371 | P36: =D36/$B36 -> 1.4488832 | Q36: =E36/$B36 -> 2.6237128 | R36: =F36/$B36 -> 5.0889125
A37: Income taxes payable | B37: 0 | C37: 0 | D37: 50424 | E37: 10834 | F37: 49612 | H37: 0 | I37: 0 | J37: =D37/$D$31 -> 0.032819664 | K37: =E37/$E$31 -> 0.0061317089 | L37: =F37/$F$31 -> 0.0096905611 | N37: N/A | O37: N/A | P37: =D37/$D37 -> 1 | Q37: =E37/$D37 -> 0.214858 | R37: =F37/$D37 -> 0.98389656
A38: Other current liabilities | B38: 20682 | C38: 53955 | D38: 121229 | E38: 164634 | F38: 660463 | H38: =B38/$B$31 -> 0.065862466 | I38: =C38/$C$31 -> 0.044150535 | J38: =D38/$D$31 -> 0.078904788 | K38: =E38/$E$31 -> 0.093177752 | L38: =F38/$F$31 -> 0.12900623 | N38: =B38/$B38 -> 1 | O38: =C38/$B38 -> 2.6087903 | P38: =D38/$B38 -> 5.8615704 | Q38: =E38/$B38 -> 7.9602553 | R38: =F38/$B38 -> 31.934194
A39: Accrued distributor termination fees | B39: 0 | C39: 3986 | D39: 0 | E39: 0 | F39: 264088 | H39: 0 | I39: =C39/$C$31 -> 0.0032616816 | J39: 0 | K39: 0 | L39: =F39/$F$31 -> 0.051583506 | N39: N/A | O39: N/A | P39: N/A | Q39: N/A | R39: =F39/$F39 -> 1
A40: Accrued promotional allowance | B40: 19037 | C40: 35977 | D40: 99787 | E40: 135948 | F40: 307922 | H40: =B40/$B$31 -> 0.060623913 | I40: =C40/$C$31 -> 0.029439418 | J40: =D40/$D$31 -> 0.06494875 | K40: =E40/$E$31 -> 0.076942363 | L40: =F40/$F$31 -> 0.060145468 | N40: =B40/$B40 -> 1 | O40: =C40/$B40 -> 1.8898461 | P40: =D40/$B40 -> 5.2417398 | Q40: =E40/$B40 -> 7.1412512 | R40: =F40/$B40 -> 16.174923
A41: Lease liability operating leases (current) | B41: 512 | C41: 661 | D41: 980 | E41: 3265 | F41: 0 | H41: =B41/$B$31 -> 0.0016304798 | I41: =C41/$C$31 -> 0.00054088599 | J41: =D41/$D$31 -> 0.00063785639 | K41: =E41/$E$31 -> 0.001847889 | L41: 0 | N41: =B41/$B41 -> 1 | O41: =C41/$B41 -> 1.2910156 | P41: =D41/$B41 -> 1.9140625 | Q41: =E41/$B41 -> 6.3769531 | R41: =F41/$B41 -> 0
A42: Lease liability finance leases (current) | B42: 157 | C42: 70 | D42: 59 | E42: 100 | F42: 0 | H42: =B42/$B$31 -> 0.00049997134 | I42: =C42/$C$31 -> 5.7279908e-05 | J42: =D42/$D$31 -> 3.8401558e-05 | K42: =E42/$E$31 -> 5.6596907e-05 | L42: 0 | N42: =B42/$B42 -> 1 | O42: =C42/$B42 -> 0.44585987 | P42: =D42/$B42 -> 0.37579618 | Q42: =E42/$B42 -> 0.63694268 | R42: =F42/$B42 -> 0
A43: Deferred revenue-current | B43: 0 | C43: 9675 | D43: 9513 | E43: 9513 | F43: 26988 | H43: 0 | I43: =C43/$C$31 -> 0.0079169016 | J43: =D43/$D$31 -> 0.0061917631 | K43: =E43/$E$31 -> 0.0053840638 | L43: =F43/$F$31 -> 0.005271484 | N43: N/A | O43: =C43/$C43 -> 1 | P43: =D43/$C43 -> 0.98325581 | Q43: =E43/$C43 -> 0.98325581 | R43: =F43/$C43 -> 2.7894574
A44: Contingent consideration | B44: 0 | C44: 0 | D44: 0 | E44: 0 | F44: 25000 | H44: 0 | I44: 0 | J44: 0 | K44: 0 | L44: =F44/$F$31 -> 0.004883174 | N44: N/A | O44: N/A | P44: N/A | Q44: N/A | R44: =F44/$F44 -> 1
A45: Other current liabilities (detail) | B45: 976 | C45: 3586 | D45: 10890 | E45: 15808 | F45: 36465 | H45: =B45/$B$31 -> 0.0031081021 | I45: =C45/$C$31 -> 0.0029343679 | J45: =D45/$D$31 -> 0.0070880164 | K45: =E45/$E$31 -> 0.0089468391 | L45: =F45/$F$31 -> 0.0071225976 | N45: =B45/$B45 -> 1 | O45: =C45/$B45 -> 3.6741803 | P45: =D45/$B45 -> 11.157787 | Q45: =E45/$B45 -> 16.196721 | R45: =F45/$B45 -> 37.36168
A46: Total current liabilities | B46: 93124 | C46: 161295 | D46: 276613 | E46: 365535 | F46: 1078726 | H46: =B46/$B$31 -> 0.29655625 | I46: =C46/$C$31 -> 0.13198518 | J46: =D46/$D$31 -> 0.18004017 | K46: =E46/$E$31 -> 0.2068815 | L46: =F46/$F$31 -> 0.21070427 | N46: =B46/$B46 -> 1 | O46: =C46/$B46 -> 1.7320454 | P46: =D46/$B46 -> 2.9703728 | Q46: =E46/$B46 -> 3.9252502 | R46: =F46/$B46 -> 11.583759
A48: Long-term liabilities
A49: Long-term debt | B49: 0 | C49: 0 | D49: 0 | E49: 0 | F49: 669926 | H49: 0 | I49: 0 | J49: 0 | K49: 0 | L49: =F49/$F$31 -> 0.13085461 | N49: N/A | O49: N/A | P49: N/A | Q49: N/A | R49: =F49/$F49 -> 1
A50: Deferred revenue-non-current | B50: 0 | C50: 179788 | D50: 167227 | E50: 157714 | F50: 401155 | H50: 0 | I50: =C50/$C$31 -> 0.14711772 | J50: =D50/$D$31 -> 0.10884368 | K50: =E50/$E$31 -> 0.089261246 | L50: =F50/$F$31 -> 0.078356386 | N50: N/A | O50: =C50/$C50 -> 1 | P50: =D50/$C50 -> 0.93013438 | Q50: =E50/$C50 -> 0.87722206 | R50: =F50/$C50 -> 2.2312668
A51: Other long-term liabilities | B51: 3849 | C51: 16407 | D51: 4028 | E51: 19215 | F51: 28372 | H51: =B51/$B$31 -> 0.012257259 | I51: =C51/$C$31 -> 0.013425592 | J51: =D51/$D$31 -> 0.0026217199 | K51: =E51/$E$31 -> 0.010875096 | L51: =F51/$F$31 -> 0.0055418165 | N51: =B51/$B51 -> 1 | O51: =C51/$B51 -> 4.2626656 | P51: =D51/$B51 -> 1.0465056 | Q51: =E51/$B51 -> 4.9922058 | R51: =F51/$B51 -> 7.3712653
A53: Total Liabilities | B53: 96973 | C53: 357490 | D53: 447868 | E53: 542464 | F53: 2178179 | H53: =B53/$B$31 -> 0.30881351 | I53: =C53/$C$31 -> 0.29252849 | J53: =D53/$D$31 -> 0.29150558 | K53: =E53/$E$31 -> 0.30701785 | L53: =F53/$F$31 -> 0.42545708 | N53: =B53/$B53 -> 1 | O53: =C53/$B53 -> 3.6864901 | P53: =D53/$B53 -> 4.6184814 | Q53: =E53/$B53 -> 5.5939695 | R53: =F53/$B53 -> 22.461706
A55: Mezzanine equity
A56: Series A convertible preferred stock | B56: 0 | C56: 824488 | D56: 824488 | E56: 824488 | F56: 852355 | H56: 0 | I56: =C56/$C$31 -> 0.67466567 | J56: =D56/$D$31 -> 0.53663769 | K56: =E56/$E$31 -> 0.46663471 | L56: =F56/$F$31 -> 0.16648791 | N56: N/A | O56: =C56/$C56 -> 1 | P56: =D56/$C56 -> 1 | Q56: =E56/$C56 -> 1 | R56: =F56/$C56 -> 1.0337992
A57: Series B convertible preferred stock | B57: 0 | C57: 0 | D57: 0 | E57: 0 | F57: 907620 | L57: =F57/$F$31 -> 0.17728265 | N57: N/A | O57: N/A | P57: N/A | Q57: N/A | R57: =F57/$F57 -> 1
A58: Total mezzanine equity | B58: 0 | C58: 824488 | D58: 824488 | E58: 824488 | F58: 1759975 | H58: 0 | I58: =C58/$C$31 -> 0.67466567 | J58: =D58/$D$31 -> 0.53663769 | K58: =E58/$E$31 -> 0.46663471 | L58: =F58/$F$31 -> 0.34377056 | N58: N/A | O58: =C58/$C58 -> 1 | P58: =D58/$C58 -> 1 | Q58: =E58/$C58 -> 1 | R58: =F58/$C58 -> 2.1346278
A59: Stockholders’ equity
A60: Common stock | B60: 75 | C60: 76 | D60: 77 | E60: 79 | F60: 101 | H60: =B60/$B$31 -> 0.00023883981 | I60: =C60/$C$31 -> 6.2189614e-05 | J60: =D60/$D$31 -> 5.0117287e-05 | K60: =E60/$E$31 -> 4.4711557e-05 | L60: =F60/$F$31 -> 1.9728023e-05 | N60: =B60/$B60 -> 1 | O60: =C60/$B60 -> 1.0133333 | P60: =D60/$B60 -> 1.0266667 | Q60: =E60/$B60 -> 1.0533333 | R60: =F60/$B60 -> 1.3466667
A61: Additional paid-in capital | B61: 267846 | C61: 280668 | D61: 276717 | E61: 297579 | F61: 1050518 | H61: =B61/$B$31 -> 0.85296384 | I61: =C61/$C$31 -> 0.22966625 | J61: =D61/$D$31 -> 0.18010786 | K61: =E61/$E$31 -> 0.16842051 | L61: =F61/$F$31 -> 0.20519449 | N61: =B61/$B61 -> 1 | O61: =C61/$B61 -> 1.0478708 | P61: =D61/$B61 -> 1.0331198 | Q61: =E61/$B61 -> 1.1110078 | R61: =F61/$B61 -> 3.922097
A62: Treasury stock | F62: -48226 | H62: 0 | I62: 0 | J62: 0 | K62: 0 | L62: =F62/$F$31 -> -0.0094198379 | N62: N/A | O62: N/A | P62: N/A | Q62: N/A | R62: =F62/$F62 -> 1
A63: Accumulated other comprehensive income (loss) | B63: 614 | C63: -1881 | D63: -701 | E63: -3250 | F63: 3162 | H63: =B63/$B$31 -> 0.0019553019 | I63: =C63/$C$31 -> -0.001539193 | J63: =D63/$D$31 -> -0.00045626258 | K63: =E63/$E$31 -> -0.0018393995 | L63: =F63/$F$31 -> 0.00061762384 | N63: =B63/$B63 -> 1 | O63: =C63/$B63 -> -3.0635179 | P63: =D63/$B63 -> -1.1416938 | Q63: =E63/$B63 -> -5.2931596 | R63: =F63/$B63 -> 5.1498371
A64: Retained earnings (accumulated deficit) | B64: -51490 | C64: -238772 | D64: -12053 | E64: 105521 | F64: 175912 | H64: =B64/$B$31 -> -0.16397149 | I64: =C64/$C$31 -> -0.1953834 | J64: =D64/$D$31 -> -0.0078449827 | K64: =E64/$E$31 -> 0.059721622 | L64: =F64/$F$31 -> 0.034360356 | N64: =B64/$B64 -> 1 | O64: =C64/$B64 -> 4.63725 | P64: =D64/$B64 -> 0.23408429 | Q64: =E64/$B64 -> -2.0493494 | R64: =F64/$B64 -> -3.4164304
A66: Total Stockholders’ Equity | B66: 217045 | C66: 40091 | D66: 264040 | E66: 399929 | F66: 1181467 | H66: =B66/$B$31 -> 0.69118649 | I66: =C66/$C$31 -> 0.03280584 | J66: =D66/$D$31 -> 0.17185673 | K66: =E66/$E$31 -> 0.22634745 | L66: =F66/$F$31 -> 0.23077236 | N66: =B66/$B66 -> 1 | O66: =C66/$B66 -> 0.18471285 | P66: =D66/$B66 -> 1.2165219 | Q66: =E66/$B66 -> 1.8426087 | R66: =F66/$B66 -> 5.4434196
A68: Total Liabilities, Mezzanine Equity and Stockholders’ Equity | B68: 314018 | C68: 1222069 | D68: 1536396 | E68: 1766881 | F68: 5119621 | H68: =B68/$B$31 -> 1 | I68: =C68/$C$31 -> 1 | J68: =D68/$D$31 -> 1 | K68: =E68/$E$31 -> 1 | L68: =F68/$F$31 -> 1 | N68: =B68/$B68 -> 1 | O68: =C68/$B68 -> 3.8917164 | P68: =D68/$B68 -> 4.8927004 | Q68: =E68/$B68 -> 5.626687 | R68: =F68/$B68 -> 16.303591
A77: Celsius Holdings, INC.
A78: COMMON SIZING AND TREND ANALYSIS (in 000's Except Per Share Data)
A79: INCOME STATEMENT DATA
A81: CELH Income Statement ($ in thousands) | H81: Common Size Income statement % Sales | N81: Trend Analysis Base year 2021
A82: Line Item | B82: 2021 | C82: 2022 | D82: 2023 | E82: 2024 | F82: 2025 | H82: 2021 | I82: 2022 | J82: 2023 | K82: 2024 | L82: 2025 | N82: 2021 | O82: 2022 | P82: 2023 | Q82: 2024 | R82: 2025
A83: Revenue | B83: 314272 | C83: 653604 | D83: 1318014 | E83: 1355630 | F83: 2515269 | H83: =B83/$B$83 -> 1 | I83: =C83/$C$83 -> 1 | J83: =D83/$D$83 -> 1 | K83: =E83/$E$83 -> 1 | L83: =F83/$F$83 -> 1 | N83: =B83/$B83 -> 1 | O83: =C83/$B83 -> 2.0797398 | P83: =D83/$B83 -> 4.1938639 | Q83: =E83/$B83 -> 4.3135564 | R83: =F83/$B83 -> 8.0034779
A84: Cost of revenue | B84: 186103 | C84: 382735 | D84: 684875 | E84: 675423 | F84: 1247936 | H84: =B84/$B$83 -> 0.59217175 | I84: =C84/$C$83 -> 0.58557628 | J84: =D84/$D$83 -> 0.5196265 | K84: =E84/$E$83 -> 0.49823551 | L84: =F84/$F$83 -> 0.49614415 | N84: =B84/$B84 -> 1 | O84: =C84/$B84 -> 2.0565762 | P84: =D84/$B84 -> 3.6800858 | Q84: =E84/$B84 -> 3.6292967 | R84: =F84/$B84 -> 6.70562
A85: Gross profit | B85: 128169 | C85: 270869 | D85: 633139 | E85: 680207 | F85: 1267333 | H85: =B85/$B$83 -> 0.40782825 | I85: =C85/$C$83 -> 0.41442372 | J85: =D85/$D$83 -> 0.4803735 | K85: =E85/$E$83 -> 0.50176449 | L85: =F85/$F$83 -> 0.50385585 | N85: =B85/$B85 -> 1 | O85: =C85/$B85 -> 2.1133737 | P85: =D85/$B85 -> 4.9398763 | Q85: =E85/$B85 -> 5.3071101 | R85: =F85/$B85 -> 9.8879838
A87: Operating expenses
A88: Selling, general and administrative expenses | B88: 132259 | C88: 428670 | D88: 366773 | E88: 524479 | F88: 798810 | H88: =B88/$B$83 -> 0.42084245 | I88: =C88/$C$83 -> 0.65585584 | J88: =D88/$D$83 -> 0.27827701 | K88: =E88/$E$83 -> 0.38688949 | L88: =F88/$F$83 -> 0.31758432 | N88: =B88/$B88 -> 1 | O88: =C88/$B88 -> 3.2411405 | P88: =D88/$B88 -> 2.7731421 | Q88: =E88/$B88 -> 3.9655449 | R88: =F88/$B88 -> 6.0397402
A89: Distributor termination fees | C89: - | D89: - | E89: - | F89: 327461 | L89: =F89/$F$83 -> 0.13018926 | R89: =L89/L89 -> 1
A90: Total operating expense | B90: 132259 | C90: 428670 | D90: 366773 | E90: 524479 | F90: 1126271 | H90: =B90/$B$83 -> 0.42084245 | I90: =C90/$C$83 -> 0.65585584 | J90: =D90/$D$83 -> 0.27827701 | K90: =E90/$E$83 -> 0.38688949 | L90: =F90/$F$83 -> 0.44777358 | N90: =B90/$B90 -> 1 | O90: =C90/$B90 -> 3.2411405 | P90: =D90/$B90 -> 2.7731421 | Q90: =E90/$B90 -> 3.9655449 | R90: =F90/$B90 -> 8.5156473
A92: Income from operations (EBIT) | B92: -4090 | C92: -157801 | D92: 266366 | E92: 155728 | F92: 141062 | H92: =B92/$B$83 -> -0.013014204 | I92: =C92/$C$83 -> -0.24143212 | J92: =D92/$D$83 -> 0.20209649 | K92: =E92/$E$83 -> 0.114875 | L92: =F92/$F$83 -> 0.056082272 | N92: =B92/$B92 -> 1 | O92: =C92/$B92 -> 38.582152 | P92: =D92/$B92 -> -65.126161 | Q92: =E92/$B92 -> -38.075306 | R92: =F92/$B92 -> -34.489487
A94: Other income (expense), net | B94: 31 | C94: 5137 | D94: 25383 | E94: 39322 | F94: -16029 | H94: =B94/$B$83 -> 9.8640668e-05 | I94: =C94/$C$83 -> 0.007859499 | J94: =D94/$D$83 -> 0.019258521 | K94: =E94/$E$83 -> 0.02900644 | L94: =F94/$F$83 -> -0.0063726782 | N94: =B94/$B94 -> 1 | O94: =C94/$B94 -> 165.70968 | P94: =D94/$B94 -> 818.80645 | Q94: =E94/$B94 -> 1268.4516 | R94: =F94/$B94 -> -517.06452
A95: Interest income | B95: 315 | C95: 237 | D95: 26629 | E95: 39263 | F95: 21085 | H95: =B95/$B$83 -> 0.0010023165 | I95: =C95/$C$83 -> 0.00036260488 | J95: =D95/$D$83 -> 0.020203883 | K95: =E95/$E$83 -> 0.028962918 | L95: =F95/$F$83 -> 0.0083828012 | N95: =B95/$B95 -> 1 | O95: =C95/$B95 -> 0.75238095 | P95: =D95/$B95 -> 84.536508 | Q95: =E95/$B95 -> 124.64444 | R95: =F95/$B95 -> 66.936508
A96: Interest expense | B96: -8 | C96: 5292 | D96: - | E96: - | F96: -48977 | H96: =B96/$B$83 -> -2.5455656e-05 | I96: =C96/$C$83 -> 0.0080966457 | L96: =F96/$F$83 -> -0.019471874 | N96: =B96/$B96 -> 1 | O96: =C96/$B96 -> -661.5 | R96: =F96/$B96 -> 6122.125
A97: Other, net | C97: -392 | D97: -1246 | E97: 59 | F97: 11863 | I97: =C97/$C$83 -> -0.00059975153 | J97: =D97/$D$83 -> -0.00094536173 | K97: =E97/$E$83 -> 4.35222e-05 | L97: =F97/$F$83 -> 0.0047163942
A98: Net income before income taxes | B98: -4059 | C98: -152664 | D98: 291749 | E98: 195050 | F98: 125033 | H98: =B98/$B$83 -> -0.012915564 | I98: =C98/$C$83 -> -0.23357262 | J98: =D98/$D$83 -> 0.22135501 | K98: =E98/$E$83 -> 0.14388144 | L98: =F98/$F$83 -> 0.049709594 | N98: =B98/$B98 -> 1 | O98: =C98/$B98 -> 37.611234 | P98: =D98/$B98 -> -71.877063 | Q98: =E98/$B98 -> -48.053708 | R98: =F98/$B98 -> -30.803893
A100: Provision for income taxes | B100: 7996 | C100: -34618 | D100: -64948 | E100: -49976 | F100: -17034 | H100: =B100/$B$83 -> 0.025442928 | I100: =C100/$C$83 -> -0.052964792 | J100: =D100/$D$83 -> -0.04927717 | K100: =E100/$E$83 -> -0.036865516 | L100: =F100/$F$83 -> -0.0067722379 | N100: =B100/$B100 -> 1 | O100: =C100/$B100 -> -4.3294147 | P100: =D100/$B100 -> -8.1225613 | Q100: =E100/$B100 -> -6.2501251 | R100: =F100/$B100 -> -2.1303152
A101: Net income | B101: 3937 | C101: -187282 | D101: 226801 | E101: 145074 | F101: 107999 | H101: =B101/$B$83 -> 0.012527365 | I101: =C101/$C$83 -> -0.28653741 | J101: =D101/$D$83 -> 0.17207784 | K101: =E101/$E$83 -> 0.10701593 | L101: =F101/$F$83 -> 0.042937356 | N101: =B101/$B101 -> 1 | O101: =C101/$B101 -> -47.569723 | P101: =D101/$B101 -> 57.607569 | Q101: =E101/$B101 -> 36.84887 | R101: =F101/$B101 -> 27.431801
A104: Depreciation | B104: 1264 | C104: 1917 | D104: 3226 | E104: 7274 | F104: 29451
A110: Year | B110: 2021 | C110: 2022 | D110: 2023 | E110: 2024 | F110: 2025
A111: number of shares outstanding | B111: =74909000/1000 -> 74909 | C111: =76382000/1000 -> 76382 | D111: =231787482/1000 -> 231787.48 | E111: =235014000/1000 -> 235014 | F111: =256906000/1000 -> 256906
A112: Par value | B112: 0.001 | C112: 0.001 | D112: 0.001 | E112: 0.001 | F112: 0.001
A113: Stock price | B113: 24.86 | C113: 34.68 | D113: 54.52 | E113: 26.34 | F113: 45.74

Sheet Company 5
A1: COMPANY NAME
A2: COMMON SIZING AND TREND ANALYSIS (in 000's Except Per Share Data)
A3: INCOME STATEMENT DATA
A4: NAME | T4: Page 1 of 3
A5: FIN320 Section B
I6: Common-Size Analysis | P6: Trend Analysis
I7: (as a percentage of sales) | P7: (using 2020 as the base year)
A8: Income Statement | B8: 2020 | C8: 2021 | D8: 2022 | E8: 2023 | F8: 2024 | I8: 2020 | J8: 2021 | K8: 2022 | L8: 2023 | M8: 2024 | P8: 2020 | Q8: 2021 | R8: 2022 | S8: 2023 | T8: 2024
A9: Revenue
A10: Cost of sales
A11: Gross Profit
A13: Operating expenses
A14: R&D
A15: SGA
A16: Depreciation
A17: Other
A18: Total Oper. Exp
A20: Operating Income (EBIT)
A21: Interest Expense
A22: Other expenses (net)
... A55: BALANCE SHEET DATA
A56: YOUR NAME | T56: Page 2 of 3
A57: =A5 -> FIN320 Section B
I59: Common-Size Analysis | P59: Trend Analysis
I60: (as a percentage of total assets) | P60: (using 2020 as a base year)
A61: Balance Sheet | B61: 2020 | C61: 2021 | D61: 2022 | E61: 2023 | F61: 2024 | I61: 2020 | J61: 2021 | K61: 2022 | L61: 2023 | M61: 2024 | P61: 2020 | Q61: 2021 | R61: 2022 | S61: 2023 | T61: 2024
A62: ASSETS:
A63: Current assets:
A64: Cash/Cash equivalents
A65: Short-term market sect
A66: Accounts receivable
A67: Inventories
A68: Other current assets
A69: Total Current Assets
A70: PP&E, net
A71: Other assets
A72: Total Assets
A74: LIABILITIES AND SHAREHOLDERS' EQUITY:
... A90: Total Liabilities and S/E

Sheet FINANCIAL RATIOS
B2: Market Value of Equity Calculation | J2: Financials
B4: Market Value = Number of shares outstanding * Stock Price | J4: Total Assets
C5: 2021 | D5: 2022 | E5: 2023 | F5: 2024 | G5: 2025 | K5: 2021 | L5: 2022 | M5: 2023 | N5: 2024 | O5: 2025
B6: Monster | C6: ='MONSTER (MNST)'!C30*'MONSTER (MNST)'!C31 -> 22208.046 | D6: ='MONSTER (MNST)'!D30*'MONSTER (MNST)'!D31 -> 23178.276 | E6: ='MONSTER (MNST)'!E30*'MONSTER (MNST)'!E31 -> 45975.028 | F6: ='MONSTER (MNST)'!F30*'MONSTER (MNST)'!F31 -> 55251.13 | G6: ='MONSTER (MNST)'!G30*'MONSTER (MNST)'!G31 -> 77095.073 | J6: Monster | K6: ='MONSTER (MNST)'!C67 -> 7804.784 | L6: ='MONSTER (MNST)'!D67 -> 8293.105 | M6: ='MONSTER (MNST)'!E67 -> 9686.522 | N6: ='MONSTER (MNST)'!F67 -> 7719.089 | O6: ='MONSTER (MNST)'!G67 -> 9988.945
B7: PepsiCo | C7: ='PepsiCo (PEP)'!B27*'PepsiCo (PEP)'!B28 -> 209898.16 | D7: ='PepsiCo (PEP)'!C27*'PepsiCo (PEP)'!C28 -> 223808.4 | E7: ='PepsiCo (PEP)'!D27*'PepsiCo (PEP)'!D28 -> 215825.6 | F7: ='PepsiCo (PEP)'!E27*'PepsiCo (PEP)'!E28 -> 198975.16 | G7: ='PepsiCo (PEP)'!F27*'PepsiCo (PEP)'!F28 -> 194740.25 | J7: PepsiCo | K7: ='PepsiCo (PEP)'!B68 -> 92377 | L7: ='PepsiCo (PEP)'!C68 -> 92197 | M7: ='PepsiCo (PEP)'!D68 -> 100495 | N7: ='PepsiCo (PEP)'!E68 -> 99467 | O7: ='PepsiCo (PEP)'!F68 -> 107399
