Workbook

Sheet Cover letter
B2: Church & Dwight Co Inc
B3: Financial Model
B4: =TODAY() -> 46301
B5: By: Shobitha SM

Sheet Summary Results Table
B2: ='Cover letter'!B2 -> Church & Dwight Co Inc
B3: SUMMARY RESULTS
B4: DCF VALUATION
B5: Scenarios | C5: Assumed Probablities | E5: Enterprise Values | F5: Equity Values | G5: Value Per Share | H5: Market Price
E6: ( $ millions) | F6: ( $ millions) | H6: 52 Week Range 81.33 - 106.34
B7: Base Case | C7: 0.5 | E7: 26835.762 | F7: 24453.762 | G7: 100.09727 | H7: Current Price | I7: 92.65
B8: Best Case | C8: 0.25 | E8: 32835.229 | F8: 30453.229 | G8: 124.65505 | H8: Recommendation: | I8: HOLD
B9: Worst Case | C9: 0.25 | E9: 26374.328 | F9: 23992.328 | G9: 98.208464
B10: Expected Value | E10: =IFERROR(E7*$C$7+E8*$C$8+E9*$C$9,"") -> 28220.27 | F10: =IFERROR(F7*$C$7+F8*$C$8+F9*$C$9,"") -> 25838.27 | G10: =IFERROR(G7*$C$7+G8*$C$8+G9*$C$9,"") -> 105.76451
B12: Multiple Based Valuation, Value per share
B13: Scenarios | C13: P/E Multiple | D13: EBITDA Multiple | E13: Revenue Multiple
B14: Base Case | C14: 59.002493 | D14: 69.697584 | E14: 71.447908
B15: Best Case | C15: 78.836812 | D15: 69.697584 | E15: 92.159825
B16: Worst Case | C16: 41.097849 | D16: 69.697584 | E16: 52.751047
B17: Expected Value | C17: =IFERROR(C14*$C$7+C15*$C$8+C16*$C$9,"") -> 59.484912 | D17: =IFERROR(D14*$C$7+D15*$C$8+D16*$C$9,"") -> 69.697584 | E17: =IFERROR(E14*$C$7+E15*$C$8+E16*$C$9,"") -> 71.951672
B19: Trading Multiples (Peer Average) | D19: Trading Multiple of CHD
B20: NTM TEV/Forward Total Revenue (Capital IQ) | C20: ='Assumption table'!K54 -> 13.83 | D20: ='Assumption table'!K58 -> 18.41
B21: NTM TEV/Forward EBITDA (Capital IQ) | C21: ='Assumption table'!K55 -> 3.1 | D21: ='Assumption table'!K59 -> 3.35
B22: NTM Forward P/E (Capital IQ) | C22: ='Assumption table'!K56 -> 17.2 | D22: ='Assumption table'!K60 -> 26.3

Sheet Assumption table
B2: ='Summary Results Table'!B2 -> Church & Dwight Co Inc
B3: MODEL ASSUMPTIONS
B6: GENERAL | I6: Capital Expenditure Assumptions, average of % Revenue | J6: 26E - 30E
B7: - | C7: First year of forecast period in the model: | F7: 2026 | I7: Land | J7: ='Data Source'!Q550 -> 0.0047739935
B8: - | C8: The model is a 5-year cash flow model discounted to Dec. 31, 2025 | I8: Buildings and improvements | J8: ='Data Source'!Q551 -> 0.056046274
I9: Machinery and equipment | J9: ='Data Source'!Q552 -> 0.15738719
I10: Software | J10: ='Data Source'!Q553 -> 0.021101728
I11: Office equipment and other assets | J11: ='Data Source'!Q554 -> 0.018930675
B12: Organic Growth | I12: Construction in progress | J12: ='Data Source'!Q555 -> 0.03217138
B13: Product volumes sold , based on historical arithmetic average | E13: 26E | F13: 27E - 30E
B14: Consumer Domestic: | E14: 0.0105 | F14: 0.01
B15: Consumer International: | E15: ='Data Source'!H198 -> 0.0352 | F15: ='Data Source'!I198 -> 0.0352 | I15: Depreciation Assumptions | J15: Straight Line
B16: SPD | E16: 0.005 | F16: 0.0005 | I16: Asset | J16: Useful Life
I17: Land | J17: No Depreciation
B18: Pricing/Product mix , based on historical arithmetic average | E18: 26E | F18: 27E - 30E | I18: Buildings and improvements | J18: 40
B19: Consumer Domestic: | E19: ='Data Source'!H184 -> 0.0312 | F19: ='Data Source'!I184 -> 0.0312 | I19: Machinery and equipment | J19: 15
B20: Consumer International: | E20: ='Data Source'!H199 -> 0.0264 | F20: ='Data Source'!I199 -> 0.0264 | I20: Software | J20: 10
B21: SPD | E21: ='Data Source'!H216 -> 0.0418 | F21: =E21 -> 0.0418 | I21: Office equipment and other assets | J21: 10
I22: Construction in progress | J22: N/A (not depreciated)
I23: Amortization Assumptions
B24: Inorganic Growth | I24: Asset | J24: Useful Life
B25: Acquisitions | E25: 26E | F25: 27E - 30E | I25: Trade names | J25: 20
B26: Consumer Domestic: | E26: ='Data Source'!H185 -> 0.025768577 | F26: ='Data Source'!I185 -> 0 | I26: Customer Relationships | J26: 15
B27: Consumer International: | E27: ='Data Source'!H202 -> 0.011212309 | F27: ='Data Source'!I202 -> 0 | I27: Patents/Formulas | J27: 10
B28: SPD | E28: 0 | F28: =E28 -> 0
B30: Exit of product lines | E30: 26E | F30: 27E - 30E
B31: Consumer Domestic: | E31: ='Data Source'!H186 -> -0.067 | F31: ='Data Source'!I186 -> 0 | I31: Long Term Debt Assumption | J31: 2026 | K31: 2027 | L31: 2028 | M31: 2029 | N31: 2030
B32: Consumer International: | E32: ='Data Source'!H201 -> -0.036 | F32: ='Data Source'!I201 -> 0 | I32: Beginning Debt Level as (2025), in $MM | J32: ='Data Source'!G598 -> 2205.1
B33: SPD | E33: ='Data Source'!H218 -> 0 | F33: =E33 -> 0 | I33: Long Term Debt Growth Rate | J33: 0
I34: Interest rate on long term debt | J34: ='Data Source'!M624 -> 0.041877805
I35: Long Term Debt Repayment
B36: Foreign exchange rate fluctuations / Other | E36: ='Data Source'!H221 -> 0 | F36: ='Data Source'!J221 -> 0 | I36: Long term debt+capital lease payment | J36: ='Data Source'!D642 -> 32.4 | K36: ='Data Source'!D643 -> 30.7 | L36: ='Data Source'!D644 -> 26.6 | M36: ='Data Source'!D645 -> 26 | N36: ='Data Source'!D646 -> 25.9
I37: Bond Principal Repayments | J37: 0 | K37: 425 | L37: 0 | M37: 0 | N37: 0
B38: Total Revenue Growth | E38: 26E | F38: 27E - 30E | I38: Total Scheduled Repayments | J38: =J36+J37 -> 32.4 | K38: =K36+K37 -> 455.7 | L38: =L36+L37 -> 26.6 | M38: =M36+M37 -> 26 | N38: =N36+N37 -> 25.9
B39: Consumer Domestic: | E39: =E14+E19+E26+E31+E36 -> 0.00046857669 | F39: =F14+F19+F26+F31+F36 -> 0.0412
B40: Consumer International: | E40: =E15+E20+E27+E32+E36 -> 0.036812309 | F40: =F15+F20+F27+F32+F36 -> 0.0616
B41: SPD | E41: =E16+E21+E28+E33+E36 -> 0.0468 | F41: =F16+F21+F28+F33+F36 -> 0.0423 | I41: Long Term Commitment Ex Operating Lease | J41: 2025 | K41: 2026
I42: Long term debt including capital lease payment schedule, in $MM | J42: $ 1,819 | K42: 566
I43: Of Which Capital Leasse, in $MM | J43: $ 104.0 | K43: 70.4
I44: Other Contractual Obligation ( Purchase), in $MM | J44: $ 2,925 | K44: 2462
B45: Consumer Domestic Revenue Mix, based on 5 years historical arithmetic average | F45: 26E - 30E
B46: Household Products | F46: ='Data Source'!H230 -> 0.5417016
B47: Personal Care Products | F47: ='Data Source'!H232 -> 0.4582984 | I47: Tax rate, DPO and Grwoth rate Assumptions
B48: Total Consumer Domestic: | F48: =F46+F47 -> 1 | I48: Tax rate assumed in this model | K48: ='WACC Model'!B21 -> 0.23
I49: Dividend Payout Ratio ( Average of 4 years) | K49: 0.353
I50: Base Case Terminal Growth Rate | K50: 0.03
B52: Adjusted Gross Margin; Historical arithmatic avearage, by Segment | F52: 26E - 30E
B53: Consumer Domestic: | F53: ='Data Source'!H250 -> 0.48247146 | I53: Trading Multiples (7 Peers: PG, CL, KMB, CLX, RKT, HLN, ULVR)
B54: Consumer International: | F54: ='Data Source'!H267 -> 0.4441408 | I54: NTM EV/EBITDA (Peer Median) | K54: =VALUE(SUBSTITUTE('Data Source'!B783,"x","")) -> 13.83
B55: SPD | F55: ='Data Source'!H283 -> 0.36011634 | I55: NTM EV/Revenue (Peer Median) | K55: =VALUE(SUBSTITUTE('Data Source'!E783,"x","")) -> 3.1
I56: NTM Fwd P/E (Peer Median) | K56: =VALUE(SUBSTITUTE('Data Source'!D783,"x","")) -> 17.2
I57: Trading Multiples of CHD
I58: CHD EV/EBITDA (TTM) | K58: =VALUE(SUBSTITUTE('Data Source'!B773,"x","")) -> 18.41
B59: Adjusted Operating Expenses as a % of segemental sales, 5 years Historical arithmatic avearage, by Segment | F59: 26E - 30E | I59: CHD EV/Revenue | K59: =VALUE(SUBSTITUTE('Data Source'!E773,"x","")) -> 3.35
B60: Consumer Domestic: | I60: CHD Fwd P/E | K60: =VALUE(SUBSTITUTE('Data Source'!D773,"x","")) -> 26.3
B61: Marketing expenses | F61: ='Data Source'!H252 -> 0.10978433
B62: Research and Development | F62: ='Data Source'!H254 -> 0.024973482
B63: Selling and distribution expenses excluding amortization | F63: ='Data Source'!H256 -> 0.093950457
B64: Consumer International:
B65: Marketing expenses | F65: ='Data Source'!H269 -> 0.14105782
B66: Research and Development | F66: ='Data Source'!H271 -> 0.011585427
B67: Selling and distribution expenses excluding amortization | F67: ='Data Source'!H273 -> 0.14420479
B68: SPD
B69: Marketing expenses | F69: ='Data Source'!H285 -> 0.011994526
B70: Research and Development | F70: ='Data Source'!H287 -> 0.011225437
B71: Selling and distribution expenses excluding amortization | F71: ='Data Source'!H289 -> 0.17838442
B74: Depreciation & amortization as a % of total, 5 years Historical arithmatic avearage, by Segment | F74: 26E - 30E
B75: Consumer Domestic: | F75: ='Data Source'!H375 -> 0.81775692
B76: Consumer International: | F76: ='Data Source'!H376 -> 0.12567599
B77: SPD | F77: ='Data Source'!H377 -> 0.056567081
B81: Consolidated Non - Operating Expense | F81: 26E - 30E
B82: Equity in earnings of affiliates, 5 year growth average | F82: ='Data Source'!O397 -> 0.066584333
B83: Interest Income | F83: 0.0425
B84: Other income (expense), net | F84: ='Data Source'!H400 -> -20.88
B85: Income before Income Taxes
B88: Working Capital Assumptions
B89: Assumed to change as % of revenue based on historical arithmetic average
B90: Cash and ST Invesments | F90: ='Data Source'!O433 -> 0.067586043
B91: Accounts receivable, | F91: ='Data Source'!O434 -> 0.08146372
B92: Inventories | F92: ='Data Source'!O435 -> 0.10090686
B93: Other Current Assets | F93: ='Data Source'!O436 -> 0.0087118551
B94: Accounts payable | F94: ='Data Source'!O450 -> 0.093002657
B95: Accrued Exp. | F95: ='Data Source'!O451 -> 0.11778103
B96: Curr. Portion LT Debt | F96: ='Data Source'!O449 -> 0.033764652
B97: Short-term borrowings | F97: ='Data Source'!O448 -> 0.012627731
B98: Other line items of working capital are assumed to stay the same as of 2025 for the forecast period
B102: Scenario Analysis Assuptions
B103: Selecting the most Risky Variables for Scenario Analysis
B104: Key Revenue Risk Variable
B105: Consumer Domestic:
B106: Product volumes
B107: Best Case: growth rates higher than the Base Case by | F107: 0.02
B108: Worst Case: growth rates lower than the Base Case by | F108: -0.02
B109: Pricing/Product mix
B110: Best Case: growth rates higher than the Base Case by | F110: 0.01
B111: Worst Case: growth rates lower than the Base Case by | F111: -0.005
B112: Acquisitions
B113: Best Case: growth rates higher than the Base Case by | F113: 0.02
B114: Worst Case: growth rates lower than the Base Case by | F114: 0
B115: Exit of product lines
...

Sheet Model
A2: Total Revenue Breakdown | B2: ='Data Source'!E227 -> 2023 | C2: ='Data Source'!F227 -> 2024 | D2: ='Data Source'!G227 -> 2025 | E2: =D2+1 -> 2026 | F2: =E2+1 -> 2027 | G2: =F2+1 -> 2028 | H2: =G2+1 -> 2029 | I2: =H2+1 -> 2030
A3: Consumer Domestic Segements
A4: Revenue | B4: ='Data Source'!E182 -> 4571.2 | C4: ='Data Source'!F182 -> 4732.3 | D4: ='Data Source'!G182 -> 4774.8 | E4: =D4*(1+E5) -> 4777.0374 | F4: =E4*(1+F5) -> 4973.8513 | G4: =F4*(1+G5) -> 5178.774 | H4: =G4*(1+H5) -> 5392.1395 | I4: =H4*(1+I5) -> 5614.2956
A5: YoY % | B5: ='Data Source'!E187 -> 0.107 | C5: ='Data Source'!F187 -> 0.035 | D5: ='Data Source'!G187 -> 0.009 | E5: ='Assumption table'!E39 -> 0.00046857669 | F5: ='Assumption table'!$F$39 -> 0.0412 | G5: ='Assumption table'!$F$39 -> 0.0412 | H5: ='Assumption table'!$F$39 -> 0.0412 | I5: ='Assumption table'!$F$39 -> 0.0412
A6: Change ('000) | B6: ='Data Source'!E188 -> 442.017 | C6: ='Data Source'!F188 -> 159.992 | D6: ='Data Source'!G188 -> 42.5907 | E6: =SUM(E7:E10) -> 2.23736 | F6: =SUM(F7:F10) -> 196.81394 | G6: =SUM(G7:G10) -> 204.92267 | H6: =SUM(H7:H10) -> 213.36549 | I6: =SUM(I7:I10) -> 222.15615
A7: Product volumes | B7: ='Data Source'!E189 -> 41.31 | C7: ='Data Source'!F189 -> 127.9936 | D7: ='Data Source'!G189 -> 0 | E7: =D$4*'Scenarios Table'!G12 -> 50.1354 | F7: =E$4*'Scenarios Table'!$H$12 -> 47.770374 | G7: =F$4*'Scenarios Table'!$H$12 -> 49.738513 | H7: =G$4*'Scenarios Table'!$H$12 -> 51.78774 | I7: =H$4*'Scenarios Table'!$H$12 -> 53.921395
A8: Pricing/Product mix | B8: ='Data Source'!E190 -> 194.157 | C8: ='Data Source'!F190 -> 31.9984 | D8: ='Data Source'!G190 -> -23.6615 | E8: =D$4*'Scenarios Table'!G19 -> 148.97376 | F8: =E$4*'Scenarios Table'!$H$19 -> 149.04357 | G8: =F$4*'Scenarios Table'!$H$19 -> 155.18416 | H8: =G$4*'Scenarios Table'!$H$19 -> 161.57775 | I8: =H$4*'Scenarios Table'!$H$19 -> 168.23475
A9: Acquisitions | B9: ='Data Source'!E191 -> 206.55 | C9: ='Data Source'!F191 -> 0 | D9: ='Data Source'!G191 -> 104.1106 | E9: =D$4*'Scenarios Table'!G26 -> 123.0398 | F9: =E$4*'Scenarios Table'!$H$26 -> 0 | G9: =F$4*'Scenarios Table'!$H$26 -> 0 | H9: =G$4*'Scenarios Table'!$H$26 -> 0 | I9: =H$4*'Scenarios Table'!$H$26 -> 0
A10: Exit of product lines | B10: ='Data Source'!E192 -> 0 | C10: ='Data Source'!F192 -> 0 | D10: ='Data Source'!G192 -> -37.8584 | E10: =D$4*'Scenarios Table'!G33 -> -319.9116 | F10: =E$4*'Scenarios Table'!$H$33 -> 0 | G10: =F$4*'Scenarios Table'!$H$33 -> 0 | H10: =G$4*'Scenarios Table'!$H$33 -> 0 | I10: =H$4*'Scenarios Table'!$H$33 -> 0
A11: Check | E11: =(E6/D4)-E5 -> -6.1257423e-18 | F11: =(F6/E4)-F5 -> 0 | G11: =(G6/F4)-G5 -> 0 | H11: =(H6/G4)-H5 -> 0 | I11: =(I6/H4)-I5 -> 0
A13: Consumer International Segements
A14: Revenue | B14: ='Data Source'!E197 -> 975.7 | C14: ='Data Source'!F197 -> 1071.5 | D14: ='Data Source'!G197 -> 1129.4 | E14: =D14*(1+E15) -> 1170.9758 | F14: =E14*(1+F15) -> 1243.1079 | G14: =F14*(1+G15) -> 1319.6834 | H14: =G14*(1+H15) -> 1400.9759 | I14: =H14*(1+I15) -> 1487.276
A15: YoY % | B15: ='Data Source'!E203 -> 0.089 | C15: ='Data Source'!F203 -> 0.098 | D15: ='Data Source'!G203 -> 0.054 | E15: ='Assumption table'!E40 -> 0.036812309 | F15: ='Assumption table'!$F$40 -> 0.0616 | G15: ='Assumption table'!$F$40 -> 0.0616 | H15: ='Assumption table'!$F$40 -> 0.0616 | I15: ='Assumption table'!$F$40 -> 0.0616
A16: Change ('000) | B16: ='Data Source'!E204 -> 79.7529 | C16: ='Data Source'!F204 -> 95.6186 | D16: ='Data Source'!G204 -> 57.861 | E16: =SUM(E17:E21) -> 41.575822 | F16: =SUM(F17:F21) -> 72.132111 | G16: =SUM(G17:G21) -> 76.575449 | H16: =SUM(H17:H21) -> 81.292496 | I16: =SUM(I17:I21) -> 86.300114
A17: Product volumes sold | B17: ='Data Source'!E205 -> 30.4674 | C17: ='Data Source'!F205 -> 55.6149 | D17: ='Data Source'!G205 -> 52.5035 | E17: =D$14*'Scenarios Table'!G42 -> 39.75488 | F17: =E$14*'Scenarios Table'!$H$42 -> 41.218349 | G17: =F$14*'Scenarios Table'!$H$42 -> 43.757399 | H17: =G$14*'Scenarios Table'!$H$42 -> 46.452855 | I17: =H$14*'Scenarios Table'!$H$42 -> 49.314351
A18: Pricing/Product mix | B18: ='Data Source'!E206 -> 45.7011 | C18: ='Data Source'!F206 -> 32.1981 | D18: ='Data Source'!G206 -> 6.429 | E18: =D$14*'Scenarios Table'!G49 -> 29.81616 | F18: =E$14*'Scenarios Table'!$H$49 -> 30.913762 | G18: =F$14*'Scenarios Table'!$H$49 -> 32.818049 | H18: =G$14*'Scenarios Table'!$H$49 -> 34.839641 | I18: =H$14*'Scenarios Table'!$H$49 -> 36.985763
A19: Foreign exchange rate fluctuations | B19: ='Data Source'!E207 -> 0.8961 | C19: ='Data Source'!F207 -> -1.9514 | D19: ='Data Source'!G207 -> -2.143 | E19: =D$14*'Assumption table'!E36 -> 0 | F19: =E$14*'Assumption table'!$F$36 -> 0 | G19: =F$14*'Assumption table'!$F$36 -> 0 | H19: =G$14*'Assumption table'!$F$36 -> 0 | I19: =H$14*'Assumption table'!$F$36 -> 0
A20: Acquisitions | B20: ='Data Source'!E209 -> 2.6883 | C20: ='Data Source'!F209 -> 9.757 | D20: ='Data Source'!G209 -> 10.715 | E20: =D$14*'Scenarios Table'!G56 -> 12.663182 | F20: =E$14*'Scenarios Table'!$H$56 -> 0 | G20: =F$14*'Scenarios Table'!$H$56 -> 0 | H20: =G$14*'Scenarios Table'!$H$56 -> 0 | I20: =H$14*'Scenarios Table'!$H$56 -> 0
A21: Exit of product lines | B21: ='Data Source'!E208 -> 0 | C21: ='Data Source'!F208 -> 0 | D21: ='Data Source'!G208 -> -9.6435 | E21: =D$14*'Scenarios Table'!G63 -> -40.6584 | F21: =E$14*'Scenarios Table'!$H$63 -> 0 | G21: =F$14*'Scenarios Table'!$H$63 -> 0 | H21: =G$14*'Scenarios Table'!$H$63 -> 0 | I21: =H$14*'Scenarios Table'!$H$63 -> 0
A22: Check | E22: =(E16/D14)-E15 -> 0 | F22: =(F16/E14)-F15 -> 0 | G22: =(G16/F14)-G15 -> 0 | H22: =(H16/G14)-H15 -> 0 | I22: =(I16/H14)-I15 -> 0
A24: SPD
A25: Revenue | B25: ='Data Source'!E214 -> 321 | C25: ='Data Source'!F214 -> 303.3 | D25: ='Data Source'!G214 -> 299 | E25: =D25*(1+E26) -> 312.9932 | F25: =E25*(1+F26) -> 326.23281 | G25: =F25*(1+G26) -> 340.03246 | H25: =G25*(1+H26) -> 354.41583 | I25: =H25*(1+I26) -> 369.40762
A26: YoY % | B26: ='Data Source'!E219 -> -0.079 | C26: ='Data Source'!F219 -> -0.055 | D26: ='Data Source'!G219 -> -0.014 | E26: ='Assumption table'!E41 -> 0.0468 | F26: ='Assumption table'!$F$41 -> 0.0423 | G26: ='Assumption table'!$F$41 -> 0.0423 | H26: ='Assumption table'!$F$41 -> 0.0423 | I26: ='Assumption table'!$F$41 -> 0.0423
A27: Change ('000) | B27: ='Data Source'!E220 -> -27.5315 | C27: ='Data Source'!F220 -> -17.655 | D27: ='Data Source'!G220 -> -4.2462 | E27: =SUM(E28:E31) -> 13.9932 | F27: =SUM(F28:F31) -> 13.239612 | G27: =SUM(G28:G31) -> 13.799648 | H27: =SUM(H28:H31) -> 14.383373 | I27: =SUM(I28:I31) -> 14.99179
A28: Product volumes | B28: ='Data Source'!E221 -> -25.092 | C28: ='Data Source'!F221 -> 12.84 | D28: ='Data Source'!G221 -> 0.9099 | E28: =D$25*'Scenarios Table'!G72 -> 1.495 | F28: =E$25*'Scenarios Table'!$H$72 -> 0.1564966 | G28: =F$25*'Scenarios Table'!$H$72 -> 0.16311641 | H28: =G$25*'Scenarios Table'!$H$72 -> 0.17001623 | I28: =H$25*'Scenarios Table'!$H$72 -> 0.17720792
A29: Pricing/Product mix | B29: ='Data Source'!E222 -> -2.4395 | C29: ='Data Source'!F222 -> 9.951 | D29: ='Data Source'!G222 -> 6.9759 | E29: =D$25*'Scenarios Table'!G79 -> 12.4982 | F29: =E$25*'Scenarios Table'!$H$79 -> 13.083116 | G29: =F$25*'Scenarios Table'!$H$79 -> 13.636532 | H29: =G$25*'Scenarios Table'!$H$79 -> 14.213357 | I29: =H$25*'Scenarios Table'!$H$79 -> 14.814582
A30: Acquisitions | B30: ='Data Source'!E223 -> 0 | C30: ='Data Source'!F223 -> 0 | D30: ='Data Source'!G223 -> 0.9099 | E30: =D$25*'Assumption table'!E28 -> 0 | F30: =E$25*'Assumption table'!$F$28 -> 0 | G30: =F$25*'Assumption table'!$F$28 -> 0 | H30: =G$25*'Assumption table'!$F$28 -> 0 | I30: =H$25*'Assumption table'!$F$28 -> 0
A31: Exit of product lines | B31: ='Data Source'!E224 -> 0 | C31: ='Data Source'!F224 -> -40.446 | D31: ='Data Source'!G224 -> -13.0419 | E31: =D$25*'Assumption table'!E33 -> 0 | F31: =E$25*'Assumption table'!$F$33 -> 0 | G31: =F$25*'Assumption table'!$F$33 -> 0 | H31: =G$25*'Assumption table'!$F$33 -> 0 | I31: =H$25*'Assumption table'!$F$33 -> 0
A32: Check | E32: =(E27/D25)-E26 -> 0 | F32: =(F27/E25)-F26 -> 0 | G32: =(G27/F25)-G26 -> 0 | H32: =(H27/G25)-H26 -> 0 | I32: =(I27/H25)-I26 -> 0
A34: Total Consolidated Revenue
A35: Household Products | B35: ='Data Source'!E229 -> 2484.1 | C35: ='Data Source'!F229 -> 2584.3 | D35: ='Data Source'!G229 -> 2556.9 | E35: ='Assumption table'!$F$46*E37 -> 2587.7288 | F35: ='Assumption table'!$F$46*F37 -> 2694.3432 | G35: ='Assumption table'!$F$46*G37 -> 2805.3501 | H35: ='Assumption table'!$F$46*H37 -> 2920.9305 | I35: ='Assumption table'!$F$46*I37 -> 3041.2729
A36: Personal Care Products | B36: ='Data Source'!E231 -> 2087.1 | C36: ='Data Source'!F231 -> 2148 | D36: ='Data Source'!G231 -> 2217.9 | E36: ='Assumption table'!$F$47*E37 -> 2189.3086 | F36: ='Assumption table'!$F$47*F37 -> 2279.5081 | G36: ='Assumption table'!$F$47*G37 -> 2373.4238 | H36: ='Assumption table'!$F$47*H37 -> 2471.2089 | I36: ='Assumption table'!$F$47*I37 -> 2573.0227
A37: Total Consumer Domestic | B37: ='Data Source'!E228 -> 4571.2 | C37: ='Data Source'!F228 -> 4732.3 | D37: ='Data Source'!G228 -> 4774.8 | E37: =E4 -> 4777.0374 | F37: =F4 -> 4973.8513 | G37: =G4 -> 5178.774 | H37: =H4 -> 5392.1395 | I37: =I4 -> 5614.2956
A39: Total Consumer International | B39: ='Data Source'!E233 -> 975.7 | C39: ='Data Source'!F233 -> 1071.5 | D39: ='Data Source'!G233 -> 1129.4 | E39: =E14 -> 1170.9758 | F39: =F14 -> 1243.1079 | G39: =G14 -> 1319.6834 | H39: =H14 -> 1400.9759 | I39: =I14 -> 1487.276
A41: Total SPD | B41: ='Data Source'!E234 -> 321 | C41: ='Data Source'!F234 -> 303.3 | D41: ='Data Source'!G234 -> 299 | E41: =E25 -> 312.9932 | F41: =F25 -> 326.23281 | G41: =G25 -> 340.03246 | H41: =H25 -> 354.41583 | I41: =I25 -> 369.40762
A42: Total Consolidated Net Sales | B42: ='Data Source'!E235 -> 5867.9 | C42: ='Data Source'!F235 -> 6107.1 | D42: ='Data Source'!G235 -> 6203.2 | E42: =SUM(E37:E41) -> 6261.0064 | F42: =SUM(F37:F41) -> 6543.192 | G42: =SUM(G37:G41) -> 6838.4898 | H42: =SUM(H37:H41) -> 7147.5312 | I42: =SUM(I37:I41) -> 7470.9792
A43: Check | B43: =B37+B39+B41-B42 -> 0 | C43: =C37+C39+C41-C42 -> 0 | D43: =D37+D39+D41-D42 -> 0 | E43: =E37+E39+E41-E42 -> 0 | F43: =F37+F39+F41-F42 -> 0 | G43: =G37+G39+G41-G42 -> 0 | H43: =H37+H39+H41-H42 -> 0 | I43: =I37+I39+I41-I42 -> 0
A44: YoY% | B44: ='Data Source'!E236 -> 0.092 | C44: ='Data Source'!F236 -> 0.041 | D44: ='Data Source'!G236 -> 0.016 | E44: =E42/D42-1 -> 0.0093188003 | F44: =F42/E42-1 -> 0.045070336 | G44: =G42/F42-1 -> 0.045130537 | H44: =H42/G42-1 -> 0.045191463 | I44: =I42/H42-1 -> 0.045253115
A48: Segemental Detail Breakdown | B48: =B$2 -> 2023 | C48: =C$2 -> 2024 | D48: =D$2 -> 2025 | E48: =E$2 -> 2026 | F48: =F$2 -> 2027 | G48: =G$2 -> 2028 | H48: =H$2 -> 2029 | I48: =I$2 -> 2030
A49: Consumer Domestic Segements
A50: Net Sales | B50: =B4 -> 4571.2 | C50: =C4 -> 4732.3 | D50: =D4 -> 4774.8 | E50: =E4 -> 4777.0374 | F50: =F4 -> 4973.8513 | G50: =G4 -> 5178.774 | H50: =H4 -> 5392.1395 | I50: =I4 -> 5614.2956
A51: COGS excluding depreciation | B51: ='Data Source'!E248 -> 2374.551 | C51: ='Data Source'!F248 -> 2380.5753 | D51: ='Data Source'!G248 -> 2467.8239 | E51: =E50-E52 -> 2472.2532 | F51: =F50-F52 -> 2574.11 | G51: =G50-G52 -> 2680.1633 | H51: =H50-H52 -> 2790.5861 | I51: =I50-I52 -> 2905.5582
A52: Gross Profit | B52: ='Data Source'!E249 -> 2196.649 | C52: ='Data Source'!F249 -> 2351.7247 | D52: ='Data Source'!G249 -> 2306.9761 | E52: =E$50*'Scenarios Table'!$G$87 -> 2304.7842 | F52: =F$50*'Scenarios Table'!$G$87 -> 2399.7413 | G52: =G$50*'Scenarios Table'!$G$87 -> 2498.6106 | H52: =H$50*'Scenarios Table'!$G$87 -> 2601.5534 | I52: =I$50*'Scenarios Table'!$G$87 -> 2708.7374
A53: Marketing expenses | B53: ='Data Source'!E251 -> 509.5 | C53: ='Data Source'!F251 -> 538.5 | D53: ='Data Source'!G251 -> 532.7 | E53: =E$50*'Scenarios Table'!$G$110 -> 524.44385 | F53: =F$50*'Scenarios Table'!$G$110 -> 546.05093 | G53: =G$50*'Scenarios Table'!$G$110 -> 568.54823 | H53: =H$50*'Scenarios Table'!$G$110 -> 591.97242 | I53: =I$50*'Scenarios Table'!$G$110 -> 616.36168
A54: Research and Development | B54: ='Data Source'!E253 -> 107.1 | C54: ='Data Source'!F253 -> 123.7 | D54: ='Data Source'!G253 -> 129.1 | E54: =E$50*'Assumption table'!$F$62 -> 119.29926 | F54: =F$50*'Assumption table'!$F$62 -> 124.21438 | G54: =G$50*'Assumption table'!$F$62 -> 129.33202 | H54: =H$50*'Assumption table'!$F$62 -> 134.6605 | I54: =I$50*'Assumption table'!$F$62 -> 140.20851
A55: Selling and distribution expenses excluding amortization | B55: ='Data Source'!E255 -> 466.44902 | C55: ='Data Source'!F255 -> 477.42472 | D55: ='Data Source'!G255 -> 514.27611 | E55: =E$50*'Scenarios Table'!$G$117 -> 448.80484 | F55: =F$50*'Scenarios Table'!$G$117 -> 467.2956 | G55: =G$50*'Scenarios Table'!$G$117 -> 486.54818 | H55: =H$50*'Scenarios Table'!$G$117 -> 506.59397 | I55: =I$50*'Scenarios Table'!$G$117 -> 527.46564
A56: Depreciation | B56: ='Data Source'!E257 -> 59.449023 | C56: ='Data Source'!F257 -> 69.524718 | D56: ='Data Source'!G257 -> 76.176112 | E56: =E$181*'Assumption table'!$F$75 -> 81.391713 | F56: =F$181*'Assumption table'!$F$75 -> 85.060064 | G56: =G$181*'Assumption table'!$F$75 -> 88.898871 | H56: =H$181*'Assumption table'!$F$75 -> 92.916341 | I56: =I$181*'Assumption table'!$F$75 -> 97.121095
A57: Amortization | B57: ='Data Source'!E258 -> 124.45098 | C57: ='Data Source'!F258 -> 130.27528 | D57: ='Data Source'!G258 -> 133.92389 | E57: =E$212*'Assumption table'!$F$75 -> 135.85396 | F57: =F$212*'Assumption table'!$F$75 -> 135.85396 | G57: =G$212*'Assumption table'!$F$75 -> 135.85396 | H57: =H$212*'Assumption table'!$F$75 -> 135.85396 | I57: =I$212*'Assumption table'!$F$75 -> 135.85396
A58: VMS Trade name and other asset impairments | B58: ='Data Source'!E259 -> 0 | C58: ='Data Source'!F259 -> 327.4 | D58: ='Data Source'!G259 -> 0 | E58: =D58 -> 0 | F58: =E58 -> 0 | G58: =F58 -> 0 | H58: =G58 -> 0 | I58: =H58 -> 0
A59: Income from Operations | B59: =B52-B53-B54-B55-B56-B57-B58 -> 929.7 | C59: =C52-C53-C54-C55-C56-C57-C58 -> 684.9 | D59: =D52-D53-D54-D55-D56-D57-D58 -> 920.8 | E59: =E52-E53-E54-E55-E56-E57-E58 -> 994.99056 | F59: =F52-F53-F54-F55-F56-F57-F58 -> 1041.2663 | G59: =G52-G53-G54-G55-G56-G57-G58 -> 1089.4294 | H59: =H52-H53-H54-H55-H56-H57-H58 -> 1139.5562 | I59: =I52-I53-I54-I55-I56-I57-I58 -> 1191.7265
A62: Consumer International Segements
A63: Net Sales | B63: ='Data Source'!E264 -> 975.7 | C63: ='Data Source'!F264 -> 1071.5 | D63: ='Data Source'!G264 -> 1129.4 | E63: =E14 -> 1170.9758 | F63: =F14 -> 1243.1079 | G63: =G14 -> 1319.6834 | H63: =H14 -> 1400.9759 | I63: =I14 -> 1487.276
A64: COGS excluding depreciation | B64: ='Data Source'!E265 -> 559.74547 | C64: ='Data Source'!F265 -> 595.37403 | D64: ='Data Source'!G265 -> 616.14568 | E64: =E63-E65 -> 650.89769 | F64: =F63-F65 -> 690.99298 | G64: =G63-G65 -> 733.55815 | H64: =H63-H65 -> 778.74533 | I64: =I63-I65 -> 826.71605
A65: Gross Profit | B65: ='Data Source'!E266 -> 415.95453 | C65: ='Data Source'!F266 -> 476.12597 | D65: ='Data Source'!G266 -> 513.25432 | E65: =E$63*'Scenarios Table'!$G$94 -> 520.07813 | F65: =F$63*'Scenarios Table'!$G$94 -> 552.11495 | G65: =G$63*'Scenarios Table'!$G$94 -> 586.12523 | H65: =H$63*'Scenarios Table'!$G$94 -> 622.23054 | I65: =I$63*'Scenarios Table'!$G$94 -> 660.55994
A66: Marketing expenses | B66: ='Data Source'!E268 -> 127.7 | C66: ='Data Source'!F268 -> 156.9 | D66: ='Data Source'!G268 -> 172.7 | E66: =E$63*'Scenarios Table'!$G$125 -> 165.1753 | F66: =F$63*'Scenarios Table'!$G$125 -> 175.3501 | G66: =G$63*'Scenarios Table'!$G$125 -> 186.15166 | H66: =H$63*'Scenarios Table'!$G$125 -> 197.61861 | I66: =I$63*'Scenarios Table'!$G$125 -> 209.79191
A67: Research and Development | B67: ='Data Source'!E270 -> 11.1 | C67: ='Data Source'!F270 -> 12.7 | D67: ='Data Source'!G270 -> 13.5 | E67: =E$63*'Assumption table'!$F$66 -> 13.566255 | F67: =F$63*'Assumption table'!$F$66 -> 14.401937 | G67: =G$63*'Assumption table'!$F$66 -> 15.289096 | H67: =H$63*'Assumption table'!$F$66 -> 16.230904 | I67: =I$63*'Assumption table'!$F$66 -> 17.230728
A68: Selling and distribution expenses excluding amortization | B68: ='Data Source'!E272 -> 145.25453 | C68: ='Data Source'!F272 -> 164.62597 | D68: ='Data Source'!G272 -> 185.05432 | E68: =E$63*'Scenarios Table'!$G$132 -> 168.86032 | F68: =F$63*'Scenarios Table'!$G$132 -> 179.26211 | G68: =G$63*'Scenarios Table'!$G$132 -> 190.30466 | H68: =H$63*'Scenarios Table'!$G$132 -> 202.02743 | I68: =I$63*'Scenarios Table'!$G$132 -> 214.47232
A69: Depreciation | B69: ='Data Source'!E274 -> 8.9545293 | C69: ='Data Source'!F274 -> 10.125972 | D69: ='Data Source'!G274 -> 9.354325 | E69: =E$181*'Assumption table'!$F$76 -> 12.508588 | F69: =F$181*'Assumption table'!$F$76 -> 13.072354 | G69: =G$181*'Assumption table'!$F$76 -> 13.662317 | H69: =H$181*'Assumption table'!$F$76 -> 14.279737 | I69: =I$181*'Assumption table'!$F$76 -> 14.925939
A70: Amortization | B70: ='Data Source'!E275 -> 18.745471 | C70: ='Data Source'!F275 -> 18.974028 | D70: ='Data Source'!G275 -> 16.445675 | E70: =E$212*'Assumption table'!$F$76 -> 20.878553 | F70: =F$212*'Assumption table'!$F$76 -> 20.878553 | G70: =G$212*'Assumption table'!$F$76 -> 20.878553 | H70: =H$212*'Assumption table'!$F$76 -> 20.878553 | I70: =I$212*'Assumption table'!$F$76 -> 20.878553
A71: VMS Trade name and other asset impairments | B71: ='Data Source'!E276 -> 0 | C71: ='Data Source'!F276 -> 29.7 | D71: ='Data Source'!G276 -> 0 | E71: =D71 -> 0 | F71: =E71 -> 0 | G71: =F71 -> 0 | H71: =G71 -> 0 | I71: =H71 -> 0
A72: Income from Operations | B72: =B65-B66-B67-B68-B69-B70-B71 -> 104.2 | C72: =C65-C66-C67-C68-C69-C70-C71 -> 83.1 | D72: =D65-D66-D67-D68-D69-D70-D71 -> 116.2 | E72: =E65-E66-E67-E68-E69-E70-E71 -> 139.08912 | F72: =F65-F66-F67-F68-F69-F70-F71 -> 149.14989 | G72: =G65-G66-G67-G68-G69-G70-G71 -> 159.83894 | H72: =H65-H66-H67-H68-H69-H70-H71 -> 171.19532 | I72: =I65-I66-I67-I68-I69-I70-I71 -> 183.2605
A75: SPD
A76: Net Sales | B76: =B25 -> 321 | C76: =C25 -> 303.3 | D76: =D25 -> 299 | E76: =E25 -> 312.9932 | F76: =F25 -> 326.23281 | G76: =G25 -> 340.03246 | H76: =H25 -> 354.41583 | I76: =I25 -> 369.40762
A77: COGS excluding depreciation | B77: ='Data Source'!E281 -> 211.90355 | C77: ='Data Source'!F281 -> 189.95069 | D77: ='Data Source'!G281 -> 186.23044 | E77: =E76-E78 -> 200.27923 | F77: =F76-F78 -> 208.75105 | G77: =G76-G78 -> 217.58121 | H77: =H76-H78 -> 226.7849 | I77: =I76-I78 -> 236.3779
A78: Gross Profit | B78: ='Data Source'!E282 -> 109.09645 | C78: ='Data Source'!F282 -> 113.34931 | D78: ='Data Source'!G282 -> 112.76956 | E78: =E$76*'Scenarios Table'!$G$101 -> 112.71397 | F78: =F$76*'Scenarios Table'!$G$101 -> 117.48177 | G78: =G$76*'Scenarios Table'!$G$101 -> 122.45125 | H78: =H$76*'Scenarios Table'!$G$101 -> 127.63093 | I78: =I$76*'Scenarios Table'!$G$101 -> 133.02972
A79: Marketing expenses | B79: ='Data Source'!E284 -> 4.1 | C79: ='Data Source'!F284 -> 2.7 | D79: ='Data Source'!G284 -> 3.5 | E79: =E$76*'Assumption table'!$F$69 -> 3.7542052 | F79: =F$76*'Assumption table'!$F$69 -> 3.9130081 | G79: =G$76*'Assumption table'!$F$69 -> 4.0785283 | H79: =H$76*'Assumption table'!$F$69 -> 4.25105 | I79: =I$76*'Assumption table'!$F$69 -> 4.4308695
A80: Research and Development | B80: ='Data Source'!E286 -> 4.2 | C80: ='Data Source'!F286 -> 3.3 | D80: ='Data Source'!G286 -> 3 | E80: =E$76*'Assumption table'!$F$70 -> 3.5134854 | F80: =F$76*'Assumption table'!$F$70 -> 3.6621058 | G80: =G$76*'Assumption table'!$F$70 -> 3.8170129 | H80: =H$76*'Assumption table'!$F$70 -> 3.9784725 | I80: =I$76*'Assumption table'!$F$70 -> 4.1467619
A81: Selling and distribution expenses excluding amortization | B81: ='Data Source'!E288 -> 63.696448 | C81: ='Data Source'!F288 -> 58.04931 | D81: ='Data Source'!G288 -> 54.169563 | E81: =E$76*'Assumption table'!$F$71 -> 55.83311 | F81: =F$76*'Assumption table'!$F$71 -> 58.19485 | G81: =G$76*'Assumption table'!$F$71 -> 60.656492 | H81: =H$76*'Assumption table'!$F$71 -> 63.222262 | I81: =I$76*'Assumption table'!$F$71 -> 65.896564
A82: Depreciation | B82: ='Data Source'!E290 -> 4.3964476 | C82: ='Data Source'!F290 -> 3.5493099 | D82: ='Data Source'!G290 -> 4.1695635 | E82: =E$181*'Assumption table'!$F$77 -> 5.6301469 | F82: =F$181*'Assumption table'!$F$77 -> 5.8838995 | G82: =G$181*'Assumption table'!$F$77 -> 6.149443 | H82: =H$181*'Assumption table'!$F$77 -> 6.4273454 | I82: =I$181*'Assumption table'!$F$77 -> 6.7182028
A83: Amortization | B83: ='Data Source'!E291 -> 9.2035524 | C83: ='Data Source'!F291 -> 6.6506901 | D83: ='Data Source'!G291 -> 7.3304365 | E83: =E$212*'Assumption table'!$F$77 -> 9.3974892 | F83: =F$212*'Assumption table'!$F$77 -> 9.3974892 | G83: =G$212*'Assumption table'!$F$77 -> 9.3974892 | H83: =H$212*'Assumption table'!$F$77 -> 9.3974892 | I83: =I$212*'Assumption table'!$F$77 -> 9.3974892
A84: Income from Operations | B84: =B78-B79-B80-B81-B82-B83 -> 23.5 | C84: =C78-C79-C80-C81-C82-C83 -> 39.1 | D84: =D78-D79-D80-D81-D82-D83 -> 40.6 | E84: =E78-E79-E80-E81-E82-E83 -> 34.58553 | F84: =F78-F79-F80-F81-F82-F83 -> 36.430414 | G84: =G78-G79-G80-G81-G82-G83 -> 38.35228 | H84: =H78-H79-H80-H81-H82-H83 -> 40.354314 | I84: =I78-I79-I80-I81-I82-I83 -> 42.439835
A94: Consolidated Operation Cost Schedule | B94: =B$2 -> 2023 | C94: =C$2 -> 2024 | D94: =D$2 -> 2025 | E94: =E$2 -> 2026 | F94: =F$2 -> 2027 | G94: =G$2 -> 2028 | H94: =H$2 -> 2029 | I94: =I$2 -> 2030
A95: In $MM
A96: Marketing expenses | B96: =B53+B66+B79 -> 641.3 | C96: =C53+C66+C79 -> 698.1 | D96: =D53+D66+D79 -> 708.9 | E96: =E53+E66+E79 -> 693.37335 | F96: =F53+F66+F79 -> 725.31404 | G96: =G53+G66+G79 -> 758.77842 | H96: =H53+H66+H79 -> 793.84208 | I96: =I53+I66+I79 -> 830.58447
A97: Research and Development | B97: =B54+B67+B80 -> 122.4 | C97: =C54+C67+C80 -> 139.7 | D97: =D54+D67+D80 -> 145.6 | E97: =E54+E67+E80 -> 136.379 | F97: =F54+F67+F80 -> 142.27843 | G97: =G54+G67+G80 -> 148.43813 | H97: =H54+H67+H80 -> 154.86987 | I97: =I54+I67+I80 -> 161.586
A98: Selling and distribution expenses excluding amortization | B98: =B55+B68+B81 -> 675.4 | C98: =C55+C68+C81 -> 700.1 | D98: =D55+D68+D81 -> 753.5 | E98: =E55+E68+E81 -> 673.49827 | F98: =F55+F68+F81 -> 704.75257 | G98: =G55+G68+G81 -> 737.50933 | H98: =H55+H68+H81 -> 771.84366 | I98: =I55+I68+I81 -> 807.83452
A99: Depreciation | B99: =B56+B69+B82 -> 72.8 | C99: =C56+C69+C82 -> 83.2 | D99: =D56+D69+D82 -> 89.7 | E99: =E56+E69+E82 -> 99.530447 | F99: =F56+F69+F82 -> 104.01632 | G99: =G56+G69+G82 -> 108.71063 | H99: =H56+H69+H82 -> 113.62342 | I99: =I56+I69+I82 -> 118.76524
A100: Amortization | B100: =B57+B70+B83 -> 152.4 | C100: =C57+C70+C83 -> 155.9 | D100: =D57+D70+D83 -> 157.7 | E100: =E57+E70+E83 -> 166.13 | F100: =F57+F70+F83 -> 166.13 | G100: =G57+G70+G83 -> 166.13 | H100: =H57+H70+H83 -> 166.13 | I100: =I57+I70+I83 -> 166.13
A101: VMS Trade name and other asset impairments | B101: =B58+B71 -> 0 | C101: =C58+C71 -> 357.1 | D101: =D58+D71 -> 0 | E101: =E58+E71 -> 0 | F101: =F58+F71 -> 0 | G101: =G58+G71 -> 0 | H101: =H58+H71 -> 0 | I101: =I58+I71 -> 0
A102: Total Operation Expense | B102: =SUM(B96:B101) -> 1664.3 | C102: =SUM(C96:C101) -> 2134.1 | D102: =SUM(D96:D101) -> 1855.4 | E102: =SUM(E96:E101) -> 1768.9111 | F102: =SUM(F96:F101) -> 1842.4914 | G102: =SUM(G96:G101) -> 1919.5665 | H102: =SUM(H96:H101) -> 2000.309 | I102: =SUM(I96:I101) -> 2084.9002
A104: Capital Expenditure Projections | B104: =B$2 -> 2023 | C104: =C$2 -> 2024 | D104: =D$2 -> 2025 | E104: =E$2 -> 2026 | F104: =F$2 -> 2027 | G104: =G$2 -> 2028 | H104: =H$2 -> 2029 | I104: =I$2 -> 2030
A105: In $MM
A106: Land | B106: ='Data Source'!E549 -> 28.3 | C106: ='Data Source'!F549 -> 29.2 | D106: ='Data Source'!G549 -> 16 | E106: =E42*'Assumption table'!$J$7 -> 29.890004 | F106: =F42*'Assumption table'!$J$7 -> 31.237156 | G106: =G42*'Assumption table'!$J$7 -> 32.646906 | H106: =H42*'Assumption table'!$J$7 -> 34.122267 | I106: =I42*'Assumption table'!$J$7 -> 35.666406
A107: Capex | E107: =E106-D106 -> 13.890004 | F107: =F106-E106 -> 1.3471525 | G107: =G106-F106 -> 1.4097496 | H107: =H106-G106 -> 1.4753614 | I107: =I106-H106 -> 1.5441389
A108: Buildings and improvements | B108: ='Data Source'!E550 -> 317.8 | C108: ='Data Source'!F550 -> 348.2 | D108: ='Data Source'!G550 -> 367.5 | E108: =E42*'Assumption table'!$J$8 -> 350.90608 | F108: =F42*'Assumption table'!$J$8 -> 366.72153 | G108: =G42*'Assumption table'!$J$8 -> 383.27187 | H108: =H42*'Assumption table'!$J$8 -> 400.59249 | I108: =I42*'Assumption table'!$J$8 -> 418.72055
A109: Capex | E109: =E108-D108 -> -16.59392 | F109: =F108-E108 -> 15.815455 | G109: =G108-F108 -> 16.55034 | H109: =H108-G108 -> 17.320617 | I109: =I108-H108 -> 18.128058
A110: Machinery and equipment | B110: ='Data Source'!E551 -> 895.1 | C110: ='Data Source'!F551 -> 1000.4 | D110: ='Data Source'!G551 -> 911.1 | E110: =E42*'Assumption table'!$J$9 -> 985.40223 | F110: =F42*'Assumption table'!$J$9 -> 1029.8146 | G110: =G42*'Assumption table'!$J$9 -> 1076.2907 | H110: =H42*'Assumption table'!$J$9 -> 1124.9299 | I110: =I42*'Assumption table'!$J$9 -> 1175.8365
A111: Capex | E111: =E110-D110 -> 74.302231 | F111: =F110-E110 -> 44.41241 | G111: =G110-F110 -> 46.476088 | H111: =H110-G110 -> 48.639152 | I111: =I110-H110 -> 50.906581
A112: Software | B112: ='Data Source'!E552 -> 122.6 | C112: ='Data Source'!F552 -> 129.6 | D112: ='Data Source'!G552 -> 138.9 | E112: =E42*'Assumption table'!$J$10 -> 132.11805 | F112: =F42*'Assumption table'!$J$10 -> 138.07266 | G112: =G42*'Assumption table'!$J$10 -> 144.30395 | H112: =H42*'Assumption table'!$J$10 -> 150.82526 | I112: =I42*'Assumption table'!$J$10 -> 157.65057
A113: Capex | E113: =E112-D112 -> -6.7819463 | F113: =F112-E112 -> 5.9546051 | G113: =G112-F112 -> 6.2312932 | H113: =H112-G112 -> 6.5213067 | I113: =I112-H112 -> 6.8253128
A114: Office equipment and other assets | B114: ='Data Source'!E553 -> 105.2 | C114: ='Data Source'!F553 -> 129.3 | D114: ='Data Source'!G553 -> 131.6 | E114: =E42*'Assumption table'!$J$11 -> 118.52508 | F114: =F42*'Assumption table'!$J$11 -> 123.86705 | G114: =G42*'Assumption table'!$J$11 -> 129.45723 | H114: =H42*'Assumption table'!$J$11 -> 135.30759 | I114: =I42*'Assumption table'!$J$11 -> 141.43068
A115: Capex | E115: =E114-D114 -> -13.07492 | F115: =F114-E114 -> 5.3419652 | G115: =G114-F114 -> 5.5901863 | H115: =H114-G114 -> 5.8503616 | I115: =I114-H114 -> 6.1230901
A116: Construction in progress | B116: ='Data Source'!E554 -> 348.4 | C116: ='Data Source'!F554 -> 215.1 | D116: ='Data Source'!G554 -> 131.9 | E116: =E42*'Assumption table'!$J$12 -> 201.42522 | F116: =F42*'Assumption table'!$J$12 -> 210.50352 | G116: =G42*'Assumption table'!$J$12 -> 220.00365 | H116: =H42*'Assumption table'!$J$12 -> 229.94594 | I116: =I42*'Assumption table'!$J$12 -> 240.35171
A117: Capex | E117: =E116-D116 -> 69.525215 | F117: =F116-E116 -> 9.0783022 | G117: =G116-F116 -> 9.5001368 | H117: =H116-G116 -> 9.9422869 | I117: =I116-H116 -> 10.40577
A120: Gross PP&E | B120: ='Data Source'!E555 -> 1817.4 | C120: ='Data Source'!F555 -> 1851.8 | D120: ='Data Source'!G555 -> 1697 | E120: =E106+E108+E110+E112+E114+E116 -> 1818.2667 | F120: =F106+F108+F110+F112+F114+F116 -> 1900.2166 | G120: =G106+G108+G110+G112+G114+G116 -> 1985.9743 | H120: =H106+H108+H110+H112+H114+H116 -> 2075.7234 | I120: =I106+I108+I110+I112+I114+I116 -> 2169.6564
A121: Less accumulated depreciation | B121: ='Data Source'!E556 -> 889.7 | C121: ='Data Source'!F556 -> 920.1 | D121: ='Data Source'!G556 -> 874.2 | E121: =D121+E181 -> 973.73045 | F121: =E121+F181 -> 1077.7468 | G121: =F121+G181 -> 1186.4574 | H121: =G121+H181 -> 1300.0808 | I121: =H121+I181 -> 1418.8461
A123: Depreciable Asset Schedule ( Existing and New) | B123: =B$2 -> 2023 | C123: =C$2 -> 2024 | D123: =D$2 -> 2025 | E123: =E$2 -> 2026 | F123: =F$2 -> 2027 | G123: =G$2 -> 2028 | H123: =H$2 -> 2029 | I123: =I$2 -> 2030
A124: in $MM
A125: Land | D125: =D106 -> 16 | E125: =E107 -> 13.890004 | F125: =F107 -> 1.3471525 | G125: =G107 -> 1.4097496 | H125: =H107 -> 1.4753614 | I125: =I107 -> 1.5441389
A126: Buildings and improvements | D126: =D108 -> 367.5 | E126: =E109 -> -16.59392 | F126: =F109 -> 15.815455 | G126: =G109 -> 16.55034 | H126: =H109 -> 17.320617 | I126: =I109 -> 18.128058
...

Sheet Scenarios Table
B1: Church & Dwight Co Inc
B2: Volumes, Pricing/Product mix, Acquisitions, Exit of product lines, COGS, Operating Expenses, Terminal Value and Discount Rate Scenarios
A3: SWITCH | B3: 1
G8: 2026 | H8: 2027 | I8: 2028 | J8: 2029 | K8: 2030
B9: Consumer Domestic:
B10: Volume Scenario
C11: Product volumes
D12: Currently Running | G12: =CHOOSE($B$3,G14,G15,G16) -> 0.0105 | H12: =CHOOSE($B$3,H14,H15,H16) -> 0.01 | I12: =CHOOSE($B$3,I14,I15,I16) -> 0.01 | J12: =CHOOSE($B$3,J14,J15,J16) -> 0.01 | K12: =CHOOSE($B$3,K14,K15,K16) -> 0.01
D14: Base Case | G14: ='Assumption table'!E14 -> 0.0105 | H14: ='Assumption table'!F14 -> 0.01 | I14: ='Assumption table'!F14 -> 0.01 | J14: ='Assumption table'!F14 -> 0.01 | K14: ='Assumption table'!F14 -> 0.01
D15: Best Case | G15: =G14+'Assumption table'!$F107 -> 0.0305 | H15: =H14+'Assumption table'!$F107 -> 0.03 | I15: =I14+'Assumption table'!$F107 -> 0.03 | J15: =J14+'Assumption table'!$F107 -> 0.03 | K15: =K14+'Assumption table'!$F107 -> 0.03
D16: Worst Case | G16: =G14+'Assumption table'!$F108 -> -0.0095 | H16: =H14+'Assumption table'!$F108 -> -0.01 | I16: =I14+'Assumption table'!$F108 -> -0.01 | J16: =J14+'Assumption table'!$F108 -> -0.01 | K16: =K14+'Assumption table'!$F108 -> -0.01
C18: Pricing/Product mix
D19: Currently Running | G19: =CHOOSE($B$3,G21,G22,G23) -> 0.0312 | H19: =CHOOSE($B$3,H21,H22,H23) -> 0.0312 | I19: =CHOOSE($B$3,I21,I22,I23) -> 0.0312 | J19: =CHOOSE($B$3,J21,J22,J23) -> 0.0312 | K19: =CHOOSE($B$3,K21,K22,K23) -> 0.0312
D21: Base Case | G21: ='Assumption table'!E19 -> 0.0312 | H21: ='Assumption table'!F19 -> 0.0312 | I21: ='Assumption table'!F19 -> 0.0312 | J21: ='Assumption table'!F19 -> 0.0312 | K21: ='Assumption table'!F19 -> 0.0312
D22: Best Case | G22: =G21+'Assumption table'!$F110 -> 0.0412 | H22: =H21+'Assumption table'!$F110 -> 0.0412 | I22: =I21+'Assumption table'!$F110 -> 0.0412 | J22: =J21+'Assumption table'!$F110 -> 0.0412 | K22: =K21+'Assumption table'!$F110 -> 0.0412
D23: Worst Case | G23: =G21+'Assumption table'!$F111 -> 0.0262 | H23: =H21+'Assumption table'!$F111 -> 0.0262 | I23: =I21+'Assumption table'!$F111 -> 0.0262 | J23: =J21+'Assumption table'!$F111 -> 0.0262 | K23: =K21+'Assumption table'!$F111 -> 0.0262
C25: Acquisitions
D26: Currently Running | G26: =CHOOSE($B$3,G28,G29,G30) -> 0.025768577 | H26: =CHOOSE($B$3,H28,H29,H30) -> 0 | I26: =CHOOSE($B$3,I28,I29,I30) -> 0 | J26: =CHOOSE($B$3,J28,J29,J30) -> 0 | K26: =CHOOSE($B$3,K28,K29,K30) -> 0
D28: Base Case | G28: ='Assumption table'!E26 -> 0.025768577 | H28: ='Assumption table'!F26 -> 0 | I28: ='Assumption table'!F26 -> 0 | J28: ='Assumption table'!F26 -> 0 | K28: ='Assumption table'!F26 -> 0
D29: Best Case | G29: =G28+'Assumption table'!$F113 -> 0.045768577 | H29: =H28+'Assumption table'!$F113 -> 0.02 | I29: =I28+'Assumption table'!$F113 -> 0.02 | J29: =J28+'Assumption table'!$F113 -> 0.02 | K29: =K28+'Assumption table'!$F113 -> 0.02
D30: Worst Case | G30: =G28+'Assumption table'!$F114 -> 0.025768577 | H30: =H28+'Assumption table'!$F114 -> 0 | I30: =I28+'Assumption table'!$F114 -> 0 | J30: =J28+'Assumption table'!$F114 -> 0 | K30: =K28+'Assumption table'!$F114 -> 0
C32: Exit of product lines
D33: Currently Running | G33: =CHOOSE($B$3,G35,G36,G37) -> -0.067 | H33: =CHOOSE($B$3,H35,H36,H37) -> 0 | I33: =CHOOSE($B$3,I35,I36,I37) -> 0 | J33: =CHOOSE($B$3,J35,J36,J37) -> 0 | K33: =CHOOSE($B$3,K35,K36,K37) -> 0
D35: Base Case | G35: ='Assumption table'!E31 -> -0.067 | H35: ='Assumption table'!F31 -> 0 | I35: ='Assumption table'!F31 -> 0 | J35: ='Assumption table'!F31 -> 0 | K35: ='Assumption table'!F31 -> 0
D36: Best Case | G36: =G35+'Assumption table'!$F116 -> -0.067 | H36: =H35+'Assumption table'!$F116 -> 0 | I36: =I35+'Assumption table'!$F116 -> 0 | J36: =J35+'Assumption table'!$F116 -> 0 | K36: =K35+'Assumption table'!$F116 -> 0
D37: Worst Case | G37: =G35+'Assumption table'!$F117 -> -0.067 | H37: =H35+'Assumption table'!$F117 -> 0 | I37: =I35+'Assumption table'!$F117 -> 0 | J37: =J35+'Assumption table'!$F117 -> 0 | K37: =K35+'Assumption table'!$F117 -> 0
B39: Consumer International:
B40: Volume Scenario
C41: Product volumes
D42: Currently Running | G42: =CHOOSE($B$3,G44,G45,G46) -> 0.0352 | H42: =CHOOSE($B$3,H44,H45,H46) -> 0.0352 | I42: =CHOOSE($B$3,I44,I45,I46) -> 0.0352 | J42: =CHOOSE($B$3,J44,J45,J46) -> 0.0352 | K42: =CHOOSE($B$3,K44,K45,K46) -> 0.0352
D44: Base Case | G44: ='Assumption table'!E15 -> 0.0352 | H44: ='Assumption table'!F15 -> 0.0352 | I44: ='Assumption table'!F15 -> 0.0352 | J44: ='Assumption table'!F15 -> 0.0352 | K44: ='Assumption table'!F15 -> 0.0352
D45: Best Case | G45: =G44+'Assumption table'!$F120 -> 0.0652 | H45: =H44+'Assumption table'!$F120 -> 0.0652 | I45: =I44+'Assumption table'!$F120 -> 0.0652 | J45: =J44+'Assumption table'!$F120 -> 0.0652 | K45: =K44+'Assumption table'!$F120 -> 0.0652
D46: Worst Case | G46: =G44+'Assumption table'!$F121 -> 0.0252 | H46: =H44+'Assumption table'!$F121 -> 0.0252 | I46: =I44+'Assumption table'!$F121 -> 0.0252 | J46: =J44+'Assumption table'!$F121 -> 0.0252 | K46: =K44+'Assumption table'!$F121 -> 0.0252
C48: Pricing/Product mix
D49: Currently Running | G49: =CHOOSE($B$3,G51,G52,G53) -> 0.0264 | H49: =CHOOSE($B$3,H51,H52,H53) -> 0.0264 | I49: =CHOOSE($B$3,I51,I52,I53) -> 0.0264 | J49: =CHOOSE($B$3,J51,J52,J53) -> 0.0264 | K49: =CHOOSE($B$3,K51,K52,K53) -> 0.0264
D51: Base Case | G51: ='Assumption table'!E20 -> 0.0264 | H51: ='Assumption table'!F20 -> 0.0264 | I51: ='Assumption table'!F20 -> 0.0264 | J51: ='Assumption table'!F20 -> 0.0264 | K51: ='Assumption table'!F20 -> 0.0264
D52: Best Case | G52: =G51+'Assumption table'!$F123 -> 0.0314 | H52: =H51+'Assumption table'!$F123 -> 0.0314 | I52: =I51+'Assumption table'!$F123 -> 0.0314 | J52: =J51+'Assumption table'!$F123 -> 0.0314 | K52: =K51+'Assumption table'!$F123 -> 0.0314
D53: Worst Case | G53: =G51+'Assumption table'!$F124 -> 0.0254 | H53: =H51+'Assumption table'!$F124 -> 0.0254 | I53: =I51+'Assumption table'!$F124 -> 0.0254 | J53: =J51+'Assumption table'!$F124 -> 0.0254 | K53: =K51+'Assumption table'!$F124 -> 0.0254
C55: Acquisitions
D56: Currently Running | G56: =CHOOSE($B$3,G58,G59,G60) -> 0.011212309 | H56: =CHOOSE($B$3,H58,H59,H60) -> 0 | I56: =CHOOSE($B$3,I58,I59,I60) -> 0 | J56: =CHOOSE($B$3,J58,J59,J60) -> 0 | K56: =CHOOSE($B$3,K58,K59,K60) -> 0
D58: Base Case | G58: ='Assumption table'!E27 -> 0.011212309 | H58: ='Assumption table'!F27 -> 0 | I58: ='Assumption table'!F27 -> 0 | J58: ='Assumption table'!F27 -> 0 | K58: ='Assumption table'!F27 -> 0
D59: Best Case | G59: =G58+'Assumption table'!$F126 -> 0.026212309 | H59: =H58+'Assumption table'!$F126 -> 0.015 | I59: =I58+'Assumption table'!$F126 -> 0.015 | J59: =J58+'Assumption table'!$F126 -> 0.015 | K59: =K58+'Assumption table'!$F126 -> 0.015
D60: Worst Case | G60: =G58+'Assumption table'!$F127 -> 0.011212309 | H60: =H58+'Assumption table'!$F127 -> 0 | I60: =I58+'Assumption table'!$F127 -> 0 | J60: =J58+'Assumption table'!$F127 -> 0 | K60: =K58+'Assumption table'!$F127 -> 0
C62: Exit of product lines
D63: Currently Running | G63: =CHOOSE($B$3,G65,G66,G67) -> -0.036 | H63: =CHOOSE($B$3,H65,H66,H67) -> 0 | I63: =CHOOSE($B$3,I65,I66,I67) -> 0 | J63: =CHOOSE($B$3,J65,J66,J67) -> 0 | K63: =CHOOSE($B$3,K65,K66,K67) -> 0
D65: Base Case | G65: ='Assumption table'!E32 -> -0.036 | H65: ='Assumption table'!F32 -> 0 | I65: ='Assumption table'!F32 -> 0 | J65: ='Assumption table'!F32 -> 0 | K65: ='Assumption table'!F32 -> 0
D66: Best Case | G66: =G65+'Assumption table'!$F129 -> -0.036 | H66: =H65+'Assumption table'!$F129 -> 0 | I66: =I65+'Assumption table'!$F129 -> 0 | J66: =J65+'Assumption table'!$F129 -> 0 | K66: =K65+'Assumption table'!$F129 -> 0
D67: Worst Case | G67: =G65+'Assumption table'!$F130 -> -0.036 | H67: =H65+'Assumption table'!$F130 -> 0 | I67: =I65+'Assumption table'!$F130 -> 0 | J67: =J65+'Assumption table'!$F130 -> 0 | K67: =K65+'Assumption table'!$F130 -> 0
B69: SPD:
B70: Volume Scenario
C71: Product volumes
D72: Currently Running | G72: =CHOOSE($B$3,G74,G75,G76) -> 0.005 | H72: =CHOOSE($B$3,H74,H75,H76) -> 0.0005 | I72: =CHOOSE($B$3,I74,I75,I76) -> 0.0005 | J72: =CHOOSE($B$3,J74,J75,J76) -> 0.0005 | K72: =CHOOSE($B$3,K74,K75,K76) -> 0.0005
D74: Base Case | G74: ='Assumption table'!E16 -> 0.005 | H74: ='Assumption table'!F16 -> 0.0005 | I74: ='Assumption table'!F16 -> 0.0005 | J74: ='Assumption table'!F16 -> 0.0005 | K74: ='Assumption table'!F16 -> 0.0005
D75: Best Case | G75: =G74+'Assumption table'!$F133 -> 0.015 | H75: =H74+'Assumption table'!$F133 -> 0.0105 | I75: =I74+'Assumption table'!$F133 -> 0.0105 | J75: =J74+'Assumption table'!$F133 -> 0.0105 | K75: =K74+'Assumption table'!$F133 -> 0.0105
D76: Worst Case | G76: =G74+'Assumption table'!$F134 -> -0.005 | H76: =H74+'Assumption table'!$F134 -> -0.0095 | I76: =I74+'Assumption table'!$F134 -> -0.0095 | J76: =J74+'Assumption table'!$F134 -> -0.0095 | K76: =K74+'Assumption table'!$F134 -> -0.0095
C78: Pricing/Product mix
D79: Currently Running | G79: =CHOOSE($B$3,G81,G82,G83) -> 0.0418 | H79: =CHOOSE($B$3,H81,H82,H83) -> 0.0418 | I79: =CHOOSE($B$3,I81,I82,I83) -> 0.0418 | J79: =CHOOSE($B$3,J81,J82,J83) -> 0.0418 | K79: =CHOOSE($B$3,K81,K82,K83) -> 0.0418
D81: Base Case | G81: ='Assumption table'!E21 -> 0.0418 | H81: ='Assumption table'!F21 -> 0.0418 | I81: ='Assumption table'!F21 -> 0.0418 | J81: ='Assumption table'!F21 -> 0.0418 | K81: ='Assumption table'!F21 -> 0.0418
D82: Best Case | G82: =G81+'Assumption table'!$F136 -> 0.0468 | H82: =H81+'Assumption table'!$F136 -> 0.0468 | I82: =I81+'Assumption table'!$F136 -> 0.0468 | J82: =J81+'Assumption table'!$F136 -> 0.0468 | K82: =K81+'Assumption table'!$F136 -> 0.0468
D83: Worst Case | G83: =G81+'Assumption table'!$F137 -> 0.0318 | H83: =H81+'Assumption table'!$F137 -> 0.0318 | I83: =I81+'Assumption table'!$F137 -> 0.0318 | J83: =J81+'Assumption table'!$F137 -> 0.0318 | K83: =K81+'Assumption table'!$F137 -> 0.0318
B85: Gross Margin (as % of segment sales)
C86: Consumer Domestic
D87: Currently Running | G87: =CHOOSE($B$3,G89,G90,G91) -> 0.48247146 | H87: =CHOOSE($B$3,H89,H90,H91) -> 0.48247146 | I87: =CHOOSE($B$3,I89,I90,I91) -> 0.48247146 | J87: =CHOOSE($B$3,J89,J90,J91) -> 0.48247146 | K87: =CHOOSE($B$3,K89,K90,K91) -> 0.48247146
D89: Base Case | G89: ='Assumption table'!$F$53 -> 0.48247146 | H89: ='Assumption table'!$F$53 -> 0.48247146 | I89: ='Assumption table'!$F$53 -> 0.48247146 | J89: ='Assumption table'!$F$53 -> 0.48247146 | K89: ='Assumption table'!$F$53 -> 0.48247146
D90: Best Case | G90: =G89+'Assumption table'!$F147 -> 0.50247146 | H90: =H89+'Assumption table'!$F147 -> 0.50247146 | I90: =I89+'Assumption table'!$F147 -> 0.50247146 | J90: =J89+'Assumption table'!$F147 -> 0.50247146 | K90: =K89+'Assumption table'!$F147 -> 0.50247146
D91: Worst Case | G91: =G89+'Assumption table'!$F148 -> 0.46747146 | H91: =H89+'Assumption table'!$F148 -> 0.46747146 | I91: =I89+'Assumption table'!$F148 -> 0.46747146 | J91: =J89+'Assumption table'!$F148 -> 0.46747146 | K91: =K89+'Assumption table'!$F148 -> 0.46747146
C93: Consumer International
D94: Currently Running | G94: =CHOOSE($B$3,G96,G97,G98) -> 0.4441408 | H94: =CHOOSE($B$3,H96,H97,H98) -> 0.4441408 | I94: =CHOOSE($B$3,I96,I97,I98) -> 0.4441408 | J94: =CHOOSE($B$3,J96,J97,J98) -> 0.4441408 | K94: =CHOOSE($B$3,K96,K97,K98) -> 0.4441408
D96: Base Case | G96: ='Assumption table'!$F$54 -> 0.4441408 | H96: ='Assumption table'!$F$54 -> 0.4441408 | I96: ='Assumption table'!$F$54 -> 0.4441408 | J96: ='Assumption table'!$F$54 -> 0.4441408 | K96: ='Assumption table'!$F$54 -> 0.4441408
D97: Best Case | G97: =G96+'Assumption table'!$F150 -> 0.4691408 | H97: =H96+'Assumption table'!$F150 -> 0.4691408 | I97: =I96+'Assumption table'!$F150 -> 0.4691408 | J97: =J96+'Assumption table'!$F150 -> 0.4691408 | K97: =K96+'Assumption table'!$F150 -> 0.4691408
D98: Worst Case | G98: =G96+'Assumption table'!$F151 -> 0.4291408 | H98: =H96+'Assumption table'!$F151 -> 0.4291408 | I98: =I96+'Assumption table'!$F151 -> 0.4291408 | J98: =J96+'Assumption table'!$F151 -> 0.4291408 | K98: =K96+'Assumption table'!$F151 -> 0.4291408
C100: SPD
D101: Currently Running | G101: =CHOOSE($B$3,G103,G104,G105) -> 0.36011634 | H101: =CHOOSE($B$3,H103,H104,H105) -> 0.36011634 | I101: =CHOOSE($B$3,I103,I104,I105) -> 0.36011634 | J101: =CHOOSE($B$3,J103,J104,J105) -> 0.36011634 | K101: =CHOOSE($B$3,K103,K104,K105) -> 0.36011634
D103: Base Case | G103: ='Assumption table'!$F$55 -> 0.36011634 | H103: ='Assumption table'!$F$55 -> 0.36011634 | I103: ='Assumption table'!$F$55 -> 0.36011634 | J103: ='Assumption table'!$F$55 -> 0.36011634 | K103: ='Assumption table'!$F$55 -> 0.36011634
D104: Best Case | G104: =G103+'Assumption table'!$F153 -> 0.37011634 | H104: =H103+'Assumption table'!$F153 -> 0.37011634 | I104: =I103+'Assumption table'!$F153 -> 0.37011634 | J104: =J103+'Assumption table'!$F153 -> 0.37011634 | K104: =K103+'Assumption table'!$F153 -> 0.37011634
D105: Worst Case | G105: =G103+'Assumption table'!$F154 -> 0.35011634 | H105: =H103+'Assumption table'!$F154 -> 0.35011634 | I105: =I103+'Assumption table'!$F154 -> 0.35011634 | J105: =J103+'Assumption table'!$F154 -> 0.35011634 | K105: =K103+'Assumption table'!$F154 -> 0.35011634
B107: Operating Expenses (as % of segment sales)
B108: Consumer Domestic:
C109: Marketing expenses
D110: Currently Running | G110: =CHOOSE($B$3,G112,G113,G114) -> 0.10978433 | H110: =CHOOSE($B$3,H112,H113,H114) -> 0.10978433 | I110: =CHOOSE($B$3,I112,I113,I114) -> 0.10978433 | J110: =CHOOSE($B$3,J112,J113,J114) -> 0.10978433 | K110: =CHOOSE($B$3,K112,K113,K114) -> 0.10978433
D112: Base Case | G112: ='Assumption table'!$F$61 -> 0.10978433 | H112: ='Assumption table'!$F$61 -> 0.10978433 | I112: ='Assumption table'!$F$61 -> 0.10978433 | J112: ='Assumption table'!$F$61 -> 0.10978433 | K112: ='Assumption table'!$F$61 -> 0.10978433
D113: Best Case | G113: =G112+'Assumption table'!$F$158 -> 0.08978433 | H113: =H112+'Assumption table'!$F$158 -> 0.08978433 | I113: =I112+'Assumption table'!$F$158 -> 0.08978433 | J113: =J112+'Assumption table'!$F$158 -> 0.08978433 | K113: =K112+'Assumption table'!$F$158 -> 0.08978433
D114: Worst Case | G114: =G112+'Assumption table'!$F$159 -> 0.12978433 | H114: =H112+'Assumption table'!$F$159 -> 0.12978433 | I114: =I112+'Assumption table'!$F$159 -> 0.12978433 | J114: =J112+'Assumption table'!$F$159 -> 0.12978433 | K114: =K112+'Assumption table'!$F$159 -> 0.12978433
C116: Selling & distribution
D117: Currently Running | G117: =CHOOSE($B$3,G119,G120,G121) -> 0.093950457 | H117: =CHOOSE($B$3,H119,H120,H121) -> 0.093950457 | I117: =CHOOSE($B$3,I119,I120,I121) -> 0.093950457 | J117: =CHOOSE($B$3,J119,J120,J121) -> 0.093950457 | K117: =CHOOSE($B$3,K119,K120,K121) -> 0.093950457
D119: Base Case | G119: ='Assumption table'!$F$63 -> 0.093950457 | H119: ='Assumption table'!$F$63 -> 0.093950457 | I119: ='Assumption table'!$F$63 -> 0.093950457 | J119: ='Assumption table'!$F$63 -> 0.093950457 | K119: ='Assumption table'!$F$63 -> 0.093950457
D120: Best Case | G120: =G119+'Assumption table'!$F$161 -> 0.073950457 | H120: =H119+'Assumption table'!$F$161 -> 0.073950457 | I120: =I119+'Assumption table'!$F$161 -> 0.073950457 | J120: =J119+'Assumption table'!$F$161 -> 0.073950457 | K120: =K119+'Assumption table'!$F$161 -> 0.073950457
D121: Worst Case | G121: =G119+'Assumption table'!$F$162 -> 0.11395046 | H121: =H119+'Assumption table'!$F$162 -> 0.11395046 | I121: =I119+'Assumption table'!$F$162 -> 0.11395046 | J121: =J119+'Assumption table'!$F$162 -> 0.11395046 | K121: =K119+'Assumption table'!$F$162 -> 0.11395046
B123: Consumer International:
C124: Marketing expenses
D125: Currently Running | G125: =CHOOSE($B$3,G127,G128,G129) -> 0.14105782 | H125: =CHOOSE($B$3,H127,H128,H129) -> 0.14105782 | I125: =CHOOSE($B$3,I127,I128,I129) -> 0.14105782 | J125: =CHOOSE($B$3,J127,J128,J129) -> 0.14105782 | K125: =CHOOSE($B$3,K127,K128,K129) -> 0.14105782
D127: Base Case | G127: ='Assumption table'!$F$65 -> 0.14105782 | H127: ='Assumption table'!$F$65 -> 0.14105782 | I127: ='Assumption table'!$F$65 -> 0.14105782 | J127: ='Assumption table'!$F$65 -> 0.14105782 | K127: ='Assumption table'!$F$65 -> 0.14105782
D128: Best Case | G128: =G127+'Assumption table'!$F$158 -> 0.12105782 | H128: =H127+'Assumption table'!$F$158 -> 0.12105782 | I128: =I127+'Assumption table'!$F$158 -> 0.12105782 | J128: =J127+'Assumption table'!$F$158 -> 0.12105782 | K128: =K127+'Assumption table'!$F$158 -> 0.12105782
D129: Worst Case | G129: =G127+'Assumption table'!$F$159 -> 0.16105782 | H129: =H127+'Assumption table'!$F$159 -> 0.16105782 | I129: =I127+'Assumption table'!$F$159 -> 0.16105782 | J129: =J127+'Assumption table'!$F$159 -> 0.16105782 | K129: =K127+'Assumption table'!$F$159 -> 0.16105782
C131: Selling & distribution
D132: Currently Running | G132: =CHOOSE($B$3,G134,G135,G136) -> 0.14420479 | H132: =CHOOSE($B$3,H134,H135,H136) -> 0.14420479 | I132: =CHOOSE($B$3,I134,I135,I136) -> 0.14420479 | J132: =CHOOSE($B$3,J134,J135,J136) -> 0.14420479 | K132: =CHOOSE($B$3,K134,K135,K136) -> 0.14420479
D134: Base Case | G134: ='Assumption table'!$F$67 -> 0.14420479 | H134: ='Assumption table'!$F$67 -> 0.14420479 | I134: ='Assumption table'!$F$67 -> 0.14420479 | J134: ='Assumption table'!$F$67 -> 0.14420479 | K134: ='Assumption table'!$F$67 -> 0.14420479
D135: Best Case | G135: =G134+'Assumption table'!$F$161 -> 0.12420479 | H135: =H134+'Assumption table'!$F$161 -> 0.12420479 | I135: =I134+'Assumption table'!$F$161 -> 0.12420479 | J135: =J134+'Assumption table'!$F$161 -> 0.12420479 | K135: =K134+'Assumption table'!$F$161 -> 0.12420479
D136: Worst Case | G136: =G134+'Assumption table'!$F$162 -> 0.16420479 | H136: =H134+'Assumption table'!$F$162 -> 0.16420479 | I136: =I134+'Assumption table'!$F$162 -> 0.16420479 | J136: =J134+'Assumption table'!$F$162 -> 0.16420479 | K136: =K134+'Assumption table'!$F$162 -> 0.16420479
B141: Terminal Growth Rate
...

Sheet WACC Model
A1: Principal Due in Millions of the reported currency.
A2: Debt Structure
A3: Debt description | B3: Type | C3: Principal Due (USD) | D3: Coupon/Base Rate | E3: Debt Weights | F3: Debt Rd Contribution
A4: 2.30% Senior Notes Due December 15, 2031 | B4: Bonds and Notes | C4: ='Data Source'!C616 -> 400 | D4: ='Data Source'!D616 -> 0.023 | E4: =C4/$C$10 -> 0.16653483 | F4: =D4*E4 -> 0.003830301
A5: 3.15% Senior Notes Due August 1, 2027 | B5: Bonds and Notes | C5: ='Data Source'!C617 -> 425 | D5: ='Data Source'!D617 -> 0.0315 | E5: =C5/$C$10 -> 0.17694325 | F5: =D5*E5 -> 0.0055737125
A6: 3.95% Senior Notes Due August 1, 2047 | B6: Bonds and Notes | C6: ='Data Source'!C618 -> 400 | D6: ='Data Source'!D618 -> 0.0395 | E6: =C6/$C$10 -> 0.16653483 | F6: =D6*E6 -> 0.0065781257
A7: 5.00% Senior Notes Due June 15, 2052 | B7: Bonds and Notes | C7: ='Data Source'!C619 -> 500 | D7: ='Data Source'!D619 -> 0.05 | E7: =C7/$C$10 -> 0.20816853 | F7: =D7*E7 -> 0.010408427
A8: 5.60% Senior Notes Due November 15, 2032 | B8: Bonds and Notes | C8: ='Data Source'!C620 -> 500 | D8: ='Data Source'!D620 -> 0.056 | E8: =C8/$C$10 -> 0.20816853 | F8: =D8*E8 -> 0.011657438
A9: Operating Lease Obligation | B9: Capital Lease | C9: ='Data Source'!C622 -> 176.9 | D9: ='Data Source'!D622 -> 0.052 | E9: =C9/$C$10 -> 0.073650027 | F9: =D9*E9 -> 0.0038298014
A10: Total Interest bearing debt including capital Lease | C10: =SUM(C4:C9) -> 2401.9 | F10: =SUM(F4:F9) -> 0.041877805 | G10: Weighted Cost of debt
A13: Cost of Equity (CAPM)
A14: Equity Beta | B14: =SLOPE('Data Source'!D656:D726,'Data Source'!E656:E726) -> 0.53009556
A15: Market Risk Premium | B15: 0.055
A16: Risk Free Rate (20 Years Treasury) | B16: 0.0482 | C16: Source: https://www.treasury.gov | E16: as of May 2, 2025
A17: Equity Cost of Capital of CHD | B17: =B16+B14*B15 -> 0.077355256 | C17: CAPM
A20: Weighted Average Cost of Capital Calculations
A21: Tax Rate | B21: 0.23
A22: Market Value of Equity | B22: ='Data Source'!B726*'Data Source'!G421 -> 20421.037 | C22: Market Capitalization table
A23: Market Value of Debt long term debt including Capital Lease | B23: =C10 -> 2401.9 | C23: See above
A24: E/V | B24: =B22/(B22+B23) -> 0.89475938
A25: D/V | B25: =B23/(B22+B23) -> 0.10524062
A26: WACC | B26: =B24*B17+B25*F10*(1-B21) -> 0.07260792

Sheet DCF
F3: ="Currently Running: "&CHOOSE('Scenarios Table'!B3,"BASE CASE","BEST CASE","WORST CASE") -> Currently Running: BASE CASE
A4: Cost of Equity | B4: ='Scenarios Table'!G150 -> 0.077355256
A5: Cost of Debt | B5: ='Scenarios Table'!G157 -> 0.041877805
A6: WACC | B6: ='WACC Model'!B24*B4+'WACC Model'!B25*B5*(1-'WACC Model'!B21) -> 0.07260792
A7: Terminal, Sustainable Long Term Growth Rate | B7: ='Scenarios Table'!G142 -> 0.03 | D7: 2026 | E7: 2027 | F7: 2028 | G7: 2029 | H7: 2030
C9: In millions of $
C11: FCF to Equity
C12: Net Income | D12: =Model!E266 -> 838.04123 | E12: =Model!F266 -> 884.07466 | F12: =Model!G266 -> 932.16715 | G12: =Model!H266 -> 982.41355 | H12: =Model!I266 -> 1034.9132
C13: Depreciation | D13: =Model!E276+Model!E277 -> 265.66045 | E13: =Model!F276+Model!F277 -> 270.14632 | F13: =Model!G276+Model!G277 -> 274.84063 | G13: =Model!H276+Model!H277 -> 279.75342 | H13: =Model!I276+Model!I277 -> 284.89524
C14: CAPEX | D14: =Model!E301 -> -121.26666 | E14: =Model!F301 -> -81.94989 | F14: =Model!G301 -> -85.757793 | G14: =Model!H301 -> -89.749085 | H14: =Model!I301 -> -93.932951
C15: Changes in working capital | D15: =Model!E298 -> -182.95034 | E15: =Model!F298 -> 5.5594104 | F15: =Model!G298 -> 5.8177353 | G15: =Model!H298 -> 6.0885012 | H15: =Model!I298 -> 6.3723311
C16: Net Debt | D16: =Model!E309+Model!E310+Model!E311 -> 0 | E16: =Model!F309+Model!F310+Model!F311 -> 0 | F16: =Model!G309+Model!G310+Model!G311 -> 0 | G16: =Model!H309+Model!H310+Model!H311 -> 0 | H16: =Model!I309+Model!I310+Model!I311 -> 0
C17: FCF to Equity (NI+Dep-Capex-chge NWC+ Net Debt) | D17: =D12+D13+D14+D15+D16 -> 799.48467 | E17: =E12+E13+E14+E15+E16 -> 1077.8305 | F17: =F12+F13+F14+F15+F16 -> 1127.0677 | G17: =G12+G13+G14+G15+G16 -> 1178.5064 | H17: =H12+H13+H14+H15+H16 -> 1232.2479
C18: Terminal Value at end of 2030 | H18: =H17*(1+$B$7)/($B$4-$B$7) -> 26801.994
C19: Total FCF to Equity (both first stage and second stage) | D19: =D17 -> 799.48467 | E19: =E17 -> 1077.8305 | F19: =F17 -> 1127.0677 | G19: =G17 -> 1178.5064 | H19: =H17+H18 -> 28034.242
C20: Total Equity Value | D20: =NPV($B$4,D19:H19) -> 22761.746
C21: Total number of Shares Outstanding, in Millions | D21: ='Data Source'!G421 -> 244.3
C22: Per Share | D22: =D20/D21 -> 93.171291
C23: Total FCF to the Firm
C24: After Tax Interest Expense | D24: =-Model!E262*(1-'WACC Model'!$B$21) -> 71.105456 | E24: =-Model!F262*(1-'WACC Model'!$B$21) -> 71.105456 | F24: =-Model!G262*(1-'WACC Model'!$B$21) -> 71.105456 | G24: =-Model!H262*(1-'WACC Model'!$B$21) -> 71.105456 | H24: =-Model!I262*(1-'WACC Model'!$B$21) -> 71.105456
C26: Total FCF to the Firm (Total FCF Equity + After tax Interest Expense - Net Debt) | D26: =D17+D24-D16 -> 870.59012 | E26: =E17+E24-E16 -> 1148.936 | F26: =F17+F24-F16 -> 1198.1732 | G26: =G17+G24-G16 -> 1249.6118 | H26: =H17+H24-H16 -> 1303.3533
C27: Terminal Value at end of 2030 | H27: =H26*(1+$B$7)/($B$6-$B$7) -> 31507.145
C28: Total FCF to the Firm | D28: =D26 -> 870.59012 | E28: =E26 -> 1148.936 | F28: =F26 -> 1198.1732 | G28: =G26 -> 1249.6118 | H28: =H26+H27 -> 32810.498
C29: Enterprise Value | D29: =NPV($B$6,D28:H28) -> 26835.762
C30: Less Total Debt | D30: ='Data Source'!G745 -> 2382
C31: Total Equity Value | D31: =D29-D30 -> 24453.762
C32: Number of Shares (in millions) | D32: =D21 -> 244.3
C33: Equity Value Per Share | D33: =D31/D32 -> 100.09727
F37: Growth Rate
E38: =D33 -> 100.09727 | F38: 0.01 | G38: 0.02 | H38: 0.03 | I38: 0.04 | J38: 0.05
D39: WACC | E39: 0.07 | F39: 73.428503 | G39: 86.995456 | H39: 107.34589 | I39: 141.26327 | J39: 209.09803
E40: 0.072 | F40: 70.678821 | G40: 83.209209 | H40: 101.70645 | I40: 131.76446 | J40: 189.14794
E41: 0.075 | F41: 66.872272 | G41: 78.046789 | H41: 94.187759 | I41: 119.55214 | J41: 165.20803
E42: 0.079 | F42: 62.312985 | G42: 71.981323 | H42: 85.595921 | I42: 106.19236 | J42: 140.99325
E43: 0.08 | F43: 61.254791 | G43: 70.591512 | H43: 83.662921 | I43: 103.27004 | J43: 135.94856
E44: 0.084 | F44: 57.308805 | G44: 65.467296 | H44: 76.647451 | I44: 92.909495 | J44: 118.73745

Sheet Multiples Valuation
E1: Currently Running: BASE CASE
A4: Trading Multiples ( The average of the top Comparables) | D4: Trading Multiple of CHD
A5: NTM EV/EBITDA (Peer Median) | B5: ='Assumption table'!K54 -> 13.83 | D5: CHD EV/EBITDA (TTM) | E5: ='Assumption table'!K58 -> 18.41
A6: NTM EV/Revenue (Peer Median) | B6: ='Assumption table'!K55 -> 3.1 | D6: CHD EV/Revenue | E6: ='Assumption table'!K59 -> 3.35
A7: NTM Fwd P/E (Peer Median) | B7: ='Assumption table'!K56 -> 17.2 | D7: CHD Fwd P/E | E7: ='Assumption table'!K60 -> 26.3
A10: CHD NTM data | D10: Valuation using CHD's Own Multiples
A11: CHD In MM $, except EPS
A12: Forward Total Revenue (2026) | B12: =Model!E250 -> 6261.0064 | D12: Forward Total Revenue (2026) | E12: =B12 -> 6261.0064
A13: Forward EBITDA (2026) | B13: =Model!E259+Model!E256+Model!E257 -> 1434.3257 | D13: Forward EBITDA (2026) | E13: =B13 -> 1434.3257
A14: Forward Net Income, 2026 | B14: =Model!E266 -> 838.04123 | D14: Forward Net Income, 2026 | E14: =B14 -> 838.04123
A15: Number of Shares outstanding (MM) | B15: =DCF!D32 -> 244.3 | D15: Number of Shares outstanding (MM) | E15: =B15 -> 244.3
A16: Forward EPS | B16: =B14/B15 -> 3.4303775 | D16: Forward EPS | E16: =B16 -> 3.4303775
A20: Total Enterprise Value, based on EBITDA Multiple | B20: =B13*B5 -> 19836.724 | D20: Total Enterprise Value, based on EBITDA Multiple | E20: =E13*'Assumption table'!K54 -> 19836.724
A21: Total Debt | B21: =DCF!D30 -> 2382 | D21: Total Debt | E21: =B21 -> 2382
A22: Total Equity | B22: =B20-B21 -> 17454.724 | D22: Total Equity | E22: =E20-E21 -> 17454.724
A23: Equity per share | B23: =B22/B15 -> 71.447908 | D23: Equity per share | E23: =E22/E15 -> 71.447908
A25: Total Enterprise Value, based on Revenue Multiple | B25: =B12*B6 -> 19409.12 | D25: Total Enterprise Value, based on Revenue Multiple | E25: =E12*'Assumption table'!K55 -> 19409.12
A26: Total Debt | B26: =DCF!D30 -> 2382 | D26: Total Debt | E26: =B26 -> 2382
A27: Total Equity | B27: =B25-B26 -> 17027.12 | D27: Total Equity | E27: =E25-E26 -> 17027.12
A28: Equity per share | B28: =B27/B15 -> 69.697584 | D28: Equity per share | E28: =E27/E15 -> 69.697584
A30: Equity Value, based on PE Multiple | B30: =B16*B7 -> 59.002493 | D30: Equity Value, based on PE Multiple | E30: =E16*E7 -> 90.218929
A33: Relative Valuation — CHD vs. Peer Group
A34: As of May 2, 2026
A36: Company | B36: EV/EBITDA | C36: P/E (TTM) | D36: Fwd P/E | E36: EV/Revenue | F36: EV/FCF | G36: PEG
A37: CHD (Church & Dwight) | B37: =VALUE(SUBSTITUTE('Data Source'!B773,"x","")) -> 18.41 | C37: =VALUE(SUBSTITUTE('Data Source'!C773,"x","")) -> 32.83 | D37: =VALUE(SUBSTITUTE('Data Source'!D773,"x","")) -> 26.3 | E37: =VALUE(SUBSTITUTE('Data Source'!E773,"x","")) -> 3.35 | F37: =VALUE(SUBSTITUTE('Data Source'!F773,"x","")) -> 23.28 | G37: =VALUE(SUBSTITUTE('Data Source'!G773,"x","")) -> 3.66
A38: Procter & Gamble | B38: =VALUE(SUBSTITUTE('Data Source'!B774,"x","")) -> 14.94 | C38: =VALUE(SUBSTITUTE('Data Source'!C774,"x","")) -> 21.61 | D38: =VALUE(SUBSTITUTE('Data Source'!D774,"x","")) -> 19.5 | E38: =VALUE(SUBSTITUTE('Data Source'!E774,"x","")) -> 3.8 | F38: =VALUE(SUBSTITUTE('Data Source'!F774,"x","")) -> 22 | G38: =VALUE(SUBSTITUTE('Data Source'!G774,"x","")) -> 2.8
A39: Colgate-Palmolive | B39: =VALUE(SUBSTITUTE('Data Source'!B775,"x","")) -> 15.24 | C39: =VALUE(SUBSTITUTE('Data Source'!C775,"x","")) -> 31.76 | D39: =VALUE(SUBSTITUTE('Data Source'!D775,"x","")) -> 21.77 | E39: =VALUE(SUBSTITUTE('Data Source'!E775,"x","")) -> 3.6 | F39: =VALUE(SUBSTITUTE('Data Source'!F775,"x","")) -> 20.41 | G39: =VALUE(SUBSTITUTE('Data Source'!G775,"x","")) -> 4.29
A40: Kimberly-Clark | B40: =VALUE(SUBSTITUTE('Data Source'!B776,"x","")) -> 12.53 | C40: =VALUE(SUBSTITUTE('Data Source'!C776,"x","")) -> 20.63 | D40: =VALUE(SUBSTITUTE('Data Source'!D776,"x","")) -> 13.22 | E40: =VALUE(SUBSTITUTE('Data Source'!E776,"x","")) -> 2.2 | F40: =VALUE(SUBSTITUTE('Data Source'!F776,"x","")) -> 24.45 | G40: =VALUE(SUBSTITUTE('Data Source'!G776,"x","")) -> 3.46
A41: Clorox | B41: =VALUE(SUBSTITUTE('Data Source'!B777,"x","")) -> 10.75 | C41: =VALUE(SUBSTITUTE('Data Source'!C777,"x","")) -> 14.42 | D41: =VALUE(SUBSTITUTE('Data Source'!D777,"x","")) -> 13.9 | E41: =VALUE(SUBSTITUTE('Data Source'!E777,"x","")) -> 2.16 | F41: =VALUE(SUBSTITUTE('Data Source'!F777,"x","")) -> 36.47 | G41: =VALUE(SUBSTITUTE('Data Source'!G777,"x","")) -> 2.1
A42: Reckitt Benckiser | B42: =VALUE(SUBSTITUTE('Data Source'!B778,"x","")) -> 13.79 | C42: =VALUE(SUBSTITUTE('Data Source'!C778,"x","")) -> 33.14 | D42: =VALUE(SUBSTITUTE('Data Source'!D778,"x","")) -> 17.47 | E42: =VALUE(SUBSTITUTE('Data Source'!E778,"x","")) -> 3.1 | F42: =VALUE(SUBSTITUTE('Data Source'!F778,"x","")) -> 23.45 | G42: =VALUE(SUBSTITUTE('Data Source'!G778,"x","")) -> 2.9
A43: Haleon | B43: =VALUE(SUBSTITUTE('Data Source'!B779,"x","")) -> 13.83 | C43: =VALUE(SUBSTITUTE('Data Source'!C779,"x","")) -> 18.31 | D43: =VALUE(SUBSTITUTE('Data Source'!D779,"x","")) -> 16.55 | E43: =VALUE(SUBSTITUTE('Data Source'!E779,"x","")) -> 3.4 | F43: =VALUE(SUBSTITUTE('Data Source'!F779,"x","")) -> 16.19 | G43: =VALUE(SUBSTITUTE('Data Source'!G779,"x","")) -> 2.5
A44: Unilever | B44: =VALUE(SUBSTITUTE('Data Source'!B780,"x","")) -> 14.64 | C44: =VALUE(SUBSTITUTE('Data Source'!C780,"x","")) -> 19.8 | D44: =VALUE(SUBSTITUTE('Data Source'!D780,"x","")) -> 17.2 | E44: =VALUE(SUBSTITUTE('Data Source'!E780,"x","")) -> 2.5 | F44: =VALUE(SUBSTITUTE('Data Source'!F780,"x","")) -> 21 | G44: =VALUE(SUBSTITUTE('Data Source'!G780,"x","")) -> 2.6
A46: Peer Median | B46: =MEDIAN(B38:B44) -> 13.83 | C46: =MEDIAN(C38:C44) -> 20.63 | D46: =MEDIAN(D38:D44) -> 17.2 | E46: =MEDIAN(E38:E44) -> 3.1 | F46: =MEDIAN(F38:F44) -> 22 | G46: =MEDIAN(G38:G44) -> 2.8
A47: Peer Mean | B47: =AVERAGE(B38:B44) -> 13.674286 | C47: =AVERAGE(C38:C44) -> 22.81 | D47: =AVERAGE(D38:D44) -> 17.087143 | E47: =AVERAGE(E38:E44) -> 2.9657143 | F47: =AVERAGE(F38:F44) -> 23.424286 | G47: =AVERAGE(G38:G44) -> 2.95
A49: CHD Premium/(Discount) to Peer Median | B49: =B37/B46-1 -> 0.33116414 | C49: =C37/C46-1 -> 0.59137179 | D49: =D37/D46-1 -> 0.52906977 | E49: =E37/E46-1 -> 0.080645161 | F49: =F37/F46-1 -> 0.058181818 | G49: =G37/G46-1 -> 0.30714286

Sheet Data Source
A1: Global Factors/Trends
A2: Global Inflation Trends (2020–2031)
A3: Source: IMF World Economic Outlook, April 2025
A5: Year | B5: World | C5: Advanced | D5: Emerging | E5: US | F5: Euro Area | G5: Data Type
A6: 2020 | B6: 0.032 | C6: 0.007 | D6: 0.051 | E6: 0.02027 | F6: 0.003 | G6: Actual
A7: 2021 | B7: 0.047 | C7: 0.031 | D7: 0.059 | E7: 0.047 | F7: 0.026 | G7: Actual
A8: 2022 | B8: 0.087 | C8: 0.073 | D8: 0.098 | E8: 0.08 | F8: 0.084 | G8: Actual
A9: 2023 | B9: 0.069 | C9: 0.046 | D9: 0.085 | E9: 0.041 | F9: 0.054 | G9: Actual
A10: 2024 | B10: 0.058 | C10: 0.027 | D10: 0.078 | E10: 0.029 | F10: 0.024 | G10: Actual
A11: 2025 | B11: 0.041 | C11: 0.025 | D11: 0.057 | E11: 0.027 | F11: 0.021 | G11: Actual
A12: 2026 | B12: 0.044 | C12: 0.027 | D12: 0.058 | E12: 0.032 | F12: 0.026 | G12: Confirmed forecast
A13: 2027 | B13: 0.034 | C13: 0.022 | D13: 0.043 | E13: 0.021 | F13: 0.022 | G13: Confirmed forecast
A14: 2028 | B14: 0.031 | C14: 0.021 | D14: 0.04 | E14: 0.021 | F14: 0.02 | G14: Medium-term projection
A15: 2029 | B15: 0.029 | C15: 0.02 | D15: 0.037 | E15: 0.021 | F15: 0.02 | G15: Medium-term projection
A16: 2030 | B16: 0.028 | C16: 0.02 | D16: 0.035 | E16: 0.02 | F16: 0.02 | G16: Medium-term projection
A17: 2031 | B17: 0.027 | C17: 0.019 | D17: 0.033 | E17: 0.02 | F17: 0.019 | G17: Medium-term projection
A19: IMF Scenario Ranges for 2026–2027
A20: Scenario | B20: 2026 | C20: 2027 | D20: Description
A21: Reference scenario | B21: 0.044 | C21: 0.034 | D21: Baseline (confirmed forecast) | H21: Impact on CHD:
A22: Short-lived conflict | B22: 0.054 | C22: 0.045 | D22: Adverse scenario | H22: Global inflation directly affects CHD’s COGS (raw materials, packaging, freight), pricing power, and consumer demand elasticity.
A23: Prolonged disruption | B23: 0.058 | C23: 0.06 | D23: Extended energy shock - severe scenario | H23: US inflation normalizing to 2.0–2.1% by 2028+ supports CHD’s margin recovery and the 3% terminal growth assumption in the DCF.
A27: Global Real GDP Growth (2020–2031)
A28: Source: IMF World Economic Outlook, April 2025
A30: Year | B30: World | C30: Advanced | D30: Emerging | E30: US | F30: Euro Area
A31: 2020 | B31: -0.028 | C31: -0.042 | D31: -0.018 | E31: -0.028 | F31: -0.063
A32: 2021 | B32: 0.063 | C32: 0.054 | D32: 0.069 | E32: 0.059 | F32: 0.056
A33: 2022 | B33: 0.035 | C33: 0.027 | D33: 0.042 | E33: 0.019 | F33: 0.036
A34: 2023 | B34: 0.034 | C34: 0.017 | D34: 0.045 | E34: 0.029 | F34: 0.004
A35: 2024 | B35: 0.032 | C35: 0.018 | D35: 0.042 | E35: 0.028 | F35: 0.008
A36: 2025 | B36: 0.028 | C36: 0.014 | D36: 0.038 | E36: 0.016 | F36: 0.009
A37: 2026 | B37: 0.03 | C37: 0.015 | D37: 0.04 | E37: 0.017 | F37: 0.01
A38: 2027 | B38: 0.03 | C38: 0.016 | D38: 0.039 | E38: 0.018 | F38: 0.013
A39: 2028 | B39: 0.031 | C39: 0.016 | D39: 0.039 | E39: 0.019 | F39: 0.013
A40: 2029 | B40: 0.031 | C40: 0.016 | D40: 0.039 | E40: 0.02 | F40: 0.013
A41: 2030 | B41: 0.031 | C41: 0.016 | D41: 0.039 | E41: 0.02 | F41: 0.013
A42: 2031 | B42: 0.031 | C42: 0.016 | D42: 0.039 | E42: 0.02 | F42: 0.013
H43: Impact on CHD:
H44: US GDP slowing from 2.8% (2024) to 1.6–2.0% (2025–30) compresses consumer spending growth — CHD’s domestic segment (~77% of revenue) tracks household consumption closely.
H45: Emerging market GDP growth (3.8–4.0%) supports CHD’s international expansion (6.2% CAGR). Global GDP stabilizing at ~3.0–3.1% underpins the 3% terminal growth rate.
A47: Regional Factors
A48: Global commodity prices (oil, gas, agriculture) - Chemical producers raise output prices (PPI chemicals)-- CHD pays more for surfactants, resins, soda ash-- COGS rises / gross margin compresses-- CHD raises prices (pass-through) OR absorbs hit-- Higher prices risk volume destruction (as seen in 2022)
A49: Sources: BLS/FRED (PPI Final Demand, Chemical PPI, Packaging PPI, Diesel PPI), Deloitte Chemical Industry Outlook 2026, IMF WEO Apr 2025
A51: 0.04 | B51: YoY final demand · BLS | C51: 2022 Chemical PPI Peak | D51: 30–40% | E51: Organic chemicals surge
A52: 0.085 | B52: Gasoline +15.7% · Mar 2026 | C52: Mgmt Flagged Inflation | D52: $25–30M | E52: Q1 2026 · oil-based inputs
A55: Input Category | B55: FRED Series | C55: CHD Products Affected | D55: 2022 Peak Impact | E55: Segment
A56: Surfactants & Detergent Chemicals | B56: PCU325199325199 | C56: ARM & HAMMER Laundry, OxiClean, XTRA | D56: +30–40%-- 170 bps margin hit | E56: Consumer Domestic
A57: Plastic & Resin Packaging | B57: WPU0571 | C57: All products (bottles, tubs, pouches) | D57: Oil $130/bbl-- packaging surge | E57: All Segments
A58: Diesel & Transportation Freight | B58: WPU057104 | C58: All distribution & logistics | D58: +50% at peak-- distribution cost surge | E58: All Segments
A59: Sodium Bicarbonate / Trona Mining | B59: Proprietary | C59: ARM & HAMMER Baking Soda | D59: Partially insulated (own mine) | E59: Consumer Domestic
A60: Agricultural Commodities | B60: WPU01 | C60: SPD supplements, palm oil derivatives | D60: Russia-Ukraine-- commodity spike | E60: SPD
A64: Revenue ($M) | B64: COGS ($M) | C64: Gross Margin | D64: PPI Final Demand YoY | E64: Chemical PPI (est.) | F64: Key PPI Driver
A65: 4896 | B65: 2682 | C65: 0.452 | D65: -0.009 | E65: -0.05 | F65: Low PPI — COVID deflation
A66: 5190 | B66: 2927 | C66: 0.436 | D66: 0.1 | E66: 0.2 | F66: PPI starts rising — supply chain stress
A67: 5376 | B67: 3126 | C67: 0.419 | D67: 0.095 | E67: 0.35 | F67: PPI surges — oil, chemicals, transport
A68: 5868 | B68: 3279 | C68: 0.441 | D68: 0.012 | E68: -0.05 | F68: PPI moderates — disinflation begins
A69: 6107 | B69: 3317 | C69: 0.457 | D69: 0.018 | E69: 0.02 | F69: PPI stable — margin recovery
A70: 6203 | B70: 3428 | C70: 0.447 | D70: 0.025 | E70: 0.03 | F70: Slight uptick — energy re-acceleration
A73: Chemical PPI | B73: Energy PPI | C73: CHD Gross Margin Impact | D73: Oil Price Assumption | E73: Source / Basis
A74: +2.5–3.0% | B74: +3–4% | C74: +100 bps expansion | D74: $70–80/bbl | E74: Deloitte Chemical Outlook; CHD mgmt guidance
A75: +5–6% | B75: +8–10% | C75: Flat to -50 bps | D75: $90–100/bbl | E75: Mid-East short-lived conflict; consumer spending +1.4%
A76: +8–10% | B76: +15–20% | C76: -150 to -200 bps | D76: >$100/bbl | E76: Extended energy shock; replicates 2022 conditions
A79: PPI Final Demand | B79: Chemical PPI (WPU06) | C79: Energy PPI | D79: CHD Gross Margin | E79: Data Type
A80: 0.018 | B80: 0.005 | C80: -0.04 | E80: Actual · BLS
A81: -0.009 | B81: -0.05 | C81: -0.25 | D81: 0.452 | E81: Actual · BLS
A82: 0.1 | B82: 0.2 | C82: 0.35 | D82: 0.436 | E82: Actual · BLS
A83: 0.095 | B83: 0.35 | C83: 0.4 | D83: 0.419 | E83: Actual · BLS ◆ PEAK
A84: 0.012 | B84: -0.05 | C84: -0.15 | D84: 0.441 | E84: Actual · BLS
A85: 0.018 | B85: 0.02 | C85: 0.05 | D85: 0.457 | E85: Actual · BLS
A86: 0.025 | B86: 0.03 | C86: 0.085 | D86: 0.447 | E86: Actual · BLS (thru Mar)
A87: 0.03 | B87: 0.028 | C87: 0.035 | D87: 0.457 | E87: Base Case Forecast
A88: 0.025 | B88: 0.022 | C88: 0.025 | D88: 0.462 | E88: Base Case Forecast
A89: 0.022 | B89: 0.02 | C89: 0.02 | D89: 0.468 | E89: Medium-term Projection
A90: 0.02 | B90: 0.018 | C90: 0.018 | D90: 0.472 | E90: Medium-term Projection
A91: 0.02 | B91: 0.018 | C91: 0.018 | D91: 0.475 | E91: Medium-term Projection
A98: CHD Gross Margin — Scenario Comparison (2026–2030)
A99: Year | B99: Base Case | C99: Adverse Case | D99: Severe Case | E99: Key Driver
A100: 2026 | B100: 0.457 | C100: 0.442 | D100: 0.43 | E100: Chem PPI: Base +2.8% / Adverse +5.5% / Severe +9%
A101: 2027 | B101: 0.462 | C101: 0.445 | D101: 0.425 | E101: Adverse: Mid-East conflict persists; Severe: oil >$100
A102: 2028 | B102: 0.468 | C102: 0.452 | D102: 0.435 | E102: PPI normalizes in adverse; severe persists
A103: 2029 | B103: 0.472 | C103: 0.458 | D103: 0.44 | E103: Gradual recovery all scenarios as hedging kicks in
A104: 2030 | B104: 0.475 | C104: 0.462 | D104: 0.445 | E104: Base: near-peak margins; Severe: still below 2024 level
A107: Year | B107: CHD Gross Margin | C107: PPI Final Demand | D107: Chemical PPI (est.)
A108: 2019 | B108: 0.452 | C108: 0.018 | D108: 0.005
A109: 2020 | B109: 0.452 | C109: -0.009 | D109: -0.05
A110: 2021 | B110: 0.436 | C110: 0.1 | D110: 0.2
A111: 2022 | B111: 0.419 | C111: 0.095 | D111: 0.35
A112: 2023 | B112: 0.441 | C112: 0.012 | D112: -0.05
A113: 2024 | B113: 0.457 | C113: 0.018 | D113: 0.02
A114: 2025 | B114: 0.447 | C114: 0.025 | D114: 0.03
A115: 2026 | B115: 0.457 | C115: 0.03 | D115: 0.028
A116: 2027 | B116: 0.462 | C116: 0.025 | D116: 0.022
A117: 2028 | B117: 0.468 | C117: 0.022 | D117: 0.02
A118: 2029 | B118: 0.472 | C118: 0.02 | D118: 0.018
A119: 2030 | B119: 0.475 | C119: 0.02 | D119: 0.018
A123: Each +100 bps in chemical PPI above expectations ≈ 40–60 bps gross margin compression for CHD (based on 2021–2022 historical relationship).
A124: 1. COGS Growth Rate: Base case assumes COGS grows at ≈CPI + 0.5% when PPI stable; CPI + 2–3% when PPI accelerates (as in 2022). 2026 base assumes chemical PPI +2.0–2.5%.
A125: 2. Gross Margin Trajectory: Most PPI-sensitive line in the model. 2022 demonstrated the inverse correlation — chemical PPI up 35%, gross margin collapsed 170 bps to 41.9%.
A126: 3. Scenario Trigger: PPI is the worst-case trigger. Oil >$100/bbl-- chemical PPI +6–10%-- gross margin -150 to -200 bps, replicating 2022. This drives the worst-case DCF scenario.
A127: 4. Q1 2026 Update: CHD mgmt flagged $25–30M incremental inflation from oil-based inputs & transport (surfactants + diesel channels). Offset via productivity & hedging, not immediate price increases.
I128: Year | J128: Headline CPI | K128: Core CPI | L128: CBO Forecast | M128: Fed (FOMC) | N128: IMF
...
